Workbook
Name AA: recibos!$W$4
Name ABR_2013: recibos!$B$978:$AI$1162
Name AGO: 8
Name AGO_2013: recibos!$B$1763:$AI$1933
Name AGO_2013_A: recibos!$B$4:$AI$1933
Name BASE_A: base!$B$5:$K$446
Name BASE_B: base!$A$5:$B$446
Name BCO_ABR13: chequera!$B$52:$J$59
Name BCO_AGO13: chequera!$B$91:$J$96
Name BCO_AGO13_A: chequera!$B$3:$J$96
Name BCO_ENE13: chequera!$B$3:$J$22
Name BCO_FEB13: chequera!$B$23:$J$39
Name BCO_JUL13: chequera!$B$83:$J$90
Name BCO_JUL13_A: chequera!$B$3:$J$90
Name BCO_JUN13: chequera!$B$74:$J$82
Name BCO_JUN13_A: chequera!$B$3:$J$82
Name BCO_MAR13: chequera!$B$40:$J$51
Name BCO_MAY13: chequera!$B$61:$J$73
Name BCO_MAY13_A: chequera!$B$3:$J$73
Name BCO_SEP13: chequera!$B$97:$J$100
Name BCO_SEP13_A: chequera!$B$3:$J$100
Name Cafetales: criterios!$D$135:$E$136
Name CALLES: 'cobranza 2013'!$B$6:$J$448
Name Calzada_del_Hueso: criterios!$D$138:$E$139
Name Carmel: criterios!$FI$8:$FI$9
Name CL: criterios!$HS$2:$HS$3
Name CL_101_: criterios!$FF$2:$FG$3
Name CL_107_: criterios!$FH$2:$FI$3
Name CL_11_: criterios!$N$2:$O$3
Name CL_110_: criterios!$FJ$2:$FK$3
Name CL_111_: criterios!$FL$2:$FM$3
Name CL_112_PA: criterios!$FN$2:$FO$3
Name CL_112_PB: criterios!$FP$2:$FQ$3
Name CL_115_: criterios!$FR$2:$FS$3
Name CL_116_: criterios!$FT$2:$FU$3
Name CL_117_: criterios!$FV$2:$FW$3
Name CL_118_: criterios!$FX$2:$FY$3
Name CL_119_: criterios!$FZ$2:$GA$3
Name CL_12_: criterios!$P$2:$Q$3
Name CL_120_: criterios!$GB$2:$GC$3
Name CL_121_: criterios!$GD$2:$GE$3
Name CL_122_: criterios!$GF$2:$GG$3
Name CL_125_: criterios!$GH$2:$GI$3
Name CL_127_: criterios!$GJ$2:$GK$3
Name CL_129_: criterios!$GL$2:$GM$3
Name CL_13_: criterios!$R$2:$S$3
Name CL_130_: criterios!$GN$2:$GO$3
Name CL_131_: criterios!$GP$2:$GQ$3
Name CL_132_: criterios!$GR$2:$GS$3
Name CL_133_: criterios!$GT$2:$GU$3
Name CL_134_: criterios!$GV$2:$GW$3
Name CL_135_: criterios!$GX$2:$GY$3
Name CL_137_: criterios!$GZ$2:$HA$3
Name CL_139_: criterios!$HB$2:$HC$3
Name CL_14_: criterios!$T$2:$U$3
Name CL_141_: criterios!$HD$2:$HE$3
Name CL_144_: criterios!$HF$2:$HG$3
Name CL_145_: criterios!$HH$2:$HI$3
Name CL_147_: criterios!$HJ$2:$HK$3
Name CL_148_: criterios!$HL$2:$HM$3

Sheet base
B4: 1 | C4: 2 | D4: 3 | E4: 4 | F4: 5 | G4: 6 | H4: 7 | I4: 8 | J4: 9
A5: N° | B5: CASA | C5: CALLE | D5: N° | E5: INT | G5: DOMICILIO | H5: Domicilio | I5: FAMILIA | J5: CUOTA
A6: 1 | B6: =CONCATENATE(C6,"_",D6,"_",E6) -> CL_7_101 | C6: CL | D6: 7 | E6: 101 | F6: Rancho La Cuchilla | G6: =IF(E6=0,CONCATENATE(F6," No. ",D6),CONCATENATE(F6," No. ",D6,", ",E6)) -> Rancho La Cuchilla No. 7, 101 | H6: Cuchil 7-101 | I6: Olivares | J6: 100
A7: 2 | B7: =CONCATENATE(C7,"_",D7,"_",E7) -> CL_7_102 | C7: CL | D7: 7 | E7: 102 | F7: Rancho La Cuchilla | G7: =IF(E7=0,CONCATENATE(F7," No. ",D7),CONCATENATE(F7," No. ",D7,", ",E7)) -> Rancho La Cuchilla No. 7, 102 | H7: Cuhill 7- 102 | I7: García Moreno | J7: 100
A8: 3 | B8: =CONCATENATE(C8,"_",D8,"_",E8) -> CL_7_201 | C8: CL | D8: 7 | E8: 201 | F8: Rancho La Cuchilla | G8: =IF(E8=0,CONCATENATE(F8," No. ",D8),CONCATENATE(F8," No. ",D8,", ",E8)) -> Rancho La Cuchilla No. 7, 201 | H8: Cuchil 7-201 | I8: Solís Susana | J8: 100
A9: 4 | B9: =CONCATENATE(C9,"_",D9,"_",E9) -> CL_7_202 | C9: CL | D9: 7 | E9: 202 | F9: Rancho La Cuchilla | G9: =IF(E9=0,CONCATENATE(F9," No. ",D9),CONCATENATE(F9," No. ",D9,", ",E9)) -> Rancho La Cuchilla No. 7, 202 | H9: Cuc 7-202 | I9: Carbajal Zayas | J9: 100
A10: 5 | B10: =CONCATENATE(C10,"_",D10,"_",E10) -> CL_9_ | C10: CL | D10: 9 | F10: Rancho La Cuchilla | G10: =IF(E10=0,CONCATENATE(F10," No. ",D10),CONCATENATE(F10," No. ",D10,", ",E10)) -> Rancho La Cuchilla No. 9 | H10: Cuchi 9 | I10: Martín del Campo | J10: 300
A11: 6 | B11: =CONCATENATE(C11,"_",D11,"_",E11) -> CL_11_ | C11: CL | D11: 11 | F11: Rancho La Cuchilla | G11: =IF(E11=0,CONCATENATE(F11," No. ",D11),CONCATENATE(F11," No. ",D11,", ",E11)) -> Rancho La Cuchilla No. 11 | H11: Cuchi 11 | I11: Santiago | J11: 300
A12: 7 | B12: =CONCATENATE(C12,"_",D12,"_",E12) -> CL_12_ | C12: CL | D12: 12 | F12: Rancho La Cuchilla | G12: =IF(E12=0,CONCATENATE(F12," No. ",D12),CONCATENATE(F12," No. ",D12,", ",E12)) -> Rancho La Cuchilla No. 12 | H12: Cuchi 12C.E | I12: Rivera Flores | J12: 300
A13: 8 | B13: =CONCATENATE(C13,"_",D13,"_",E13) -> CL_13_ | C13: CL | D13: 13 | F13: Rancho La Cuchilla | G13: =IF(E13=0,CONCATENATE(F13," No. ",D13),CONCATENATE(F13," No. ",D13,", ",E13)) -> Rancho La Cuchilla No. 13 | H13: Cuchi 13 | I13: Torres | J13: 300
A14: 9 | B14: =CONCATENATE(C14,"_",D14,"_",E14) -> CL_14_ | C14: CL | D14: 14 | F14: Rancho La Cuchilla | G14: =IF(E14=0,CONCATENATE(F14," No. ",D14),CONCATENATE(F14," No. ",D14,", ",E14)) -> Rancho La Cuchilla No. 14 | H14: Cuchi 14 | I14: Chávez Lara | J14: 300
A15: 10 | B15: =CONCATENATE(C15,"_",D15,"_",E15) -> CL_15_ | C15: CL | D15: 15 | F15: Rancho La Cuchilla | G15: =IF(E15=0,CONCATENATE(F15," No. ",D15),CONCATENATE(F15," No. ",D15,", ",E15)) -> Rancho La Cuchilla No. 15 | H15: Cuchi 15 | I15: Guerrero Ponce | J15: 300
A16: 11 | B16: =CONCATENATE(C16,"_",D16,"_",E16) -> CL_18_ | C16: CL | D16: 18 | F16: Rancho La Cuchilla | G16: =IF(E16=0,CONCATENATE(F16," No. ",D16),CONCATENATE(F16," No. ",D16,", ",E16)) -> Rancho La Cuchilla No. 18 | H16: Cuc 18 C.E | I16: Aldana Sánchez | J16: 300
A17: 12 | B17: =CONCATENATE(C17,"_",D17,"_",E17) -> CL_19_ | C17: CL | D17: 19 | F17: Rancho La Cuchilla | G17: =IF(E17=0,CONCATENATE(F17," No. ",D17),CONCATENATE(F17," No. ",D17,", ",E17)) -> Rancho La Cuchilla No. 19 | H17: Cuchi 19 | I17: Tapia Vázquez | J17: 300
A18: 13 | B18: =CONCATENATE(C18,"_",D18,"_",E18) -> CL_20_ | C18: CL | D18: 20 | F18: Rancho La Cuchilla | G18: =IF(E18=0,CONCATENATE(F18," No. ",D18),CONCATENATE(F18," No. ",D18,", ",E18)) -> Rancho La Cuchilla No. 20 | H18: Cuc 20 C.EX | I18: Sánchez López | J18: 300
A19: 14 | B19: =CONCATENATE(C19,"_",D19,"_",E19) -> CL_21_ | C19: CL | D19: 21 | F19: Rancho La Cuchilla | G19: =IF(E19=0,CONCATENATE(F19," No. ",D19),CONCATENATE(F19," No. ",D19,", ",E19)) -> Rancho La Cuchilla No. 21 | H19: Cuch 21 C.E | I19: Solórzano Calderón | J19: 300
A20: 15 | B20: =CONCATENATE(C20,"_",D20,"_",E20) -> CL_23_ | C20: CL | D20: 23 | F20: Rancho La Cuchilla | G20: =IF(E20=0,CONCATENATE(F20," No. ",D20),CONCATENATE(F20," No. ",D20,", ",E20)) -> Rancho La Cuchilla No. 23 | H20: Cuchil 23 | I20: Ocampo | J20: 200
A21: 16 | B21: =CONCATENATE(C21,"_",D21,"_",E21) -> CL_25_ | C21: CL | D21: 25 | F21: Rancho La Cuchilla | G21: =IF(E21=0,CONCATENATE(F21," No. ",D21),CONCATENATE(F21," No. ",D21,", ",E21)) -> Rancho La Cuchilla No. 25 | H21: Cuchi 25 | I21: García de León | J21: 300
A22: 17 | B22: =CONCATENATE(C22,"_",D22,"_",E22) -> CL_27_ | C22: CL | D22: 27 | F22: Rancho La Cuchilla | G22: =IF(E22=0,CONCATENATE(F22," No. ",D22),CONCATENATE(F22," No. ",D22,", ",E22)) -> Rancho La Cuchilla No. 27 | H22: Cuchi 27 | I22: Montoya | J22: 300
A23: 18 | B23: =CONCATENATE(C23,"_",D23,"_",E23) -> CL_28_ | C23: CL | D23: 28 | F23: Rancho La Cuchilla | G23: =IF(E23=0,CONCATENATE(F23," No. ",D23),CONCATENATE(F23," No. ",D23,", ",E23)) -> Rancho La Cuchilla No. 28 | H23: Cuc 2 C. E | I23: Prado de los S. | J23: 300 | K23: Cambio de número de vivienda de 2 a 28. BS 14JUN13
A24: 19 | B24: =CONCATENATE(C24,"_",D24,"_",E24) -> CL_29_ | C24: CL | D24: 29 | F24: Rancho La Cuchilla | G24: =IF(E24=0,CONCATENATE(F24," No. ",D24),CONCATENATE(F24," No. ",D24,", ",E24)) -> Rancho La Cuchilla No. 29 | H24: Cuch 29 C.E | I24: Vega Sánchez C. | J24: 300
A25: 20 | B25: =CONCATENATE(C25,"_",D25,"_",E25) -> CL_30_ | C25: CL | D25: 30 | F25: Rancho La Cuchilla | G25: =IF(E25=0,CONCATENATE(F25," No. ",D25),CONCATENATE(F25," No. ",D25,", ",E25)) -> Rancho La Cuchilla No. 30 | H25: Cuchil 30 | I25: Ruiz Navarrete | J25: 300
A26: 21 | B26: =CONCATENATE(C26,"_",D26,"_",E26) -> CL_31_ | C26: CL | D26: 31 | F26: Rancho La Cuchilla | G26: =IF(E26=0,CONCATENATE(F26," No. ",D26),CONCATENATE(F26," No. ",D26,", ",E26)) -> Rancho La Cuchilla No. 31 | H26: Cuch 31 | I26: Espinoza Serrano | J26: 300
A27: 22 | B27: =CONCATENATE(C27,"_",D27,"_",E27) -> CL_32_ | C27: CL | D27: 32 | F27: Rancho La Cuchilla | G27: =IF(E27=0,CONCATENATE(F27," No. ",D27),CONCATENATE(F27," No. ",D27,", ",E27)) -> Rancho La Cuchilla No. 32 | H27: Cuchi 32 | I27: Hernández | J27: 300
A28: 23 | B28: =CONCATENATE(C28,"_",D28,"_",E28) -> CL_33_ | C28: CL | D28: 33 | F28: Rancho La Cuchilla | G28: =IF(E28=0,CONCATENATE(F28," No. ",D28),CONCATENATE(F28," No. ",D28,", ",E28)) -> Rancho La Cuchilla No. 33 | H28: Cuchi 33 C.E | I28: Tanús | J28: 300
A29: 24 | B29: =CONCATENATE(C29,"_",D29,"_",E29) -> CL_35_ | C29: CL | D29: 35 | F29: Rancho La Cuchilla | G29: =IF(E29=0,CONCATENATE(F29," No. ",D29),CONCATENATE(F29," No. ",D29,", ",E29)) -> Rancho La Cuchilla No. 35 | H29: Cuchill 35 | I29: Mendoza | J29: 150
A30: 25 | B30: =CONCATENATE(C30,"_",D30,"_",E30) -> CL_36_ | C30: CL | D30: 36 | F30: Rancho La Cuchilla | G30: =IF(E30=0,CONCATENATE(F30," No. ",D30),CONCATENATE(F30," No. ",D30,", ",E30)) -> Rancho La Cuchilla No. 36 | H30: Cuch 36 C.E | I30: Castillo | J30: 300
A31: 26 | B31: =CONCATENATE(C31,"_",D31,"_",E31) -> CL_38_ | C31: CL | D31: 38 | F31: Rancho La Cuchilla | G31: =IF(E31=0,CONCATENATE(F31," No. ",D31),CONCATENATE(F31," No. ",D31,", ",E31)) -> Rancho La Cuchilla No. 38 | H31: Cuchill 38 | I31: Cerecedo | J31: 300
A32: 27 | B32: =CONCATENATE(C32,"_",D32,"_",E32) -> CL_39_ | C32: CL | D32: 39 | F32: Rancho La Cuchilla | G32: =IF(E32=0,CONCATENATE(F32," No. ",D32),CONCATENATE(F32," No. ",D32,", ",E32)) -> Rancho La Cuchilla No. 39 | H32: Cuchill 39 | I32: Arenas | J32: 300
A33: 28 | B33: =CONCATENATE(C33,"_",D33,"_",E33) -> CL_40_ | C33: CL | D33: 40 | F33: Rancho La Cuchilla | G33: =IF(E33=0,CONCATENATE(F33," No. ",D33),CONCATENATE(F33," No. ",D33,", ",E33)) -> Rancho La Cuchilla No. 40 | H33: Cuchil 40 C.E | I33: López Pico | J33: 300
A34: 29 | B34: =CONCATENATE(C34,"_",D34,"_",E34) -> CL_41_ | C34: CL | D34: 41 | F34: Rancho La Cuchilla | G34: =IF(E34=0,CONCATENATE(F34," No. ",D34),CONCATENATE(F34," No. ",D34,", ",E34)) -> Rancho La Cuchilla No. 41 | H34: Cuchill 41C.E | I34: Arriaga Lemus | J34: 250
A35: 30 | B35: =CONCATENATE(C35,"_",D35,"_",E35) -> CL_42_ | C35: CL | D35: 42 | F35: Rancho La Cuchilla | G35: =IF(E35=0,CONCATENATE(F35," No. ",D35),CONCATENATE(F35," No. ",D35,", ",E35)) -> Rancho La Cuchilla No. 42 | H35: Cuchi 42 C.E | I35: Mac Kinney | J35: 300
A36: 31 | B36: =CONCATENATE(C36,"_",D36,"_",E36) -> CL_43_A | C36: CL | D36: 43 | E36: A | F36: Rancho La Cuchilla | G36: =IF(E36=0,CONCATENATE(F36," No. ",D36),CONCATENATE(F36," No. ",D36,", ",E36)) -> Rancho La Cuchilla No. 43, A | H36: Cuchi 43-A | I36: De la Rosa | J36: 200
A37: 32 | B37: =CONCATENATE(C37,"_",D37,"_",E37) -> CL_43_B | C37: CL | D37: 43 | E37: B | F37: Rancho La Cuchilla | G37: =IF(E37=0,CONCATENATE(F37," No. ",D37),CONCATENATE(F37," No. ",D37,", ",E37)) -> Rancho La Cuchilla No. 43, B | H37: Cuchil 43-B | I37: Luna Albertano | J37: 125
A38: 33 | B38: =CONCATENATE(C38,"_",D38,"_",E38) -> CL_44_ | C38: CL | D38: 44 | F38: Rancho La Cuchilla | G38: =IF(E38=0,CONCATENATE(F38," No. ",D38),CONCATENATE(F38," No. ",D38,", ",E38)) -> Rancho La Cuchilla No. 44 | H38: Cuchill 44 | I38: Garduño | J38: 300
A39: 34 | B39: =CONCATENATE(C39,"_",D39,"_",E39) -> CL_45_ | C39: CL | D39: 45 | F39: Rancho La Cuchilla | G39: =IF(E39=0,CONCATENATE(F39," No. ",D39),CONCATENATE(F39," No. ",D39,", ",E39)) -> Rancho La Cuchilla No. 45 | H39: Cuchill 45 | I39: Estévez Hernández | J39: 300
A40: 35 | B40: =CONCATENATE(C40,"_",D40,"_",E40) -> CL_46_ | C40: CL | D40: 46 | F40: Rancho La Cuchilla | G40: =IF(E40=0,CONCATENATE(F40," No. ",D40),CONCATENATE(F40," No. ",D40,", ",E40)) -> Rancho La Cuchilla No. 46 | H40: Cuch 46 C.E | I40: Cruz López | J40: 300
A41: 36 | B41: =CONCATENATE(C41,"_",D41,"_",E41) -> CL_47_ | C41: CL | D41: 47 | F41: Rancho La Cuchilla | G41: =IF(E41=0,CONCATENATE(F41," No. ",D41),CONCATENATE(F41," No. ",D41,", ",E41)) -> Rancho La Cuchilla No. 47 | H41: Cuch 47 C.E | I41: López | J41: 300
A42: 37 | B42: =CONCATENATE(C42,"_",D42,"_",E42) -> CL_49_ | C42: CL | D42: 49 | F42: Rancho La Cuchilla | G42: =IF(E42=0,CONCATENATE(F42," No. ",D42),CONCATENATE(F42," No. ",D42,", ",E42)) -> Rancho La Cuchilla No. 49 | H42: Cuchi 49 | I42: Orozco Castelazo | J42: 300
A43: 38 | B43: =CONCATENATE(C43,"_",D43,"_",E43) -> CL_52_ | C43: CL | D43: 52 | F43: Rancho La Cuchilla | G43: =IF(E43=0,CONCATENATE(F43," No. ",D43),CONCATENATE(F43," No. ",D43,", ",E43)) -> Rancho La Cuchilla No. 52 | H43: Cuchi 52 | I43: Velázquez | J43: 300
A44: 39 | B44: =CONCATENATE(C44,"_",D44,"_",E44) -> CL_53_ | C44: CL | D44: 53 | F44: Rancho La Cuchilla | G44: =IF(E44=0,CONCATENATE(F44," No. ",D44),CONCATENATE(F44," No. ",D44,", ",E44)) -> Rancho La Cuchilla No. 53 | H44: Cuch 53 C.E | I44: Loyo Ochoa | J44: 300
A45: 40 | B45: CL_54_ | C45: CL | D45: 54 | F45: Rancho La Cuchilla | G45: =IF(E45=0,CONCATENATE(F45," No. ",D45),CONCATENATE(F45," No. ",D45,", ",E45)) -> Rancho La Cuchilla No. 54 | I45: Mendoza León | J45: 300
A46: 41 | B46: =CONCATENATE(C46,"_",D46,"_",E46) -> CL_55_ | C46: CL | D46: 55 | F46: Rancho La Cuchilla | G46: =IF(E46=0,CONCATENATE(F46," No. ",D46),CONCATENATE(F46," No. ",D46,", ",E46)) -> Rancho La Cuchilla No. 55 | H46: Cuchi 55 | I46: López Velázquez | J46: 300
A47: 42 | B47: =CONCATENATE(C47,"_",D47,"_",E47) -> CL_57_ | C47: CL | D47: 57 | F47: Rancho La Cuchilla | G47: =IF(E47=0,CONCATENATE(F47," No. ",D47),CONCATENATE(F47," No. ",D47,", ",E47)) -> Rancho La Cuchilla No. 57 | J47: 300 | K47: Agregado el 14JUN13. BS
A48: 43 | B48: =CONCATENATE(C48,"_",D48,"_",E48) -> CL_58_ | C48: CL | D48: 58 | F48: Rancho La Cuchilla | G48: =IF(E48=0,CONCATENATE(F48," No. ",D48),CONCATENATE(F48," No. ",D48,", ",E48)) -> Rancho La Cuchilla No. 58 | H48: Cuchi 58 | I48: Serdán | J48: 300
A49: 44 | B49: =CONCATENATE(C49,"_",D49,"_",E49) -> CL_59_ | C49: CL | D49: 59 | F49: Rancho La Cuchilla | G49: =IF(E49=0,CONCATENATE(F49," No. ",D49),CONCATENATE(F49," No. ",D49,", ",E49)) -> Rancho La Cuchilla No. 59 | H49: Cuchi 59 | I49: Ortega Vega | J49: 300
A50: 45 | B50: =CONCATENATE(C50,"_",D50,"_",E50) -> CL_60_ | C50: CL | D50: 60 | F50: Rancho La Cuchilla | G50: =IF(E50=0,CONCATENATE(F50," No. ",D50),CONCATENATE(F50," No. ",D50,", ",E50)) -> Rancho La Cuchilla No. 60 | J50: 300 | K50: Agregado el 14JUN13. BS
A51: 46 | B51: =CONCATENATE(C51,"_",D51,"_",E51) -> CL_61_ | C51: CL | D51: 61 | F51: Rancho La Cuchilla | G51: =IF(E51=0,CONCATENATE(F51," No. ",D51),CONCATENATE(F51," No. ",D51,", ",E51)) -> Rancho La Cuchilla No. 61 | H51: Cuchi 61 | I51: Rivera | J51: 300
A52: 47 | B52: =CONCATENATE(C52,"_",D52,"_",E52) -> CL_62_ | C52: CL | D52: 62 | F52: Rancho La Cuchilla | G52: =IF(E52=0,CONCATENATE(F52," No. ",D52),CONCATENATE(F52," No. ",D52,", ",E52)) -> Rancho La Cuchilla No. 62 | H52: Cuchi 62 | I52: Frías | J52: 200
A53: 48 | B53: =CONCATENATE(C53,"_",D53,"_",E53) -> CL_63_ | C53: CL | D53: 63 | F53: Rancho La Cuchilla | G53: =IF(E53=0,CONCATENATE(F53," No. ",D53),CONCATENATE(F53," No. ",D53,", ",E53)) -> Rancho La Cuchilla No. 63 | H53: Cuchi 63 | I53: Díaz de la Rosa | J53: 300
A54: 49 | B54: =CONCATENATE(C54,"_",D54,"_",E54) -> CL_65_ | C54: CL | D54: 65 | F54: Rancho La Cuchilla | G54: =IF(E54=0,CONCATENATE(F54," No. ",D54),CONCATENATE(F54," No. ",D54,", ",E54)) -> Rancho La Cuchilla No. 65 | I54: Garduño | J54: 300 | K54: Agregado el 14JUN13. BS
A55: 50 | B55: =CONCATENATE(C55,"_",D55,"_",E55) -> CL_66_ | C55: CL | D55: 66 | F55: Rancho La Cuchilla | G55: =IF(E55=0,CONCATENATE(F55," No. ",D55),CONCATENATE(F55," No. ",D55,", ",E55)) -> Rancho La Cuchilla No. 66 | H55: Cuchi 66 C.E | I55: Prieto | J55: 300
A56: 51 | B56: =CONCATENATE(C56,"_",D56,"_",E56) -> CL_67_ | C56: CL | D56: 67 | F56: Rancho La Cuchilla | G56: =IF(E56=0,CONCATENATE(F56," No. ",D56),CONCATENATE(F56," No. ",D56,", ",E56)) -> Rancho La Cuchilla No. 67 | H56: Cuchi 67 | I56: Quezada Viruega | J56: 300
A57: 52 | B57: =CONCATENATE(C57,"_",D57,"_",E57) -> CL_68_ | C57: CL | D57: 68 | F57: Rancho La Cuchilla | G57: =IF(E57=0,CONCATENATE(F57," No. ",D57),CONCATENATE(F57," No. ",D57,", ",E57)) -> Rancho La Cuchilla No. 68 | H57: Cuchi 68 | I57: Montesinos | J57: 300
A58: 53 | B58: =CONCATENATE(C58,"_",D58,"_",E58) -> CL_69_ | C58: CL | D58: 69 | F58: Rancho La Cuchilla | G58: =IF(E58=0,CONCATENATE(F58," No. ",D58),CONCATENATE(F58," No. ",D58,", ",E58)) -> Rancho La Cuchilla No. 69 | H58: Cuchi 69 | I58: Romero | J58: 300
A59: 54 | B59: =CONCATENATE(C59,"_",D59,"_",E59) -> CL_70_ | C59: CL | D59: 70 | F59: Rancho La Cuchilla | G59: =IF(E59=0,CONCATENATE(F59," No. ",D59),CONCATENATE(F59," No. ",D59,", ",E59)) -> Rancho La Cuchilla No. 70 | J59: 300 | K59: Agregado el 14JUN13. BS
A60: 55 | B60: =CONCATENATE(C60,"_",D60,"_",E60) -> CL_71_ | C60: CL | D60: 71 | F60: Rancho La Cuchilla | G60: =IF(E60=0,CONCATENATE(F60," No. ",D60),CONCATENATE(F60," No. ",D60,", ",E60)) -> Rancho La Cuchilla No. 71 | H60: Cuchi 71 | I60: Pulido | J60: 300
A61: 56 | B61: =CONCATENATE(C61,"_",D61,"_",E61) -> CL_72_ | C61: CL | D61: 72 | F61: Rancho La Cuchilla | G61: =IF(E61=0,CONCATENATE(F61," No. ",D61),CONCATENATE(F61," No. ",D61,", ",E61)) -> Rancho La Cuchilla No. 72 | H61: Cuchi 72 C.E | I61: Ortiz González | J61: 300
A62: 57 | B62: =CONCATENATE(C62,"_",D62,"_",E62) -> CL_73_ | C62: CL | D62: 73 | F62: Rancho La Cuchilla | G62: =IF(E62=0,CONCATENATE(F62," No. ",D62),CONCATENATE(F62," No. ",D62,", ",E62)) -> Rancho La Cuchilla No. 73 | H62: Cuchill 73 | I62: Cooper | J62: 300
A63: 58 | B63: =CONCATENATE(C63,"_",D63,"_",E63) -> CL_74_ | C63: CL | D63: 74 | F63: Rancho La Cuchilla | G63: =IF(E63=0,CONCATENATE(F63," No. ",D63),CONCATENATE(F63," No. ",D63,", ",E63)) -> Rancho La Cuchilla No. 74 | H63: Cuchi 74 | I63: Gil | J63: 300
A64: 59 | B64: =CONCATENATE(C64,"_",D64,"_",E64) -> CL_75_ | C64: CL | D64: 75 | F64: Rancho La Cuchilla | G64: =IF(E64=0,CONCATENATE(F64," No. ",D64),CONCATENATE(F64," No. ",D64,", ",E64)) -> Rancho La Cuchilla No. 75 | H64: Cuch 75 C.E | I64: Sosa Lucio | J64: 300
A65: 60 | B65: =CONCATENATE(C65,"_",D65,"_",E65) -> CL_76_ | C65: CL | D65: 76 | F65: Rancho La Cuchilla | G65: =IF(E65=0,CONCATENATE(F65," No. ",D65),CONCATENATE(F65," No. ",D65,", ",E65)) -> Rancho La Cuchilla No. 76 | J65: 300 | K65: Agregado el 14JUN13. BS
A66: 61 | B66: =CONCATENATE(C66,"_",D66,"_",E66) -> CL_77_ | C66: CL | D66: 77 | F66: Rancho La Cuchilla | G66: =IF(E66=0,CONCATENATE(F66," No. ",D66),CONCATENATE(F66," No. ",D66,", ",E66)) -> Rancho La Cuchilla No. 77 | H66: Cuchl 77 | I66: Loperena | J66: 300
A67: 62 | B67: =CONCATENATE(C67,"_",D67,"_",E67) -> CL_79_ | C67: CL | D67: 79 | F67: Rancho La Cuchilla | G67: =IF(E67=0,CONCATENATE(F67," No. ",D67),CONCATENATE(F67," No. ",D67,", ",E67)) -> Rancho La Cuchilla No. 79 | H67: Cuchl 79 | I67: Hernández Laurel | J67: 300
A68: 63 | B68: =CONCATENATE(C68,"_",D68,"_",E68) -> CL_80_ | C68: CL | D68: 80 | F68: Rancho La Cuchilla | G68: =IF(E68=0,CONCATENATE(F68," No. ",D68),CONCATENATE(F68," No. ",D68,", ",E68)) -> Rancho La Cuchilla No. 80 | H68: Cuch 80 C.E | I68: Aparicio | J68: 300
A69: 64 | B69: =CONCATENATE(C69,"_",D69,"_",E69) -> CL_81_A | C69: CL | D69: 81 | E69: A | F69: Rancho La Cuchilla | G69: =IF(E69=0,CONCATENATE(F69," No. ",D69),CONCATENATE(F69," No. ",D69,", ",E69)) -> Rancho La Cuchilla No. 81, A | H69: Cuchi 81-A | I69: Barrientos López | J69: 300
A70: 65 | B70: =CONCATENATE(C70,"_",D70,"_",E70) -> CL_81_B | C70: CL | D70: 81 | E70: B | F70: Rancho La Cuchilla | G70: =IF(E70=0,CONCATENATE(F70," No. ",D70),CONCATENATE(F70," No. ",D70,", ",E70)) -> Rancho La Cuchilla No. 81, B | H70: Cuch 81 B C. Extra | I70: Suárez | J70: 300
A71: 66 | B71: =CONCATENATE(C71,"_",D71,"_",E71) -> CL_82_ | C71: CL | D71: 82 | F71: Rancho La Cuchilla | G71: =IF(E71=0,CONCATENATE(F71," No. ",D71),CONCATENATE(F71," No. ",D71,", ",E71)) -> Rancho La Cuchilla No. 82 | H71: Cuchi 82 C.E | I71: Cruz | J71: 300
A72: 67 | B72: =CONCATENATE(C72,"_",D72,"_",E72) -> CL_83_ | C72: CL | D72: 83 | F72: Rancho La Cuchilla | G72: =IF(E72=0,CONCATENATE(F72," No. ",D72),CONCATENATE(F72," No. ",D72,", ",E72)) -> Rancho La Cuchilla No. 83 | H72: Cuch 83 | I72: Barradas | J72: 300
A73: 68 | B73: =CONCATENATE(C73,"_",D73,"_",E73) -> CL_86_ | C73: CL | D73: 86 | F73: Rancho La Cuchilla | G73: =IF(E73=0,CONCATENATE(F73," No. ",D73),CONCATENATE(F73," No. ",D73,", ",E73)) -> Rancho La Cuchilla No. 86 | H73: Cuch 86 | I73: Del Villar | J73: 300
A74: 69 | B74: =CONCATENATE(C74,"_",D74,"_",E74) -> CL_87_ | C74: CL | D74: 87 | F74: Rancho La Cuchilla | G74: =IF(E74=0,CONCATENATE(F74," No. ",D74),CONCATENATE(F74," No. ",D74,", ",E74)) -> Rancho La Cuchilla No. 87 | H74: Cuch 87 C.E | I74: Villanueva S. | J74: 300
A75: 70 | B75: =CONCATENATE(C75,"_",D75,"_",E75) -> CL_88_ | C75: CL | D75: 88 | F75: Rancho La Cuchilla | G75: =IF(E75=0,CONCATENATE(F75," No. ",D75),CONCATENATE(F75," No. ",D75,", ",E75)) -> Rancho La Cuchilla No. 88 | J75: 300 | K75: Agregado el 14JUN13. BS
A76: 71 | B76: =CONCATENATE(C76,"_",D76,"_",E76) -> CL_89_ | C76: CL | D76: 89 | F76: Rancho La Cuchilla | G76: =IF(E76=0,CONCATENATE(F76," No. ",D76),CONCATENATE(F76," No. ",D76,", ",E76)) -> Rancho La Cuchilla No. 89 | H76: Cuch 89 C.E | I76: Gálvez | J76: 300
A77: 72 | B77: =CONCATENATE(C77,"_",D77,"_",E77) -> CL_90_ | C77: CL | D77: 90 | F77: Rancho La Cuchilla | G77: =IF(E77=0,CONCATENATE(F77," No. ",D77),CONCATENATE(F77," No. ",D77,", ",E77)) -> Rancho La Cuchilla No. 90 | H77: Cuch 90 C.E | I77: Porras Fuentes | J77: 150
A78: 73 | B78: =CONCATENATE(C78,"_",D78,"_",E78) -> CL_91_ | C78: CL | D78: 91 | F78: Rancho La Cuchilla | G78: =IF(E78=0,CONCATENATE(F78," No. ",D78),CONCATENATE(F78," No. ",D78,", ",E78)) -> Rancho La Cuchilla No. 91 | H78: Cuch 91 C.E. | I78: Roldán Flores | J78: 300
A79: 74 | B79: =CONCATENATE(C79,"_",D79,"_",E79) -> CL_92_ | C79: CL | D79: 92 | F79: Rancho La Cuchilla | G79: =IF(E79=0,CONCATENATE(F79," No. ",D79),CONCATENATE(F79," No. ",D79,", ",E79)) -> Rancho La Cuchilla No. 92 | H79: Cuch 92 C.E. | I79: Cabrera | J79: 300
A80: 75 | B80: =CONCATENATE(C80,"_",D80,"_",E80) -> CL_93_ | C80: CL | D80: 93 | F80: Rancho La Cuchilla | G80: =IF(E80=0,CONCATENATE(F80," No. ",D80),CONCATENATE(F80," No. ",D80,", ",E80)) -> Rancho La Cuchilla No. 93 | H80: Cuch 93 C.E. | I80: Alcántara Silva | J80: 300
A81: 76 | B81: =CONCATENATE(C81,"_",D81,"_",E81) -> CL_94_ | C81: CL | D81: 94 | F81: Rancho La Cuchilla | G81: =IF(E81=0,CONCATENATE(F81," No. ",D81),CONCATENATE(F81," No. ",D81,", ",E81)) -> Rancho La Cuchilla No. 94 | H81: Cuch 94 C.E | I81: Sánchez Márquez | J81: 300
A82: 77 | B82: =CONCATENATE(C82,"_",D82,"_",E82) -> CL_95_ | C82: CL | D82: 95 | F82: Rancho La Cuchilla | G82: =IF(E82=0,CONCATENATE(F82," No. ",D82),CONCATENATE(F82," No. ",D82,", ",E82)) -> Rancho La Cuchilla No. 95 | H82: Cuchil 95 | I82: Gutiérrez Sánchez | J82: 300
A83: 78 | B83: =CONCATENATE(C83,"_",D83,"_",E83) -> CL_96_ | C83: CL | D83: 96 | F83: Rancho La Cuchilla | G83: =IF(E83=0,CONCATENATE(F83," No. ",D83),CONCATENATE(F83," No. ",D83,", ",E83)) -> Rancho La Cuchilla No. 96 | H83: Cuchil 96 | I83: Valdez Álvarez | J83: 300
A84: 79 | B84: =CONCATENATE(C84,"_",D84,"_",E84) -> CL_97_ | C84: CL | D84: 97 | F84: Rancho La Cuchilla | G84: =IF(E84=0,CONCATENATE(F84," No. ",D84),CONCATENATE(F84," No. ",D84,", ",E84)) -> Rancho La Cuchilla No. 97 | H84: Cuchi 97 | I84: López Ruiz | J84: 300
A85: 80 | B85: =CONCATENATE(C85,"_",D85,"_",E85) -> CL_101_ | C85: CL | D85: 101 | F85: Rancho La Cuchilla | G85: =IF(E85=0,CONCATENATE(F85," No. ",D85),CONCATENATE(F85," No. ",D85,", ",E85)) -> Rancho La Cuchilla No. 101 | H85: Cuchi 101 | I85: Rodríguez Ramírez | J85: 300
A86: 81 | B86: =CONCATENATE(C86,"_",D86,"_",E86) -> CL_107_ | C86: CL | D86: 107 | F86: Rancho La Cuchilla | G86: =IF(E86=0,CONCATENATE(F86," No. ",D86),CONCATENATE(F86," No. ",D86,", ",E86)) -> Rancho La Cuchilla No. 107 | H86: CuC 107 C.E | I86: Olivares Rivera | J86: 300
A87: 82 | B87: =CONCATENATE(C87,"_",D87,"_",E87) -> CL_110_ | C87: CL | D87: 110 | F87: Rancho La Cuchilla | G87: =IF(E87=0,CONCATENATE(F87," No. ",D87),CONCATENATE(F87," No. ",D87,", ",E87)) -> Rancho La Cuchilla No. 110 | H87: Cuch 110 C.E | I87: Domínguez Canudas | J87: 300
A88: 83 | B88: =CONCATENATE(C88,"_",D88,"_",E88) -> CL_111_ | C88: CL | D88: 111 | F88: Rancho La Cuchilla | G88: =IF(E88=0,CONCATENATE(F88," No. ",D88),CONCATENATE(F88," No. ",D88,", ",E88)) -> Rancho La Cuchilla No. 111 | H88: Cuch 111 C.E | I88: García Santos Ofelia | J88: 150
A89: 84 | B89: =CONCATENATE(C89,"_",D89,"_",E89) -> CL_112_PA | C89: CL | D89: 112 | E89: PA | F89: Rancho La Cuchilla | G89: =IF(E89=0,CONCATENATE(F89," No. ",D89),CONCATENATE(F89," No. ",D89,", ",E89)) -> Rancho La Cuchilla No. 112, PA | H89: Cuch 112 Planta Alta | I89: Villalpando Pineda | J89: 150
A90: 85 | B90: =CONCATENATE(C90,"_",D90,"_",E90) -> CL_112_PB | C90: CL | D90: 112 | E90: PB | F90: Rancho La Cuchilla | G90: =IF(E90=0,CONCATENATE(F90," No. ",D90),CONCATENATE(F90," No. ",D90,", ",E90)) -> Rancho La Cuchilla No. 112, PB | H90: Cuch 112 P.B | I90: Soreque | J90: 150
A91: 86 | B91: =CONCATENATE(C91,"_",D91,"_",E91) -> CL_115_ | C91: CL | D91: 115 | F91: Rancho La Cuchilla | G91: =IF(E91=0,CONCATENATE(F91," No. ",D91),CONCATENATE(F91," No. ",D91,", ",E91)) -> Rancho La Cuchilla No. 115 | H91: Cuchi 115 | I91: Alfaro | J91: 300
A92: 87 | B92: =CONCATENATE(C92,"_",D92,"_",E92) -> CL_116_ | C92: CL | D92: 116 | F92: Rancho La Cuchilla | G92: =IF(E92=0,CONCATENATE(F92," No. ",D92),CONCATENATE(F92," No. ",D92,", ",E92)) -> Rancho La Cuchilla No. 116 | H92: Cuchi 116 | I92: Miranda | J92: 300
A93: 88 | B93: =CONCATENATE(C93,"_",D93,"_",E93) -> CL_117_ | C93: CL | D93: 117 | F93: Rancho La Cuchilla | G93: =IF(E93=0,CONCATENATE(F93," No. ",D93),CONCATENATE(F93," No. ",D93,", ",E93)) -> Rancho La Cuchilla No. 117 | H93: Cuch 117 C.E | I93: Gómez | J93: 300
A94: 89 | B94: =CONCATENATE(C94,"_",D94,"_",E94) -> CL_118_ | C94: CL | D94: 118 | F94: Rancho La Cuchilla | G94: =IF(E94=0,CONCATENATE(F94," No. ",D94),CONCATENATE(F94," No. ",D94,", ",E94)) -> Rancho La Cuchilla No. 118 | H94: Cuchill 118 | I94: Astorga Ruiz | J94: 300
A95: 90 | B95: =CONCATENATE(C95,"_",D95,"_",E95) -> CL_119_ | C95: CL | D95: 119 | F95: Rancho La Cuchilla | G95: =IF(E95=0,CONCATENATE(F95," No. ",D95),CONCATENATE(F95," No. ",D95,", ",E95)) -> Rancho La Cuchilla No. 119 | H95: Cuchill 119 | I95: Vilchis | J95: 300
A96: 91 | B96: =CONCATENATE(C96,"_",D96,"_",E96) -> CL_120_ | C96: CL | D96: 120 | F96: Rancho La Cuchilla | G96: =IF(E96=0,CONCATENATE(F96," No. ",D96),CONCATENATE(F96," No. ",D96,", ",E96)) -> Rancho La Cuchilla No. 120 | H96: Cuch 120 C.E | I96: Pozos Vilchis | J96: 300
A97: 92 | B97: =CONCATENATE(C97,"_",D97,"_",E97) -> CL_121_ | C97: CL | D97: 121 | F97: Rancho La Cuchilla | G97: =IF(E97=0,CONCATENATE(F97," No. ",D97),CONCATENATE(F97," No. ",D97,", ",E97)) -> Rancho La Cuchilla No. 121 | H97: Cuch 121 C.E | I97: Ramírez Márquez | J97: 300
A98: 93 | B98: =CONCATENATE(C98,"_",D98,"_",E98) -> CL_122_ | C98: CL | D98: 122 | F98: Rancho La Cuchilla | G98: =IF(E98=0,CONCATENATE(F98," No. ",D98),CONCATENATE(F98," No. ",D98,", ",E98)) -> Rancho La Cuchilla No. 122 | H98: Cuchi 122 | I98: Mendoza | J98: 300
A99: 94 | B99: =CONCATENATE(C99,"_",D99,"_",E99) -> CL_125_ | C99: CL | D99: 125 | F99: Rancho La Cuchilla | G99: =IF(E99=0,CONCATENATE(F99," No. ",D99),CONCATENATE(F99," No. ",D99,", ",E99)) -> Rancho La Cuchilla No. 125 | H99: Cuch 125 | I99: Ordoñez Villalpando | J99: 300
A100: 95 | B100: =CONCATENATE(C100,"_",D100,"_",E100) -> CL_127_ | C100: CL | D100: 127 | F100: Rancho La Cuchilla | G100: =IF(E100=0,CONCATENATE(F100," No. ",D100),CONCATENATE(F100," No. ",D100,", ",E100)) -> Rancho La Cuchilla No. 127 | H100: Cuchi 127 C.E | I100: Quiñones | J100: 300
A101: 96 | B101: =CONCATENATE(C101,"_",D101,"_",E101) -> CL_129_ | C101: CL | D101: 129 | F101: Rancho La Cuchilla | G101: =IF(E101=0,CONCATENATE(F101," No. ",D101),CONCATENATE(F101," No. ",D101,", ",E101)) -> Rancho La Cuchilla No. 129 | H101: Cuchi 129 | I101: Gamboa Rueda | J101: 200
A102: 97 | B102: =CONCATENATE(C102,"_",D102,"_",E102) -> CL_130_ | C102: CL | D102: 130 | F102: Rancho La Cuchilla | G102: =IF(E102=0,CONCATENATE(F102," No. ",D102),CONCATENATE(F102," No. ",D102,", ",E102)) -> Rancho La Cuchilla No. 130 | H102: Cuch 130 C.E | I102: De la Huerta | J102: 300
... A107: 102 | B107: =CONCATENATE(C107,"_",D107,"_",E107) -> CL_135_ | C107: CL | D107: 135 | F107: Rancho La Cuchilla | G107: =IF(E107=0,CONCATENATE(F107," No. ",D107),CONCATENATE(F107," No. ",D107,", ",E107)) -> Rancho La Cuchilla No. 135 | H107: Cuchi 135 | I107: Ruiz | J107: 300
...

Sheet recibos
H1: =SUBTOTAL(9,H5:H2054) -> 796280.71
B2: 1 | C2: 2 | D2: 3 | E2: 4 | F2: 5 | G2: 6 | H2: 7 | I2: 8 | J2: 9 | K2: 10 | L2: 11 | M2: 12 | N2: 13 | O2: 14 | P2: 15 | Q2: 16 | R2: 17 | S2: 18 | T2: 19 | U2: 20 | V2: 21 | W2: 22 | X2: 23 | Y2: 24 | Z2: 25 | AA2: 26 | AB2: 27 | AC2: 28 | AD2: 29 | AE2: 30 | AF2: 31 | AG2: 32 | AH2: 33 | AI2: 34 | AJ2: 35 | AK2: 36 | AL2: 64
K3: 2012 | X3: 2013
A4: CALLE | B4: NÚMERO | C4: CASA | D4: DOMICILIO | E4: FAMILIA | F4: CUOTA | G4: C_ING | H4: IMPORTE | I4: FECHA | J4: CHK | K4: ENE | L4: FEB | M4: MAR | N4: ABR | O4: MAY | P4: JUN | Q4: JUL | R4: AGO | S4: SEP | T4: OCT | U4: NOV | V4: DIC | W4: 2012 | X4: ENE | Y4: FEB | Z4: MAR | AA4: ABR | AB4: MAY | AC4: JUN | AD4: JUL | AE4: AGO | AF4: SEP | AG4: OCT | AH4: NOV | AI4: DIC | AJ4: 2013 | AK4: OBSERVACIONES
A5: Rancho Upácuaro | B5: 3698 | C5: UP_32_ | D5: Rancho Upácuaro No. 32 | E5: Sairafi Carmen | F5: 300 | G5: 1 | H5: 300 | I5: 41245 | J5: =IF(OR(G5<>1,SUM(W5,AJ5)=H5),"ok","error") -> ok | V5: 300 | W5: =SUM(K5:V5) -> 300 | AJ5: =SUM(X5:AI5) -> 0 | AL5: ok
A6: Rancho Upácuaro | B6: 3699 | C6: UP_118_ | D6: Rancho Upácuaro No. 118 | E6: Siegrist | F6: 300 | G6: 1 | H6: 600 | I6: 41245 | J6: =IF(OR(G6<>1,SUM(W6,AJ6)=H6),"ok","error") -> ok | U6: 300 | V6: 300 | W6: =SUM(K6:V6) -> 600 | AJ6: =SUM(X6:AI6) -> 0 | AL6: ok
A7: Rancho Estanzuela | B7: 3700 | C7: EZ_115_ | D7: Rancho Estanzuela No. 115 | E7: Frías Solórzano | F7: 200 | G7: 1 | H7: 400 | I7: 41245 | J7: =IF(OR(G7<>1,SUM(W7,AJ7)=H7),"ok","error") -> ok | U7: 200 | V7: 200 | W7: =SUM(K7:V7) -> 400 | AJ7: =SUM(X7:AI7) -> 0 | AL7: ok
A8: Rancho Landero | B8: 3701 | C8: LD_31_ | D8: Rancho Landero No. 31 | E8: Díaz Hernández | F8: 200 | G8: 1 | H8: 200 | I8: 41245 | J8: =IF(OR(G8<>1,SUM(W8,AJ8)=H8),"ok","error") -> ok | V8: 200 | W8: =SUM(K8:V8) -> 200 | AJ8: =SUM(X8:AI8) -> 0 | AL8: ok
A9: Rancho Landero | B9: 3702 | C9: LD_24_ | D9: Rancho Landero No. 24 | E9: Vázquez Peralta | F9: 300 | G9: 1 | H9: 300 | I9: 41245 | J9: =IF(OR(G9<>1,SUM(W9,AJ9)=H9),"ok","error") -> ok | V9: 300 | W9: =SUM(K9:V9) -> 300 | AJ9: =SUM(X9:AI9) -> 0 | AL9: ok
A10: Rancho Upácuaro | B10: 3703 | C10: UP_142_ | D10: Rancho Upácuaro No. 142 | E10: Fierro Villaneda | F10: 300 | G10: 1 | H10: 300 | I10: 41245 | J10: =IF(OR(G10<>1,SUM(W10,AJ10)=H10),"ok","error") -> ok | V10: 300 | W10: =SUM(K10:V10) -> 300 | AJ10: =SUM(X10:AI10) -> 0 | AL10: ok
A11: Rancho Estanzuela | B11: 3704 | C11: EZ_161_1 | D11: Rancho Estanzuela No. 161, 1 | E11: Guevara | F11: 150 | G11: 1 | H11: 450 | I11: 41245 | J11: =IF(OR(G11<>1,SUM(W11,AJ11)=H11),"ok","error") -> ok | S11: 150 | T11: 150 | U11: 150 | W11: =SUM(K11:V11) -> 450 | AJ11: =SUM(X11:AI11) -> 0 | AL11: ok
A12: Rancho Zinamba | B12: 3705 | C12: ZB_34_ | D12: Rancho Zinamba No. 34 | E12: Torres Zavala | F12: 300 | G12: 1 | H12: 300 | I12: 41244 | J12: =IF(OR(G12<>1,SUM(W12,AJ12)=H12),"ok","error") -> ok | V12: 300 | W12: =SUM(K12:V12) -> 300 | AJ12: =SUM(X12:AI12) -> 0 | AL12: ok
A13: Rancho Zinamba | B13: 3705 | C13: ZB_34_ | D13: Rancho Zinamba No. 34 | E13: Torres Zavala | F13: 300 | G13: 4 | H13: 160 | I13: 41244 | J13: =IF(OR(G13<>1,SUM(W13,AJ13)=H13),"ok","error") -> ok | W13: =SUM(K13:V13) -> 0 | AJ13: =SUM(X13:AI13) -> 0 | AL13: error
A14: Rancho Upácuaro | B14: 3706 | C14: UP_106_ | D14: Rancho Upácuaro No. 106 | E14: Hernández Sánchez | F14: 300 | G14: 1 | H14: 900 | I14: 41246 | J14: =IF(OR(G14<>1,SUM(W14,AJ14)=H14),"ok","error") -> ok | T14: 300 | U14: 300 | V14: 300 | W14: =SUM(K14:V14) -> 900 | AJ14: =SUM(X14:AI14) -> 0 | AL14: ok
A15: Rancho Upácuaro | B15: 3707 | C15: UP_30_ | D15: Rancho Upácuaro No. 30 | E15: Dorantes | F15: 300 | G15: 1 | H15: 300 | I15: 41244 | J15: =IF(OR(G15<>1,SUM(W15,AJ15)=H15),"ok","error") -> ok | V15: 300 | W15: =SUM(K15:V15) -> 300 | AJ15: =SUM(X15:AI15) -> 0 | AL15: ok
A16: Rancho Upácuaro | B16: 3707 | C16: UP_30_ | D16: Rancho Upácuaro No. 30 | E16: Dorantes | F16: 300 | G16: 4 | H16: 160 | I16: 41244 | J16: =IF(OR(G16<>1,SUM(W16,AJ16)=H16),"ok","error") -> ok | W16: =SUM(K16:V16) -> 0 | AJ16: =SUM(X16:AI16) -> 0 | AL16: error
A17: Rancho Upácuaro | B17: 3708 | C17: UP_106_ | D17: Rancho Upácuaro No. 106 | E17: Hernández Sánchez | F17: 300 | G17: 5 | H17: 40 | I17: 41244 | J17: =IF(OR(G17<>1,SUM(W17,AJ17)=H17),"ok","error") -> ok | W17: =SUM(K17:V17) -> 0 | AJ17: =SUM(X17:AI17) -> 0 | AL17: error
A18: Rancho Estanzuela | B18: 3709 | C18: EZ_9_A | D18: Rancho Estanzuela No. 9, A | E18: Castañeda | F18: 100 | G18: 1 | H18: 400 | I18: 41244 | J18: =IF(OR(G18<>1,SUM(W18,AJ18)=H18),"ok","error") -> ok | S18: 100 | T18: 100 | U18: 100 | V18: 100 | W18: =SUM(K18:V18) -> 400 | AJ18: =SUM(X18:AI18) -> 0 | AL18: ok
A19: Rancho Landero | B19: 3710 | C19: LD_20_ | D19: Rancho Landero No. 20 | E19: Velasco | F19: 300 | G19: 1 | H19: 900 | I19: 41244 | J19: =IF(OR(G19<>1,SUM(W19,AJ19)=H19),"ok","error") -> ok | R19: 300 | S19: 300 | T19: 300 | W19: =SUM(K19:V19) -> 900 | AJ19: =SUM(X19:AI19) -> 0 | AL19: ok
A20: Rancho Romeral | B20: 3711 | C20: RM_9_A | D20: Rancho Romeral No. 9, A | E20: Quiñones Hernández | F20: 300 | G20: 1 | H20: 600 | I20: 41244 | J20: =IF(OR(G20<>1,SUM(W20,AJ20)=H20),"ok","error") -> ok | U20: 300 | V20: 300 | W20: =SUM(K20:V20) -> 600 | AJ20: =SUM(X20:AI20) -> 0 | AL20: ok
A21: Rancho Upácuaro | B21: 3712 | C21: UP_110_ | D21: Rancho Upácuaro No. 110 | E21: Ruiz Mijangos | F21: 300 | G21: 1 | H21: 300 | I21: 41244 | J21: =IF(OR(G21<>1,SUM(W21,AJ21)=H21),"ok","error") -> ok | V21: 300 | W21: =SUM(K21:V21) -> 300 | AJ21: =SUM(X21:AI21) -> 0 | AL21: ok
A22: Rancho Upácuaro | B22: 3713 | C22: UP_114_ | D22: Rancho Upácuaro No. 114 | E22: Hernández Cornejo | F22: 300 | G22: 1 | H22: 300 | I22: 41244 | J22: =IF(OR(G22<>1,SUM(W22,AJ22)=H22),"ok","error") -> ok | V22: 300 | W22: =SUM(K22:V22) -> 300 | AJ22: =SUM(X22:AI22) -> 0 | AL22: ok
A23: Rancho Upácuaro | B23: 3714 | C23: UP_93_ | D23: Rancho Upácuaro No. 93 | E23: Valdés | F23: 300 | G23: 1 | H23: 300 | I23: 41244 | J23: =IF(OR(G23<>1,SUM(W23,AJ23)=H23),"ok","error") -> ok | V23: 300 | W23: =SUM(K23:V23) -> 300 | AJ23: =SUM(X23:AI23) -> 0 | AL23: ok
A24: Rancho Upácuaro | B24: 3715 | C24: UP_76_ | D24: Rancho Upácuaro No. 76 | E24: Ruiz de San Pedro | F24: 300 | G24: 1 | H24: 300 | I24: 41244 | J24: =IF(OR(G24<>1,SUM(W24,AJ24)=H24),"ok","error") -> ok | V24: 300 | W24: =SUM(K24:V24) -> 300 | AJ24: =SUM(X24:AI24) -> 0 | AL24: ok
A25: Rancho La Cuchilla | B25: 3716 | C25: CL_71_ | D25: Rancho La Cuchilla No. 71 | E25: Pulido | F25: 300 | G25: 1 | H25: 300 | I25: 41245 | J25: =IF(OR(G25<>1,SUM(W25,AJ25)=H25),"ok","error") -> ok | V25: 300 | W25: =SUM(K25:V25) -> 300 | AJ25: =SUM(X25:AI25) -> 0 | AL25: ok
A26: Rancho La Cuchilla | B26: 3717 | C26: CL_7_202 | D26: Rancho La Cuchilla No. 7, 202 | E26: Carbajal Zayas | F26: 100 | G26: 1 | H26: 400 | I26: 41244 | J26: =IF(OR(G26<>1,SUM(W26,AJ26)=H26),"ok","error") -> ok | S26: 100 | T26: 100 | U26: 100 | V26: 100 | W26: =SUM(K26:V26) -> 400 | AJ26: =SUM(X26:AI26) -> 0 | AL26: ok
A27: Rancho Upácuaro | B27: 3718 | C27: UP_85_ | D27: Rancho Upácuaro No. 85 | E27: Del Toro Huerta | F27: 300 | G27: 1 | H27: 300 | I27: 41244 | J27: =IF(OR(G27<>1,SUM(W27,AJ27)=H27),"ok","error") -> ok | V27: 300 | W27: =SUM(K27:V27) -> 300 | AJ27: =SUM(X27:AI27) -> 0 | AL27: ok
A28: Rancho Upácuaro | B28: 3719 | C28: UP_85_ | D28: Rancho Upácuaro No. 85 | E28: Del Toro Huerta | F28: 300 | G28: 2 | H28: 300 | I28: 41244 | J28: =IF(OR(G28<>1,SUM(W28,AJ28)=H28),"ok","error") -> ok | W28: =SUM(K28:V28) -> 0 | AJ28: =SUM(X28:AI28) -> 0 | AL28: error
A29: Rancho La Cuchilla | B29: 3720 | C29: CL_89_ | D29: Rancho La Cuchilla No. 89 | E29: Gálvez | F29: 300 | G29: 1 | H29: 300 | I29: 41244 | J29: =IF(OR(G29<>1,SUM(W29,AJ29)=H29),"ok","error") -> ok | V29: 300 | W29: =SUM(K29:V29) -> 300 | AJ29: =SUM(X29:AI29) -> 0 | AL29: ok
A30: Rancho Recoveco | B30: 3721 | C30: RV_175_0 | D30: Rancho Recoveco No. 175 | E30: Ramírez | F30: 300 | G30: 1 | H30: 300 | I30: 41244 | J30: =IF(OR(G30<>1,SUM(W30,AJ30)=H30),"ok","error") -> ok | V30: 300 | W30: =SUM(K30:V30) -> 300 | AJ30: =SUM(X30:AI30) -> 0 | AL30: ok
A31: Rancho Landero | B31: 3722 | C31: LD_42_ | D31: Rancho Landero No. 42 | E31: Ávila Fidel | F31: 300 | G31: 1 | H31: 300 | I31: 41244 | J31: =IF(OR(G31<>1,SUM(W31,AJ31)=H31),"ok","error") -> ok | V31: 300 | W31: =SUM(K31:V31) -> 300 | AJ31: =SUM(X31:AI31) -> 0 | AL31: ok
A32: Rancho Landero | B32: 3723 | C32: LD_21_ | D32: Rancho Landero No. 21 | E32: Meza | F32: 300 | G32: 1 | H32: 300 | I32: 41244 | J32: =IF(OR(G32<>1,SUM(W32,AJ32)=H32),"ok","error") -> ok | V32: 300 | W32: =SUM(K32:V32) -> 300 | AJ32: =SUM(X32:AI32) -> 0 | AL32: ok
A33: Rancho Landero | B33: 3724 | C33: LD_21_ | D33: Rancho Landero No. 21 | E33: Meza | F33: 300 | G33: 2 | H33: 300 | I33: 41244 | J33: =IF(OR(G33<>1,SUM(W33,AJ33)=H33),"ok","error") -> ok | W33: =SUM(K33:V33) -> 0 | AJ33: =SUM(X33:AI33) -> 0 | AL33: error
A34: Rancho Estanzuela | B34: 3725 | C34: EZ_89_ | D34: Rancho Estanzuela No. 89 | E34: Romero Ortiz | F34: 300 | G34: 1 | H34: 300 | I34: 41244 | J34: =IF(OR(G34<>1,SUM(W34,AJ34)=H34),"ok","error") -> ok | V34: 300 | W34: =SUM(K34:V34) -> 300 | AJ34: =SUM(X34:AI34) -> 0 | AL34: ok
A35: Rancho Upácuaro | B35: 3726 | C35: UP_18_ | D35: Rancho Upácuaro No. 18 | E35: Guzmán | F35: 300 | G35: 1 | H35: 300 | I35: 41244 | J35: =IF(OR(G35<>1,SUM(W35,AJ35)=H35),"ok","error") -> ok | V35: 300 | W35: =SUM(K35:V35) -> 300 | AJ35: =SUM(X35:AI35) -> 0 | AL35: ok
A36: Rancho Upácuaro | B36: 3727 | C36: UP_108_ | D36: Rancho Upácuaro No. 108 | E36: Mejía | F36: 300 | G36: 1 | H36: 300 | I36: 41244 | J36: =IF(OR(G36<>1,SUM(W36,AJ36)=H36),"ok","error") -> ok | U36: 300 | W36: =SUM(K36:V36) -> 300 | AJ36: =SUM(X36:AI36) -> 0 | AL36: ok
A37: Rancho La Cuchilla | B37: 3728 | C37: CL_53_ | D37: Rancho La Cuchilla No. 53 | E37: Loyo Ochoa | F37: 300 | G37: 1 | H37: 600 | I37: 41244 | J37: =IF(OR(G37<>1,SUM(W37,AJ37)=H37),"ok","error") -> ok | T37: 300 | U37: 300 | W37: =SUM(K37:V37) -> 600 | AJ37: =SUM(X37:AI37) -> 0 | AL37: ok
A38: Rancho Upácuaro | B38: 3729 | C38: UP_87_ | D38: Rancho Upácuaro No. 87 | E38: Rodríguez Parés | F38: 300 | G38: 1 | H38: 300 | I38: 41244 | J38: =IF(OR(G38<>1,SUM(W38,AJ38)=H38),"ok","error") -> ok | V38: 300 | W38: =SUM(K38:V38) -> 300 | AJ38: =SUM(X38:AI38) -> 0 | AL38: ok
A39: Rancho Upácuaro | B39: 3730 | C39: UP_47_ | D39: Rancho Upácuaro No. 47 | E39: Flores Muñoz | F39: 300 | G39: 1 | H39: 600 | I39: 41244 | J39: =IF(OR(G39<>1,SUM(W39,AJ39)=H39),"ok","error") -> ok | U39: 300 | V39: 300 | W39: =SUM(K39:V39) -> 600 | AJ39: =SUM(X39:AI39) -> 0 | AL39: ok
A40: Rancho Upácuaro | B40: 3730 | C40: UP_47_ | D40: Rancho Upácuaro No. 47 | E40: Flores Muñoz | F40: 300 | G40: 2 | H40: 300 | I40: 41244 | J40: =IF(OR(G40<>1,SUM(W40,AJ40)=H40),"ok","error") -> ok | W40: =SUM(K40:V40) -> 0 | AJ40: =SUM(X40:AI40) -> 0 | AL40: error
A41: Rancho Landero | B41: 3731 | C41: LD_93_ | D41: Rancho Landero No. 93 | E41: Ortega López | F41: 300 | G41: 1 | H41: 300 | I41: 41244 | J41: =IF(OR(G41<>1,SUM(W41,AJ41)=H41),"ok","error") -> ok | V41: 300 | W41: =SUM(K41:V41) -> 300 | AJ41: =SUM(X41:AI41) -> 0 | AL41: ok
A42: Rancho Landero | B42: 3731 | C42: LD_93_ | D42: Rancho Landero No. 93 | E42: Ortega López | F42: 300 | G42: 2 | H42: 300 | I42: 41244 | J42: =IF(OR(G42<>1,SUM(W42,AJ42)=H42),"ok","error") -> ok | W42: =SUM(K42:V42) -> 0 | AJ42: =SUM(X42:AI42) -> 0 | AL42: error
A43: Rancho La Cuchilla | B43: 3732 | C43: CL_131_ | D43: Rancho La Cuchilla No. 131 | E43: Cabrera Esc. | F43: 300 | G43: 1 | H43: 300 | I43: 41244 | J43: =IF(OR(G43<>1,SUM(W43,AJ43)=H43),"ok","error") -> ok | V43: 300 | W43: =SUM(K43:V43) -> 300 | AJ43: =SUM(X43:AI43) -> 0 | AL43: ok
A44: Rancho Recoveco | B44: 3733 | C44: RV_197_ | D44: Rancho Recoveco No. 197 | E44: Colín González | F44: 300 | G44: 1 | H44: 300 | I44: 41244 | J44: =IF(OR(G44<>1,SUM(W44,AJ44)=H44),"ok","error") -> ok | V44: 300 | W44: =SUM(K44:V44) -> 300 | AJ44: =SUM(X44:AI44) -> 0 | AL44: ok
A45: Rancho Estanzuela | B45: 3734 | C45: EZ_91_ | D45: Rancho Estanzuela No. 91 | E45: Lobato Torres | F45: 300 | G45: 1 | H45: 900 | I45: 41244 | J45: =IF(OR(G45<>1,SUM(W45,AJ45)=H45),"ok","error") -> ok | T45: 300 | U45: 300 | V45: 300 | W45: =SUM(K45:V45) -> 900 | AJ45: =SUM(X45:AI45) -> 0 | AL45: ok
A46: Rancho Estanzuela | B46: 3734 | C46: EZ_91_ | D46: Rancho Estanzuela No. 91 | E46: Lobato Torres | F46: 300 | G46: 2 | H46: 300 | I46: 41244 | J46: =IF(OR(G46<>1,SUM(W46,AJ46)=H46),"ok","error") -> ok | W46: =SUM(K46:V46) -> 0 | AJ46: =SUM(X46:AI46) -> 0 | AL46: error
A47: Rancho Estanzuela | B47: 3735 | C47: EZ_35_ | D47: Rancho Estanzuela No. 35 | E47: Rodríguez | F47: 300 | G47: 1 | H47: 300 | I47: 41244 | J47: =IF(OR(G47<>1,SUM(W47,AJ47)=H47),"ok","error") -> ok | V47: 300 | W47: =SUM(K47:V47) -> 300 | AJ47: =SUM(X47:AI47) -> 0 | AL47: ok
A48: Rancho La Cuchilla | B48: 3736 | C48: CL_43_B | D48: Rancho La Cuchilla No. 43, B | E48: Luna Albertano | F48: 125 | G48: 1 | H48: 125 | I48: 41245 | J48: =IF(OR(G48<>1,SUM(W48,AJ48)=H48),"ok","error") -> ok | V48: 125 | W48: =SUM(K48:V48) -> 125 | AJ48: =SUM(X48:AI48) -> 0 | AL48: ok
A49: Rancho Landero | B49: 3737 | C49: LD_80_ | D49: Rancho Landero No. 80 | E49: Villaseñor | F49: 300 | G49: 1 | H49: 300 | I49: 41245 | J49: =IF(OR(G49<>1,SUM(W49,AJ49)=H49),"ok","error") -> ok | V49: 300 | W49: =SUM(K49:V49) -> 300 | AJ49: =SUM(X49:AI49) -> 0 | AL49: ok
A50: Rancho Zinamba | B50: 3738 | C50: ZB_68_ | D50: Rancho Zinamba No. 68 | E50: Rivera Villicaña | F50: 300 | G50: 1 | H50: 300 | I50: 41245 | J50: =IF(OR(G50<>1,SUM(W50,AJ50)=H50),"ok","error") -> ok | V50: 300 | W50: =SUM(K50:V50) -> 300 | AJ50: =SUM(X50:AI50) -> 0 | AL50: ok
A51: Rancho Estanzuela | B51: 3739 | C51: EZ_9_B | D51: Rancho Estanzuela No. 9, B | E51: Velasco Rojas | F51: 200 | G51: 1 | H51: 200 | I51: 41245 | J51: =IF(OR(G51<>1,SUM(W51,AJ51)=H51),"ok","error") -> ok | V51: 200 | W51: =SUM(K51:V51) -> 200 | AJ51: =SUM(X51:AI51) -> 0 | AL51: ok
A52: Rancho Estanzuela | B52: 3740 | C52: EZ_9_B | D52: Rancho Estanzuela No. 9, B | E52: Velasco Rojas | F52: 200 | G52: 4 | H52: 160 | I52: 41245 | J52: =IF(OR(G52<>1,SUM(W52,AJ52)=H52),"ok","error") -> ok | W52: =SUM(K52:V52) -> 0 | AJ52: =SUM(X52:AI52) -> 0 | AL52: error
A53: Rancho La Cuchilla | B53: 3741 | C53: CL_40_ | D53: Rancho La Cuchilla No. 40 | E53: López Pico | F53: 300 | G53: 1 | H53: 300 | I53: 41244 | J53: =IF(OR(G53<>1,SUM(W53,AJ53)=H53),"ok","error") -> ok | V53: 300 | W53: =SUM(K53:V53) -> 300 | AJ53: =SUM(X53:AI53) -> 0 | AL53: ok
A54: Rancho Upácuaro | B54: 3742 | C54: UP_120_ | D54: Rancho Upácuaro No. 120 | E54: Rayas Rivera | F54: 300 | G54: 1 | H54: 300 | I54: 41244 | J54: =IF(OR(G54<>1,SUM(W54,AJ54)=H54),"ok","error") -> ok | V54: 300 | W54: =SUM(K54:V54) -> 300 | AJ54: =SUM(X54:AI54) -> 0 | AL54: ok
A55: Rancho Upácuaro | B55: 3743 | C55: UP_24_ | D55: Rancho Upácuaro No. 24 | E55: Parra | F55: 300 | G55: 1 | H55: 900 | I55: 41253 | J55: =IF(OR(G55<>1,SUM(W55,AJ55)=H55),"ok","error") -> ok | Q55: 300 | R55: 300 | S55: 300 | W55: =SUM(K55:V55) -> 900 | AJ55: =SUM(X55:AI55) -> 0 | AL55: ok
A56: Rancho La Cuchilla | B56: 3744 | C56: CL_20_ | D56: Rancho La Cuchilla No. 20 | E56: Sánchez López | F56: 300 | G56: 1 | H56: 300 | I56: 41244 | J56: =IF(OR(G56<>1,SUM(W56,AJ56)=H56),"ok","error") -> ok | V56: 300 | W56: =SUM(K56:V56) -> 300 | AJ56: =SUM(X56:AI56) -> 0 | AL56: ok
A57: Rancho Upácuaro | B57: 3745 | C57: UP_64_ | D57: Rancho Upácuaro No. 64 | E57: Méndez Oliva | F57: 300 | G57: 1 | H57: 300 | I57: 41244 | J57: =IF(OR(G57<>1,SUM(W57,AJ57)=H57),"ok","error") -> ok | V57: 300 | W57: =SUM(K57:V57) -> 300 | AJ57: =SUM(X57:AI57) -> 0 | AL57: ok
A58: Rancho La Cuchilla | B58: 3746 | C58: CL_81_A | D58: Rancho La Cuchilla No. 81, A | E58: Barrientos López | F58: 300 | G58: 1 | H58: 300 | I58: 41244 | J58: =IF(OR(G58<>1,SUM(W58,AJ58)=H58),"ok","error") -> ok | V58: 300 | W58: =SUM(K58:V58) -> 300 | AJ58: =SUM(X58:AI58) -> 0 | AL58: ok
A59: Rancho La Cuchilla | B59: 3747 | C59: CL_33_ | D59: Rancho La Cuchilla No. 33 | E59: Tanús | F59: 300 | G59: 1 | H59: 300 | I59: 41244 | J59: =IF(OR(G59<>1,SUM(W59,AJ59)=H59),"ok","error") -> ok | V59: 300 | W59: =SUM(K59:V59) -> 300 | AJ59: =SUM(X59:AI59) -> 0 | AL59: ok
A60: Rancho La Cuchilla | B60: 3747 | C60: CL_33_ | D60: Rancho La Cuchilla No. 33 | E60: Tanús | F60: 300 | G60: 2 | H60: 300 | I60: 41244 | J60: =IF(OR(G60<>1,SUM(W60,AJ60)=H60),"ok","error") -> ok | W60: =SUM(K60:V60) -> 0 | AJ60: =SUM(X60:AI60) -> 0 | AL60: error
A61: Rancho Estanzuela | B61: 3748 | C61: EZ_61_ | D61: Rancho Estanzuela No. 61 | E61: González Almazán | F61: 300 | G61: 1 | H61: 300 | I61: 41244 | J61: =IF(OR(G61<>1,SUM(W61,AJ61)=H61),"ok","error") -> ok | V61: 300 | W61: =SUM(K61:V61) -> 300 | AJ61: =SUM(X61:AI61) -> 0 | AL61: ok
A62: Rancho Estanzuela | B62: 3748 | C62: EZ_61_ | D62: Rancho Estanzuela No. 61 | E62: González Almazán | F62: 300 | G62: 2 | H62: 300 | I62: 41244 | J62: =IF(OR(G62<>1,SUM(W62,AJ62)=H62),"ok","error") -> ok | W62: =SUM(K62:V62) -> 0 | AJ62: =SUM(X62:AI62) -> 0 | AL62: error
A63: Rancho Estanzuela | B63: 3749 | C63: EZ_31_ | D63: Rancho Estanzuela No. 31 | E63: Chávez Valdés | F63: 300 | G63: 1 | H63: 300 | I63: 41244 | J63: =IF(OR(G63<>1,SUM(W63,AJ63)=H63),"ok","error") -> ok | V63: 300 | W63: =SUM(K63:V63) -> 300 | AJ63: =SUM(X63:AI63) -> 0 | AL63: ok
A64: Rancho Estanzuela | B64: 3750 | C64: EZ_25_ | D64: Rancho Estanzuela No. 25 | E64: Contreras Figueroa | F64: 300 | G64: 1 | H64: 300 | I64: 41245 | J64: =IF(OR(G64<>1,SUM(W64,AJ64)=H64),"ok","error") -> ok | V64: 300 | W64: =SUM(K64:V64) -> 300 | AJ64: =SUM(X64:AI64) -> 0 | AL64: ok
A65: Rancho Upácuaro | B65: 3751 | C65: UP_33_ | D65: Rancho Upácuaro No. 33 | E65: Ulloa Miranda | F65: 300 | G65: 1 | H65: 300 | I65: 41245 | J65: =IF(OR(G65<>1,SUM(W65,AJ65)=H65),"ok","error") -> ok | V65: 300 | W65: =SUM(K65:V65) -> 300 | AJ65: =SUM(X65:AI65) -> 0 | AL65: ok
A66: Rancho Landero | B66: 3752 | C66: LD_91_ | D66: Rancho Landero No. 91 | E66: Llaca | F66: 300 | G66: 1 | H66: 300 | I66: 41244 | J66: =IF(OR(G66<>1,SUM(W66,AJ66)=H66),"ok","error") -> ok | V66: 300 | W66: =SUM(K66:V66) -> 300 | AJ66: =SUM(X66:AI66) -> 0 | AL66: ok
A67: Rancho La Cuchilla | B67: 3753 | C67: CL_46_ | D67: Rancho La Cuchilla No. 46 | E67: Cruz López | F67: 300 | G67: 1 | H67: 600 | I67: 41244 | J67: =IF(OR(G67<>1,SUM(W67,AJ67)=H67),"ok","error") -> ok | U67: 300 | V67: 300 | W67: =SUM(K67:V67) -> 600 | AJ67: =SUM(X67:AI67) -> 0 | AL67: ok
A68: Rancho Landero | B68: 3754 | C68: LD_69_ | D68: Rancho Landero No. 69 | E68: Gómez Ayala | F68: 300 | G68: 1 | H68: 900 | I68: 41245 | J68: =IF(OR(G68<>1,SUM(W68,AJ68)=H68),"ok","error") -> ok | T68: 300 | U68: 300 | V68: 300 | W68: =SUM(K68:V68) -> 900 | AJ68: =SUM(X68:AI68) -> 0 | AL68: ok
A69: Rancho Landero | B69: 3754 | C69: LD_69_ | D69: Rancho Landero No. 69 | E69: Gómez Ayala | F69: 300 | G69: 2 | H69: 300 | I69: 41245 | J69: =IF(OR(G69<>1,SUM(W69,AJ69)=H69),"ok","error") -> ok | W69: =SUM(K69:V69) -> 0 | AJ69: =SUM(X69:AI69) -> 0 | AL69: error
A70: Rancho La Cuchilla | B70: 3755 | C70: CL_87_ | D70: Rancho La Cuchilla No. 87 | E70: Villanueva S. | F70: 300 | G70: 1 | H70: 300 | I70: 41244 | J70: =IF(OR(G70<>1,SUM(W70,AJ70)=H70),"ok","error") -> ok | V70: 300 | W70: =SUM(K70:V70) -> 300 | AJ70: =SUM(X70:AI70) -> 0 | AL70: ok
A71: Rancho La Cuchilla | B71: 3756 | C71: CL_87_ | D71: Rancho La Cuchilla No. 87 | E71: Villanueva S. | F71: 300 | G71: 1 | H71: 300 | I71: 41244 | J71: =IF(OR(G71<>1,SUM(W71,AJ71)=H71),"ok","error") -> ok | U71: 300 | W71: =SUM(K71:V71) -> 300 | AJ71: =SUM(X71:AI71) -> 0 | AL71: ok
A72: Rancho Zinamba | B72: 3757 | C72: ZB_56_ | D72: Rancho Zinamba No. 56 | E72: Aguado | F72: 250 | G72: 2 | H72: 300 | I72: 41244 | J72: =IF(OR(G72<>1,SUM(W72,AJ72)=H72),"ok","error") -> ok | W72: =SUM(K72:V72) -> 0 | AJ72: =SUM(X72:AI72) -> 0 | AL72: error
A73: Rancho Zinamba | B73: 3758 | C73: ZB_56_ | D73: Rancho Zinamba No. 56 | E73: Aguado | F73: 250 | G73: 1 | H73: 250 | I73: 41244 | J73: =IF(OR(G73<>1,SUM(W73,AJ73)=H73),"ok","error") -> ok | V73: 250 | W73: =SUM(K73:V73) -> 250 | AJ73: =SUM(X73:AI73) -> 0 | AL73: ok
A74: Rancho Landero | B74: 3759 | C74: LD_92_ | D74: Rancho Landero No. 92 | E74: Ruiz Velasco | F74: 300 | G74: 1 | H74: 300 | I74: 41244 | J74: =IF(OR(G74<>1,SUM(W74,AJ74)=H74),"ok","error") -> ok | V74: 300 | W74: =SUM(K74:V74) -> 300 | AJ74: =SUM(X74:AI74) -> 0 | AL74: ok
A75: Rancho Landero | B75: 3760 | C75: LD_92_ | D75: Rancho Landero No. 92 | E75: Ruiz Velasco | F75: 300 | G75: 2 | H75: 300 | I75: 41244 | J75: =IF(OR(G75<>1,SUM(W75,AJ75)=H75),"ok","error") -> ok | W75: =SUM(K75:V75) -> 0 | AJ75: =SUM(X75:AI75) -> 0 | AL75: error
A76: Rancho Estanzuela | B76: 3761 | C76: EZ_99_ | D76: Rancho Estanzuela No. 99 | E76: García López | F76: 300 | G76: 1 | H76: 300 | I76: 41244 | J76: =IF(OR(G76<>1,SUM(W76,AJ76)=H76),"ok","error") -> ok | U76: 300 | W76: =SUM(K76:V76) -> 300 | AJ76: =SUM(X76:AI76) -> 0 | AL76: ok
A77: Rancho Landero | B77: 3762 | C77: LD_45_ | D77: Rancho Landero No. 45 | E77: Almazán | F77: 250 | G77: 1 | H77: 250 | I77: 41246 | J77: =IF(OR(G77<>1,SUM(W77,AJ77)=H77),"ok","error") -> ok | V77: 250 | W77: =SUM(K77:V77) -> 250 | AJ77: =SUM(X77:AI77) -> 0 | AL77: ok
A78: Rancho La Cuchilla | B78: 3763 | C78: CL_139_ | D78: Rancho La Cuchilla No. 139 | E78: Gloria García | F78: 200 | G78: 1 | H78: 200 | I78: 41247 | J78: =IF(OR(G78<>1,SUM(W78,AJ78)=H78),"ok","error") -> ok | V78: 200 | W78: =SUM(K78:V78) -> 200 | AJ78: =SUM(X78:AI78) -> 0 | AL78: ok
A79: Rancho Landero | B79: 3764 | C79: LD_85_ | D79: Rancho Landero No. 85 | E79: Martínez Olague | F79: 300 | G79: 1 | H79: 300 | I79: 41247 | J79: =IF(OR(G79<>1,SUM(W79,AJ79)=H79),"ok","error") -> ok | V79: 300 | W79: =SUM(K79:V79) -> 300 | AJ79: =SUM(X79:AI79) -> 0 | AL79: ok
A80: Rancho La Cuchilla | B80: 3765 | C80: CL_19_ | D80: Rancho La Cuchilla No. 19 | E80: Tapia Vázquez | F80: 300 | G80: 1 | H80: 300 | I80: 41247 | J80: =IF(OR(G80<>1,SUM(W80,AJ80)=H80),"ok","error") -> ok | V80: 300 | W80: =SUM(K80:V80) -> 300 | AJ80: =SUM(X80:AI80) -> 0 | AL80: ok
B81: 3766 | G81: 8 | J81: =IF(OR(G81<>1,SUM(W81,AJ81)=H81),"ok","error") -> ok | W81: =SUM(K81:V81) -> 0 | AJ81: =SUM(X81:AI81) -> 0 | AK81: CANCELADO | AL81: ok
A82: Rancho Estanzuela | B82: 3767 | C82: EZ_123_ | D82: Rancho Estanzuela No. 123 | E82: Bueno Rendón | F82: 150 | G82: 1 | H82: 150 | I82: 41248 | J82: =IF(OR(G82<>1,SUM(W82,AJ82)=H82),"ok","error") -> ok | V82: 150 | W82: =SUM(K82:V82) -> 150 | AJ82: =SUM(X82:AI82) -> 0 | AL82: ok
A83: Rancho La Cuchilla | B83: 3768 | C83: CL_15_ | D83: Rancho La Cuchilla No. 15 | E83: Guerrero Ponce | F83: 300 | G83: 3 | H83: 150 | I83: 41249 | J83: =IF(OR(G83<>1,SUM(W83,AJ83)=H83),"ok","error") -> ok | W83: =SUM(K83:V83) -> 0 | AJ83: =SUM(X83:AI83) -> 0 | AL83: error
A84: Rancho La Cuchilla | B84: 3769 | C84: CL_90_ | D84: Rancho La Cuchilla No. 90 | E84: Porras Fuentes | F84: 150 | G84: 1 | H84: 300 | I84: 41249 | J84: =IF(OR(G84<>1,SUM(W84,AJ84)=H84),"ok","error") -> ok | U84: 150 | V84: 150 | W84: =SUM(K84:V84) -> 300 | AJ84: =SUM(X84:AI84) -> 0 | AL84: ok
A85: Rancho La Cuchilla | B85: 3770 | C85: CL_75_ | D85: Rancho La Cuchilla No. 75 | E85: Sosa Lucio | F85: 300 | G85: 1 | H85: 300 | I85: 41249 | J85: =IF(OR(G85<>1,SUM(W85,AJ85)=H85),"ok","error") -> ok | V85: 300 | W85: =SUM(K85:V85) -> 300 | AJ85: =SUM(X85:AI85) -> 0 | AL85: ok
A86: Rancho La Cuchilla | B86: 3770 | C86: CL_75_ | D86: Rancho La Cuchilla No. 75 | E86: Sosa Lucio | F86: 300 | G86: 5 | H86: 40 | I86: 41249 | J86: =IF(OR(G86<>1,SUM(W86,AJ86)=H86),"ok","error") -> ok | W86: =SUM(K86:V86) -> 0 | AJ86: =SUM(X86:AI86) -> 0 | AL86: error
A87: Rancho La Cuchilla | B87: 3770 | C87: CL_75_ | D87: Rancho La Cuchilla No. 75 | E87: Sosa Lucio | F87: 300 | G87: 4 | H87: 160 | I87: 41249 | J87: =IF(OR(G87<>1,SUM(W87,AJ87)=H87),"ok","error") -> ok | W87: =SUM(K87:V87) -> 0 | AJ87: =SUM(X87:AI87) -> 0 | AL87: error
A88: Rancho La Cuchilla | B88: 3771 | C88: CL_90_ | D88: Rancho La Cuchilla No. 90 | E88: Porras Fuentes | F88: 150 | G88: 5 | H88: 40 | I88: 41249 | J88: =IF(OR(G88<>1,SUM(W88,AJ88)=H88),"ok","error") -> ok | W88: =SUM(K88:V88) -> 0 | AJ88: =SUM(X88:AI88) -> 0 | AL88: error
A89: Rancho Landero | B89: 3772 | C89: LD_89_ | D89: Rancho Landero No. 89 | E89: Del Pozo Solís | F89: 300 | G89: 1 | H89: 300 | I89: 41250 | J89: =IF(OR(G89<>1,SUM(W89,AJ89)=H89),"ok","error") -> ok | V89: 300 | W89: =SUM(K89:V89) -> 300 | AJ89: =SUM(X89:AI89) -> 0 | AL89: ok
A90: Rancho Landero | B90: 3773 | C90: LD_40_ | D90: Rancho Landero No. 40 | E90: Almaguer Mireles | F90: 300 | G90: 1 | H90: 1800 | I90: 41250 | J90: =IF(OR(G90<>1,SUM(W90,AJ90)=H90),"ok","error") -> ok | Q90: 300 | R90: 300 | S90: 300 | T90: 300 | U90: 300 | V90: 300 | W90: =SUM(K90:V90) -> 1800 | AJ90: =SUM(X90:AI90) -> 0 | AL90: ok
A91: Rancho Upácuaro | B91: 3774 | C91: UP_65_ | D91: Rancho Upácuaro No. 65 | E91: Olguín | F91: 300 | G91: 1 | H91: 300 | I91: 41252 | J91: =IF(OR(G91<>1,SUM(W91,AJ91)=H91),"ok","error") -> ok | V91: 300 | W91: =SUM(K91:V91) -> 300 | AJ91: =SUM(X91:AI91) -> 0 | AL91: ok
A92: Rancho Upácuaro | B92: 3775 | C92: UP_65_ | D92: Rancho Upácuaro No. 65 | E92: Olguín | F92: 300 | G92: 2 | H92: 300 | I92: 41252 | J92: =IF(OR(G92<>1,SUM(W92,AJ92)=H92),"ok","error") -> ok | W92: =SUM(K92:V92) -> 0 | AJ92: =SUM(X92:AI92) -> 0 | AL92: error
A93: Rancho La Cuchilla | B93: 3776 | C93: CL_77_ | D93: Rancho La Cuchilla No. 77 | E93: Loperena | F93: 300 | G93: 1 | H93: 600 | I93: 41252 | J93: =IF(OR(G93<>1,SUM(W93,AJ93)=H93),"ok","error") -> ok | T93: 300 | U93: 300 | W93: =SUM(K93:V93) -> 600 | AJ93: =SUM(X93:AI93) -> 0 | AL93: ok
A94: Rancho Estanzuela | B94: 3777 | C94: EZ_47_ | D94: Rancho Estanzuela No. 47 | E94: Bussey García | F94: 300 | G94: 1 | H94: 300 | I94: 41252 | J94: =IF(OR(G94<>1,SUM(W94,AJ94)=H94),"ok","error") -> ok | V94: 300 | W94: =SUM(K94:V94) -> 300 | AJ94: =SUM(X94:AI94) -> 0 | AL94: ok
A95: Rancho Zinamba | B95: 3778 | C95: ZB_26_ | D95: Rancho Zinamba No. 26 | E95: Ayala | F95: 300 | G95: 1 | H95: 300 | I95: 41252 | J95: =IF(OR(G95<>1,SUM(W95,AJ95)=H95),"ok","error") -> ok | V95: 300 | W95: =SUM(K95:V95) -> 300 | AJ95: =SUM(X95:AI95) -> 0 | AL95: ok
A96: Rancho Zinamba | B96: 3778 | C96: ZB_26_ | D96: Rancho Zinamba No. 26 | E96: Ayala | F96: 300 | G96: 3 | H96: 150 | I96: 41252 | J96: =IF(OR(G96<>1,SUM(W96,AJ96)=H96),"ok","error") -> ok | W96: =SUM(K96:V96) -> 0 | AJ96: =SUM(X96:AI96) -> 0 | AL96: error
A97: Rancho Landero | B97: 3779 | C97: LD_38_ | D97: Rancho Landero No. 38 | E97: Sánchez Peña | F97: 300 | G97: 1 | H97: 300 | I97: 41252 | J97: =IF(OR(G97<>1,SUM(W97,AJ97)=H97),"ok","error") -> ok | V97: 300 | W97: =SUM(K97:V97) -> 300 | AJ97: =SUM(X97:AI97) -> 0 | AL97: ok
A98: Rancho Landero | B98: 3780 | C98: LD_38_ | D98: Rancho Landero No. 38 | E98: Sánchez Peña | F98: 300 | G98: 2 | H98: 200 | I98: 41252 | J98: =IF(OR(G98<>1,SUM(W98,AJ98)=H98),"ok","error") -> ok | W98: =SUM(K98:V98) -> 0 | AJ98: =SUM(X98:AI98) -> 0 | AL98: error
A99: Rancho Estanzuela | B99: 3781 | C99: EZ_119_2 | D99: Rancho Estanzuela No. 119, 2 | E99: García Medina | F99: 300 | G99: 3 | H99: 150 | I99: 41252 | J99: =IF(OR(G99<>1,SUM(W99,AJ99)=H99),"ok","error") -> ok | W99: =SUM(K99:V99) -> 0 | AJ99: =SUM(X99:AI99) -> 0 | AL99: error
A100: Rancho Recoveco | B100: 3782 | C100: RV_173_ | D100: Rancho Recoveco No. 173 | E100: Velarde | F100: 300 | G100: 2 | H100: 2200 | I100: 41252 | J100: =IF(OR(G100<>1,SUM(W100,AJ100)=H100),"ok","error") -> ok | W100: =SUM(K100:V100) -> 0 | AJ100: =SUM(X100:AI100) -> 0 | AL100: error
...

Sheet criterios
D1: Casas / código de cobranza
A2: Calles | D2: CASA | E2: C_ING | F2: CASA | G2: C_ING | H2: CASA | I2: C_ING | J2: CASA | K2: C_ING | L2: CASA | M2: C_ING | N2: CASA | O2: C_ING | P2: CASA | Q2: C_ING | R2: CASA | S2: C_ING | T2: CASA | U2: C_ING | V2: CASA | W2: C_ING | X2: CASA | Y2: C_ING | Z2: CASA | AA2: C_ING | AB2: CASA | AC2: C_ING | AD2: CASA | AE2: C_ING | AF2: CASA | AG2: C_ING | AH2: CASA | AI2: C_ING | AJ2: CASA | AK2: C_ING | AL2: CASA | AM2: C_ING | AN2: CASA | AO2: C_ING | AP2: CASA | AQ2: C_ING | AR2: CASA | AS2: C_ING | AT2: CASA | AU2: C_ING | AV2: CASA | AW2: C_ING | AX2: CASA | AY2: C_ING | AZ2: CASA | BA2: C_ING | BB2: CASA | BC2: C_ING | BD2: CASA | BE2: C_ING | BF2: CASA | BG2: C_ING | BH2: CASA | BI2: C_ING | BJ2: CASA | BK2: C_ING | BL2: CASA | BM2: C_ING | BN2: CASA | BO2: C_ING | BP2: CASA | BQ2: C_ING | BR2: CASA | BS2: C_ING | BT2: CASA | BU2: C_ING | BV2: CASA | BW2: C_ING | BX2: CASA | BY2: C_ING | BZ2: CASA | CA2: C_ING | CB2: CASA | CC2: C_ING | CD2: CASA | CE2: C_ING | CF2: CASA | CG2: C_ING | CH2: CASA | CI2: C_ING | CJ2: CASA | CK2: C_ING | CL2: CASA | CM2: C_ING | CN2: CASA | CO2: C_ING | CP2: CASA | CQ2: C_ING | CR2: CASA | CS2: C_ING | CT2: CASA | CU2: C_ING | CV2: CASA | CW2: C_ING | CX2: CASA | CY2: C_ING | CZ2: CASA | DA2: C_ING | DB2: CASA | DC2: C_ING | DD2: CASA | DE2: C_ING | DF2: CASA | DG2: C_ING | DH2: CASA | DI2: C_ING | DJ2: CASA | DK2: C_ING | DL2: CASA | DM2: C_ING | DN2: CASA | DO2: C_ING | DP2: CASA | DQ2: C_ING | DR2: CASA | DS2: C_ING | DT2: CASA | DU2: C_ING | DV2: CASA | DW2: C_ING | DX2: CASA | DY2: C_ING | DZ2: CASA | EA2: C_ING | EB2: CASA | EC2: C_ING | ED2: CASA | EE2: C_ING | EF2: CASA | EG2: C_ING | EH2: CASA | EI2: C_ING | EJ2: CASA | EK2: C_ING | EL2: CASA | EM2: C_ING | EN2: CASA | EO2: C_ING | EP2: CASA | EQ2: C_ING | ER2: CASA | ES2: C_ING | ET2: CASA | EU2: C_ING | EV2: CASA | EW2: C_ING | EX2: CASA | EY2: C_ING | EZ2: CASA | FA2: C_ING | FB2: CASA | FC2: C_ING | FD2: CASA | FE2: C_ING | FF2: CASA | FG2: C_ING | FH2: CASA | FI2: C_ING | FJ2: CASA | FK2: C_ING | FL2: CASA | FM2: C_ING | FN2: CASA | FO2: C_ING | FP2: CASA | FQ2: C_ING | FR2: CASA | FS2: C_ING | FT2: CASA | FU2: C_ING | FV2: CASA | FW2: C_ING | FX2: CASA | FY2: C_ING | FZ2: CASA | GA2: C_ING | GB2: CASA | GC2: C_ING | GD2: CASA | GE2: C_ING | GF2: CASA | GG2: C_ING | GH2: CASA | GI2: C_ING | GJ2: CASA | GK2: C_ING | GL2: CASA | GM2: C_ING | GN2: CASA | GO2: C_ING | GP2: CASA | GQ2: C_ING | GR2: CASA | GS2: C_ING | GT2: CASA | GU2: C_ING | GV2: CASA | GW2: C_ING | GX2: CASA | GY2: C_ING | GZ2: CASA | HA2: C_ING | HB2: CASA | HC2: C_ING | HD2: CASA | HE2: C_ING | HF2: CASA | HG2: C_ING | HH2: CASA | HI2: C_ING | HJ2: CASA | HK2: C_ING | HL2: CASA | HM2: C_ING | HN2: CASA | HO2: C_ING | HP2: CASA | HQ2: C_ING | HR2: CALLE | HS2: calle
A3: CL | B3: Rancho La Cuchilla | D3: CL_7_101 | E3: 1 | F3: CL_7_102 | G3: 1 | H3: CL_7_201 | I3: 1 | J3: CL_7_202 | K3: 1 | L3: CL_9_ | M3: 1 | N3: CL_11_ | O3: 1 | P3: CL_12_ | Q3: 1 | R3: CL_13_ | S3: 1 | T3: CL_14_ | U3: 1 | V3: CL_15_ | W3: 1 | X3: CL_18_ | Y3: 1 | Z3: CL_19_ | AA3: 1 | AB3: CL_20_ | AC3: 1 | AD3: CL_21_ | AE3: 1 | AF3: CL_23_ | AG3: 1 | AH3: CL_25_ | AI3: 1 | AJ3: CL_27_ | AK3: 1 | AL3: CL_28_ | AM3: 1 | AN3: CL_29_ | AO3: 1 | AP3: CL_30_ | AQ3: 1 | AR3: CL_31_ | AS3: 1 | AT3: CL_32_ | AU3: 1 | AV3: CL_33_ | AW3: 1 | AX3: CL_35_ | AY3: 1 | AZ3: CL_36_ | BA3: 1 | BB3: CL_38_ | BC3: 1 | BD3: CL_39_ | BE3: 1 | BF3: CL_40_ | BG3: 1 | BH3: CL_41_ | BI3: 1 | BJ3: CL_42_ | BK3: 1 | BL3: CL_43_A | BM3: 1 | BN3: CL_43_B | BO3: 1 | BP3: CL_44_ | BQ3: 1 | BR3: CL_45_ | BS3: 1 | BT3: CL_46_ | BU3: 1 | BV3: CL_47_ | BW3: 1 | BX3: CL_49_ | BY3: 1 | BZ3: CL_52_ | CA3: 1 | CB3: CL_54_ | CC3: 1 | CD3: CL_53_ | CE3: 1 | CF3: CL_55_ | CG3: 1 | CH3: CL_57_ | CI3: 1 | CJ3: CL_58_ | CK3: 1 | CL3: CL_59_ | CM3: 1 | CN3: CL_60_ | CO3: 1 | CP3: CL_61_ | CQ3: 1 | CR3: CL_62_ | CS3: 1 | CT3: CL_63_ | CU3: 1 | CV3: CL_65_ | CW3: 1 | CX3: CL_66_ | CY3: 1 | CZ3: CL_67_ | DA3: 1 | DB3: CL_68_ | DC3: 1 | DD3: CL_69_ | DE3: 1 | DF3: CL_70_ | DG3: 1 | DH3: CL_71_ | DI3: 1 | DJ3: CL_72_ | DK3: 1 | DL3: CL_73_ | DM3: 1 | DN3: CL_74_ | DO3: 1 | DP3: CL_75_ | DQ3: 1 | DR3: CL_76_ | DS3: 1 | DT3: CL_77_ | DU3: 1 | DV3: CL_79_ | DW3: 1 | DX3: CL_80_ | DY3: 1 | DZ3: CL_81_A | EA3: 1 | EB3: CL_81_B | EC3: 1 | ED3: CL_82_ | EE3: 1 | EF3: CL_83_ | EG3: 1 | EH3: CL_86_ | EI3: 1 | EJ3: CL_87_ | EK3: 1 | EL3: CL_88_ | EM3: 1 | EN3: CL_89_ | EO3: 1 | EP3: CL_90_ | EQ3: 1 | ER3: CL_91_ | ES3: 1 | ET3: CL_92_ | EU3: 1 | EV3: CL_93_ | EW3: 1 | EX3: CL_94_ | EY3: 1 | EZ3: CL_95_ | FA3: 1 | FB3: CL_96_ | FC3: 1 | FD3: CL_97_ | FE3: 1 | FF3: CL_101_ | FG3: 1 | FH3: CL_107_ | FI3: 1 | FJ3: CL_110_ | FK3: 1 | FL3: CL_111_ | FM3: 1 | FN3: CL_112_PA | FO3: 1 | FP3: CL_112_PB | FQ3: 1 | FR3: CL_115_ | FS3: 1 | FT3: CL_116_ | FU3: 1 | FV3: CL_117_ | FW3: 1 | FX3: CL_118_ | FY3: 1 | FZ3: CL_119_ | GA3: 1 | GB3: CL_120_ | GC3: 1 | GD3: CL_121_ | GE3: 1 | GF3: CL_122_ | GG3: 1 | GH3: CL_125_ | GI3: 1 | GJ3: CL_127_ | GK3: 1 | GL3: CL_129_ | GM3: 1 | GN3: CL_130_ | GO3: 1 | GP3: CL_131_ | GQ3: 1 | GR3: CL_132_ | GS3: 1 | GT3: CL_133_ | GU3: 1 | GV3: CL_134_ | GW3: 1 | GX3: CL_135_ | GY3: 1 | GZ3: CL_137_ | HA3: 1 | HB3: CL_139_ | HC3: 1 | HD3: CL_141_ | HE3: 1 | HF3: CL_144_ | HG3: 1 | HH3: CL_145_ | HI3: 1 | HJ3: CL_147_ | HK3: 1 | HL3: CL_148_ | HM3: 1 | HN3: CL_149_ | HO3: 1 | HP3: CL_terreno_ | HQ3: 1 | HR3: CL | HS3: Cuchilla
A4: CT | B4: Cafetales
A5: EP | B5: Rancho Estopila | D5: CASA | E5: C_ING | F5: CASA | G5: C_ING | H5: CASA | I5: C_ING | J5: CASA | K5: C_ING | L5: CASA | M5: C_ING | N5: calle | O5: CALLE
A6: EZ | B6: Rancho Estanzuela | D6: EP_15_ | E6: 1 | F6: EP_18_ | G6: 1 | H6: EP_22_A | I6: 1 | J6: EP_22_B | K6: 1 | L6: EP_44_ | M6: 1 | N6: Estopila | O6: EP
A7: HS | B7: Calzada del Hueso
A8: LD | B8: Rancho Landero | D8: CASA | E8: C_ING | F8: CASA | G8: C_ING | H8: CASA | I8: C_ING | J8: CASA | K8: C_ING | L8: CASA | M8: C_ING | N8: CASA | O8: C_ING | P8: CASA | Q8: C_ING | R8: CASA | S8: C_ING | T8: CASA | U8: C_ING | V8: CASA | W8: C_ING | X8: CASA | Y8: C_ING | Z8: CASA | AA8: C_ING | AB8: CASA | AC8: C_ING | AD8: CASA | AE8: C_ING | AF8: CASA | AG8: C_ING | AH8: CASA | AI8: C_ING | AJ8: CASA | AK8: C_ING | AL8: CASA | AM8: C_ING | AN8: CASA | AO8: C_ING | AP8: CASA | AQ8: C_ING | AR8: CASA | AS8: C_ING | AT8: CASA | AU8: C_ING | AV8: CASA | AW8: C_ING | AX8: CASA | AY8: C_ING | AZ8: CASA | BA8: C_ING | BB8: CASA | BC8: C_ING | BD8: CASA | BE8: C_ING | BF8: CASA | BG8: C_ING | BH8: CASA | BI8: C_ING | BJ8: CASA | BK8: C_ING | BL8: CASA | BM8: C_ING | BN8: CASA | BO8: C_ING | BP8: CASA | BQ8: C_ING | BR8: CASA | BS8: C_ING | BT8: CASA | BU8: C_ING | BV8: CASA | BW8: C_ING | BX8: CASA | BY8: C_ING | BZ8: CASA | CA8: C_ING | CB8: CASA | CC8: C_ING | CD8: CASA | CE8: C_ING | CF8: CASA | CG8: C_ING | CH8: CASA | CI8: C_ING | CJ8: CASA | CK8: C_ING | CL8: CASA | CM8: C_ING | CN8: CASA | CO8: C_ING | CP8: CASA | CQ8: C_ING | CR8: CASA | CS8: C_ING | CT8: CASA | CU8: C_ING | CV8: CASA | CW8: C_ING | CX8: CASA | CY8: C_ING | CZ8: CASA | DA8: C_ING | DB8: CASA | DC8: C_ING | DD8: CASA | DE8: C_ING | DF8: CASA | DG8: C_ING | DH8: CASA | DI8: C_ING | DJ8: CASA | DK8: C_ING | DL8: CASA | DM8: C_ING | DN8: CASA | DO8: C_ING | DP8: CASA | DQ8: C_ING | DR8: CASA | DS8: C_ING | DT8: CASA | DU8: C_ING | DV8: CASA | DW8: C_ING | DX8: CASA | DY8: C_ING | DZ8: CASA | EA8: C_ING | EB8: CASA | EC8: C_ING | ED8: CASA | EE8: C_ING | EF8: CASA | EG8: C_ING | EH8: CASA | EI8: C_ING | EJ8: CASA | EK8: C_ING | EL8: CASA | EM8: C_ING | EN8: CASA | EO8: C_ING | EP8: CASA | EQ8: C_ING | ER8: CASA | ES8: C_ING | ET8: CASA | EU8: C_ING | EV8: CASA | EW8: C_ING | EX8: CASA | EY8: C_ING | EZ8: CASA | FA8: C_ING | FB8: CASA | FC8: C_ING | FD8: CASA | FE8: C_ING | FF8: calle | FG8: CALLE | FH8: calle | FI8: CALLE
A9: RM | B9: Rancho Romeral | D9: EZ_3_ | E9: 1 | F9: EZ_5_A | G9: 1 | H9: EZ_5_B | I9: 1 | J9: EZ_7_A | K9: 1 | L9: EZ_7_B | M9: 1 | N9: EZ_9_A | O9: 1 | P9: EZ_9_B | Q9: 1 | R9: EZ_11_A | S9: 1 | T9: EZ_11_B | U9: 1 | V9: EZ_15_A | W9: 1 | X9: EZ_15_B | Y9: 1 | Z9: EZ_17_ | AA9: 1 | AB9: EZ_19_ | AC9: 1 | AD9: EZ_21_ | AE9: 1 | AF9: EZ_25_ | AG9: 1 | AH9: EZ_31_ | AI9: 1 | AJ9: EZ_33_ | AK9: 1 | AL9: EZ_35_ | AM9: 1 | AN9: EZ_37_ | AO9: 1 | AP9: EZ_41_ | AQ9: 1 | AR9: EZ_43_ | AS9: 1 | AT9: EZ_45_ | AU9: 1 | AV9: EZ_47_ | AW9: 1 | AX9: EZ_49_ | AY9: 1 | AZ9: EZ_53_ | BA9: 1 | BB9: EZ_55_ | BC9: 1 | BD9: EZ_57_ | BE9: 1 | BF9: EZ_59_ | BG9: 1 | BH9: EZ_61_ | BI9: 1 | BJ9: EZ_63_ | BK9: 1 | BL9: EZ_65_ | BM9: 1 | BN9: EZ_67_ | BO9: 1 | BP9: EZ_69_ | BQ9: 1 | BR9: EZ_71_ | BS9: 1 | BT9: EZ_73_ | BU9: 1 | BV9: EZ_75_ | BW9: 1 | BX9: EZ_77_ | BY9: 1 | BZ9: EZ_79_ | CA9: 1 | CB9: EZ_89_ | CC9: 1 | CD9: EZ_91_ | CE9: 1 | CF9: EZ_93_ | CG9: 1 | CH9: EZ_95_ | CI9: 1 | CJ9: EZ_97_ | CK9: 1 | CL9: EZ_99_ | CM9: 1 | CN9: EZ_100_ | CO9: 1 | CP9: EZ_101_ | CQ9: 1 | CR9: EZ_103_ | CS9: 1 | CT9: EZ_105_ | CU9: 1 | CV9: EZ_111_ | CW9: 1 | CX9: EZ_115_ | CY9: 1 | CZ9: EZ_117_ | DA9: 1 | DB9: EZ_119_2 | DC9: 1 | DD9: EZ_119_0 | DE9: 1 | DF9: EZ_121_ | DG9: 1 | DH9: EZ_123_ | DI9: 1 | DJ9: EZ_127_ | DK9: 1 | DL9: EZ_129_ | DM9: 1 | DN9: CM_130_A | DO9: 1 | DP9: EZ_130_B | DQ9: 1 | DR9: EZ_133_ | DS9: 1 | DT9: EZ_135_ | DU9: 1 | DV9: EZ_139_ | DW9: 1 | DX9: EZ_141_ | DY9: 1 | DZ9: EZ_147_1 | EA9: 1 | EB9: EZ_147_2 | EC9: 1 | ED9: EZ_147_3 | EE9: 1 | EF9: EZ_149_ | EG9: 1 | EH9: EZ_151_ | EI9: 1 | EJ9: EZ_153_ | EK9: 1 | EL9: EZ_155_ | EM9: 1 | EN9: EZ_157_1 | EO9: 1 | EP9: EZ_157_2 | EQ9: 1 | ER9: EZ_157_3 | ES9: 1 | ET9: EZ_159_ | EU9: 1 | EV9: EZ_161_1 | EW9: 1 | EX9: EZ_161_B | EY9: 1 | EZ9: EZ_163_ | FA9: 1 | FB9: EZ_165_A | FC9: 1 | FD9: EZ_165_B | FE9: 1 | FF9: Estanzuela | FG9: EZ | FH9: Carmel | FI9: CM
A10: RV | B10: Rancho Recoveco
A11: UP | B11: Rancho Upácuaro | D11: CASA | E11: C_ING | F11: CASA | G11: C_ING | H11: CASA | I11: C_ING | J11: CASA | K11: C_ING | L11: CASA | M11: C_ING | N11: calle | O11: CALLE
A12: ZB | B12: Rancho Zinamba | D12: HS_828_ | E12: 1 | F12: HS_840_ | G12: 1 | H12: HS_A_ | I12: 1 | J12: HS_B_ | K12: 1 | L12: HS_C_ | M12: 1 | N12: Hueso | O12: HS
D14: CASA | E14: C_ING | F14: CASA | G14: C_ING | H14: CASA | I14: C_ING | J14: CASA | K14: C_ING | L14: CASA | M14: C_ING | N14: CASA | O14: C_ING | P14: CASA | Q14: C_ING | R14: CASA | S14: C_ING | T14: CASA | U14: C_ING | V14: CASA | W14: C_ING | X14: CASA | Y14: C_ING | Z14: CASA | AA14: C_ING | AB14: CASA | AC14: C_ING | AD14: CASA | AE14: C_ING | AF14: CASA | AG14: C_ING | AH14: CASA | AI14: C_ING | AJ14: CASA | AK14: C_ING | AL14: CASA | AM14: C_ING | AN14: CASA | AO14: C_ING | AP14: CASA | AQ14: C_ING | AR14: CASA | AS14: C_ING | AT14: CASA | AU14: C_ING | AV14: CASA | AW14: C_ING | AX14: CASA | AY14: C_ING | AZ14: CASA | BA14: C_ING | BB14: CASA | BC14: C_ING | BD14: CASA | BE14: C_ING | BF14: CASA | BG14: C_ING | BH14: CASA | BI14: C_ING | BJ14: CASA | BK14: C_ING | BL14: CASA | BM14: C_ING | BN14: CASA | BO14: C_ING | BP14: CASA | BQ14: C_ING | BR14: CASA | BS14: C_ING | BT14: CASA | BU14: C_ING | BV14: CASA | BW14: C_ING | BX14: CASA | BY14: C_ING | BZ14: CASA | CA14: C_ING | CB14: CASA | CC14: C_ING | CD14: CASA | CE14: C_ING | CF14: CASA | CG14: C_ING | CH14: CASA | CI14: C_ING | CJ14: CASA | CK14: C_ING | CL14: CASA | CM14: C_ING | CN14: CASA | CO14: C_ING | CP14: CASA | CQ14: C_ING | CR14: CASA | CS14: C_ING | CT14: CASA | CU14: C_ING | CV14: CASA | CW14: C_ING | CX14: CASA | CY14: C_ING | CZ14: CASA | DA14: C_ING | DB14: CASA | DC14: C_ING | DD14: CASA | DE14: C_ING | DF14: CASA | DG14: C_ING | DH14: CASA | DI14: C_ING | DJ14: CASA | DK14: C_ING | DL14: CASA | DM14: C_ING | DN14: CASA | DO14: C_ING | DP14: CASA | DQ14: C_ING | DR14: CASA | DS14: C_ING | DT14: CASA | DU14: C_ING | DV14: CASA | DW14: C_ING | DX14: CASA | DY14: C_ING | DZ14: CASA | EA14: C_ING | EB14: CASA | EC14: C_ING | ED14: CASA | EE14: C_ING | EF14: CASA | EG14: C_ING | EH14: CASA | EI14: C_ING | EJ14: CASA | EK14: C_ING | EL14: CASA | EM14: C_ING | EN14: CASA | EO14: C_ING | EP14: CASA | EQ14: C_ING | ER14: CASA | ES14: C_ING | ET14: CASA | EU14: C_ING | EV14: CASA | EW14: C_ING | EX14: CASA | EY14: C_ING | EZ14: CASA | FA14: C_ING | FB14: CASA | FC14: C_ING | FD14: CASA | FE14: C_ING | FF14: CASA | FG14: C_ING | FH14: CASA | FI14: C_ING | FJ14: CASA | FK14: C_ING | FL14: calle | FM14: CALLE
D15: LD_1_ | E15: 1 | F15: LD_1_ | G15: 1 | H15: LD_2_3 | I15: 1 | J15: LD_2_A | K15: 1 | L15: LD_2_B | M15: 1 | N15: LD_7_ | O15: 1 | P15: LD_8_ | Q15: 1 | R15: LD_10_ | S15: 1 | T15: LD_11_ | U15: 1 | V15: LD_12_ | W15: 1 | X15: LD_13_ | Y15: 1 | Z15: LD_14_ | AA15: 1 | AB15: LD_15_ | AC15: 1 | AD15: LD_17_ | AE15: 1 | AF15: LD_18_ | AG15: 1 | AH15: LD_19_ | AI15: 1 | AJ15: LD_20_ | AK15: 1 | AL15: LD_21_ | AM15: 1 | AN15: LD_22_ | AO15: 1 | AP15: LD_24_ | AQ15: 1 | AR15: LD_25_ | AS15: 1 | AT15: LD_26_ | AU15: 1 | AV15: LD_28_ | AW15: 1 | AX15: LD_29_ | AY15: 1 | AZ15: LD_30_ | BA15: 1 | BB15: LD_31_ | BC15: 1 | BD15: LD_33_ | BE15: 1 | BF15: LD_34_ | BG15: 1 | BH15: LD_35_ | BI15: 1 | BJ15: LD_36_ | BK15: 1 | BL15: LD_37_ | BM15: 1 | BN15: LD_38_ | BO15: 1 | BP15: LD_39_ | BQ15: 1 | BR15: LD_40_ | BS15: 1 | BT15: LD_41_ | BU15: 1 | BV15: LD_42_ | BW15: 1 | BX15: LD_44_ | BY15: 1 | BZ15: LD_45_ | CA15: 1 | CB15: LD_47_ | CC15: 1 | CD15: LD_49_ | CE15: 1 | CF15: LD_50_ | CG15: 1 | CH15: LD_51_ | CI15: 1 | CJ15: LD_52_ | CK15: 1 | CL15: LD_54_1 | CM15: 1 | CN15: LD_54_2 | CO15: 1 | CP15: LD_58_ | CQ15: 1 | CR15: LD_60_ | CS15: 1 | CT15: LD_61_ | CU15: 1 | CV15: LD_62_ | CW15: 1 | CX15: LD_63_ | CY15: 1 | CZ15: LD_64_ | DA15: 1 | DB15: LD_65_ | DC15: 1 | DD15: LD_66_ | DE15: 1 | DF15: LD_68_ | DG15: 1 | DH15: LD_69_ | DI15: 1 | DJ15: LD_70_ | DK15: 1 | DL15: LD_71_ | DM15: 1 | DN15: LD_72_ | DO15: 1 | DP15: LD_73_ | DQ15: 1 | DR15: LD_74_ | DS15: 1 | DT15: LD_75_ | DU15: 1 | DV15: LD_76_ | DW15: 1 | DX15: LD_77_ | DY15: 1 | DZ15: LD_80_ | EA15: 1 | EB15: LD_81_ | EC15: 1 | ED15: LD_83_ | EE15: 1 | EF15: LD_84_ | EG15: 1 | EH15: LD_85_ | EI15: 1 | EJ15: LD_86_ | EK15: 1 | EL15: LD_87_ | EM15: 1 | EN15: LD_88_ | EO15: 1 | EP15: LD_89_ | EQ15: 1 | ER15: LD_90_ | ES15: 1 | ET15: LD_91_ | EU15: 1 | EV15: LD_92_ | EW15: 1 | EX15: LD_93_ | EY15: 1 | EZ15: LD_94_ | FA15: 1 | FB15: LD_95_ | FC15: 1 | FD15: LD_96_ | FE15: 1 | FF15: LD_99_ | FG15: 1 | FH15: LD_100_ | FI15: 1 | FJ15: LD_101_ | FK15: 1 | FL15: Landero | FM15: LD
D17: CASA | E17: C_ING | F17: CASA | G17: C_ING | H17: CASA | I17: C_ING | J17: CASA | K17: C_ING | L17: CASA | M17: C_ING | N17: CASA | O17: C_ING | P17: CASA | Q17: C_ING | R17: CASA | S17: C_ING | T17: CASA | U17: C_ING | V17: CASA | W17: C_ING | X17: calle | Y17: CALLE
D18: RM_9_A | E18: 1 | F18: RM_9_B | G18: 1 | H18: RM_10_A | I18: 1 | J18: RM_10_B | K18: 1 | L18: RM_17_ | M18: 1 | N18: RM_23_A | O18: 1 | P18: RM_23_B | Q18: 1 | R18: RM_30_ | S18: 1 | T18: RM_33_ | U18: 1 | V18: RM_58_ | W18: 1 | X18: Romeral | Y18: RM
D20: CASA | E20: C_ING | F20: CASA | G20: C_ING | H20: CASA | I20: C_ING | J20: CASA | K20: C_ING | L20: CASA | M20: C_ING | N20: CASA | O20: C_ING | P20: CASA | Q20: C_ING | R20: CASA | S20: C_ING | T20: CASA | U20: C_ING | V20: CASA | W20: C_ING | X20: CASA | Y20: C_ING | Z20: CASA | AA20: C_ING | AB20: CASA | AC20: C_ING | AD20: CASA | AE20: C_ING | AF20: CASA | AG20: C_ING | AH20: calle | AI20: CALLE
D21: RV_1_ | E21: 1 | F21: RV_2_ | G21: 1 | H21: RV_3_ | I21: 1 | J21: RV_173_ | K21: 1 | L21: RV_175_A | M21: 1 | N21: RV_175_B | O21: 1 | P21: RV_175_0 | Q21: 1 | R21: RV_179_ | S21: 1 | T21: RV_181_ | U21: 1 | V21: RV_183_ | W21: 1 | X21: RV_187_ | Y21: 1 | Z21: RV_189_ | AA21: 1 | AB21: RV_193_ | AC21: 1 | AD21: RV_195_ | AE21: 1 | AF21: RV_197_ | AG21: 1 | AH21: Recoveco | AI21: RV
D23: CASA | E23: C_ING | F23: CASA | G23: C_ING | H23: CASA | I23: C_ING | J23: CASA | K23: C_ING | L23: CASA | M23: C_ING | N23: CASA | O23: C_ING | P23: CASA | Q23: C_ING | R23: CASA | S23: C_ING | T23: CASA | U23: C_ING | V23: CASA | W23: C_ING | X23: CASA | Y23: C_ING | Z23: CASA | AA23: C_ING | AB23: CASA | AC23: C_ING | AD23: CASA | AE23: C_ING | AF23: CASA | AG23: C_ING | AH23: CASA | AI23: C_ING | AJ23: CASA | AK23: C_ING | AL23: CASA | AM23: C_ING | AN23: CASA | AO23: C_ING | AP23: CASA | AQ23: C_ING | AR23: CASA | AS23: C_ING | AT23: CASA | AU23: C_ING | AV23: CASA | AW23: C_ING | AX23: CASA | AY23: C_ING | AZ23: CASA | BA23: C_ING | BB23: CASA | BC23: C_ING | BD23: CASA | BE23: C_ING | BF23: CASA | BG23: C_ING | BH23: CASA | BI23: C_ING | BJ23: CASA | BK23: C_ING | BL23: CASA | BM23: C_ING | BN23: CASA | BO23: C_ING | BP23: CASA | BQ23: C_ING | BR23: CASA | BS23: C_ING | BT23: CASA | BU23: C_ING | BV23: CASA | BW23: C_ING | BX23: CASA | BY23: C_ING | BZ23: CASA | CA23: C_ING | CB23: CASA | CC23: C_ING | CD23: CASA | CE23: C_ING | CF23: CASA | CG23: C_ING | CH23: CASA | CI23: C_ING | CJ23: CASA | CK23: C_ING | CL23: CASA | CM23: C_ING | CN23: CASA | CO23: C_ING | CP23: CASA | CQ23: C_ING | CR23: CASA | CS23: C_ING | CT23: CASA | CU23: C_ING | CV23: CASA | CW23: C_ING | CX23: CASA | CY23: C_ING | CZ23: CASA | DA23: C_ING | DB23: CASA | DC23: C_ING | DD23: CASA | DE23: C_ING | DF23: CASA | DG23: C_ING | DH23: CASA | DI23: C_ING | DJ23: CASA | DK23: C_ING | DL23: CASA | DM23: C_ING | DN23: CASA | DO23: C_ING | DP23: CASA | DQ23: C_ING | DR23: CASA | DS23: C_ING | DT23: CASA | DU23: C_ING | DV23: CASA | DW23: C_ING | DX23: CASA | DY23: C_ING | DZ23: CASA | EA23: C_ING | EB23: CASA | EC23: C_ING | ED23: CASA | EE23: C_ING | EF23: CASA | EG23: C_ING | EH23: CASA | EI23: C_ING | EJ23: CASA | EK23: C_ING | EL23: CASA | EM23: C_ING | EN23: CASA | EO23: C_ING | EP23: CASA | EQ23: C_ING | ER23: CASA | ES23: C_ING | ET23: CASA | EU23: C_ING | EV23: CASA | EW23: C_ING | EX23: CASA | EY23: C_ING | EZ23: CASA | FA23: C_ING | FB23: CASA | FC23: C_ING | FD23: CASA | FE23: C_ING | FF23: CASA | FG23: C_ING | FH23: CASA | FI23: C_ING | FJ23: CASA | FK23: C_ING | FL23: CASA | FM23: C_ING | FN23: CASA | FO23: C_ING | FP23: CASA | FQ23: C_ING | FR23: CASA | FS23: C_ING | FT23: CASA | FU23: C_ING | FV23: CASA | FW23: C_ING | FX23: CASA | FY23: C_ING | FZ23: CASA | GA23: C_ING | GB23: CASA | GC23: C_ING | GD23: CASA | GE23: C_ING | GF23: CASA | GG23: C_ING | GH23: CASA | GI23: C_ING | GJ23: CASA | GK23: C_ING | GL23: CASA | GM23: C_ING | GN23: CASA | GO23: C_ING | GP23: CASA | GQ23: C_ING | GR23: CASA | GS23: C_ING | GT23: CASA | GU23: C_ING | GV23: CASA | GW23: C_ING | GX23: calle | GY23: CALLE
D24: UP_5_B | E24: 1 | F24: UP_7_ | G24: 1 | H24: UP_8_ | I24: 1 | J24: UP_9_ | K24: 1 | L24: UP_10_ | M24: 1 | N24: UP_11_ | O24: 1 | P24: UP_12_ | Q24: 1 | R24: UP_14_ | S24: 1 | T24: UP_15_ | U24: 1 | V24: UP_16_ | W24: 1 | X24: UP_18_ | Y24: 1 | Z24: UP_19_ | AA24: 1 | AB24: UP_20_ | AC24: 1 | AD24: UP_21_ | AE24: 1 | AF24: UP_23_ | AG24: 1 | AH24: UP_24_ | AI24: 1 | AJ24: UP_26_ | AK24: 1 | AL24: UP_30_ | AM24: 1 | AN24: UP_31_ | AO24: 1 | AP24: UP_32_ | AQ24: 1 | AR24: UP_33_ | AS24: 1 | AT24: UP_34_ | AU24: 1 | AV24: UP_35_ | AW24: 1 | AX24: UP_36_ | AY24: 1 | AZ24: UP_37_ | BA24: 1 | BB24: UP_39_ | BC24: 1 | BD24: UP_40_ | BE24: 1 | BF24: UP_42_ | BG24: 1 | BH24: UP_43_ | BI24: 1 | BJ24: UP_44_ | BK24: 1 | BL24: UP_45_ | BM24: 1 | BN24: UP_46_ | BO24: 1 | BP24: UP_47_ | BQ24: 1 | BR24: UP_48_ | BS24: 1 | BT24: UP_49_ | BU24: 1 | BV24: UP_50_ | BW24: 1 | BX24: UP_51_1 | BY24: 1 | BZ24: UP_51_2 | CA24: 1 | CB24: UP_52_ | CC24: 1 | CD24: UP_54_ | CE24: 1 | CF24: UP_55_ | CG24: 1 | CH24: UP_56_ | CI24: 1 | CJ24: UP_57_ | CK24: 1 | CL24: UP_60_ | CM24: 1 | CN24: UP_61_ | CO24: 1 | CP24: UP_62_ | CQ24: 1 | CR24: UP_63_ | CS24: 1 | CT24: UP_64_ | CU24: 1 | CV24: UP_65_ | CW24: 1 | CX24: UP_68_ | CY24: 1 | CZ24: UP_69_ | DA24: 1 | DB24: UP_70_ | DC24: 1 | DD24: UP_72_ | DE24: 1 | DF24: UP_71_ | DG24: 1 | DH24: UP_73_A | DI24: 1 | DJ24: UP_73_B | DK24: 1 | DL24: UP_74_ | DM24: 1 | DN24: UP_75_ | DO24: 1 | DP24: UP_76_ | DQ24: 1 | DR24: UP_77_ | DS24: 1 | DT24: UP_78_ | DU24: 1 | DV24: UP_79_ | DW24: 1 | DX24: UP_80_ | DY24: 1 | DZ24: UP_85_ | EA24: 1 | EB24: UP_86_ | EC24: 1 | ED24: UP_87_ | EE24: 1 | EF24: UP_88_ | EG24: 1 | EH24: UP_89_ | EI24: 1 | EJ24: UP_90_ | EK24: 1 | EL24: UP_91_ | EM24: 1 | EN24: UP_92_ | EO24: 1 | EP24: UP_93_ | EQ24: 1 | ER24: UP_94_ | ES24: 1 | ET24: UP_95_ | EU24: 1 | EV24: UP_96_ | EW24: 1 | EX24: UP_99_ | EY24: 1 | EZ24: UP_100_ | FA24: 1 | FB24: UP_101_ | FC24: 1 | FD24: UP_102_ | FE24: 1 | FF24: UP_103_ | FG24: 1 | FH24: UP_104_ | FI24: 1 | FJ24: UP_106_ | FK24: 1 | FL24: UP_108_ | FM24: 1 | FN24: UP_110_ | FO24: 1 | FP24: UP_114_ | FQ24: 1 | FR24: UP_116_ | FS24: 1 | FT24: UP_118_ | FU24: 1 | FV24: UP_120_ | FW24: 1 | FX24: UP_122_ | FY24: 1 | FZ24: UP_124_ | GA24: 1 | GB24: UP_128_ | GC24: 1 | GD24: UP_130_ | GE24: 1 | GF24: UP_132_ | GG24: 1 | GH24: UP_134_ | GI24: 1 | GJ24: UP_136_ | GK24: 1 | GL24: UP_138_ | GM24: 1 | GN24: UP_140_ | GO24: 1 | GP24: UP_142_ | GQ24: 1 | GR24: UP_144_ | GS24: 1 | GT24: UP_146_ | GU24: 1 | GV24: UP_148_ | GW24: 1 | GX24: Upácuaro | GY24: UP
D26: CASA | E26: C_ING | F26: CASA | G26: C_ING | H26: CASA | I26: C_ING | J26: CASA | K26: C_ING | L26: CASA | M26: C_ING | N26: CASA | O26: C_ING | P26: CASA | Q26: C_ING | R26: CASA | S26: C_ING | T26: CASA | U26: C_ING | V26: CASA | W26: C_ING | X26: CASA | Y26: C_ING | Z26: CASA | AA26: C_ING | AB26: CASA | AC26: C_ING | AD26: CASA | AE26: C_ING | AF26: CASA | AG26: C_ING | AH26: CASA | AI26: C_ING | AJ26: CASA | AK26: C_ING | AL26: CASA | AM26: C_ING | AN26: CASA | AO26: C_ING | AP26: CASA | AQ26: C_ING | AR26: CASA | AS26: C_ING | AT26: CASA | AU26: C_ING | AV26: CASA | AW26: C_ING | AX26: CASA | AY26: C_ING | AZ26: CASA | BA26: C_ING | BB26: CASA | BC26: C_ING | BD26: CASA | BE26: C_ING | BF26: CASA | BG26: C_ING | BH26: CASA | BI26: C_ING | BJ26: CASA | BK26: C_ING | BL26: CASA | BM26: C_ING | BN26: CASA | BO26: C_ING | BP26: CASA | BQ26: C_ING | BR26: calle | BS26: CALLE
D27: ZB_6_ | E27: 1 | F27: ZB_8_ | G27: 1 | H27: ZB_10_ | I27: 1 | J27: ZB_12_ | K27: 1 | L27: ZB_14_ | M27: 1 | N27: ZB_18_ | O27: 1 | P27: ZB_20_ | Q27: 1 | R27: ZB_22_ | S27: 1 | T27: ZB_24_ | U27: 1 | V27: ZB_26_ | W27: 1 | X27: ZB_30_ | Y27: 1 | Z27: ZB_34_ | AA27: 1 | AB27: ZB_36_ | AC27: 1 | AD27: ZB_38_ | AE27: 1 | AF27: ZB_40_ | AG27: 1 | AH27: ZB_42_ | AI27: 1 | AJ27: ZB_44_ | AK27: 1 | AL27: ZB_46_ | AM27: 1 | AN27: ZB_50_ | AO27: 1 | AP27: ZB_54_ | AQ27: 1 | AR27: ZB_56_ | AS27: 1 | AT27: ZB_58_ | AU27: 1 | AV27: ZB_60_ | AW27: 1 | AX27: ZB_62_ | AY27: 1 | AZ27: ZB_66_ | BA27: 1 | BB27: ZB_68_ | BC27: 1 | BD27: ZB_72_ | BE27: 1 | BF27: ZB_74_ | BG27: 1 | BH27: ZB_76_ | BI27: 1 | BJ27: ZB_80_ | BK27: 1 | BL27: ZB_82_ | BM27: 1 | BN27: ZB_84_ | BO27: 1 | BP27: ZB_88_ | BQ27: 1 | BR27: Zinamba | BS27: ZB
D30: Ingresos / código de ingresos
D31: C_ING | E31: C_ING | F31: C_ING | G31: C_ING | H31: C_ING | I31: C_ING | J31: C_ING | K31: C_ING
D32: 1 | E32: 2 | F32: 3 | G32: 4 | H32: 5 | I32: 6 | J32: 7
A33: 1 | B33: Cuotas de vigilancia
A34: 2 | B34: Cuotas extraordinarias
A35: 3 | B35: Venta de llaves
A36: 4 | B36: Venta de tarjetas electrónicas
A37: 5 | B37: Venta de tarjetones
A38: 6 | B38: Aportación Colegio Carmel
A39: 7 | B39: Otros ingresos | D39: Criterios para índices de cobranza. Todas las viviendas
B40: Suma de ingresos | D40: calle | E40: factor | F40: calle | G40: factor | H40: calle | I40: factor | J40: calle | K40: factor | L40: calle | M40: factor | N40: calle | O40: factor | P40: calle | Q40: factor | R40: calle | S40: factor | T40: calle | U40: factor | V40: calle | W40: factor | X40: calle | Y40: factor
D41: Cuchilla | F41: Cafetales | H41: Estopila | J41: Estanzuela | L41: Hueso | N41: Landero | P41: Romeral | R41: Recoveco | T41: Upácuaro | V41: Zinamba | X41: Carmel
D43: Criterios para índices de cobranza. Viviendas con algún pago en el período.
D44: calle | E44: factor | F44: calle | G44: factor | H44: calle | I44: factor | J44: calle | K44: factor | L44: calle | M44: factor | N44: calle | O44: factor | P44: calle | Q44: factor | R44: calle | S44: factor | T44: calle | U44: factor | V44: calle | W44: factor | X44: calle | Y44: factor
D45: Cuchilla | E45: >0 | F45: Cafetales | G45: >0 | H45: Estopila | I45: >0 | J45: Estanzuela | K45: >0 | L45: Hueso | M45: >0 | N45: Landero | O45: >0 | P45: Romeral | Q45: >0 | R45: Recoveco | S45: >0 | T45: Upácuaro | U45: >0 | V45: Zinamba | W45: >0 | X45: Carmel | Y45: >0
D48: Criterios para localizar depósitos de cuotas en chequera
D49: CASA | E49: CASA | F49: CASA | G49: CASA | H49: CASA | I49: CASA | J49: CASA
D50: CM_130_A | E50: CL_29_ | F50: EZ_15_A | G50: UP_46_ | H50: UP_86_ | I50: LD_58_ | J50: CL_18_
B51: Importe del depósito mensual: | D51: 10000 | E51: 300.29 | F51: 150.15 | G51: 300.46 | H51: 300.1 | I51: 300.58 | J51: 300.18
B55: Código de gastos | D55: clave
D56: G_NMNVG
D58: clave
D59: G_AGUA
D61: clave
D62: G_ALMVG
D64: clave
D65: G_UNF
D67: clave
D68: G_MDC
D70: clave
D71: G_TRSP
D73: clave
... D133: clave
E135: C_ING
D136: CASA | E136: 1
D137: INFRA
E138: C_ING
D139: CASA | E139: 1
D140: HJRD
E141: C_ING
E142: 1
D144: CALLE | E144: C_ING
D145: Cafetales | E145: 1
D147: CALLE | E147: C_ING
D148: Calzada del Hueso | E148: 1
D150: CALLE | E150: C_ING
D151: Rancho Estanzuela | E151: 1
D153: CALLE | E153: C_ING
D154: Rancho Estopila | E154: 1
D156: CALLE | E156: C_ING
D157: Rancho La Cuchilla | E157: 1
D159: CALLE | E159: C_ING
D160: Rancho Landero | E160: 1
D162: CALLE | E162: C_ING
D163: Rancho Recoveco | E163: 1
D165: CALLE
D166: Rancho Romeral
D168: CALLE
D169: Rancho Upácuaro
D171: CALLE
D172: Rancho Zinamba

Sheet cobranza 2013
B1: 1 | C1: 2 | D1: 3 | E1: 4 | F1: 5 | G1: 6 | H1: 7 | I1: 8 | J1: 9 | K1: 10 | L1: 11 | M1: 12 | N1: 13 | O1: 14 | P1: 15 | Q1: 16 | R1: 17 | S1: 18 | T1: 19 | U1: 20 | V1: 21
C2: Asociación de Colonos HACIENDAS DE COYOACÁN
C3: Reporte de cuotas de vigilancia recibidas
C4: Período: enero - septiembre de 2013
F5: =SUM(F8:F448) -> 102125 | G5: =SUM(G8:G448) -> 763495 | H5: =SUM(H8:H448) -> 865620 | K5: =SUM(K8:K448) -> 92475 | L5: =SUM(L8:L448) -> 93125.28 | M5: =SUM(M8:M448) -> 87725 | N5: =SUM(N8:N448) -> 75225 | O5: =SUM(O8:O448) -> 95645 | P5: =SUM(P8:P448) -> 83475 | Q5: =SUM(Q8:Q448) -> 79425 | R5: =SUM(R8:R448) -> 76875 | ... V5: =SUM(V8:V448) -> 3350
B6: CASA | C6: Domicilio | D6: Familia | E6: cuota | F6: 2012 | G6: 2013 | H6: importe | I6: factor | J6: calle | K6: ENE | L6: FEB | M6: MAR | N6: ABR | O6: MAY | P6: JUN | Q6: JUL | R6: AGO | S6: SEP | T6: OCT | U6: NOV | V6: DIC
B8: CL_7_101 | C8: =VLOOKUP(B8,BASE_A,6,FALSE) -> Rancho La Cuchilla No. 7, 101 | D8: =VLOOKUP(B8,BASE_A,8,FALSE) -> Olivares | E8: =VLOOKUP(B8,BASE_A,9,FALSE) -> 100 | F8: =DSUM(SEP_2013_A,AA,CL_7_101) -> 100 | G8: =H8-F8 -> 900 | H8: =DSUM(SEP_2013_A,importe,CL_7_101) -> 1000 | I8: =IF(VLOOKUP(B8,BASE_A,9,FALSE)=0,0,G8/VLOOKUP(B8,BASE_A,9,FALSE)) -> 9 | J8: Cuchilla | K8: =DSUM(SEP_2013_A,23,CL_7_101) -> 100 | L8: =DSUM(SEP_2013_A,24,CL_7_101) -> 100 | M8: =DSUM(SEP_2013_A,25,CL_7_101) -> 100 | N8: =DSUM(SEP_2013_A,26,CL_7_101) -> 100 | O8: =DSUM(SEP_2013_A,27,CL_7_101) -> 100 | P8: =DSUM(SEP_2013_A,28,CL_7_101) -> 100 | Q8: =DSUM(SEP_2013_A,29,CL_7_101) -> 100 | R8: =DSUM(SEP_2013_A,30,CL_7_101) -> 100 | S8: =DSUM(SEP_2013_A,31,CL_7_101) -> 100 | T8: =DSUM(SEP_2013_A,32,CL_7_101) -> 0 | U8: =DSUM(SEP_2013_A,33,CL_7_101) -> 0 | V8: =DSUM(SEP_2013_A,34,CL_7_101) -> 0
B9: CL_7_102 | C9: =VLOOKUP(B9,BASE_A,6,FALSE) -> Rancho La Cuchilla No. 7, 102 | D9: =VLOOKUP(B9,BASE_A,8,FALSE) -> García Moreno | E9: =VLOOKUP(B9,BASE_A,9,FALSE) -> 100 | F9: =DSUM(SEP_2013_A,AA,CL_7_102) -> 300 | G9: =H9-F9 -> 900 | H9: =DSUM(SEP_2013_A,importe,CL_7_102) -> 1200 | I9: =IF(VLOOKUP(B9,BASE_A,9,FALSE)=0,0,G9/VLOOKUP(B9,BASE_A,9,FALSE)) -> 9 | J9: Cuchilla | K9: =DSUM(SEP_2013_A,23,CL_7_102) -> 100 | L9: =DSUM(SEP_2013_A,24,CL_7_102) -> 100 | M9: =DSUM(SEP_2013_A,25,CL_7_102) -> 100 | N9: =DSUM(SEP_2013_A,26,CL_7_102) -> 100 | O9: =DSUM(SEP_2013_A,27,CL_7_102) -> 100 | P9: =DSUM(SEP_2013_A,28,CL_7_102) -> 100 | Q9: =DSUM(SEP_2013_A,29,CL_7_102) -> 100 | R9: =DSUM(SEP_2013_A,30,CL_7_102) -> 100 | S9: =DSUM(SEP_2013_A,31,CL_7_102) -> 100 | T9: =DSUM(SEP_2013_A,32,CL_7_102) -> 0 | U9: =DSUM(SEP_2013_A,33,CL_7_102) -> 0 | V9: =DSUM(SEP_2013_A,34,CL_7_102) -> 0
B10: CL_7_201 | C10: =VLOOKUP(B10,BASE_A,6,FALSE) -> Rancho La Cuchilla No. 7, 201 | D10: =VLOOKUP(B10,BASE_A,8,FALSE) -> Solís Susana | E10: =VLOOKUP(B10,BASE_A,9,FALSE) -> 100 | F10: =DSUM(SEP_2013_A,AA,CL_7_201) -> 0 | G10: =H10-F10 -> 0 | H10: =DSUM(SEP_2013_A,importe,CL_7_201) -> 0 | I10: =IF(VLOOKUP(B10,BASE_A,9,FALSE)=0,0,G10/VLOOKUP(B10,BASE_A,9,FALSE)) -> 0 | J10: Cuchilla | K10: =DSUM(SEP_2013_A,23,CL_7_201) -> 0 | L10: =DSUM(SEP_2013_A,24,CL_7_201) -> 0 | M10: =DSUM(SEP_2013_A,25,CL_7_201) -> 0 | N10: =DSUM(SEP_2013_A,26,CL_7_201) -> 0 | O10: =DSUM(SEP_2013_A,27,CL_7_201) -> 0 | P10: =DSUM(SEP_2013_A,28,CL_7_201) -> 0 | Q10: =DSUM(SEP_2013_A,29,CL_7_201) -> 0 | R10: =DSUM(SEP_2013_A,30,CL_7_201) -> 0 | S10: =DSUM(SEP_2013_A,31,CL_7_201) -> 0 | T10: =DSUM(SEP_2013_A,32,CL_7_201) -> 0 | U10: =DSUM(SEP_2013_A,33,CL_7_201) -> 0 | V10: =DSUM(SEP_2013_A,34,CL_7_201) -> 0
B11: CL_7_202 | C11: =VLOOKUP(B11,BASE_A,6,FALSE) -> Rancho La Cuchilla No. 7, 202 | D11: =VLOOKUP(B11,BASE_A,8,FALSE) -> Carbajal Zayas | E11: =VLOOKUP(B11,BASE_A,9,FALSE) -> 100 | F11: =DSUM(SEP_2013_A,AA,CL_7_202) -> 400 | G11: =H11-F11 -> 800 | H11: =DSUM(SEP_2013_A,importe,CL_7_202) -> 1200 | I11: =IF(VLOOKUP(B11,BASE_A,9,FALSE)=0,0,G11/VLOOKUP(B11,BASE_A,9,FALSE)) -> 8 | J11: Cuchilla | K11: =DSUM(SEP_2013_A,23,CL_7_202) -> 100 | L11: =DSUM(SEP_2013_A,24,CL_7_202) -> 100 | M11: =DSUM(SEP_2013_A,25,CL_7_202) -> 100 | N11: =DSUM(SEP_2013_A,26,CL_7_202) -> 100 | O11: =DSUM(SEP_2013_A,27,CL_7_202) -> 100 | P11: =DSUM(SEP_2013_A,28,CL_7_202) -> 100 | Q11: =DSUM(SEP_2013_A,29,CL_7_202) -> 100 | R11: =DSUM(SEP_2013_A,30,CL_7_202) -> 100 | S11: =DSUM(SEP_2013_A,31,CL_7_202) -> 0 | T11: =DSUM(SEP_2013_A,32,CL_7_202) -> 0 | U11: =DSUM(SEP_2013_A,33,CL_7_202) -> 0 | V11: =DSUM(SEP_2013_A,34,CL_7_202) -> 0
B12: CL_9_ | C12: =VLOOKUP(B12,BASE_A,6,FALSE) -> Rancho La Cuchilla No. 9 | D12: =VLOOKUP(B12,BASE_A,8,FALSE) -> Martín del Campo | E12: =VLOOKUP(B12,BASE_A,9,FALSE) -> 300 | F12: =DSUM(SEP_2013_A,AA,CL_9_) -> 600 | G12: =H12-F12 -> 300 | H12: =DSUM(SEP_2013_A,importe,CL_9_) -> 900 | I12: =IF(VLOOKUP(B12,BASE_A,9,FALSE)=0,0,G12/VLOOKUP(B12,BASE_A,9,FALSE)) -> 1 | J12: Cuchilla | K12: =DSUM(SEP_2013_A,23,CL_9_) -> 300 | L12: =DSUM(SEP_2013_A,24,CL_9_) -> 0 | M12: =DSUM(SEP_2013_A,25,CL_9_) -> 0 | N12: =DSUM(SEP_2013_A,26,CL_9_) -> 0 | O12: =DSUM(SEP_2013_A,27,CL_9_) -> 0 | P12: =DSUM(SEP_2013_A,28,CL_9_) -> 0 | Q12: =DSUM(SEP_2013_A,29,CL_9_) -> 0 | R12: =DSUM(SEP_2013_A,30,CL_9_) -> 0 | S12: =DSUM(SEP_2013_A,31,CL_9_) -> 0 | T12: =DSUM(SEP_2013_A,32,CL_9_) -> 0 | U12: =DSUM(SEP_2013_A,33,CL_9_) -> 0 | V12: =DSUM(SEP_2013_A,34,CL_9_) -> 0
B13: CL_11_ | C13: =VLOOKUP(B13,BASE_A,6,FALSE) -> Rancho La Cuchilla No. 11 | D13: =VLOOKUP(B13,BASE_A,8,FALSE) -> Santiago | E13: =VLOOKUP(B13,BASE_A,9,FALSE) -> 300 | F13: =DSUM(SEP_2013_A,AA,CL_11_) -> 0 | G13: =H13-F13 -> 0 | H13: =DSUM(SEP_2013_A,importe,CL_11_) -> 0 | I13: =IF(VLOOKUP(B13,BASE_A,9,FALSE)=0,0,G13/VLOOKUP(B13,BASE_A,9,FALSE)) -> 0 | J13: Cuchilla | K13: =DSUM(SEP_2013_A,23,CL_11_) -> 0 | L13: =DSUM(SEP_2013_A,24,CL_11_) -> 0 | M13: =DSUM(SEP_2013_A,25,CL_11_) -> 0 | N13: =DSUM(SEP_2013_A,26,CL_11_) -> 0 | O13: =DSUM(SEP_2013_A,27,CL_11_) -> 0 | P13: =DSUM(SEP_2013_A,28,CL_11_) -> 0 | Q13: =DSUM(SEP_2013_A,29,CL_11_) -> 0 | R13: =DSUM(SEP_2013_A,30,CL_11_) -> 0 | S13: =DSUM(SEP_2013_A,31,CL_11_) -> 0 | T13: =DSUM(SEP_2013_A,32,CL_11_) -> 0 | U13: =DSUM(SEP_2013_A,33,CL_11_) -> 0 | V13: =DSUM(SEP_2013_A,34,CL_11_) -> 0
B14: CL_12_ | C14: =VLOOKUP(B14,BASE_A,6,FALSE) -> Rancho La Cuchilla No. 12 | D14: =VLOOKUP(B14,BASE_A,8,FALSE) -> Rivera Flores | E14: =VLOOKUP(B14,BASE_A,9,FALSE) -> 300 | F14: =DSUM(SEP_2013_A,AA,CL_12_) -> 250 | G14: =H14-F14 -> 2700 | H14: =DSUM(SEP_2013_A,importe,CL_12_) -> 2950 | I14: =IF(VLOOKUP(B14,BASE_A,9,FALSE)=0,0,G14/VLOOKUP(B14,BASE_A,9,FALSE)) -> 9 | J14: Cuchilla | K14: =DSUM(SEP_2013_A,23,CL_12_) -> 300 | L14: =DSUM(SEP_2013_A,24,CL_12_) -> 300 | M14: =DSUM(SEP_2013_A,25,CL_12_) -> 300 | N14: =DSUM(SEP_2013_A,26,CL_12_) -> 300 | O14: =DSUM(SEP_2013_A,27,CL_12_) -> 300 | P14: =DSUM(SEP_2013_A,28,CL_12_) -> 300 | Q14: =DSUM(SEP_2013_A,29,CL_12_) -> 300 | R14: =DSUM(SEP_2013_A,30,CL_12_) -> 300 | S14: =DSUM(SEP_2013_A,31,CL_12_) -> 300 | T14: =DSUM(SEP_2013_A,32,CL_12_) -> 0 | U14: =DSUM(SEP_2013_A,33,CL_12_) -> 0 | V14: =DSUM(SEP_2013_A,34,CL_12_) -> 0
B15: CL_13_ | C15: =VLOOKUP(B15,BASE_A,6,FALSE) -> Rancho La Cuchilla No. 13 | D15: =VLOOKUP(B15,BASE_A,8,FALSE) -> Torres | E15: =VLOOKUP(B15,BASE_A,9,FALSE) -> 300 | F15: =DSUM(SEP_2013_A,AA,CL_13_) -> 0 | G15: =H15-F15 -> 0 | H15: =DSUM(SEP_2013_A,importe,CL_13_) -> 0 | I15: =IF(VLOOKUP(B15,BASE_A,9,FALSE)=0,0,G15/VLOOKUP(B15,BASE_A,9,FALSE)) -> 0 | J15: Cuchilla | K15: =DSUM(SEP_2013_A,23,CL_13_) -> 0 | L15: =DSUM(SEP_2013_A,24,CL_13_) -> 0 | M15: =DSUM(SEP_2013_A,25,CL_13_) -> 0 | N15: =DSUM(SEP_2013_A,26,CL_13_) -> 0 | O15: =DSUM(SEP_2013_A,27,CL_13_) -> 0 | P15: =DSUM(SEP_2013_A,28,CL_13_) -> 0 | Q15: =DSUM(SEP_2013_A,29,CL_13_) -> 0 | R15: =DSUM(SEP_2013_A,30,CL_13_) -> 0 | S15: =DSUM(SEP_2013_A,31,CL_13_) -> 0 | T15: =DSUM(SEP_2013_A,32,CL_13_) -> 0 | U15: =DSUM(SEP_2013_A,33,CL_13_) -> 0 | V15: =DSUM(SEP_2013_A,34,CL_13_) -> 0
B16: CL_14_ | C16: =VLOOKUP(B16,BASE_A,6,FALSE) -> Rancho La Cuchilla No. 14 | D16: =VLOOKUP(B16,BASE_A,8,FALSE) -> Chávez Lara | E16: =VLOOKUP(B16,BASE_A,9,FALSE) -> 300 | F16: =DSUM(SEP_2013_A,AA,CL_14_) -> 0 | G16: =H16-F16 -> 1200 | H16: =DSUM(SEP_2013_A,importe,CL_14_) -> 1200 | I16: =IF(VLOOKUP(B16,BASE_A,9,FALSE)=0,0,G16/VLOOKUP(B16,BASE_A,9,FALSE)) -> 4 | J16: Cuchilla | K16: =DSUM(SEP_2013_A,23,CL_14_) -> 0 | L16: =DSUM(SEP_2013_A,24,CL_14_) -> 0 | M16: =DSUM(SEP_2013_A,25,CL_14_) -> 0 | N16: =DSUM(SEP_2013_A,26,CL_14_) -> 0 | O16: =DSUM(SEP_2013_A,27,CL_14_) -> 300 | P16: =DSUM(SEP_2013_A,28,CL_14_) -> 300 | Q16: =DSUM(SEP_2013_A,29,CL_14_) -> 300 | R16: =DSUM(SEP_2013_A,30,CL_14_) -> 300 | S16: =DSUM(SEP_2013_A,31,CL_14_) -> 0 | T16: =DSUM(SEP_2013_A,32,CL_14_) -> 0 | U16: =DSUM(SEP_2013_A,33,CL_14_) -> 0 | V16: =DSUM(SEP_2013_A,34,CL_14_) -> 0
B17: CL_15_ | C17: =VLOOKUP(B17,BASE_A,6,FALSE) -> Rancho La Cuchilla No. 15 | D17: =VLOOKUP(B17,BASE_A,8,FALSE) -> Guerrero Ponce | E17: =VLOOKUP(B17,BASE_A,9,FALSE) -> 300 | F17: =DSUM(SEP_2013_A,AA,CL_15_) -> 900 | G17: =H17-F17 -> 2400 | H17: =DSUM(SEP_2013_A,importe,CL_15_) -> 3300 | I17: =IF(VLOOKUP(B17,BASE_A,9,FALSE)=0,0,G17/VLOOKUP(B17,BASE_A,9,FALSE)) -> 8 | J17: Cuchilla | K17: =DSUM(SEP_2013_A,23,CL_15_) -> 300 | L17: =DSUM(SEP_2013_A,24,CL_15_) -> 300 | M17: =DSUM(SEP_2013_A,25,CL_15_) -> 300 | N17: =DSUM(SEP_2013_A,26,CL_15_) -> 300 | O17: =DSUM(SEP_2013_A,27,CL_15_) -> 300 | P17: =DSUM(SEP_2013_A,28,CL_15_) -> 300 | Q17: =DSUM(SEP_2013_A,29,CL_15_) -> 300 | R17: =DSUM(SEP_2013_A,30,CL_15_) -> 300 | S17: =DSUM(SEP_2013_A,31,CL_15_) -> 0 | T17: =DSUM(SEP_2013_A,32,CL_15_) -> 0 | U17: =DSUM(SEP_2013_A,33,CL_15_) -> 0 | V17: =DSUM(SEP_2013_A,34,CL_15_) -> 0
B18: CL_18_ | C18: =VLOOKUP(B18,BASE_A,6,FALSE) -> Rancho La Cuchilla No. 18 | D18: =VLOOKUP(B18,BASE_A,8,FALSE) -> Aldana Sánchez | E18: =VLOOKUP(B18,BASE_A,9,FALSE) -> 300 | F18: =DSUM(SEP_2013_A,AA,CL_18_) -> 300 | G18: =H18-F18 -> 2700 | H18: =DSUM(SEP_2013_A,importe,CL_18_) -> 3000 | I18: =IF(VLOOKUP(B18,BASE_A,9,FALSE)=0,0,G18/VLOOKUP(B18,BASE_A,9,FALSE)) -> 9 | J18: Cuchilla | K18: =DSUM(SEP_2013_A,23,CL_18_) -> 300 | L18: =DSUM(SEP_2013_A,24,CL_18_) -> 300 | M18: =DSUM(SEP_2013_A,25,CL_18_) -> 300 | N18: =DSUM(SEP_2013_A,26,CL_18_) -> 300 | O18: =DSUM(SEP_2013_A,27,CL_18_) -> 300 | P18: =DSUM(SEP_2013_A,28,CL_18_) -> 300 | Q18: =DSUM(SEP_2013_A,29,CL_18_) -> 300 | R18: =DSUM(SEP_2013_A,30,CL_18_) -> 300 | S18: =DSUM(SEP_2013_A,31,CL_18_) -> 300 | T18: =DSUM(SEP_2013_A,32,CL_18_) -> 0 | U18: =DSUM(SEP_2013_A,33,CL_18_) -> 0 | V18: =DSUM(SEP_2013_A,34,CL_18_) -> 0
B19: CL_19_ | C19: =VLOOKUP(B19,BASE_A,6,FALSE) -> Rancho La Cuchilla No. 19 | D19: =VLOOKUP(B19,BASE_A,8,FALSE) -> Tapia Vázquez | E19: =VLOOKUP(B19,BASE_A,9,FALSE) -> 300 | F19: =DSUM(SEP_2013_A,AA,CL_19_) -> 300 | G19: =H19-F19 -> 2700 | H19: =DSUM(SEP_2013_A,importe,CL_19_) -> 3000 | I19: =IF(VLOOKUP(B19,BASE_A,9,FALSE)=0,0,G19/VLOOKUP(B19,BASE_A,9,FALSE)) -> 9 | J19: Cuchilla | K19: =DSUM(SEP_2013_A,23,CL_19_) -> 300 | L19: =DSUM(SEP_2013_A,24,CL_19_) -> 300 | M19: =DSUM(SEP_2013_A,25,CL_19_) -> 300 | N19: =DSUM(SEP_2013_A,26,CL_19_) -> 300 | O19: =DSUM(SEP_2013_A,27,CL_19_) -> 300 | P19: =DSUM(SEP_2013_A,28,CL_19_) -> 300 | Q19: =DSUM(SEP_2013_A,29,CL_19_) -> 300 | R19: =DSUM(SEP_2013_A,30,CL_19_) -> 300 | S19: =DSUM(SEP_2013_A,31,CL_19_) -> 300 | T19: =DSUM(SEP_2013_A,32,CL_19_) -> 0 | U19: =DSUM(SEP_2013_A,33,CL_19_) -> 0 | V19: =DSUM(SEP_2013_A,34,CL_19_) -> 0
B20: CL_20_ | C20: =VLOOKUP(B20,BASE_A,6,FALSE) -> Rancho La Cuchilla No. 20 | D20: =VLOOKUP(B20,BASE_A,8,FALSE) -> Sánchez López | E20: =VLOOKUP(B20,BASE_A,9,FALSE) -> 300 | F20: =DSUM(SEP_2013_A,AA,CL_20_) -> 300 | G20: =H20-F20 -> 2700 | H20: =DSUM(SEP_2013_A,importe,CL_20_) -> 3000 | I20: =IF(VLOOKUP(B20,BASE_A,9,FALSE)=0,0,G20/VLOOKUP(B20,BASE_A,9,FALSE)) -> 9 | J20: Cuchilla | K20: =DSUM(SEP_2013_A,23,CL_20_) -> 300 | L20: =DSUM(SEP_2013_A,24,CL_20_) -> 300 | M20: =DSUM(SEP_2013_A,25,CL_20_) -> 300 | N20: =DSUM(SEP_2013_A,26,CL_20_) -> 300 | O20: =DSUM(SEP_2013_A,27,CL_20_) -> 300 | P20: =DSUM(SEP_2013_A,28,CL_20_) -> 300 | Q20: =DSUM(SEP_2013_A,29,CL_20_) -> 300 | R20: =DSUM(SEP_2013_A,30,CL_20_) -> 300 | S20: =DSUM(SEP_2013_A,31,CL_20_) -> 300 | T20: =DSUM(SEP_2013_A,32,CL_20_) -> 0 | U20: =DSUM(SEP_2013_A,33,CL_20_) -> 0 | V20: =DSUM(SEP_2013_A,34,CL_20_) -> 0
B21: CL_21_ | C21: =VLOOKUP(B21,BASE_A,6,FALSE) -> Rancho La Cuchilla No. 21 | D21: =VLOOKUP(B21,BASE_A,8,FALSE) -> Solórzano Calderón | E21: =VLOOKUP(B21,BASE_A,9,FALSE) -> 300 | F21: =DSUM(SEP_2013_A,AA,CL_21_) -> 0 | G21: =H21-F21 -> 3300 | H21: =DSUM(SEP_2013_A,importe,CL_21_) -> 3300 | I21: =IF(VLOOKUP(B21,BASE_A,9,FALSE)=0,0,(G21/VLOOKUP(B21,BASE_A,9,FALSE)))+1 -> 12 | J21: Cuchilla | K21: =DSUM(SEP_2013_A,23,CL_21_) -> 300 | L21: =DSUM(SEP_2013_A,24,CL_21_) -> 300 | M21: =DSUM(SEP_2013_A,25,CL_21_) -> 300 | N21: =DSUM(SEP_2013_A,26,CL_21_) -> 300 | O21: =DSUM(SEP_2013_A,27,CL_21_) -> 300 | P21: =DSUM(SEP_2013_A,28,CL_21_) -> 300 | Q21: =DSUM(SEP_2013_A,29,CL_21_) -> 300 | R21: =DSUM(SEP_2013_A,30,CL_21_) -> 300 | S21: =DSUM(SEP_2013_A,31,CL_21_) -> 300 | T21: =DSUM(SEP_2013_A,32,CL_21_) -> 300 | U21: =DSUM(SEP_2013_A,33,CL_21_) -> 300 | V21: =DSUM(SEP_2013_A,34,CL_21_) -> 0
B22: CL_23_ | C22: =VLOOKUP(B22,BASE_A,6,FALSE) -> Rancho La Cuchilla No. 23 | D22: =VLOOKUP(B22,BASE_A,8,FALSE) -> Ocampo | E22: =VLOOKUP(B22,BASE_A,9,FALSE) -> 200 | F22: =DSUM(SEP_2013_A,AA,CL_23_) -> 200 | G22: =H22-F22 -> 600 | H22: =DSUM(SEP_2013_A,importe,CL_23_) -> 800 | I22: =IF(VLOOKUP(B22,BASE_A,9,FALSE)=0,0,G22/VLOOKUP(B22,BASE_A,9,FALSE)) -> 3 | J22: Cuchilla | K22: =DSUM(SEP_2013_A,23,CL_23_) -> 200 | L22: =DSUM(SEP_2013_A,24,CL_23_) -> 200 | M22: =DSUM(SEP_2013_A,25,CL_23_) -> 200 | N22: =DSUM(SEP_2013_A,26,CL_23_) -> 0 | O22: =DSUM(SEP_2013_A,27,CL_23_) -> 0 | P22: =DSUM(SEP_2013_A,28,CL_23_) -> 0 | Q22: =DSUM(SEP_2013_A,29,CL_23_) -> 0 | R22: =DSUM(SEP_2013_A,30,CL_23_) -> 0 | S22: =DSUM(SEP_2013_A,31,CL_23_) -> 0 | T22: =DSUM(SEP_2013_A,32,CL_23_) -> 0 | U22: =DSUM(SEP_2013_A,33,CL_23_) -> 0 | V22: =DSUM(SEP_2013_A,34,CL_23_) -> 0
B23: CL_25_ | C23: =VLOOKUP(B23,BASE_A,6,FALSE) -> Rancho La Cuchilla No. 25 | D23: =VLOOKUP(B23,BASE_A,8,FALSE) -> García de León | E23: =VLOOKUP(B23,BASE_A,9,FALSE) -> 300 | F23: =DSUM(SEP_2013_A,AA,CL_25_) -> 0 | G23: =H23-F23 -> 0 | H23: =DSUM(SEP_2013_A,importe,CL_25_) -> 0 | I23: =IF(VLOOKUP(B23,BASE_A,9,FALSE)=0,0,G23/VLOOKUP(B23,BASE_A,9,FALSE)) -> 0 | J23: Cuchilla | K23: =DSUM(SEP_2013_A,23,CL_25_) -> 0 | L23: =DSUM(SEP_2013_A,24,CL_25_) -> 0 | M23: =DSUM(SEP_2013_A,25,CL_25_) -> 0 | N23: =DSUM(SEP_2013_A,26,CL_25_) -> 0 | O23: =DSUM(SEP_2013_A,27,CL_25_) -> 0 | P23: =DSUM(SEP_2013_A,28,CL_25_) -> 0 | Q23: =DSUM(SEP_2013_A,29,CL_25_) -> 0 | R23: =DSUM(SEP_2013_A,30,CL_25_) -> 0 | S23: =DSUM(SEP_2013_A,31,CL_25_) -> 0 | T23: =DSUM(SEP_2013_A,32,CL_25_) -> 0 | U23: =DSUM(SEP_2013_A,33,CL_25_) -> 0 | V23: =DSUM(SEP_2013_A,34,CL_25_) -> 0
B24: CL_27_ | C24: =VLOOKUP(B24,BASE_A,6,FALSE) -> Rancho La Cuchilla No. 27 | D24: =VLOOKUP(B24,BASE_A,8,FALSE) -> Montoya | E24: =VLOOKUP(B24,BASE_A,9,FALSE) -> 300 | F24: =DSUM(SEP_2013_A,AA,CL_27_) -> 0 | G24: =H24-F24 -> 0 | H24: =DSUM(SEP_2013_A,importe,CL_27_) -> 0 | I24: =IF(VLOOKUP(B24,BASE_A,9,FALSE)=0,0,G24/VLOOKUP(B24,BASE_A,9,FALSE)) -> 0 | J24: Cuchilla | K24: =DSUM(SEP_2013_A,23,CL_27_) -> 0 | L24: =DSUM(SEP_2013_A,24,CL_27_) -> 0 | M24: =DSUM(SEP_2013_A,25,CL_27_) -> 0 | N24: =DSUM(SEP_2013_A,26,CL_27_) -> 0 | O24: =DSUM(SEP_2013_A,27,CL_27_) -> 0 | P24: =DSUM(SEP_2013_A,28,CL_27_) -> 0 | Q24: =DSUM(SEP_2013_A,29,CL_27_) -> 0 | R24: =DSUM(SEP_2013_A,30,CL_27_) -> 0 | S24: =DSUM(SEP_2013_A,31,CL_27_) -> 0 | T24: =DSUM(SEP_2013_A,32,CL_27_) -> 0 | U24: =DSUM(SEP_2013_A,33,CL_27_) -> 0 | V24: =DSUM(SEP_2013_A,34,CL_27_) -> 0
B25: CL_28_ | C25: =VLOOKUP(B25,BASE_A,6,FALSE) -> Rancho La Cuchilla No. 28 | D25: =VLOOKUP(B25,BASE_A,8,FALSE) -> Prado de los S. | E25: =VLOOKUP(B25,BASE_A,9,FALSE) -> 300 | F25: =DSUM(SEP_2013_A,AA,CL_28_) -> 0 | G25: =H25-F25 -> 0 | H25: =DSUM(SEP_2013_A,importe,CL_28_) -> 0 | I25: =IF(VLOOKUP(B25,BASE_A,9,FALSE)=0,0,G25/VLOOKUP(B25,BASE_A,9,FALSE)) -> 0 | J25: Cuchilla | K25: =DSUM(BCO_ENE13,7,CL_28_) -> 0 | L25: =DSUM(BCO_FEB13,7,CL_28_) -> 3300.28 | M25: =DSUM(BCO_MAR13,7,CL_28_) -> 0 | N25: =DSUM(BCO_ABR13,7,CL_28_) -> 0 | O25: =DSUM(BCO_MAY13,7,CL_28_) -> 0 | P25: =DSUM(BCO_JUN13,7,CL_28_) -> 0 | Q25: =DSUM(BCO_JUL13,7,CL_28_) -> 0 | R25: =DSUM(BCO_AGO13,7,CL_28_) -> 0 | S25: =DSUM(BCO_SEP13,7,CL_28_) -> 0
B26: CL_29_ | C26: =VLOOKUP(B26,BASE_A,6,FALSE) -> Rancho La Cuchilla No. 29 | D26: =VLOOKUP(B26,BASE_A,8,FALSE) -> Vega Sánchez C. | E26: =VLOOKUP(B26,BASE_A,9,FALSE) -> 300 | F26: =DSUM(SEP_2013_A,AA,CL_29_) -> 0 | G26: =H26-F26 -> 2100 | H26: =DSUM(BCO_SEP13_A,7,CL_29_) -> 2100 | I26: =IF(VLOOKUP(B26,BASE_A,9,FALSE)=0,0,G26/VLOOKUP(B26,BASE_A,9,FALSE)) -> 7 | J26: Cuchilla | K26: =DSUM(BCO_ENE13,7,CL_29_) -> 300 | L26: =DSUM(BCO_FEB13,7,CL_29_) -> 300 | M26: =DSUM(BCO_MAR13,7,CL_29_) -> 300 | N26: =DSUM(BCO_ABR13,7,CL_29_) -> 300 | O26: =DSUM(BCO_MAY13,7,CL_29_) -> 300 | P26: =DSUM(BCO_JUN13,7,CL_29_) -> 300 | Q26: =DSUM(BCO_JUL13,7,CL_29_) -> 0 | R26: =DSUM(BCO_AGO13,7,CL_29_) -> 300 | S26: =DSUM(BCO_SEP13,7,CL_29_) -> 0
B27: CL_30_ | C27: =VLOOKUP(B27,BASE_A,6,FALSE) -> Rancho La Cuchilla No. 30 | D27: =VLOOKUP(B27,BASE_A,8,FALSE) -> Ruiz Navarrete | E27: =VLOOKUP(B27,BASE_A,9,FALSE) -> 300 | F27: =DSUM(SEP_2013_A,AA,CL_30_) -> 0 | G27: =H27-F27 -> 0 | H27: =DSUM(SEP_2013_A,importe,CL_30_) -> 0 | I27: =IF(VLOOKUP(B27,BASE_A,9,FALSE)=0,0,G27/VLOOKUP(B27,BASE_A,9,FALSE)) -> 0 | J27: Cuchilla | K27: =DSUM(SEP_2013_A,23,CL_30_) -> 0 | L27: =DSUM(SEP_2013_A,24,CL_30_) -> 0 | M27: =DSUM(SEP_2013_A,25,CL_30_) -> 0 | N27: =DSUM(SEP_2013_A,26,CL_30_) -> 0 | O27: =DSUM(SEP_2013_A,27,CL_30_) -> 0 | P27: =DSUM(SEP_2013_A,28,CL_30_) -> 0 | Q27: =DSUM(SEP_2013_A,29,CL_30_) -> 0 | R27: =DSUM(SEP_2013_A,30,CL_30_) -> 0 | S27: =DSUM(SEP_2013_A,31,CL_30_) -> 0 | T27: =DSUM(SEP_2013_A,32,CL_30_) -> 0 | U27: =DSUM(SEP_2013_A,33,CL_30_) -> 0 | V27: =DSUM(SEP_2013_A,34,CL_30_) -> 0
B28: CL_31_ | C28: =VLOOKUP(B28,BASE_A,6,FALSE) -> Rancho La Cuchilla No. 31 | D28: =VLOOKUP(B28,BASE_A,8,FALSE) -> Espinoza Serrano | E28: =VLOOKUP(B28,BASE_A,9,FALSE) -> 300 | F28: =DSUM(SEP_2013_A,AA,CL_31_) -> 0 | G28: =H28-F28 -> 1000 | H28: =DSUM(SEP_2013_A,importe,CL_31_) -> 1000 | I28: =IF(VLOOKUP(B28,BASE_A,9,FALSE)=0,0,G28/VLOOKUP(B28,BASE_A,9,FALSE)) -> 3.3333333 | J28: Cuchilla | K28: =DSUM(SEP_2013_A,23,CL_31_) -> 300 | L28: =DSUM(SEP_2013_A,24,CL_31_) -> 300 | M28: =DSUM(SEP_2013_A,25,CL_31_) -> 300 | N28: =DSUM(SEP_2013_A,26,CL_31_) -> 100 | O28: =DSUM(SEP_2013_A,27,CL_31_) -> 0 | P28: =DSUM(SEP_2013_A,28,CL_31_) -> 0 | Q28: =DSUM(SEP_2013_A,29,CL_31_) -> 0 | R28: =DSUM(SEP_2013_A,30,CL_31_) -> 0 | S28: =DSUM(SEP_2013_A,31,CL_31_) -> 0 | T28: =DSUM(SEP_2013_A,32,CL_31_) -> 0 | U28: =DSUM(SEP_2013_A,33,CL_31_) -> 0 | V28: =DSUM(SEP_2013_A,34,CL_31_) -> 0
B29: CL_32_ | C29: =VLOOKUP(B29,BASE_A,6,FALSE) -> Rancho La Cuchilla No. 32 | D29: =VLOOKUP(B29,BASE_A,8,FALSE) -> Hernández | E29: =VLOOKUP(B29,BASE_A,9,FALSE) -> 300 | F29: =DSUM(SEP_2013_A,AA,CL_32_) -> 1200 | G29: =H29-F29 -> 2400 | H29: =DSUM(SEP_2013_A,importe,CL_32_) -> 3600 | I29: =IF(VLOOKUP(B29,BASE_A,9,FALSE)=0,0,G29/VLOOKUP(B29,BASE_A,9,FALSE)) -> 8 | J29: Cuchilla | K29: =DSUM(SEP_2013_A,23,CL_32_) -> 300 | L29: =DSUM(SEP_2013_A,24,CL_32_) -> 300 | M29: =DSUM(SEP_2013_A,25,CL_32_) -> 300 | N29: =DSUM(SEP_2013_A,26,CL_32_) -> 300 | O29: =DSUM(SEP_2013_A,27,CL_32_) -> 300 | P29: =DSUM(SEP_2013_A,28,CL_32_) -> 300 | Q29: =DSUM(SEP_2013_A,29,CL_32_) -> 300 | R29: =DSUM(SEP_2013_A,30,CL_32_) -> 300 | S29: =DSUM(SEP_2013_A,31,CL_32_) -> 0 | T29: =DSUM(SEP_2013_A,32,CL_32_) -> 0 | U29: =DSUM(SEP_2013_A,33,CL_32_) -> 0 | V29: =DSUM(SEP_2013_A,34,CL_32_) -> 0
B30: CL_33_ | C30: =VLOOKUP(B30,BASE_A,6,FALSE) -> Rancho La Cuchilla No. 33 | D30: =VLOOKUP(B30,BASE_A,8,FALSE) -> Tanús | E30: =VLOOKUP(B30,BASE_A,9,FALSE) -> 300 | F30: =DSUM(SEP_2013_A,AA,CL_33_) -> 300 | G30: =H30-F30 -> 2700 | H30: =DSUM(SEP_2013_A,importe,CL_33_) -> 3000 | I30: =IF(VLOOKUP(B30,BASE_A,9,FALSE)=0,0,G30/VLOOKUP(B30,BASE_A,9,FALSE)) -> 9 | J30: Cuchilla | K30: =DSUM(SEP_2013_A,23,CL_33_) -> 300 | L30: =DSUM(SEP_2013_A,24,CL_33_) -> 300 | M30: =DSUM(SEP_2013_A,25,CL_33_) -> 300 | N30: =DSUM(SEP_2013_A,26,CL_33_) -> 300 | O30: =DSUM(SEP_2013_A,27,CL_33_) -> 300 | P30: =DSUM(SEP_2013_A,28,CL_33_) -> 300 | Q30: =DSUM(SEP_2013_A,29,CL_33_) -> 300 | R30: =DSUM(SEP_2013_A,30,CL_33_) -> 300 | S30: =DSUM(SEP_2013_A,31,CL_33_) -> 300 | T30: =DSUM(SEP_2013_A,32,CL_33_) -> 0 | U30: =DSUM(SEP_2013_A,33,CL_33_) -> 0 | V30: =DSUM(SEP_2013_A,34,CL_33_) -> 0
B31: CL_35_ | C31: =VLOOKUP(B31,BASE_A,6,FALSE) -> Rancho La Cuchilla No. 35 | D31: =VLOOKUP(B31,BASE_A,8,FALSE) -> Mendoza | E31: =VLOOKUP(B31,BASE_A,9,FALSE) -> 150 | F31: =DSUM(SEP_2013_A,AA,CL_35_) -> 150 | G31: =H31-F31 -> 450 | H31: =DSUM(SEP_2013_A,importe,CL_35_) -> 600 | I31: =IF(VLOOKUP(B31,BASE_A,9,FALSE)=0,0,G31/VLOOKUP(B31,BASE_A,9,FALSE)) -> 3 | J31: Cuchilla | K31: =DSUM(SEP_2013_A,23,CL_35_) -> 150 | L31: =DSUM(SEP_2013_A,24,CL_35_) -> 150 | M31: =DSUM(SEP_2013_A,25,CL_35_) -> 150 | N31: =DSUM(SEP_2013_A,26,CL_35_) -> 0 | O31: =DSUM(SEP_2013_A,27,CL_35_) -> 0 | P31: =DSUM(SEP_2013_A,28,CL_35_) -> 0 | Q31: =DSUM(SEP_2013_A,29,CL_35_) -> 0 | R31: =DSUM(SEP_2013_A,30,CL_35_) -> 0 | S31: =DSUM(SEP_2013_A,31,CL_35_) -> 0 | T31: =DSUM(SEP_2013_A,32,CL_35_) -> 0 | U31: =DSUM(SEP_2013_A,33,CL_35_) -> 0 | V31: =DSUM(SEP_2013_A,34,CL_35_) -> 0
B32: CL_36_ | C32: =VLOOKUP(B32,BASE_A,6,FALSE) -> Rancho La Cuchilla No. 36 | D32: =VLOOKUP(B32,BASE_A,8,FALSE) -> Castillo | E32: =VLOOKUP(B32,BASE_A,9,FALSE) -> 300 | F32: =DSUM(SEP_2013_A,AA,CL_36_) -> 300 | G32: =H32-F32 -> 2400 | H32: =DSUM(SEP_2013_A,importe,CL_36_) -> 2700 | I32: =IF(VLOOKUP(B32,BASE_A,9,FALSE)=0,0,G32/VLOOKUP(B32,BASE_A,9,FALSE)) -> 8 | J32: Cuchilla | K32: =DSUM(SEP_2013_A,23,CL_36_) -> 300 | L32: =DSUM(SEP_2013_A,24,CL_36_) -> 300 | M32: =DSUM(SEP_2013_A,25,CL_36_) -> 300 | N32: =DSUM(SEP_2013_A,26,CL_36_) -> 300 | O32: =DSUM(SEP_2013_A,27,CL_36_) -> 300 | P32: =DSUM(SEP_2013_A,28,CL_36_) -> 300 | Q32: =DSUM(SEP_2013_A,29,CL_36_) -> 300 | R32: =DSUM(SEP_2013_A,30,CL_36_) -> 300 | S32: =DSUM(SEP_2013_A,31,CL_36_) -> 0 | T32: =DSUM(SEP_2013_A,32,CL_36_) -> 0 | U32: =DSUM(SEP_2013_A,33,CL_36_) -> 0 | V32: =DSUM(SEP_2013_A,34,CL_36_) -> 0
B33: CL_38_ | C33: =VLOOKUP(B33,BASE_A,6,FALSE) -> Rancho La Cuchilla No. 38 | D33: =VLOOKUP(B33,BASE_A,8,FALSE) -> Cerecedo | E33: =VLOOKUP(B33,BASE_A,9,FALSE) -> 300 | F33: =DSUM(SEP_2013_A,AA,CL_38_) -> 600 | G33: =H33-F33 -> 0 | H33: =DSUM(SEP_2013_A,importe,CL_38_) -> 600 | I33: =IF(VLOOKUP(B33,BASE_A,9,FALSE)=0,0,G33/VLOOKUP(B33,BASE_A,9,FALSE)) -> 0 | J33: Cuchilla | K33: =DSUM(SEP_2013_A,23,CL_38_) -> 0 | L33: =DSUM(SEP_2013_A,24,CL_38_) -> 0 | M33: =DSUM(SEP_2013_A,25,CL_38_) -> 0 | N33: =DSUM(SEP_2013_A,26,CL_38_) -> 0 | O33: =DSUM(SEP_2013_A,27,CL_38_) -> 0 | P33: =DSUM(SEP_2013_A,28,CL_38_) -> 0 | Q33: =DSUM(SEP_2013_A,29,CL_38_) -> 0 | R33: =DSUM(SEP_2013_A,30,CL_38_) -> 0 | S33: =DSUM(SEP_2013_A,31,CL_38_) -> 0 | T33: =DSUM(SEP_2013_A,32,CL_38_) -> 0 | U33: =DSUM(SEP_2013_A,33,CL_38_) -> 0 | V33: =DSUM(SEP_2013_A,34,CL_38_) -> 0
B34: CL_39_ | C34: =VLOOKUP(B34,BASE_A,6,FALSE) -> Rancho La Cuchilla No. 39 | D34: =VLOOKUP(B34,BASE_A,8,FALSE) -> Arenas | E34: =VLOOKUP(B34,BASE_A,9,FALSE) -> 300 | F34: =DSUM(SEP_2013_A,AA,CL_39_) -> 0 | G34: =H34-F34 -> 0 | H34: =DSUM(SEP_2013_A,importe,CL_39_) -> 0 | I34: =IF(VLOOKUP(B34,BASE_A,9,FALSE)=0,0,G34/VLOOKUP(B34,BASE_A,9,FALSE)) -> 0 | J34: Cuchilla | K34: =DSUM(SEP_2013_A,23,CL_39_) -> 0 | L34: =DSUM(SEP_2013_A,24,CL_39_) -> 0 | M34: =DSUM(SEP_2013_A,25,CL_39_) -> 0 | N34: =DSUM(SEP_2013_A,26,CL_39_) -> 0 | O34: =DSUM(SEP_2013_A,27,CL_39_) -> 0 | P34: =DSUM(SEP_2013_A,28,CL_39_) -> 0 | Q34: =DSUM(SEP_2013_A,29,CL_39_) -> 0 | R34: =DSUM(SEP_2013_A,30,CL_39_) -> 0 | S34: =DSUM(SEP_2013_A,31,CL_39_) -> 0 | T34: =DSUM(SEP_2013_A,32,CL_39_) -> 0 | U34: =DSUM(SEP_2013_A,33,CL_39_) -> 0 | V34: =DSUM(SEP_2013_A,34,CL_39_) -> 0
B35: CL_40_ | C35: =VLOOKUP(B35,BASE_A,6,FALSE) -> Rancho La Cuchilla No. 40 | D35: =VLOOKUP(B35,BASE_A,8,FALSE) -> López Pico | E35: =VLOOKUP(B35,BASE_A,9,FALSE) -> 300 | F35: =DSUM(SEP_2013_A,AA,CL_40_) -> 300 | G35: =H35-F35 -> 2700 | H35: =DSUM(SEP_2013_A,importe,CL_40_) -> 3000 | I35: =IF(VLOOKUP(B35,BASE_A,9,FALSE)=0,0,G35/VLOOKUP(B35,BASE_A,9,FALSE)) -> 9 | J35: Cuchilla | K35: =DSUM(SEP_2013_A,23,CL_40_) -> 300 | L35: =DSUM(SEP_2013_A,24,CL_40_) -> 300 | M35: =DSUM(SEP_2013_A,25,CL_40_) -> 300 | N35: =DSUM(SEP_2013_A,26,CL_40_) -> 300 | O35: =DSUM(SEP_2013_A,27,CL_40_) -> 300 | P35: =DSUM(SEP_2013_A,28,CL_40_) -> 300 | Q35: =DSUM(SEP_2013_A,29,CL_40_) -> 300 | R35: =DSUM(SEP_2013_A,30,CL_40_) -> 300 | S35: =DSUM(SEP_2013_A,31,CL_40_) -> 300 | T35: =DSUM(SEP_2013_A,32,CL_40_) -> 0 | U35: =DSUM(SEP_2013_A,33,CL_40_) -> 0 | V35: =DSUM(SEP_2013_A,34,CL_40_) -> 0
B36: CL_41_ | C36: =VLOOKUP(B36,BASE_A,6,FALSE) -> Rancho La Cuchilla No. 41 | D36: =VLOOKUP(B36,BASE_A,8,FALSE) -> Arriaga Lemus | E36: =VLOOKUP(B36,BASE_A,9,FALSE) -> 250 | F36: =DSUM(SEP_2013_A,AA,CL_41_) -> 250 | G36: =H36-F36 -> 2100 | H36: =DSUM(SEP_2013_A,importe,CL_41_) -> 2350 | I36: =IF(VLOOKUP(B36,BASE_A,9,FALSE)=0,0,G36/VLOOKUP(B36,BASE_A,9,FALSE)) -> 8.4 | J36: Cuchilla | K36: =DSUM(SEP_2013_A,23,CL_41_) -> 250 | L36: =DSUM(SEP_2013_A,24,CL_41_) -> 250 | M36: =DSUM(SEP_2013_A,25,CL_41_) -> 250 | N36: =DSUM(SEP_2013_A,26,CL_41_) -> 250 | O36: =DSUM(SEP_2013_A,27,CL_41_) -> 250 | P36: =DSUM(SEP_2013_A,28,CL_41_) -> 250 | Q36: =DSUM(SEP_2013_A,29,CL_41_) -> 300 | R36: =DSUM(SEP_2013_A,30,CL_41_) -> 300 | S36: =DSUM(SEP_2013_A,31,CL_41_) -> 0 | T36: =DSUM(SEP_2013_A,32,CL_41_) -> 0 | U36: =DSUM(SEP_2013_A,33,CL_41_) -> 0 | V36: =DSUM(SEP_2013_A,34,CL_41_) -> 0
B37: CL_42_ | C37: =VLOOKUP(B37,BASE_A,6,FALSE) -> Rancho La Cuchilla No. 42 | D37: =VLOOKUP(B37,BASE_A,8,FALSE) -> Mac Kinney | E37: =VLOOKUP(B37,BASE_A,9,FALSE) -> 300 | F37: =DSUM(SEP_2013_A,AA,CL_42_) -> 300 | G37: =H37-F37 -> 2700 | H37: =DSUM(SEP_2013_A,importe,CL_42_) -> 3000 | I37: =IF(VLOOKUP(B37,BASE_A,9,FALSE)=0,0,G37/VLOOKUP(B37,BASE_A,9,FALSE)) -> 9 | J37: Cuchilla | K37: =DSUM(SEP_2013_A,23,CL_42_) -> 300 | L37: =DSUM(SEP_2013_A,24,CL_42_) -> 300 | M37: =DSUM(SEP_2013_A,25,CL_42_) -> 300 | N37: =DSUM(SEP_2013_A,26,CL_42_) -> 300 | O37: =DSUM(SEP_2013_A,27,CL_42_) -> 300 | P37: =DSUM(SEP_2013_A,28,CL_42_) -> 300 | Q37: =DSUM(SEP_2013_A,29,CL_42_) -> 300 | R37: =DSUM(SEP_2013_A,30,CL_42_) -> 300 | S37: =DSUM(SEP_2013_A,31,CL_42_) -> 300 | T37: =DSUM(SEP_2013_A,32,CL_42_) -> 0 | U37: =DSUM(SEP_2013_A,33,CL_42_) -> 0 | V37: =DSUM(SEP_2013_A,34,CL_42_) -> 0
B38: CL_43_A | C38: =VLOOKUP(B38,BASE_A,6,FALSE) -> Rancho La Cuchilla No. 43, A | D38: =VLOOKUP(B38,BASE_A,8,FALSE) -> De la Rosa | E38: =VLOOKUP(B38,BASE_A,9,FALSE) -> 200 | F38: =DSUM(SEP_2013_A,AA,CL_43_A) -> 200 | G38: =H38-F38 -> 1800 | H38: =DSUM(SEP_2013_A,importe,CL_43_A) -> 2000 | I38: =IF(VLOOKUP(B38,BASE_A,9,FALSE)=0,0,G38/VLOOKUP(B38,BASE_A,9,FALSE)) -> 9 | J38: Cuchilla | K38: =DSUM(SEP_2013_A,23,CL_43_A) -> 200 | L38: =DSUM(SEP_2013_A,24,CL_43_A) -> 200 | M38: =DSUM(SEP_2013_A,25,CL_43_A) -> 200 | N38: =DSUM(SEP_2013_A,26,CL_43_A) -> 200 | O38: =DSUM(SEP_2013_A,27,CL_43_A) -> 200 | P38: =DSUM(SEP_2013_A,28,CL_43_A) -> 200 | Q38: =DSUM(SEP_2013_A,29,CL_43_A) -> 200 | R38: =DSUM(SEP_2013_A,30,CL_43_A) -> 400 | S38: =DSUM(SEP_2013_A,31,CL_43_A) -> 0 | T38: =DSUM(SEP_2013_A,32,CL_43_A) -> 0 | U38: =DSUM(SEP_2013_A,33,CL_43_A) -> 0 | V38: =DSUM(SEP_2013_A,34,CL_43_A) -> 0
B39: CL_43_B | C39: =VLOOKUP(B39,BASE_A,6,FALSE) -> Rancho La Cuchilla No. 43, B | D39: =VLOOKUP(B39,BASE_A,8,FALSE) -> Luna Albertano | E39: =VLOOKUP(B39,BASE_A,9,FALSE) -> 125 | F39: =DSUM(SEP_2013_A,AA,CL_43_B) -> 125 | G39: =H39-F39 -> 1125 | H39: =DSUM(SEP_2013_A,importe,CL_43_B) -> 1250 | I39: =IF(VLOOKUP(B39,BASE_A,9,FALSE)=0,0,G39/VLOOKUP(B39,BASE_A,9,FALSE)) -> 9 | J39: Cuchilla | K39: =DSUM(SEP_2013_A,23,CL_43_B) -> 125 | L39: =DSUM(SEP_2013_A,24,CL_43_B) -> 125 | M39: =DSUM(SEP_2013_A,25,CL_43_B) -> 125 | N39: =DSUM(SEP_2013_A,26,CL_43_B) -> 125 | O39: =DSUM(SEP_2013_A,27,CL_43_B) -> 125 | P39: =DSUM(SEP_2013_A,28,CL_43_B) -> 125 | Q39: =DSUM(SEP_2013_A,29,CL_43_B) -> 125 | R39: =DSUM(SEP_2013_A,30,CL_43_B) -> 125 | S39: =DSUM(SEP_2013_A,31,CL_43_B) -> 125 | T39: =DSUM(SEP_2013_A,32,CL_43_B) -> 0 | U39: =DSUM(SEP_2013_A,33,CL_43_B) -> 0 | V39: =DSUM(SEP_2013_A,34,CL_43_B) -> 0
B40: CL_44_ | C40: =VLOOKUP(B40,BASE_A,6,FALSE) -> Rancho La Cuchilla No. 44 | D40: =VLOOKUP(B40,BASE_A,8,FALSE) -> Garduño | E40: =VLOOKUP(B40,BASE_A,9,FALSE) -> 300 | F40: =DSUM(SEP_2013_A,AA,CL_44_) -> 0 | G40: =H40-F40 -> 0 | H40: =DSUM(SEP_2013_A,importe,CL_44_) -> 0 | I40: =IF(VLOOKUP(B40,BASE_A,9,FALSE)=0,0,G40/VLOOKUP(B40,BASE_A,9,FALSE)) -> 0 | J40: Cuchilla | K40: =DSUM(SEP_2013_A,23,CL_44_) -> 0 | L40: =DSUM(SEP_2013_A,24,CL_44_) -> 0 | M40: =DSUM(SEP_2013_A,25,CL_44_) -> 0 | N40: =DSUM(SEP_2013_A,26,CL_44_) -> 0 | O40: =DSUM(SEP_2013_A,27,CL_44_) -> 0 | P40: =DSUM(SEP_2013_A,28,CL_44_) -> 0 | Q40: =DSUM(SEP_2013_A,29,CL_44_) -> 0 | R40: =DSUM(SEP_2013_A,30,CL_44_) -> 0 | S40: =DSUM(SEP_2013_A,31,CL_44_) -> 0 | T40: =DSUM(SEP_2013_A,32,CL_44_) -> 0 | U40: =DSUM(SEP_2013_A,33,CL_44_) -> 0 | V40: =DSUM(SEP_2013_A,34,CL_44_) -> 0
B41: CL_45_ | C41: =VLOOKUP(B41,BASE_A,6,FALSE) -> Rancho La Cuchilla No. 45 | D41: =VLOOKUP(B41,BASE_A,8,FALSE) -> Estévez Hernández | E41: =VLOOKUP(B41,BASE_A,9,FALSE) -> 300 | F41: =DSUM(SEP_2013_A,AA,CL_45_) -> 600 | G41: =H41-F41 -> 2700 | H41: =DSUM(SEP_2013_A,importe,CL_45_) -> 3300 | I41: =IF(VLOOKUP(B41,BASE_A,9,FALSE)=0,0,G41/VLOOKUP(B41,BASE_A,9,FALSE)) -> 9 | J41: Cuchilla | K41: =DSUM(SEP_2013_A,23,CL_45_) -> 300 | L41: =DSUM(SEP_2013_A,24,CL_45_) -> 300 | M41: =DSUM(SEP_2013_A,25,CL_45_) -> 300 | N41: =DSUM(SEP_2013_A,26,CL_45_) -> 300 | O41: =DSUM(SEP_2013_A,27,CL_45_) -> 300 | P41: =DSUM(SEP_2013_A,28,CL_45_) -> 300 | Q41: =DSUM(SEP_2013_A,29,CL_45_) -> 300 | R41: =DSUM(SEP_2013_A,30,CL_45_) -> 300 | S41: =DSUM(SEP_2013_A,31,CL_45_) -> 300 | T41: =DSUM(SEP_2013_A,32,CL_45_) -> 0 | U41: =DSUM(SEP_2013_A,33,CL_45_) -> 0 | V41: =DSUM(SEP_2013_A,34,CL_45_) -> 0
B42: CL_46_ | C42: =VLOOKUP(B42,BASE_A,6,FALSE) -> Rancho La Cuchilla No. 46 | D42: =VLOOKUP(B42,BASE_A,8,FALSE) -> Cruz López | E42: =VLOOKUP(B42,BASE_A,9,FALSE) -> 300 | F42: =DSUM(SEP_2013_A,AA,CL_46_) -> 600 | G42: =H42-F42 -> 3000 | H42: =DSUM(SEP_2013_A,importe,CL_46_) -> 3600 | I42: =IF(VLOOKUP(B42,BASE_A,9,FALSE)=0,0,G42/VLOOKUP(B42,BASE_A,9,FALSE)) -> 10 | J42: Cuchilla | K42: =DSUM(SEP_2013_A,23,CL_46_) -> 300 | L42: =DSUM(SEP_2013_A,24,CL_46_) -> 300 | M42: =DSUM(SEP_2013_A,25,CL_46_) -> 300 | N42: =DSUM(SEP_2013_A,26,CL_46_) -> 300 | O42: =DSUM(SEP_2013_A,27,CL_46_) -> 300 | P42: =DSUM(SEP_2013_A,28,CL_46_) -> 300 | Q42: =DSUM(SEP_2013_A,29,CL_46_) -> 300 | R42: =DSUM(SEP_2013_A,30,CL_46_) -> 300 | S42: =DSUM(SEP_2013_A,31,CL_46_) -> 300 | T42: =DSUM(SEP_2013_A,32,CL_46_) -> 300 | U42: =DSUM(SEP_2013_A,33,CL_46_) -> 0 | V42: =DSUM(SEP_2013_A,34,CL_46_) -> 0
B43: CL_47_ | C43: =VLOOKUP(B43,BASE_A,6,FALSE) -> Rancho La Cuchilla No. 47 | D43: =VLOOKUP(B43,BASE_A,8,FALSE) -> López | E43: =VLOOKUP(B43,BASE_A,9,FALSE) -> 300 | F43: =DSUM(SEP_2013_A,AA,CL_47_) -> 600 | G43: =H43-F43 -> 1500 | H43: =DSUM(SEP_2013_A,importe,CL_47_) -> 2100 | I43: =IF(VLOOKUP(B43,BASE_A,9,FALSE)=0,0,G43/VLOOKUP(B43,BASE_A,9,FALSE)) -> 5 | J43: Cuchilla | K43: =DSUM(SEP_2013_A,23,CL_47_) -> 300 | L43: =DSUM(SEP_2013_A,24,CL_47_) -> 300 | M43: =DSUM(SEP_2013_A,25,CL_47_) -> 300 | N43: =DSUM(SEP_2013_A,26,CL_47_) -> 300 | O43: =DSUM(SEP_2013_A,27,CL_47_) -> 300 | P43: =DSUM(SEP_2013_A,28,CL_47_) -> 0 | Q43: =DSUM(SEP_2013_A,29,CL_47_) -> 0 | R43: =DSUM(SEP_2013_A,30,CL_47_) -> 0 | S43: =DSUM(SEP_2013_A,31,CL_47_) -> 0 | T43: =DSUM(SEP_2013_A,32,CL_47_) -> 0 | U43: =DSUM(SEP_2013_A,33,CL_47_) -> 0 | V43: =DSUM(SEP_2013_A,34,CL_47_) -> 0
B44: CL_49_ | C44: =VLOOKUP(B44,BASE_A,6,FALSE) -> Rancho La Cuchilla No. 49 | D44: =VLOOKUP(B44,BASE_A,8,FALSE) -> Orozco Castelazo | E44: =VLOOKUP(B44,BASE_A,9,FALSE) -> 300 | F44: =DSUM(SEP_2013_A,AA,CL_49_) -> 0 | G44: =H44-F44 -> 0 | H44: =DSUM(SEP_2013_A,importe,CL_49_) -> 0 | I44: =IF(VLOOKUP(B44,BASE_A,9,FALSE)=0,0,G44/VLOOKUP(B44,BASE_A,9,FALSE)) -> 0 | J44: Cuchilla | K44: =DSUM(SEP_2013_A,23,CL_49_) -> 0 | L44: =DSUM(SEP_2013_A,24,CL_49_) -> 0 | M44: =DSUM(SEP_2013_A,25,CL_49_) -> 0 | N44: =DSUM(SEP_2013_A,26,CL_49_) -> 0 | O44: =DSUM(SEP_2013_A,27,CL_49_) -> 0 | P44: =DSUM(SEP_2013_A,28,CL_49_) -> 0 | Q44: =DSUM(SEP_2013_A,29,CL_49_) -> 0 | R44: =DSUM(SEP_2013_A,30,CL_49_) -> 0 | S44: =DSUM(SEP_2013_A,31,CL_49_) -> 0 | T44: =DSUM(SEP_2013_A,32,CL_49_) -> 0 | U44: =DSUM(SEP_2013_A,33,CL_49_) -> 0 | V44: =DSUM(SEP_2013_A,34,CL_49_) -> 0
B45: CL_52_ | C45: =VLOOKUP(B45,BASE_A,6,FALSE) -> Rancho La Cuchilla No. 52 | D45: =VLOOKUP(B45,BASE_A,8,FALSE) -> Velázquez | E45: =VLOOKUP(B45,BASE_A,9,FALSE) -> 300 | F45: =DSUM(SEP_2013_A,AA,CL_52_) -> 0 | G45: =H45-F45 -> 0 | H45: =DSUM(SEP_2013_A,importe,CL_52_) -> 0 | I45: =IF(VLOOKUP(B45,BASE_A,9,FALSE)=0,0,G45/VLOOKUP(B45,BASE_A,9,FALSE)) -> 0 | J45: Cuchilla | K45: =DSUM(SEP_2013_A,23,CL_52_) -> 0 | L45: =DSUM(SEP_2013_A,24,CL_52_) -> 0 | M45: =DSUM(SEP_2013_A,25,CL_52_) -> 0 | N45: =DSUM(SEP_2013_A,26,CL_52_) -> 0 | O45: =DSUM(SEP_2013_A,27,CL_52_) -> 0 | P45: =DSUM(SEP_2013_A,28,CL_52_) -> 0 | Q45: =DSUM(SEP_2013_A,29,CL_52_) -> 0 | R45: =DSUM(SEP_2013_A,30,CL_52_) -> 0 | S45: =DSUM(SEP_2013_A,31,CL_52_) -> 0 | T45: =DSUM(SEP_2013_A,32,CL_52_) -> 0 | U45: =DSUM(SEP_2013_A,33,CL_52_) -> 0 | V45: =DSUM(SEP_2013_A,34,CL_52_) -> 0
B46: CL_53_ | C46: =VLOOKUP(B46,BASE_A,6,FALSE) -> Rancho La Cuchilla No. 53 | D46: =VLOOKUP(B46,BASE_A,8,FALSE) -> Loyo Ochoa | E46: =VLOOKUP(B46,BASE_A,9,FALSE) -> 300 | F46: =DSUM(SEP_2013_A,AA,CL_53_) -> 900 | G46: =H46-F46 -> 3600 | H46: =DSUM(SEP_2013_A,importe,CL_53_) -> 4500 | I46: =IF(VLOOKUP(B46,BASE_A,9,FALSE)=0,0,G46/VLOOKUP(B46,BASE_A,9,FALSE)) -> 12 | J46: Cuchilla | K46: =DSUM(SEP_2013_A,23,CL_53_) -> 300 | L46: =DSUM(SEP_2013_A,24,CL_53_) -> 300 | M46: =DSUM(SEP_2013_A,25,CL_53_) -> 300 | N46: =DSUM(SEP_2013_A,26,CL_53_) -> 300 | O46: =DSUM(SEP_2013_A,27,CL_53_) -> 300 | P46: =DSUM(SEP_2013_A,28,CL_53_) -> 300 | Q46: =DSUM(SEP_2013_A,29,CL_53_) -> 300 | R46: =DSUM(SEP_2013_A,30,CL_53_) -> 300 | S46: =DSUM(SEP_2013_A,31,CL_53_) -> 300 | T46: =DSUM(SEP_2013_A,32,CL_53_) -> 300 | U46: =DSUM(SEP_2013_A,33,CL_53_) -> 300 | V46: =DSUM(SEP_2013_A,34,CL_53_) -> 300
B47: CL_54_ | C47: =VLOOKUP(B47,BASE_A,6,FALSE) -> Rancho La Cuchilla No. 54 | D47: =VLOOKUP(B47,BASE_A,8,FALSE) -> Mendoza León | E47: =VLOOKUP(B47,BASE_A,9,FALSE) -> 300 | F47: =DSUM(SEP_2013_A,AA,CL_54_) -> 0 | G47: =H47-F47 -> 600 | H47: =DSUM(SEP_2013_A,importe,CL_54_) -> 600 | I47: =IF(VLOOKUP(B47,BASE_A,9,FALSE)=0,0,G47/VLOOKUP(B47,BASE_A,9,FALSE)) -> 2 | J47: Cuchilla | K47: =DSUM(SEP_2013_A,23,CL_54_) -> 0 | L47: =DSUM(SEP_2013_A,24,CL_54_) -> 0 | M47: =DSUM(SEP_2013_A,25,CL_54_) -> 0 | N47: =DSUM(SEP_2013_A,26,CL_54_) -> 0 | O47: =DSUM(SEP_2013_A,27,CL_54_) -> 0 | P47: =DSUM(SEP_2013_A,28,CL_54_) -> 0 | Q47: =DSUM(SEP_2013_A,29,CL_54_) -> 300 | R47: =DSUM(SEP_2013_A,30,CL_54_) -> 300 | S47: =DSUM(SEP_2013_A,31,CL_54_) -> 0 | T47: =DSUM(SEP_2013_A,32,CL_54_) -> 0 | U47: =DSUM(SEP_2013_A,33,CL_54_) -> 0 | V47: =DSUM(SEP_2013_A,34,CL_54_) -> 0
B48: CL_55_ | C48: =VLOOKUP(B48,BASE_A,6,FALSE) -> Rancho La Cuchilla No. 55 | D48: =VLOOKUP(B48,BASE_A,8,FALSE) -> López Velázquez | E48: =VLOOKUP(B48,BASE_A,9,FALSE) -> 300 | F48: =DSUM(SEP_2013_A,AA,CL_55_) -> 300 | G48: =H48-F48 -> 2400 | H48: =DSUM(SEP_2013_A,importe,CL_55_) -> 2700 | I48: =IF(VLOOKUP(B48,BASE_A,9,FALSE)=0,0,G48/VLOOKUP(B48,BASE_A,9,FALSE)) -> 8 | J48: Cuchilla | K48: =DSUM(SEP_2013_A,23,CL_55_) -> 300 | L48: =DSUM(SEP_2013_A,24,CL_55_) -> 300 | M48: =DSUM(SEP_2013_A,25,CL_55_) -> 300 | N48: =DSUM(SEP_2013_A,26,CL_55_) -> 300 | O48: =DSUM(SEP_2013_A,27,CL_55_) -> 300 | P48: =DSUM(SEP_2013_A,28,CL_55_) -> 300 | Q48: =DSUM(SEP_2013_A,29,CL_55_) -> 300 | R48: =DSUM(SEP_2013_A,30,CL_55_) -> 300 | S48: =DSUM(SEP_2013_A,31,CL_55_) -> 0 | T48: =DSUM(SEP_2013_A,32,CL_55_) -> 0 | U48: =DSUM(SEP_2013_A,33,CL_55_) -> 0 | V48: =DSUM(SEP_2013_A,34,CL_55_) -> 0
B49: CL_57_ | C49: =VLOOKUP(B49,BASE_A,6,FALSE) -> Rancho La Cuchilla No. 57 | D49: =VLOOKUP(B49,BASE_A,8,FALSE) -> 0 | E49: =VLOOKUP(B49,BASE_A,9,FALSE) -> 300 | F49: =DSUM(SEP_2013_A,AA,CL_57_) -> 0 | G49: =H49-F49 -> 0 | H49: =DSUM(SEP_2013_A,importe,CL_57_) -> 0 | I49: =IF(VLOOKUP(B49,BASE_A,9,FALSE)=0,0,G49/VLOOKUP(B49,BASE_A,9,FALSE)) -> 0 | J49: Cuchilla | K49: =DSUM(SEP_2013_A,23,CL_57_) -> 0 | L49: =DSUM(SEP_2013_A,24,CL_57_) -> 0 | M49: =DSUM(SEP_2013_A,25,CL_57_) -> 0 | N49: =DSUM(SEP_2013_A,26,CL_57_) -> 0 | O49: =DSUM(SEP_2013_A,27,CL_57_) -> 0 | P49: =DSUM(SEP_2013_A,28,CL_57_) -> 0 | Q49: =DSUM(SEP_2013_A,29,CL_57_) -> 0 | R49: =DSUM(SEP_2013_A,30,CL_57_) -> 0 | S49: =DSUM(SEP_2013_A,31,CL_57_) -> 0 | T49: =DSUM(SEP_2013_A,32,CL_57_) -> 0 | U49: =DSUM(SEP_2013_A,33,CL_57_) -> 0 | V49: =DSUM(SEP_2013_A,34,CL_57_) -> 0
B50: CL_58_ | C50: =VLOOKUP(B50,BASE_A,6,FALSE) -> Rancho La Cuchilla No. 58 | D50: =VLOOKUP(B50,BASE_A,8,FALSE) -> Serdán | E50: =VLOOKUP(B50,BASE_A,9,FALSE) -> 300 | F50: =DSUM(SEP_2013_A,AA,CL_58_) -> 0 | G50: =H50-F50 -> 0 | H50: =DSUM(SEP_2013_A,importe,CL_58_) -> 0 | I50: =IF(VLOOKUP(B50,BASE_A,9,FALSE)=0,0,G50/VLOOKUP(B50,BASE_A,9,FALSE)) -> 0 | J50: Cuchilla | K50: =DSUM(SEP_2013_A,23,CL_58_) -> 0 | L50: =DSUM(SEP_2013_A,24,CL_58_) -> 0 | M50: =DSUM(SEP_2013_A,25,CL_58_) -> 0 | N50: =DSUM(SEP_2013_A,26,CL_58_) -> 0 | O50: =DSUM(SEP_2013_A,27,CL_58_) -> 0 | P50: =DSUM(SEP_2013_A,28,CL_58_) -> 0 | Q50: =DSUM(SEP_2013_A,29,CL_58_) -> 0 | R50: =DSUM(SEP_2013_A,30,CL_58_) -> 0 | S50: =DSUM(SEP_2013_A,31,CL_58_) -> 0 | T50: =DSUM(SEP_2013_A,32,CL_58_) -> 0 | U50: =DSUM(SEP_2013_A,33,CL_58_) -> 0 | V50: =DSUM(SEP_2013_A,34,CL_58_) -> 0
B51: CL_59_ | C51: =VLOOKUP(B51,BASE_A,6,FALSE) -> Rancho La Cuchilla No. 59 | D51: =VLOOKUP(B51,BASE_A,8,FALSE) -> Ortega Vega | E51: =VLOOKUP(B51,BASE_A,9,FALSE) -> 300 | F51: =DSUM(SEP_2013_A,AA,CL_59_) -> 300 | G51: =H51-F51 -> 2700 | H51: =DSUM(SEP_2013_A,importe,CL_59_) -> 3000 | I51: =IF(VLOOKUP(B51,BASE_A,9,FALSE)=0,0,G51/VLOOKUP(B51,BASE_A,9,FALSE)) -> 9 | J51: Cuchilla | K51: =DSUM(SEP_2013_A,23,CL_59_) -> 300 | L51: =DSUM(SEP_2013_A,24,CL_59_) -> 300 | M51: =DSUM(SEP_2013_A,25,CL_59_) -> 300 | N51: =DSUM(SEP_2013_A,26,CL_59_) -> 300 | O51: =DSUM(SEP_2013_A,27,CL_59_) -> 300 | P51: =DSUM(SEP_2013_A,28,CL_59_) -> 300 | Q51: =DSUM(SEP_2013_A,29,CL_59_) -> 300 | R51: =DSUM(SEP_2013_A,30,CL_59_) -> 300 | S51: =DSUM(SEP_2013_A,31,CL_59_) -> 300 | T51: =DSUM(SEP_2013_A,32,CL_59_) -> 0 | U51: =DSUM(SEP_2013_A,33,CL_59_) -> 0 | V51: =DSUM(SEP_2013_A,34,CL_59_) -> 0
B52: CL_60_ | C52: =VLOOKUP(B52,BASE_A,6,FALSE) -> Rancho La Cuchilla No. 60 | D52: =VLOOKUP(B52,BASE_A,8,FALSE) -> 0 | E52: =VLOOKUP(B52,BASE_A,9,FALSE) -> 300 | F52: =DSUM(SEP_2013_A,AA,CL_60_) -> 0 | G52: =H52-F52 -> 0 | H52: =DSUM(SEP_2013_A,importe,CL_60_) -> 0 | I52: =IF(VLOOKUP(B52,BASE_A,9,FALSE)=0,0,G52/VLOOKUP(B52,BASE_A,9,FALSE)) -> 0 | J52: Cuchilla | K52: =DSUM(SEP_2013_A,23,CL_60_) -> 0 | L52: =DSUM(SEP_2013_A,24,CL_60_) -> 0 | M52: =DSUM(SEP_2013_A,25,CL_60_) -> 0 | N52: =DSUM(SEP_2013_A,26,CL_60_) -> 0 | O52: =DSUM(SEP_2013_A,27,CL_60_) -> 0 | P52: =DSUM(SEP_2013_A,28,CL_60_) -> 0 | Q52: =DSUM(SEP_2013_A,29,CL_60_) -> 0 | R52: =DSUM(SEP_2013_A,30,CL_60_) -> 0 | S52: =DSUM(SEP_2013_A,31,CL_60_) -> 0 | T52: =DSUM(SEP_2013_A,32,CL_60_) -> 0 | U52: =DSUM(SEP_2013_A,33,CL_60_) -> 0 | V52: =DSUM(SEP_2013_A,34,CL_60_) -> 0
B53: CL_61_ | C53: =VLOOKUP(B53,BASE_A,6,FALSE) -> Rancho La Cuchilla No. 61 | D53: =VLOOKUP(B53,BASE_A,8,FALSE) -> Rivera | E53: =VLOOKUP(B53,BASE_A,9,FALSE) -> 300 | F53: =DSUM(SEP_2013_A,AA,CL_61_) -> 0 | G53: =H53-F53 -> 2100 | H53: =DSUM(SEP_2013_A,importe,CL_61_) -> 2100 | I53: =IF(VLOOKUP(B53,BASE_A,9,FALSE)=0,0,G53/VLOOKUP(B53,BASE_A,9,FALSE)) -> 7 | J53: Cuchilla | K53: =DSUM(SEP_2013_A,23,CL_61_) -> 300 | L53: =DSUM(SEP_2013_A,24,CL_61_) -> 300 | M53: =DSUM(SEP_2013_A,25,CL_61_) -> 300 | N53: =DSUM(SEP_2013_A,26,CL_61_) -> 300 | O53: =DSUM(SEP_2013_A,27,CL_61_) -> 300 | P53: =DSUM(SEP_2013_A,28,CL_61_) -> 300 | Q53: =DSUM(SEP_2013_A,29,CL_61_) -> 300 | R53: =DSUM(SEP_2013_A,30,CL_61_) -> 0 | S53: =DSUM(SEP_2013_A,31,CL_61_) -> 0 | T53: =DSUM(SEP_2013_A,32,CL_61_) -> 0 | U53: =DSUM(SEP_2013_A,33,CL_61_) -> 0 | V53: =DSUM(SEP_2013_A,34,CL_61_) -> 0
B54: CL_62_ | C54: =VLOOKUP(B54,BASE_A,6,FALSE) -> Rancho La Cuchilla No. 62 | D54: =VLOOKUP(B54,BASE_A,8,FALSE) -> Frías | E54: =VLOOKUP(B54,BASE_A,9,FALSE) -> 200 | F54: =DSUM(SEP_2013_A,AA,CL_62_) -> 200 | G54: =H54-F54 -> 1800 | H54: =DSUM(SEP_2013_A,importe,CL_62_) -> 2000 | I54: =IF(VLOOKUP(B54,BASE_A,9,FALSE)=0,0,G54/VLOOKUP(B54,BASE_A,9,FALSE)) -> 9 | J54: Cuchilla | K54: =DSUM(SEP_2013_A,23,CL_62_) -> 200 | L54: =DSUM(SEP_2013_A,24,CL_62_) -> 200 | M54: =DSUM(SEP_2013_A,25,CL_62_) -> 200 | N54: =DSUM(SEP_2013_A,26,CL_62_) -> 200 | O54: =DSUM(SEP_2013_A,27,CL_62_) -> 200 | P54: =DSUM(SEP_2013_A,28,CL_62_) -> 200 | Q54: =DSUM(SEP_2013_A,29,CL_62_) -> 200 | R54: =DSUM(SEP_2013_A,30,CL_62_) -> 200 | S54: =DSUM(SEP_2013_A,31,CL_62_) -> 200 | T54: =DSUM(SEP_2013_A,32,CL_62_) -> 0 | U54: =DSUM(SEP_2013_A,33,CL_62_) -> 0 | V54: =DSUM(SEP_2013_A,34,CL_62_) -> 0
B55: CL_63_ | C55: =VLOOKUP(B55,BASE_A,6,FALSE) -> Rancho La Cuchilla No. 63 | D55: =VLOOKUP(B55,BASE_A,8,FALSE) -> Díaz de la Rosa | E55: =VLOOKUP(B55,BASE_A,9,FALSE) -> 300 | F55: =DSUM(SEP_2013_A,AA,CL_63_) -> 0 | G55: =H55-F55 -> 0 | H55: =DSUM(SEP_2013_A,importe,CL_63_) -> 0 | I55: =IF(VLOOKUP(B55,BASE_A,9,FALSE)=0,0,G55/VLOOKUP(B55,BASE_A,9,FALSE)) -> 0 | J55: Cuchilla | K55: =DSUM(SEP_2013_A,23,CL_63_) -> 0 | L55: =DSUM(SEP_2013_A,24,CL_63_) -> 0 | M55: =DSUM(SEP_2013_A,25,CL_63_) -> 0 | N55: =DSUM(SEP_2013_A,26,CL_63_) -> 0 | O55: =DSUM(SEP_2013_A,27,CL_63_) -> 0 | P55: =DSUM(SEP_2013_A,28,CL_63_) -> 0 | Q55: =DSUM(SEP_2013_A,29,CL_63_) -> 0 | R55: =DSUM(SEP_2013_A,30,CL_63_) -> 0 | S55: =DSUM(SEP_2013_A,31,CL_63_) -> 0 | T55: =DSUM(SEP_2013_A,32,CL_63_) -> 0 | U55: =DSUM(SEP_2013_A,33,CL_63_) -> 0 | V55: =DSUM(SEP_2013_A,34,CL_63_) -> 0
B56: CL_65_ | C56: =VLOOKUP(B56,BASE_A,6,FALSE) -> Rancho La Cuchilla No. 65 | D56: =VLOOKUP(B56,BASE_A,8,FALSE) -> Garduño | E56: =VLOOKUP(B56,BASE_A,9,FALSE) -> 300 | F56: =DSUM(SEP_2013_A,AA,CL_65_) -> 0 | G56: =H56-F56 -> 0 | H56: =DSUM(SEP_2013_A,importe,CL_65_) -> 0 | I56: =IF(VLOOKUP(B56,BASE_A,9,FALSE)=0,0,G56/VLOOKUP(B56,BASE_A,9,FALSE)) -> 0 | J56: Cuchilla | K56: =DSUM(SEP_2013_A,23,CL_65_) -> 0 | L56: =DSUM(SEP_2013_A,24,CL_65_) -> 0 | M56: =DSUM(SEP_2013_A,25,CL_65_) -> 0 | N56: =DSUM(SEP_2013_A,26,CL_65_) -> 0 | O56: =DSUM(SEP_2013_A,27,CL_65_) -> 0 | P56: =DSUM(SEP_2013_A,28,CL_65_) -> 0 | Q56: =DSUM(SEP_2013_A,29,CL_65_) -> 0 | R56: =DSUM(SEP_2013_A,30,CL_65_) -> 0 | S56: =DSUM(SEP_2013_A,31,CL_65_) -> 0 | T56: =DSUM(SEP_2013_A,32,CL_65_) -> 0 | U56: =DSUM(SEP_2013_A,33,CL_65_) -> 0 | V56: =DSUM(SEP_2013_A,34,CL_65_) -> 0
B57: CL_66_ | C57: =VLOOKUP(B57,BASE_A,6,FALSE) -> Rancho La Cuchilla No. 66 | D57: =VLOOKUP(B57,BASE_A,8,FALSE) -> Prieto | E57: =VLOOKUP(B57,BASE_A,9,FALSE) -> 300 | F57: =DSUM(SEP_2013_A,AA,CL_66_) -> 900 | G57: =H57-F57 -> 2700 | H57: =DSUM(SEP_2013_A,importe,CL_66_) -> 3600 | I57: =IF(VLOOKUP(B57,BASE_A,9,FALSE)=0,0,G57/VLOOKUP(B57,BASE_A,9,FALSE)) -> 9 | J57: Cuchilla | K57: =DSUM(SEP_2013_A,23,CL_66_) -> 300 | L57: =DSUM(SEP_2013_A,24,CL_66_) -> 300 | M57: =DSUM(SEP_2013_A,25,CL_66_) -> 300 | N57: =DSUM(SEP_2013_A,26,CL_66_) -> 300 | O57: =DSUM(SEP_2013_A,27,CL_66_) -> 300 | P57: =DSUM(SEP_2013_A,28,CL_66_) -> 300 | Q57: =DSUM(SEP_2013_A,29,CL_66_) -> 300 | R57: =DSUM(SEP_2013_A,30,CL_66_) -> 300 | S57: =DSUM(SEP_2013_A,31,CL_66_) -> 300 | T57: =DSUM(SEP_2013_A,32,CL_66_) -> 0 | U57: =DSUM(SEP_2013_A,33,CL_66_) -> 0 | V57: =DSUM(SEP_2013_A,34,CL_66_) -> 0
B58: CL_67_ | C58: =VLOOKUP(B58,BASE_A,6,FALSE) -> Rancho La Cuchilla No. 67 | D58: =VLOOKUP(B58,BASE_A,8,FALSE) -> Quezada Viruega | E58: =VLOOKUP(B58,BASE_A,9,FALSE) -> 300 | F58: =DSUM(SEP_2013_A,AA,CL_67_) -> 0 | G58: =H58-F58 -> 600 | H58: =DSUM(SEP_2013_A,importe,CL_67_) -> 600 | I58: =IF(VLOOKUP(B58,BASE_A,9,FALSE)=0,0,G58/VLOOKUP(B58,BASE_A,9,FALSE)) -> 2 | J58: Cuchilla | K58: =DSUM(SEP_2013_A,23,CL_67_) -> 300 | L58: =DSUM(SEP_2013_A,24,CL_67_) -> 300 | M58: =DSUM(SEP_2013_A,25,CL_67_) -> 0 | N58: =DSUM(SEP_2013_A,26,CL_67_) -> 0 | O58: =DSUM(SEP_2013_A,27,CL_67_) -> 0 | P58: =DSUM(SEP_2013_A,28,CL_67_) -> 0 | Q58: =DSUM(SEP_2013_A,29,CL_67_) -> 0 | R58: =DSUM(SEP_2013_A,30,CL_67_) -> 0 | S58: =DSUM(SEP_2013_A,31,CL_67_) -> 0 | T58: =DSUM(SEP_2013_A,32,CL_67_) -> 0 | U58: =DSUM(SEP_2013_A,33,CL_67_) -> 0 | V58: =DSUM(SEP_2013_A,34,CL_67_) -> 0
B59: CL_68_ | C59: =VLOOKUP(B59,BASE_A,6,FALSE) -> Rancho La Cuchilla No. 68 | D59: =VLOOKUP(B59,BASE_A,8,FALSE) -> Montesinos | E59: =VLOOKUP(B59,BASE_A,9,FALSE) -> 300 | F59: =DSUM(SEP_2013_A,AA,CL_68_) -> 600 | G59: =H59-F59 -> 600 | H59: =DSUM(SEP_2013_A,importe,CL_68_) -> 1200 | I59: =IF(VLOOKUP(B59,BASE_A,9,FALSE)=0,0,G59/VLOOKUP(B59,BASE_A,9,FALSE)) -> 2 | J59: Cuchilla | K59: =DSUM(SEP_2013_A,23,CL_68_) -> 300 | L59: =DSUM(SEP_2013_A,24,CL_68_) -> 300 | M59: =DSUM(SEP_2013_A,25,CL_68_) -> 0 | N59: =DSUM(SEP_2013_A,26,CL_68_) -> 0 | O59: =DSUM(SEP_2013_A,27,CL_68_) -> 0 | P59: =DSUM(SEP_2013_A,28,CL_68_) -> 0 | Q59: =DSUM(SEP_2013_A,29,CL_68_) -> 0 | R59: =DSUM(SEP_2013_A,30,CL_68_) -> 0 | S59: =DSUM(SEP_2013_A,31,CL_68_) -> 0 | T59: =DSUM(SEP_2013_A,32,CL_68_) -> 0 | U59: =DSUM(SEP_2013_A,33,CL_68_) -> 0 | V59: =DSUM(SEP_2013_A,34,CL_68_) -> 0
B60: CL_69_ | C60: =VLOOKUP(B60,BASE_A,6,FALSE) -> Rancho La Cuchilla No. 69 | D60: =VLOOKUP(B60,BASE_A,8,FALSE) -> Romero | E60: =VLOOKUP(B60,BASE_A,9,FALSE) -> 300 | F60: =DSUM(SEP_2013_A,AA,CL_69_) -> 0 | G60: =H60-F60 -> 0 | H60: =DSUM(SEP_2013_A,importe,CL_69_) -> 0 | I60: =IF(VLOOKUP(B60,BASE_A,9,FALSE)=0,0,G60/VLOOKUP(B60,BASE_A,9,FALSE)) -> 0 | J60: Cuchilla | K60: =DSUM(SEP_2013_A,23,CL_69_) -> 0 | L60: =DSUM(SEP_2013_A,24,CL_69_) -> 0 | M60: =DSUM(SEP_2013_A,25,CL_69_) -> 0 | N60: =DSUM(SEP_2013_A,26,CL_69_) -> 0 | O60: =DSUM(SEP_2013_A,27,CL_69_) -> 0 | P60: =DSUM(SEP_2013_A,28,CL_69_) -> 0 | Q60: =DSUM(SEP_2013_A,29,CL_69_) -> 0 | R60: =DSUM(SEP_2013_A,30,CL_69_) -> 0 | S60: =DSUM(SEP_2013_A,31,CL_69_) -> 0 | T60: =DSUM(SEP_2013_A,32,CL_69_) -> 0 | U60: =DSUM(SEP_2013_A,33,CL_69_) -> 0 | V60: =DSUM(SEP_2013_A,34,CL_69_) -> 0
B61: CL_70_ | C61: =VLOOKUP(B61,BASE_A,6,FALSE) -> Rancho La Cuchilla No. 70 | D61: =VLOOKUP(B61,BASE_A,8,FALSE) -> 0 | E61: =VLOOKUP(B61,BASE_A,9,FALSE) -> 300 | F61: =DSUM(SEP_2013_A,AA,CL_70_) -> 0 | G61: =H61-F61 -> 0 | H61: =DSUM(SEP_2013_A,importe,CL_70_) -> 0 | I61: =IF(VLOOKUP(B61,BASE_A,9,FALSE)=0,0,G61/VLOOKUP(B61,BASE_A,9,FALSE)) -> 0 | J61: Cuchilla | K61: =DSUM(SEP_2013_A,23,CL_70_) -> 0 | L61: =DSUM(SEP_2013_A,24,CL_70_) -> 0 | M61: =DSUM(SEP_2013_A,25,CL_70_) -> 0 | N61: =DSUM(SEP_2013_A,26,CL_70_) -> 0 | O61: =DSUM(SEP_2013_A,27,CL_70_) -> 0 | P61: =DSUM(SEP_2013_A,28,CL_70_) -> 0 | Q61: =DSUM(SEP_2013_A,29,CL_70_) -> 0 | R61: =DSUM(SEP_2013_A,30,CL_70_) -> 0 | S61: =DSUM(SEP_2013_A,31,CL_70_) -> 0 | T61: =DSUM(SEP_2013_A,32,CL_70_) -> 0 | U61: =DSUM(SEP_2013_A,33,CL_70_) -> 0 | V61: =DSUM(SEP_2013_A,34,CL_70_) -> 0
B62: CL_71_ | C62: =VLOOKUP(B62,BASE_A,6,FALSE) -> Rancho La Cuchilla No. 71 | D62: =VLOOKUP(B62,BASE_A,8,FALSE) -> Pulido | E62: =VLOOKUP(B62,BASE_A,9,FALSE) -> 300 | F62: =DSUM(SEP_2013_A,AA,CL_71_) -> 300 | G62: =H62-F62 -> 2700 | H62: =DSUM(SEP_2013_A,importe,CL_71_) -> 3000 | I62: =IF(VLOOKUP(B62,BASE_A,9,FALSE)=0,0,G62/VLOOKUP(B62,BASE_A,9,FALSE)) -> 9 | J62: Cuchilla | K62: =DSUM(SEP_2013_A,23,CL_71_) -> 300 | L62: =DSUM(SEP_2013_A,24,CL_71_) -> 300 | M62: =DSUM(SEP_2013_A,25,CL_71_) -> 300 | N62: =DSUM(SEP_2013_A,26,CL_71_) -> 300 | O62: =DSUM(SEP_2013_A,27,CL_71_) -> 300 | P62: =DSUM(SEP_2013_A,28,CL_71_) -> 300 | Q62: =DSUM(SEP_2013_A,29,CL_71_) -> 300 | R62: =DSUM(SEP_2013_A,30,CL_71_) -> 300 | S62: =DSUM(SEP_2013_A,31,CL_71_) -> 300 | T62: =DSUM(SEP_2013_A,32,CL_71_) -> 0 | U62: =DSUM(SEP_2013_A,33,CL_71_) -> 0 | V62: =DSUM(SEP_2013_A,34,CL_71_) -> 0
B63: CL_72_ | C63: =VLOOKUP(B63,BASE_A,6,FALSE) -> Rancho La Cuchilla No. 72 | D63: =VLOOKUP(B63,BASE_A,8,FALSE) -> Ortiz González | E63: =VLOOKUP(B63,BASE_A,9,FALSE) -> 300 | F63: =DSUM(SEP_2013_A,AA,CL_72_) -> 300 | G63: =H63-F63 -> 2400 | H63: =DSUM(SEP_2013_A,importe,CL_72_) -> 2700 | I63: =IF(VLOOKUP(B63,BASE_A,9,FALSE)=0,0,G63/VLOOKUP(B63,BASE_A,9,FALSE)) -> 8 | J63: Cuchilla | K63: =DSUM(SEP_2013_A,23,CL_72_) -> 300 | L63: =DSUM(SEP_2013_A,24,CL_72_) -> 300 | M63: =DSUM(SEP_2013_A,25,CL_72_) -> 300 | N63: =DSUM(SEP_2013_A,26,CL_72_) -> 300 | O63: =DSUM(SEP_2013_A,27,CL_72_) -> 300 | P63: =DSUM(SEP_2013_A,28,CL_72_) -> 0 | Q63: =DSUM(SEP_2013_A,29,CL_72_) -> 300 | R63: =DSUM(SEP_2013_A,30,CL_72_) -> 300 | S63: =DSUM(SEP_2013_A,31,CL_72_) -> 300 | T63: =DSUM(SEP_2013_A,32,CL_72_) -> 0 | U63: =DSUM(SEP_2013_A,33,CL_72_) -> 0 | V63: =DSUM(SEP_2013_A,34,CL_72_) -> 0
B64: CL_73_ | C64: =VLOOKUP(B64,BASE_A,6,FALSE) -> Rancho La Cuchilla No. 73 | D64: =VLOOKUP(B64,BASE_A,8,FALSE) -> Cooper | E64: =VLOOKUP(B64,BASE_A,9,FALSE) -> 300 | F64: =DSUM(SEP_2013_A,AA,CL_73_) -> 0 | G64: =H64-F64 -> 2100 | H64: =DSUM(SEP_2013_A,importe,CL_73_) -> 2100 | I64: =IF(VLOOKUP(B64,BASE_A,9,FALSE)=0,0,G64/VLOOKUP(B64,BASE_A,9,FALSE)) -> 7 | J64: Cuchilla | K64: =DSUM(SEP_2013_A,23,CL_73_) -> 300 | L64: =DSUM(SEP_2013_A,24,CL_73_) -> 300 | M64: =DSUM(SEP_2013_A,25,CL_73_) -> 0 | N64: =DSUM(SEP_2013_A,26,CL_73_) -> 300 | O64: =DSUM(SEP_2013_A,27,CL_73_) -> 300 | P64: =DSUM(SEP_2013_A,28,CL_73_) -> 300 | Q64: =DSUM(SEP_2013_A,29,CL_73_) -> 300 | R64: =DSUM(SEP_2013_A,30,CL_73_) -> 300 | S64: =DSUM(SEP_2013_A,31,CL_73_) -> 0 | T64: =DSUM(SEP_2013_A,32,CL_73_) -> 0 | U64: =DSUM(SEP_2013_A,33,CL_73_) -> 0 | V64: =DSUM(SEP_2013_A,34,CL_73_) -> 0
B65: CL_74_ | C65: =VLOOKUP(B65,BASE_A,6,FALSE) -> Rancho La Cuchilla No. 74 | D65: =VLOOKUP(B65,BASE_A,8,FALSE) -> Gil | E65: =VLOOKUP(B65,BASE_A,9,FALSE) -> 300 | F65: =DSUM(SEP_2013_A,AA,CL_74_) -> 0 | G65: =H65-F65 -> 1800 | H65: =DSUM(SEP_2013_A,importe,CL_74_) -> 1800 | I65: =IF(VLOOKUP(B65,BASE_A,9,FALSE)=0,0,G65/VLOOKUP(B65,BASE_A,9,FALSE)) -> 6 | J65: Cuchilla | K65: =DSUM(SEP_2013_A,23,CL_74_) -> 600 | L65: =DSUM(SEP_2013_A,24,CL_74_) -> 300 | M65: =DSUM(SEP_2013_A,25,CL_74_) -> 300 | N65: =DSUM(SEP_2013_A,26,CL_74_) -> 300 | O65: =DSUM(SEP_2013_A,27,CL_74_) -> 300 | P65: =DSUM(SEP_2013_A,28,CL_74_) -> 0 | Q65: =DSUM(SEP_2013_A,29,CL_74_) -> 0 | R65: =DSUM(SEP_2013_A,30,CL_74_) -> 0 | S65: =DSUM(SEP_2013_A,31,CL_74_) -> 0 | T65: =DSUM(SEP_2013_A,32,CL_74_) -> 0 | U65: =DSUM(SEP_2013_A,33,CL_74_) -> 0 | V65: =DSUM(SEP_2013_A,34,CL_74_) -> 0
B66: CL_75_ | C66: =VLOOKUP(B66,BASE_A,6,FALSE) -> Rancho La Cuchilla No. 75 | D66: =VLOOKUP(B66,BASE_A,8,FALSE) -> Sosa Lucio | E66: =VLOOKUP(B66,BASE_A,9,FALSE) -> 300 | F66: =DSUM(SEP_2013_A,AA,CL_75_) -> 600 | G66: =H66-F66 -> 2400 | H66: =DSUM(SEP_2013_A,importe,CL_75_) -> 3000 | I66: =IF(VLOOKUP(B66,BASE_A,9,FALSE)=0,0,G66/VLOOKUP(B66,BASE_A,9,FALSE)) -> 8 | J66: Cuchilla | K66: =DSUM(SEP_2013_A,23,CL_75_) -> 300 | L66: =DSUM(SEP_2013_A,24,CL_75_) -> 300 | M66: =DSUM(SEP_2013_A,25,CL_75_) -> 300 | N66: =DSUM(SEP_2013_A,26,CL_75_) -> 300 | O66: =DSUM(SEP_2013_A,27,CL_75_) -> 300 | P66: =DSUM(SEP_2013_A,28,CL_75_) -> 300 | Q66: =DSUM(SEP_2013_A,29,CL_75_) -> 300 | R66: =DSUM(SEP_2013_A,30,CL_75_) -> 300 | S66: =DSUM(SEP_2013_A,31,CL_75_) -> 0 | T66: =DSUM(SEP_2013_A,32,CL_75_) -> 0 | U66: =DSUM(SEP_2013_A,33,CL_75_) -> 0 | V66: =DSUM(SEP_2013_A,34,CL_75_) -> 0
B67: CL_76_ | C67: =VLOOKUP(B67,BASE_A,6,FALSE) -> Rancho La Cuchilla No. 76 | D67: =VLOOKUP(B67,BASE_A,8,FALSE) -> 0 | E67: =VLOOKUP(B67,BASE_A,9,FALSE) -> 300 | F67: =DSUM(SEP_2013_A,AA,CL_76_) -> 0 | G67: =H67-F67 -> 0 | H67: =DSUM(SEP_2013_A,importe,CL_76_) -> 0 | I67: =IF(VLOOKUP(B67,BASE_A,9,FALSE)=0,0,G67/VLOOKUP(B67,BASE_A,9,FALSE)) -> 0 | J67: Cuchilla | K67: =DSUM(SEP_2013_A,23,CL_76_) -> 0 | L67: =DSUM(SEP_2013_A,24,CL_76_) -> 0 | M67: =DSUM(SEP_2013_A,25,CL_76_) -> 0 | N67: =DSUM(SEP_2013_A,26,CL_76_) -> 0 | O67: =DSUM(SEP_2013_A,27,CL_76_) -> 0 | P67: =DSUM(SEP_2013_A,28,CL_76_) -> 0 | Q67: =DSUM(SEP_2013_A,29,CL_76_) -> 0 | R67: =DSUM(SEP_2013_A,30,CL_76_) -> 0 | S67: =DSUM(SEP_2013_A,31,CL_76_) -> 0 | T67: =DSUM(SEP_2013_A,32,CL_76_) -> 0 | U67: =DSUM(SEP_2013_A,33,CL_76_) -> 0 | V67: =DSUM(SEP_2013_A,34,CL_76_) -> 0
B68: CL_77_ | C68: =VLOOKUP(B68,BASE_A,6,FALSE) -> Rancho La Cuchilla No. 77 | D68: =VLOOKUP(B68,BASE_A,8,FALSE) -> Loperena | E68: =VLOOKUP(B68,BASE_A,9,FALSE) -> 300 | F68: =DSUM(SEP_2013_A,AA,CL_77_) -> 600 | G68: =H68-F68 -> 2400 | H68: =DSUM(SEP_2013_A,importe,CL_77_) -> 3000 | I68: =IF(VLOOKUP(B68,BASE_A,9,FALSE)=0,0,G68/VLOOKUP(B68,BASE_A,9,FALSE)) -> 8 | J68: Cuchilla | K68: =DSUM(SEP_2013_A,23,CL_77_) -> 300 | L68: =DSUM(SEP_2013_A,24,CL_77_) -> 300 | M68: =DSUM(SEP_2013_A,25,CL_77_) -> 300 | N68: =DSUM(SEP_2013_A,26,CL_77_) -> 300 | O68: =DSUM(SEP_2013_A,27,CL_77_) -> 300 | P68: =DSUM(SEP_2013_A,28,CL_77_) -> 300 | Q68: =DSUM(SEP_2013_A,29,CL_77_) -> 300 | R68: =DSUM(SEP_2013_A,30,CL_77_) -> 300 | S68: =DSUM(SEP_2013_A,31,CL_77_) -> 0 | T68: =DSUM(SEP_2013_A,32,CL_77_) -> 0 | U68: =DSUM(SEP_2013_A,33,CL_77_) -> 0 | V68: =DSUM(SEP_2013_A,34,CL_77_) -> 0
B69: CL_79_ | C69: =VLOOKUP(B69,BASE_A,6,FALSE) -> Rancho La Cuchilla No. 79 | D69: =VLOOKUP(B69,BASE_A,8,FALSE) -> Hernández Laurel | E69: =VLOOKUP(B69,BASE_A,9,FALSE) -> 300 | F69: =DSUM(SEP_2013_A,AA,CL_79_) -> 0 | G69: =H69-F69 -> 0 | H69: =DSUM(SEP_2013_A,importe,CL_79_) -> 0 | I69: =IF(VLOOKUP(B69,BASE_A,9,FALSE)=0,0,G69/VLOOKUP(B69,BASE_A,9,FALSE)) -> 0 | J69: Cuchilla | K69: =DSUM(SEP_2013_A,23,CL_79_) -> 0 | L69: =DSUM(SEP_2013_A,24,CL_79_) -> 0 | M69: =DSUM(SEP_2013_A,25,CL_79_) -> 0 | N69: =DSUM(SEP_2013_A,26,CL_79_) -> 0 | O69: =DSUM(SEP_2013_A,27,CL_79_) -> 0 | P69: =DSUM(SEP_2013_A,28,CL_79_) -> 0 | Q69: =DSUM(SEP_2013_A,29,CL_79_) -> 0 | R69: =DSUM(SEP_2013_A,30,CL_79_) -> 0 | S69: =DSUM(SEP_2013_A,31,CL_79_) -> 0 | T69: =DSUM(SEP_2013_A,32,CL_79_) -> 0 | U69: =DSUM(SEP_2013_A,33,CL_79_) -> 0 | V69: =DSUM(SEP_2013_A,34,CL_79_) -> 0
B70: CL_80_ | C70: =VLOOKUP(B70,BASE_A,6,FALSE) -> Rancho La Cuchilla No. 80 | D70: =VLOOKUP(B70,BASE_A,8,FALSE) -> Aparicio | E70: =VLOOKUP(B70,BASE_A,9,FALSE) -> 300 | F70: =DSUM(SEP_2013_A,AA,CL_80_) -> 0 | G70: =H70-F70 -> 3300 | H70: =DSUM(SEP_2013_A,importe,CL_80_) -> 3300 | I70: =IF(VLOOKUP(B70,BASE_A,9,FALSE)=0,0,(G70/VLOOKUP(B70,BASE_A,9,FALSE)))+1 -> 12 | J70: Cuchilla | K70: =DSUM(SEP_2013_A,23,CL_80_) -> 300 | L70: =DSUM(SEP_2013_A,24,CL_80_) -> 300 | M70: =DSUM(SEP_2013_A,25,CL_80_) -> 300 | N70: =DSUM(SEP_2013_A,26,CL_80_) -> 300 | O70: =DSUM(SEP_2013_A,27,CL_80_) -> 300 | P70: =DSUM(SEP_2013_A,28,CL_80_) -> 300 | Q70: =DSUM(SEP_2013_A,29,CL_80_) -> 300 | R70: =DSUM(SEP_2013_A,30,CL_80_) -> 300 | S70: =DSUM(SEP_2013_A,31,CL_80_) -> 300 | T70: =DSUM(SEP_2013_A,32,CL_80_) -> 300 | U70: =DSUM(SEP_2013_A,33,CL_80_) -> 300 | V70: =DSUM(SEP_2013_A,34,CL_80_) -> 0
B71: CL_81_A | C71: =VLOOKUP(B71,BASE_A,6,FALSE) -> Rancho La Cuchilla No. 81, A | D71: =VLOOKUP(B71,BASE_A,8,FALSE) -> Barrientos López | E71: =VLOOKUP(B71,BASE_A,9,FALSE) -> 300 | F71: =DSUM(SEP_2013_A,AA,CL_81_A) -> 300 | G71: =H71-F71 -> 2700 | H71: =DSUM(SEP_2013_A,importe,CL_81_A) -> 3000 | I71: =IF(VLOOKUP(B71,BASE_A,9,FALSE)=0,0,G71/VLOOKUP(B71,BASE_A,9,FALSE)) -> 9 | J71: Cuchilla | K71: =DSUM(SEP_2013_A,23,CL_81_A) -> 300 | L71: =DSUM(SEP_2013_A,24,CL_81_A) -> 300 | M71: =DSUM(SEP_2013_A,25,CL_81_A) -> 300 | N71: =DSUM(SEP_2013_A,26,CL_81_A) -> 300 | O71: =DSUM(SEP_2013_A,27,CL_81_A) -> 300 | P71: =DSUM(SEP_2013_A,28,CL_81_A) -> 300 | Q71: =DSUM(SEP_2013_A,29,CL_81_A) -> 300 | R71: =DSUM(SEP_2013_A,30,CL_81_A) -> 300 | S71: =DSUM(SEP_2013_A,31,CL_81_A) -> 300 | T71: =DSUM(SEP_2013_A,32,CL_81_A) -> 0 | U71: =DSUM(SEP_2013_A,33,CL_81_A) -> 0 | V71: =DSUM(SEP_2013_A,34,CL_81_A) -> 0
B72: CL_81_B | C72: =VLOOKUP(B72,BASE_A,6,FALSE) -> Rancho La Cuchilla No. 81, B | D72: =VLOOKUP(B72,BASE_A,8,FALSE) -> Suárez | E72: =VLOOKUP(B72,BASE_A,9,FALSE) -> 300 | F72: =DSUM(SEP_2013_A,AA,CL_81_B) -> 0 | G72: =H72-F72 -> 3300 | H72: =DSUM(SEP_2013_A,importe,CL_81_B) -> 3300 | I72: =IF(VLOOKUP(B72,BASE_A,9,FALSE)=0,0,(G72/VLOOKUP(B72,BASE_A,9,FALSE)))+1 -> 12 | J72: Cuchilla | K72: =DSUM(SEP_2013_A,23,CL_81_B) -> 300 | L72: =DSUM(SEP_2013_A,24,CL_81_B) -> 300 | M72: =DSUM(SEP_2013_A,25,CL_81_B) -> 300 | N72: =DSUM(SEP_2013_A,26,CL_81_B) -> 300 | O72: =DSUM(SEP_2013_A,27,CL_81_B) -> 300 | P72: =DSUM(SEP_2013_A,28,CL_81_B) -> 300 | Q72: =DSUM(SEP_2013_A,29,CL_81_B) -> 300 | R72: =DSUM(SEP_2013_A,30,CL_81_B) -> 300 | S72: =DSUM(SEP_2013_A,31,CL_81_B) -> 300 | T72: =DSUM(SEP_2013_A,32,CL_81_B) -> 300 | U72: =DSUM(SEP_2013_A,33,CL_81_B) -> 300 | V72: =DSUM(SEP_2013_A,34,CL_81_B) -> 0
B73: CL_82_ | C73: =VLOOKUP(B73,BASE_A,6,FALSE) -> Rancho La Cuchilla No. 82 | D73: =VLOOKUP(B73,BASE_A,8,FALSE) -> Cruz | E73: =VLOOKUP(B73,BASE_A,9,FALSE) -> 300 | F73: =DSUM(SEP_2013_A,AA,CL_82_) -> 600 | G73: =H73-F73 -> 2700 | H73: =DSUM(SEP_2013_A,importe,CL_82_) -> 3300 | I73: =IF(VLOOKUP(B73,BASE_A,9,FALSE)=0,0,G73/VLOOKUP(B73,BASE_A,9,FALSE)) -> 9 | J73: Cuchilla | K73: =DSUM(SEP_2013_A,23,CL_82_) -> 300 | L73: =DSUM(SEP_2013_A,24,CL_82_) -> 300 | M73: =DSUM(SEP_2013_A,25,CL_82_) -> 300 | N73: =DSUM(SEP_2013_A,26,CL_82_) -> 300 | O73: =DSUM(SEP_2013_A,27,CL_82_) -> 300 | P73: =DSUM(SEP_2013_A,28,CL_82_) -> 300 | Q73: =DSUM(SEP_2013_A,29,CL_82_) -> 300 | R73: =DSUM(SEP_2013_A,30,CL_82_) -> 300 | S73: =DSUM(SEP_2013_A,31,CL_82_) -> 300 | T73: =DSUM(SEP_2013_A,32,CL_82_) -> 0 | U73: =DSUM(SEP_2013_A,33,CL_82_) -> 0 | V73: =DSUM(SEP_2013_A,34,CL_82_) -> 0
B74: CL_83_ | C74: =VLOOKUP(B74,BASE_A,6,FALSE) -> Rancho La Cuchilla No. 83 | D74: =VLOOKUP(B74,BASE_A,8,FALSE) -> Barradas | E74: =VLOOKUP(B74,BASE_A,9,FALSE) -> 300 | F74: =DSUM(SEP_2013_A,AA,CL_83_) -> 0 | G74: =H74-F74 -> 0 | H74: =DSUM(SEP_2013_A,importe,CL_83_) -> 0 | I74: =IF(VLOOKUP(B74,BASE_A,9,FALSE)=0,0,G74/VLOOKUP(B74,BASE_A,9,FALSE)) -> 0 | J74: Cuchilla | K74: =DSUM(SEP_2013_A,23,CL_83_) -> 0 | L74: =DSUM(SEP_2013_A,24,CL_83_) -> 0 | M74: =DSUM(SEP_2013_A,25,CL_83_) -> 0 | N74: =DSUM(SEP_2013_A,26,CL_83_) -> 0 | O74: =DSUM(SEP_2013_A,27,CL_83_) -> 0 | P74: =DSUM(SEP_2013_A,28,CL_83_) -> 0 | Q74: =DSUM(SEP_2013_A,29,CL_83_) -> 0 | R74: =DSUM(SEP_2013_A,30,CL_83_) -> 0 | S74: =DSUM(SEP_2013_A,31,CL_83_) -> 0 | T74: =DSUM(SEP_2013_A,32,CL_83_) -> 0 | U74: =DSUM(SEP_2013_A,33,CL_83_) -> 0 | V74: =DSUM(SEP_2013_A,34,CL_83_) -> 0
B75: CL_86_ | C75: =VLOOKUP(B75,BASE_A,6,FALSE) -> Rancho La Cuchilla No. 86 | D75: =VLOOKUP(B75,BASE_A,8,FALSE) -> Del Villar | E75: =VLOOKUP(B75,BASE_A,9,FALSE) -> 300 | F75: =DSUM(SEP_2013_A,AA,CL_86_) -> 0 | G75: =H75-F75 -> 2700 | H75: =DSUM(SEP_2013_A,importe,CL_86_) -> 2700 | I75: =IF(VLOOKUP(B75,BASE_A,9,FALSE)=0,0,G75/VLOOKUP(B75,BASE_A,9,FALSE)) -> 9 | J75: Cuchilla | K75: =DSUM(SEP_2013_A,23,CL_86_) -> 300 | L75: =DSUM(SEP_2013_A,24,CL_86_) -> 300 | M75: =DSUM(SEP_2013_A,25,CL_86_) -> 300 | N75: =DSUM(SEP_2013_A,26,CL_86_) -> 300 | O75: =DSUM(SEP_2013_A,27,CL_86_) -> 300 | P75: =DSUM(SEP_2013_A,28,CL_86_) -> 300 | Q75: =DSUM(SEP_2013_A,29,CL_86_) -> 300 | R75: =DSUM(SEP_2013_A,30,CL_86_) -> 300 | S75: =DSUM(SEP_2013_A,31,CL_86_) -> 300 | T75: =DSUM(SEP_2013_A,32,CL_86_) -> 0 | U75: =DSUM(SEP_2013_A,33,CL_86_) -> 0 | V75: =DSUM(SEP_2013_A,34,CL_86_) -> 0
B76: CL_87_ | C76: =VLOOKUP(B76,BASE_A,6,FALSE) -> Rancho La Cuchilla No. 87 | D76: =VLOOKUP(B76,BASE_A,8,FALSE) -> Villanueva S. | E76: =VLOOKUP(B76,BASE_A,9,FALSE) -> 300 | F76: =DSUM(SEP_2013_A,AA,CL_87_) -> 600 | G76: =H76-F76 -> 2700 | H76: =DSUM(SEP_2013_A,importe,CL_87_) -> 3300 | I76: =IF(VLOOKUP(B76,BASE_A,9,FALSE)=0,0,G76/VLOOKUP(B76,BASE_A,9,FALSE)) -> 9 | J76: Cuchilla | K76: =DSUM(SEP_2013_A,23,CL_87_) -> 300 | L76: =DSUM(SEP_2013_A,24,CL_87_) -> 300 | M76: =DSUM(SEP_2013_A,25,CL_87_) -> 300 | N76: =DSUM(SEP_2013_A,26,CL_87_) -> 300 | O76: =DSUM(SEP_2013_A,27,CL_87_) -> 300 | P76: =DSUM(SEP_2013_A,28,CL_87_) -> 300 | Q76: =DSUM(SEP_2013_A,29,CL_87_) -> 300 | R76: =DSUM(SEP_2013_A,30,CL_87_) -> 300 | S76: =DSUM(SEP_2013_A,31,CL_87_) -> 300 | T76: =DSUM(SEP_2013_A,32,CL_87_) -> 0 | U76: =DSUM(SEP_2013_A,33,CL_87_) -> 0 | V76: =DSUM(SEP_2013_A,34,CL_87_) -> 0
B77: CL_88_ | C77: =VLOOKUP(B77,BASE_A,6,FALSE) -> Rancho La Cuchilla No. 88 | D77: =VLOOKUP(B77,BASE_A,8,FALSE) -> 0 | E77: =VLOOKUP(B77,BASE_A,9,FALSE) -> 300 | F77: =DSUM(SEP_2013_A,AA,CL_88_) -> 0 | G77: =H77-F77 -> 0 | H77: =DSUM(SEP_2013_A,importe,CL_88_) -> 0 | I77: =IF(VLOOKUP(B77,BASE_A,9,FALSE)=0,0,G77/VLOOKUP(B77,BASE_A,9,FALSE)) -> 0 | J77: Cuchilla | K77: =DSUM(SEP_2013_A,23,CL_88_) -> 0 | L77: =DSUM(SEP_2013_A,24,CL_88_) -> 0 | M77: =DSUM(SEP_2013_A,25,CL_88_) -> 0 | N77: =DSUM(SEP_2013_A,26,CL_88_) -> 0 | O77: =DSUM(SEP_2013_A,27,CL_88_) -> 0 | P77: =DSUM(SEP_2013_A,28,CL_88_) -> 0 | Q77: =DSUM(SEP_2013_A,29,CL_88_) -> 0 | R77: =DSUM(SEP_2013_A,30,CL_88_) -> 0 | S77: =DSUM(SEP_2013_A,31,CL_88_) -> 0 | T77: =DSUM(SEP_2013_A,32,CL_88_) -> 0 | U77: =DSUM(SEP_2013_A,33,CL_88_) -> 0 | V77: =DSUM(SEP_2013_A,34,CL_88_) -> 0
B78: CL_89_ | C78: =VLOOKUP(B78,BASE_A,6,FALSE) -> Rancho La Cuchilla No. 89 | D78: =VLOOKUP(B78,BASE_A,8,FALSE) -> Gálvez | E78: =VLOOKUP(B78,BASE_A,9,FALSE) -> 300 | F78: =DSUM(SEP_2013_A,AA,CL_89_) -> 300 | G78: =H78-F78 -> 2700 | H78: =DSUM(SEP_2013_A,importe,CL_89_) -> 3000 | I78: =IF(VLOOKUP(B78,BASE_A,9,FALSE)=0,0,G78/VLOOKUP(B78,BASE_A,9,FALSE)) -> 9 | J78: Cuchilla | K78: =DSUM(SEP_2013_A,23,CL_89_) -> 300 | L78: =DSUM(SEP_2013_A,24,CL_89_) -> 300 | M78: =DSUM(SEP_2013_A,25,CL_89_) -> 300 | N78: =DSUM(SEP_2013_A,26,CL_89_) -> 300 | O78: =DSUM(SEP_2013_A,27,CL_89_) -> 300 | P78: =DSUM(SEP_2013_A,28,CL_89_) -> 300 | Q78: =DSUM(SEP_2013_A,29,CL_89_) -> 300 | R78: =DSUM(SEP_2013_A,30,CL_89_) -> 300 | S78: =DSUM(SEP_2013_A,31,CL_89_) -> 300 | T78: =DSUM(SEP_2013_A,32,CL_89_) -> 0 | U78: =DSUM(SEP_2013_A,33,CL_89_) -> 0 | V78: =DSUM(SEP_2013_A,34,CL_89_) -> 0
B79: CL_90_ | C79: =VLOOKUP(B79,BASE_A,6,FALSE) -> Rancho La Cuchilla No. 90 | D79: =VLOOKUP(B79,BASE_A,8,FALSE) -> Porras Fuentes | E79: =VLOOKUP(B79,BASE_A,9,FALSE) -> 150 | F79: =DSUM(SEP_2013_A,AA,CL_90_) -> 300 | G79: =H79-F79 -> 1200 | H79: =DSUM(SEP_2013_A,importe,CL_90_) -> 1500 | I79: =IF(VLOOKUP(B79,BASE_A,9,FALSE)=0,0,G79/VLOOKUP(B79,BASE_A,9,FALSE)) -> 8 | J79: Cuchilla | K79: =DSUM(SEP_2013_A,23,CL_90_) -> 150 | L79: =DSUM(SEP_2013_A,24,CL_90_) -> 150 | M79: =DSUM(SEP_2013_A,25,CL_90_) -> 150 | N79: =DSUM(SEP_2013_A,26,CL_90_) -> 150 | O79: =DSUM(SEP_2013_A,27,CL_90_) -> 150 | P79: =DSUM(SEP_2013_A,28,CL_90_) -> 150 | Q79: =DSUM(SEP_2013_A,29,CL_90_) -> 150 | R79: =DSUM(SEP_2013_A,30,CL_90_) -> 150 | S79: =DSUM(SEP_2013_A,31,CL_90_) -> 0 | T79: =DSUM(SEP_2013_A,32,CL_90_) -> 0 | U79: =DSUM(SEP_2013_A,33,CL_90_) -> 0 | V79: =DSUM(SEP_2013_A,34,CL_90_) -> 0
B80: CL_91_ | C80: =VLOOKUP(B80,BASE_A,6,FALSE) -> Rancho La Cuchilla No. 91 | D80: =VLOOKUP(B80,BASE_A,8,FALSE) -> Roldán Flores | E80: =VLOOKUP(B80,BASE_A,9,FALSE) -> 300 | F80: =DSUM(SEP_2013_A,AA,CL_91_) -> 0 | G80: =H80-F80 -> 3300 | H80: =DSUM(SEP_2013_A,importe,CL_91_) -> 3300 | I80: =IF(VLOOKUP(B80,BASE_A,9,FALSE)=0,0,(G80/VLOOKUP(B80,BASE_A,9,FALSE)))+1 -> 12 | J80: Cuchilla | K80: =DSUM(SEP_2013_A,23,CL_91_) -> 300 | L80: =DSUM(SEP_2013_A,24,CL_91_) -> 300 | M80: =DSUM(SEP_2013_A,25,CL_91_) -> 300 | N80: =DSUM(SEP_2013_A,26,CL_91_) -> 300 | O80: =DSUM(SEP_2013_A,27,CL_91_) -> 300 | P80: =DSUM(SEP_2013_A,28,CL_91_) -> 300 | Q80: =DSUM(SEP_2013_A,29,CL_91_) -> 300 | R80: =DSUM(SEP_2013_A,30,CL_91_) -> 300 | S80: =DSUM(SEP_2013_A,31,CL_91_) -> 300 | T80: =DSUM(SEP_2013_A,32,CL_91_) -> 300 | U80: =DSUM(SEP_2013_A,33,CL_91_) -> 300 | V80: =DSUM(SEP_2013_A,34,CL_91_) -> 0
B81: CL_92_ | C81: =VLOOKUP(B81,BASE_A,6,FALSE) -> Rancho La Cuchilla No. 92 | D81: =VLOOKUP(B81,BASE_A,8,FALSE) -> Cabrera | E81: =VLOOKUP(B81,BASE_A,9,FALSE) -> 300 | F81: =DSUM(SEP_2013_A,AA,CL_92_) -> 0 | G81: =H81-F81 -> 2700 | H81: =DSUM(SEP_2013_A,importe,CL_92_) -> 2700 | I81: =IF(VLOOKUP(B81,BASE_A,9,FALSE)=0,0,G81/VLOOKUP(B81,BASE_A,9,FALSE)) -> 9 | J81: Cuchilla | K81: =DSUM(SEP_2013_A,23,CL_92_) -> 300 | L81: =DSUM(SEP_2013_A,24,CL_92_) -> 300 | M81: =DSUM(SEP_2013_A,25,CL_92_) -> 300 | N81: =DSUM(SEP_2013_A,26,CL_92_) -> 300 | O81: =DSUM(SEP_2013_A,27,CL_92_) -> 300 | P81: =DSUM(SEP_2013_A,28,CL_92_) -> 300 | Q81: =DSUM(SEP_2013_A,29,CL_92_) -> 300 | R81: =DSUM(SEP_2013_A,30,CL_92_) -> 300 | S81: =DSUM(SEP_2013_A,31,CL_92_) -> 300 | T81: =DSUM(SEP_2013_A,32,CL_92_) -> 0 | U81: =DSUM(SEP_2013_A,33,CL_92_) -> 0 | V81: =DSUM(SEP_2013_A,34,CL_92_) -> 0
B82: CL_93_ | C82: =VLOOKUP(B82,BASE_A,6,FALSE) -> Rancho La Cuchilla No. 93 | D82: =VLOOKUP(B82,BASE_A,8,FALSE) -> Alcántara Silva | E82: =VLOOKUP(B82,BASE_A,9,FALSE) -> 300 | F82: =DSUM(SEP_2013_A,AA,CL_93_) -> 300 | G82: =H82-F82 -> 2420 | H82: =DSUM(SEP_2013_A,importe,CL_93_) -> 2720 | I82: =IF(VLOOKUP(B82,BASE_A,9,FALSE)=0,0,G82/VLOOKUP(B82,BASE_A,9,FALSE)) -> 8.0666667 | J82: Cuchilla | K82: =DSUM(SEP_2013_A,23,CL_93_) -> 300 | L82: =DSUM(SEP_2013_A,24,CL_93_) -> 300 | M82: =DSUM(SEP_2013_A,25,CL_93_) -> 300 | N82: =DSUM(SEP_2013_A,26,CL_93_) -> 150 | O82: =DSUM(SEP_2013_A,27,CL_93_) -> 170 | P82: =DSUM(SEP_2013_A,28,CL_93_) -> 300 | Q82: =DSUM(SEP_2013_A,29,CL_93_) -> 300 | R82: =DSUM(SEP_2013_A,30,CL_93_) -> 300 | S82: =DSUM(SEP_2013_A,31,CL_93_) -> 300 | T82: =DSUM(SEP_2013_A,32,CL_93_) -> 0 | U82: =DSUM(SEP_2013_A,33,CL_93_) -> 0 | V82: =DSUM(SEP_2013_A,34,CL_93_) -> 0
B83: CL_94_ | C83: =VLOOKUP(B83,BASE_A,6,FALSE) -> Rancho La Cuchilla No. 94 | D83: =VLOOKUP(B83,BASE_A,8,FALSE) -> Sánchez Márquez | E83: =VLOOKUP(B83,BASE_A,9,FALSE) -> 300 | F83: =DSUM(SEP_2013_A,AA,CL_94_) -> 300 | G83: =H83-F83 -> 2400 | H83: =DSUM(SEP_2013_A,importe,CL_94_) -> 2700 | I83: =IF(VLOOKUP(B83,BASE_A,9,FALSE)=0,0,G83/VLOOKUP(B83,BASE_A,9,FALSE)) -> 8 | J83: Cuchilla | K83: =DSUM(SEP_2013_A,23,CL_94_) -> 300 | L83: =DSUM(SEP_2013_A,24,CL_94_) -> 300 | M83: =DSUM(SEP_2013_A,25,CL_94_) -> 0 | N83: =DSUM(SEP_2013_A,26,CL_94_) -> 300 | O83: =DSUM(SEP_2013_A,27,CL_94_) -> 300 | P83: =DSUM(SEP_2013_A,28,CL_94_) -> 300 | Q83: =DSUM(SEP_2013_A,29,CL_94_) -> 300 | R83: =DSUM(SEP_2013_A,30,CL_94_) -> 300 | S83: =DSUM(SEP_2013_A,31,CL_94_) -> 300 | T83: =DSUM(SEP_2013_A,32,CL_94_) -> 0 | U83: =DSUM(SEP_2013_A,33,CL_94_) -> 0 | V83: =DSUM(SEP_2013_A,34,CL_94_) -> 0
B84: CL_95_ | C84: =VLOOKUP(B84,BASE_A,6,FALSE) -> Rancho La Cuchilla No. 95 | D84: =VLOOKUP(B84,BASE_A,8,FALSE) -> Gutiérrez Sánchez | E84: =VLOOKUP(B84,BASE_A,9,FALSE) -> 300 | F84: =DSUM(SEP_2013_A,AA,CL_95_) -> 300 | G84: =H84-F84 -> 3000 | H84: =DSUM(SEP_2013_A,importe,CL_95_) -> 3300 | I84: =IF(VLOOKUP(B84,BASE_A,9,FALSE)=0,0,G84/VLOOKUP(B84,BASE_A,9,FALSE)) -> 10 | J84: Cuchilla | K84: =DSUM(SEP_2013_A,23,CL_95_) -> 300 | L84: =DSUM(SEP_2013_A,24,CL_95_) -> 300 | M84: =DSUM(SEP_2013_A,25,CL_95_) -> 300 | N84: =DSUM(SEP_2013_A,26,CL_95_) -> 300 | O84: =DSUM(SEP_2013_A,27,CL_95_) -> 300 | P84: =DSUM(SEP_2013_A,28,CL_95_) -> 300 | Q84: =DSUM(SEP_2013_A,29,CL_95_) -> 300 | R84: =DSUM(SEP_2013_A,30,CL_95_) -> 300 | S84: =DSUM(SEP_2013_A,31,CL_95_) -> 300 | T84: =DSUM(SEP_2013_A,32,CL_95_) -> 300 | U84: =DSUM(SEP_2013_A,33,CL_95_) -> 0 | V84: =DSUM(SEP_2013_A,34,CL_95_) -> 0
B85: CL_96_ | C85: =VLOOKUP(B85,BASE_A,6,FALSE) -> Rancho La Cuchilla No. 96 | D85: =VLOOKUP(B85,BASE_A,8,FALSE) -> Valdez Álvarez | E85: =VLOOKUP(B85,BASE_A,9,FALSE) -> 300 | F85: =DSUM(SEP_2013_A,AA,CL_96_) -> 1800 | G85: =H85-F85 -> 3600 | H85: =DSUM(SEP_2013_A,importe,CL_96_) -> 5400 | I85: =IF(VLOOKUP(B85,BASE_A,9,FALSE)=0,0,G85/VLOOKUP(B85,BASE_A,9,FALSE)) -> 12 | J85: Cuchilla | K85: =DSUM(SEP_2013_A,23,CL_96_) -> 300 | L85: =DSUM(SEP_2013_A,24,CL_96_) -> 300 | M85: =DSUM(SEP_2013_A,25,CL_96_) -> 300 | N85: =DSUM(SEP_2013_A,26,CL_96_) -> 300 | O85: =DSUM(SEP_2013_A,27,CL_96_) -> 300 | P85: =DSUM(SEP_2013_A,28,CL_96_) -> 300 | Q85: =DSUM(SEP_2013_A,29,CL_96_) -> 300 | R85: =DSUM(SEP_2013_A,30,CL_96_) -> 300 | S85: =DSUM(SEP_2013_A,31,CL_96_) -> 300 | T85: =DSUM(SEP_2013_A,32,CL_96_) -> 300 | U85: =DSUM(SEP_2013_A,33,CL_96_) -> 300 | V85: =DSUM(SEP_2013_A,34,CL_96_) -> 300
B86: CL_97_ | C86: =VLOOKUP(B86,BASE_A,6,FALSE) -> Rancho La Cuchilla No. 97 | D86: =VLOOKUP(B86,BASE_A,8,FALSE) -> López Ruiz | E86: =VLOOKUP(B86,BASE_A,9,FALSE) -> 300 | F86: =DSUM(SEP_2013_A,AA,CL_97_) -> 300 | G86: =H86-F86 -> 2700 | H86: =DSUM(SEP_2013_A,importe,CL_97_) -> 3000 | I86: =IF(VLOOKUP(B86,BASE_A,9,FALSE)=0,0,G86/VLOOKUP(B86,BASE_A,9,FALSE)) -> 9 | J86: Cuchilla | K86: =DSUM(SEP_2013_A,23,CL_97_) -> 300 | L86: =DSUM(SEP_2013_A,24,CL_97_) -> 300 | M86: =DSUM(SEP_2013_A,25,CL_97_) -> 300 | N86: =DSUM(SEP_2013_A,26,CL_97_) -> 300 | O86: =DSUM(SEP_2013_A,27,CL_97_) -> 300 | P86: =DSUM(SEP_2013_A,28,CL_97_) -> 300 | Q86: =DSUM(SEP_2013_A,29,CL_97_) -> 300 | R86: =DSUM(SEP_2013_A,30,CL_97_) -> 300 | S86: =DSUM(SEP_2013_A,31,CL_97_) -> 300 | T86: =DSUM(SEP_2013_A,32,CL_97_) -> 0 | U86: =DSUM(SEP_2013_A,33,CL_97_) -> 0 | V86: =DSUM(SEP_2013_A,34,CL_97_) -> 0
B87: CL_101_ | C87: =VLOOKUP(B87,BASE_A,6,FALSE) -> Rancho La Cuchilla No. 101 | D87: =VLOOKUP(B87,BASE_A,8,FALSE) -> Rodríguez Ramírez | E87: =VLOOKUP(B87,BASE_A,9,FALSE) -> 300 | F87: =DSUM(SEP_2013_A,AA,CL_101_) -> 0 | G87: =H87-F87 -> 0 | H87: =DSUM(SEP_2013_A,importe,CL_101_) -> 0 | I87: =IF(VLOOKUP(B87,BASE_A,9,FALSE)=0,0,G87/VLOOKUP(B87,BASE_A,9,FALSE)) -> 0 | J87: Cuchilla | K87: =DSUM(SEP_2013_A,23,CL_101_) -> 0 | L87: =DSUM(SEP_2013_A,24,CL_101_) -> 0 | M87: =DSUM(SEP_2013_A,25,CL_101_) -> 0 | N87: =DSUM(SEP_2013_A,26,CL_101_) -> 0 | O87: =DSUM(SEP_2013_A,27,CL_101_) -> 0 | P87: =DSUM(SEP_2013_A,28,CL_101_) -> 0 | Q87: =DSUM(SEP_2013_A,29,CL_101_) -> 0 | R87: =DSUM(SEP_2013_A,30,CL_101_) -> 0 | S87: =DSUM(SEP_2013_A,31,CL_101_) -> 0 | T87: =DSUM(SEP_2013_A,32,CL_101_) -> 0 | U87: =DSUM(SEP_2013_A,33,CL_101_) -> 0 | V87: =DSUM(SEP_2013_A,34,CL_101_) -> 0
B88: CL_107_ | C88: =VLOOKUP(B88,BASE_A,6,FALSE) -> Rancho La Cuchilla No. 107 | D88: =VLOOKUP(B88,BASE_A,8,FALSE) -> Olivares Rivera | E88: =VLOOKUP(B88,BASE_A,9,FALSE) -> 300 | F88: =DSUM(SEP_2013_A,AA,CL_107_) -> 300 | G88: =H88-F88 -> 2700 | H88: =DSUM(SEP_2013_A,importe,CL_107_) -> 3000 | I88: =IF(VLOOKUP(B88,BASE_A,9,FALSE)=0,0,G88/VLOOKUP(B88,BASE_A,9,FALSE)) -> 9 | J88: Cuchilla | K88: =DSUM(SEP_2013_A,23,CL_107_) -> 300 | L88: =DSUM(SEP_2013_A,24,CL_107_) -> 300 | M88: =DSUM(SEP_2013_A,25,CL_107_) -> 300 | N88: =DSUM(SEP_2013_A,26,CL_107_) -> 300 | O88: =DSUM(SEP_2013_A,27,CL_107_) -> 300 | P88: =DSUM(SEP_2013_A,28,CL_107_) -> 300 | Q88: =DSUM(SEP_2013_A,29,CL_107_) -> 300 | R88: =DSUM(SEP_2013_A,30,CL_107_) -> 300 | S88: =DSUM(SEP_2013_A,31,CL_107_) -> 300 | T88: =DSUM(SEP_2013_A,32,CL_107_) -> 0 | U88: =DSUM(SEP_2013_A,33,CL_107_) -> 0 | V88: =DSUM(SEP_2013_A,34,CL_107_) -> 0
B89: CL_110_ | C89: =VLOOKUP(B89,BASE_A,6,FALSE) -> Rancho La Cuchilla No. 110 | D89: =VLOOKUP(B89,BASE_A,8,FALSE) -> Domínguez Canudas | E89: =VLOOKUP(B89,BASE_A,9,FALSE) -> 300 | F89: =DSUM(SEP_2013_A,AA,CL_110_) -> 300 | G89: =H89-F89 -> 2700 | H89: =DSUM(SEP_2013_A,importe,CL_110_) -> 3000 | I89: =IF(VLOOKUP(B89,BASE_A,9,FALSE)=0,0,G89/VLOOKUP(B89,BASE_A,9,FALSE)) -> 9 | J89: Cuchilla | K89: =DSUM(SEP_2013_A,23,CL_110_) -> 300 | L89: =DSUM(SEP_2013_A,24,CL_110_) -> 300 | M89: =DSUM(SEP_2013_A,25,CL_110_) -> 300 | N89: =DSUM(SEP_2013_A,26,CL_110_) -> 300 | O89: =DSUM(SEP_2013_A,27,CL_110_) -> 300 | P89: =DSUM(SEP_2013_A,28,CL_110_) -> 300 | Q89: =DSUM(SEP_2013_A,29,CL_110_) -> 300 | R89: =DSUM(SEP_2013_A,30,CL_110_) -> 300 | S89: =DSUM(SEP_2013_A,31,CL_110_) -> 300 | T89: =DSUM(SEP_2013_A,32,CL_110_) -> 0 | U89: =DSUM(SEP_2013_A,33,CL_110_) -> 0 | V89: =DSUM(SEP_2013_A,34,CL_110_) -> 0
B90: CL_111_ | C90: =VLOOKUP(B90,BASE_A,6,FALSE) -> Rancho La Cuchilla No. 111 | D90: =VLOOKUP(B90,BASE_A,8,FALSE) -> García Santos Ofelia | E90: =VLOOKUP(B90,BASE_A,9,FALSE) -> 150 | F90: =DSUM(SEP_2013_A,AA,CL_111_) -> 150 | G90: =H90-F90 -> 1450 | H90: =DSUM(SEP_2013_A,importe,CL_111_) -> 1600 | I90: =IF(VLOOKUP(B90,BASE_A,9,FALSE)=0,0,G90/VLOOKUP(B90,BASE_A,9,FALSE)) -> 9.6666667 | J90: Cuchilla | K90: =DSUM(SEP_2013_A,23,CL_111_) -> 150 | L90: =DSUM(SEP_2013_A,24,CL_111_) -> 150 | M90: =DSUM(SEP_2013_A,25,CL_111_) -> 0 | N90: =DSUM(SEP_2013_A,26,CL_111_) -> 300 | O90: =DSUM(SEP_2013_A,27,CL_111_) -> 150 | P90: =DSUM(SEP_2013_A,28,CL_111_) -> 150 | Q90: =DSUM(SEP_2013_A,29,CL_111_) -> 150 | R90: =DSUM(SEP_2013_A,30,CL_111_) -> 200 | S90: =DSUM(SEP_2013_A,31,CL_111_) -> 200 | T90: =DSUM(SEP_2013_A,32,CL_111_) -> 0 | U90: =DSUM(SEP_2013_A,33,CL_111_) -> 0 | V90: =DSUM(SEP_2013_A,34,CL_111_) -> 0
B91: CL_112_PA | C91: =VLOOKUP(B91,BASE_A,6,FALSE) -> Rancho La Cuchilla No. 112, PA | D91: =VLOOKUP(B91,BASE_A,8,FALSE) -> Villalpando Pineda | E91: =VLOOKUP(B91,BASE_A,9,FALSE) -> 150 | F91: =DSUM(SEP_2013_A,AA,CL_112_PA) -> 0 | G91: =H91-F91 -> 0 | H91: =DSUM(SEP_2013_A,importe,CL_112_PA) -> 0 | I91: =IF(VLOOKUP(B91,BASE_A,9,FALSE)=0,0,G91/VLOOKUP(B91,BASE_A,9,FALSE)) -> 0 | J91: Cuchilla | K91: =DSUM(SEP_2013_A,23,CL_112_PA) -> 0 | L91: =DSUM(SEP_2013_A,24,CL_112_PA) -> 0 | M91: =DSUM(SEP_2013_A,25,CL_112_PA) -> 0 | N91: =DSUM(SEP_2013_A,26,CL_112_PA) -> 0 | O91: =DSUM(SEP_2013_A,27,CL_112_PA) -> 0 | P91: =DSUM(SEP_2013_A,28,CL_112_PA) -> 0 | Q91: =DSUM(SEP_2013_A,29,CL_112_PA) -> 0 | R91: =DSUM(SEP_2013_A,30,CL_112_PA) -> 0 | S91: =DSUM(SEP_2013_A,31,CL_112_PA) -> 0 | T91: =DSUM(SEP_2013_A,32,CL_112_PA) -> 0 | U91: =DSUM(SEP_2013_A,33,CL_112_PA) -> 0 | V91: =DSUM(SEP_2013_A,34,CL_112_PA) -> 0
B92: CL_112_PB | C92: =VLOOKUP(B92,BASE_A,6,FALSE) -> Rancho La Cuchilla No. 112, PB | D92: =VLOOKUP(B92,BASE_A,8,FALSE) -> Soreque | E92: =VLOOKUP(B92,BASE_A,9,FALSE) -> 150 | F92: =DSUM(SEP_2013_A,AA,CL_112_PB) -> 150 | G92: =H92-F92 -> 1350 | H92: =DSUM(SEP_2013_A,importe,CL_112_PB) -> 1500 | I92: =IF(VLOOKUP(B92,BASE_A,9,FALSE)=0,0,G92/VLOOKUP(B92,BASE_A,9,FALSE)) -> 9 | J92: Cuchilla | K92: =DSUM(SEP_2013_A,23,CL_112_PB) -> 150 | L92: =DSUM(SEP_2013_A,24,CL_112_PB) -> 150 | M92: =DSUM(SEP_2013_A,25,CL_112_PB) -> 150 | N92: =DSUM(SEP_2013_A,26,CL_112_PB) -> 150 | O92: =DSUM(SEP_2013_A,27,CL_112_PB) -> 150 | P92: =DSUM(SEP_2013_A,28,CL_112_PB) -> 150 | Q92: =DSUM(SEP_2013_A,29,CL_112_PB) -> 150 | R92: =DSUM(SEP_2013_A,30,CL_112_PB) -> 150 | S92: =DSUM(SEP_2013_A,31,CL_112_PB) -> 150 | T92: =DSUM(SEP_2013_A,32,CL_112_PB) -> 0 | U92: =DSUM(SEP_2013_A,33,CL_112_PB) -> 0 | V92: =DSUM(SEP_2013_A,34,CL_112_PB) -> 0
B93: CL_115_ | C93: =VLOOKUP(B93,BASE_A,6,FALSE) -> Rancho La Cuchilla No. 115 | D93: =VLOOKUP(B93,BASE_A,8,FALSE) -> Alfaro | E93: =VLOOKUP(B93,BASE_A,9,FALSE) -> 300 | F93: =DSUM(SEP_2013_A,AA,CL_115_) -> 0 | G93: =H93-F93 -> 2700 | H93: =DSUM(SEP_2013_A,importe,CL_115_) -> 2700 | I93: =IF(VLOOKUP(B93,BASE_A,9,FALSE)=0,0,G93/VLOOKUP(B93,BASE_A,9,FALSE)) -> 9 | J93: Cuchilla | K93: =DSUM(SEP_2013_A,23,CL_115_) -> 300 | L93: =DSUM(SEP_2013_A,24,CL_115_) -> 300 | M93: =DSUM(SEP_2013_A,25,CL_115_) -> 300 | N93: =DSUM(SEP_2013_A,26,CL_115_) -> 300 | O93: =DSUM(SEP_2013_A,27,CL_115_) -> 300 | P93: =DSUM(SEP_2013_A,28,CL_115_) -> 300 | Q93: =DSUM(SEP_2013_A,29,CL_115_) -> 300 | R93: =DSUM(SEP_2013_A,30,CL_115_) -> 300 | S93: =DSUM(SEP_2013_A,31,CL_115_) -> 300 | T93: =DSUM(SEP_2013_A,32,CL_115_) -> 0 | U93: =DSUM(SEP_2013_A,33,CL_115_) -> 0 | V93: =DSUM(SEP_2013_A,34,CL_115_) -> 0
B94: CL_116_ | C94: =VLOOKUP(B94,BASE_A,6,FALSE) -> Rancho La Cuchilla No. 116 | D94: =VLOOKUP(B94,BASE_A,8,FALSE) -> Miranda | E94: =VLOOKUP(B94,BASE_A,9,FALSE) -> 300 | F94: =DSUM(SEP_2013_A,AA,CL_116_) -> 0 | G94: =H94-F94 -> 0 | H94: =DSUM(SEP_2013_A,importe,CL_116_) -> 0 | I94: =IF(VLOOKUP(B94,BASE_A,9,FALSE)=0,0,G94/VLOOKUP(B94,BASE_A,9,FALSE)) -> 0 | J94: Cuchilla | K94: =DSUM(SEP_2013_A,23,CL_116_) -> 0 | L94: =DSUM(SEP_2013_A,24,CL_116_) -> 0 | M94: =DSUM(SEP_2013_A,25,CL_116_) -> 0 | N94: =DSUM(SEP_2013_A,26,CL_116_) -> 0 | O94: =DSUM(SEP_2013_A,27,CL_116_) -> 0 | P94: =DSUM(SEP_2013_A,28,CL_116_) -> 0 | Q94: =DSUM(SEP_2013_A,29,CL_116_) -> 0 | R94: =DSUM(SEP_2013_A,30,CL_116_) -> 0 | S94: =DSUM(SEP_2013_A,31,CL_116_) -> 0 | T94: =DSUM(SEP_2013_A,32,CL_116_) -> 0 | U94: =DSUM(SEP_2013_A,33,CL_116_) -> 0 | V94: =DSUM(SEP_2013_A,34,CL_116_) -> 0
B95: CL_117_ | C95: =VLOOKUP(B95,BASE_A,6,FALSE) -> Rancho La Cuchilla No. 117 | D95: =VLOOKUP(B95,BASE_A,8,FALSE) -> Gómez | E95: =VLOOKUP(B95,BASE_A,9,FALSE) -> 300 | F95: =DSUM(SEP_2013_A,AA,CL_117_) -> 0 | G95: =H95-F95 -> 3000 | H95: =DSUM(SEP_2013_A,importe,CL_117_) -> 3000 | I95: =IF(VLOOKUP(B95,BASE_A,9,FALSE)=0,0,G95/VLOOKUP(B95,BASE_A,9,FALSE)) -> 10 | J95: Cuchilla | K95: =DSUM(SEP_2013_A,23,CL_117_) -> 300 | L95: =DSUM(SEP_2013_A,24,CL_117_) -> 300 | M95: =DSUM(SEP_2013_A,25,CL_117_) -> 300 | N95: =DSUM(SEP_2013_A,26,CL_117_) -> 300 | O95: =DSUM(SEP_2013_A,27,CL_117_) -> 300 | P95: =DSUM(SEP_2013_A,28,CL_117_) -> 300 | Q95: =DSUM(SEP_2013_A,29,CL_117_) -> 300 | R95: =DSUM(SEP_2013_A,30,CL_117_) -> 300 | S95: =DSUM(SEP_2013_A,31,CL_117_) -> 300 | T95: =DSUM(SEP_2013_A,32,CL_117_) -> 300 | U95: =DSUM(SEP_2013_A,33,CL_117_) -> 0 | V95: =DSUM(SEP_2013_A,34,CL_117_) -> 0
B96: CL_118_ | C96: =VLOOKUP(B96,BASE_A,6,FALSE) -> Rancho La Cuchilla No. 118 | D96: =VLOOKUP(B96,BASE_A,8,FALSE) -> Astorga Ruiz | E96: =VLOOKUP(B96,BASE_A,9,FALSE) -> 300 | F96: =DSUM(SEP_2013_A,AA,CL_118_) -> 0 | G96: =H96-F96 -> 0 | H96: =DSUM(SEP_2013_A,importe,CL_118_) -> 0 | I96: =IF(VLOOKUP(B96,BASE_A,9,FALSE)=0,0,G96/VLOOKUP(B96,BASE_A,9,FALSE)) -> 0 | J96: Cuchilla | K96: =DSUM(SEP_2013_A,23,CL_118_) -> 0 | L96: =DSUM(SEP_2013_A,24,CL_118_) -> 0 | M96: =DSUM(SEP_2013_A,25,CL_118_) -> 0 | N96: =DSUM(SEP_2013_A,26,CL_118_) -> 0 | O96: =DSUM(SEP_2013_A,27,CL_118_) -> 0 | P96: =DSUM(SEP_2013_A,28,CL_118_) -> 0 | Q96: =DSUM(SEP_2013_A,29,CL_118_) -> 0 | R96: =DSUM(SEP_2013_A,30,CL_118_) -> 0 | S96: =DSUM(SEP_2013_A,31,CL_118_) -> 0 | T96: =DSUM(SEP_2013_A,32,CL_118_) -> 0 | U96: =DSUM(SEP_2013_A,33,CL_118_) -> 0 | V96: =DSUM(SEP_2013_A,34,CL_118_) -> 0
B97: CL_119_ | C97: =VLOOKUP(B97,BASE_A,6,FALSE) -> Rancho La Cuchilla No. 119 | D97: =VLOOKUP(B97,BASE_A,8,FALSE) -> Vilchis | E97: =VLOOKUP(B97,BASE_A,9,FALSE) -> 300 | F97: =DSUM(SEP_2013_A,AA,CL_119_) -> 0 | G97: =H97-F97 -> 0 | H97: =DSUM(SEP_2013_A,importe,CL_119_) -> 0 | I97: =IF(VLOOKUP(B97,BASE_A,9,FALSE)=0,0,G97/VLOOKUP(B97,BASE_A,9,FALSE)) -> 0 | J97: Cuchilla | K97: =DSUM(SEP_2013_A,23,CL_119_) -> 0 | L97: =DSUM(SEP_2013_A,24,CL_119_) -> 0 | M97: =DSUM(SEP_2013_A,25,CL_119_) -> 0 | N97: =DSUM(SEP_2013_A,26,CL_119_) -> 0 | O97: =DSUM(SEP_2013_A,27,CL_119_) -> 0 | P97: =DSUM(SEP_2013_A,28,CL_119_) -> 0 | Q97: =DSUM(SEP_2013_A,29,CL_119_) -> 0 | R97: =DSUM(SEP_2013_A,30,CL_119_) -> 0 | S97: =DSUM(SEP_2013_A,31,CL_119_) -> 0 | T97: =DSUM(SEP_2013_A,32,CL_119_) -> 0 | U97: =DSUM(SEP_2013_A,33,CL_119_) -> 0 | V97: =DSUM(SEP_2013_A,34,CL_119_) -> 0
B98: CL_120_ | C98: =VLOOKUP(B98,BASE_A,6,FALSE) -> Rancho La Cuchilla No. 120 | D98: =VLOOKUP(B98,BASE_A,8,FALSE) -> Pozos Vilchis | E98: =VLOOKUP(B98,BASE_A,9,FALSE) -> 300 | F98: =DSUM(SEP_2013_A,AA,CL_120_) -> 300 | G98: =H98-F98 -> 2700 | H98: =DSUM(SEP_2013_A,importe,CL_120_) -> 3000 | I98: =IF(VLOOKUP(B98,BASE_A,9,FALSE)=0,0,G98/VLOOKUP(B98,BASE_A,9,FALSE)) -> 9 | J98: Cuchilla | K98: =DSUM(SEP_2013_A,23,CL_120_) -> 300 | L98: =DSUM(SEP_2013_A,24,CL_120_) -> 300 | M98: =DSUM(SEP_2013_A,25,CL_120_) -> 300 | N98: =DSUM(SEP_2013_A,26,CL_120_) -> 300 | O98: =DSUM(SEP_2013_A,27,CL_120_) -> 300 | P98: =DSUM(SEP_2013_A,28,CL_120_) -> 300 | Q98: =DSUM(SEP_2013_A,29,CL_120_) -> 300 | R98: =DSUM(SEP_2013_A,30,CL_120_) -> 300 | S98: =DSUM(SEP_2013_A,31,CL_120_) -> 300 | T98: =DSUM(SEP_2013_A,32,CL_120_) -> 0 | U98: =DSUM(SEP_2013_A,33,CL_120_) -> 0 | V98: =DSUM(SEP_2013_A,34,CL_120_) -> 0
B99: CL_121_ | C99: =VLOOKUP(B99,BASE_A,6,FALSE) -> Rancho La Cuchilla No. 121 | D99: =VLOOKUP(B99,BASE_A,8,FALSE) -> Ramírez Márquez | E99: =VLOOKUP(B99,BASE_A,9,FALSE) -> 300 | F99: =DSUM(SEP_2013_A,AA,CL_121_) -> 0 | G99: =H99-F99 -> 3600 | H99: =DSUM(SEP_2013_A,importe,CL_121_) -> 3600 | I99: =IF(VLOOKUP(B99,BASE_A,9,FALSE)=0,0,G99/VLOOKUP(B99,BASE_A,9,FALSE)) -> 12 | J99: Cuchilla | K99: =DSUM(SEP_2013_A,23,CL_121_) -> 300 | L99: =DSUM(SEP_2013_A,24,CL_121_) -> 300 | M99: =DSUM(SEP_2013_A,25,CL_121_) -> 300 | N99: =DSUM(SEP_2013_A,26,CL_121_) -> 300 | O99: =DSUM(SEP_2013_A,27,CL_121_) -> 300 | P99: =DSUM(SEP_2013_A,28,CL_121_) -> 300 | Q99: =DSUM(SEP_2013_A,29,CL_121_) -> 300 | R99: =DSUM(SEP_2013_A,30,CL_121_) -> 300 | S99: =DSUM(SEP_2013_A,31,CL_121_) -> 300 | T99: =DSUM(SEP_2013_A,32,CL_121_) -> 300 | U99: =DSUM(SEP_2013_A,33,CL_121_) -> 300 | V99: =DSUM(SEP_2013_A,34,CL_121_) -> 300
B100: CL_122_ | C100: =VLOOKUP(B100,BASE_A,6,FALSE) -> Rancho La Cuchilla No. 122 | D100: =VLOOKUP(B100,BASE_A,8,FALSE) -> Mendoza | E100: =VLOOKUP(B100,BASE_A,9,FALSE) -> 300 | F100: =DSUM(SEP_2013_A,AA,CL_122_) -> 0 | G100: =H100-F100 -> 0 | H100: =DSUM(SEP_2013_A,importe,CL_122_) -> 0 | I100: =IF(VLOOKUP(B100,BASE_A,9,FALSE)=0,0,G100/VLOOKUP(B100,BASE_A,9,FALSE)) -> 0 | J100: Cuchilla | K100: =DSUM(SEP_2013_A,23,CL_122_) -> 0 | L100: =DSUM(SEP_2013_A,24,CL_122_) -> 0 | M100: =DSUM(SEP_2013_A,25,CL_122_) -> 0 | N100: =DSUM(SEP_2013_A,26,CL_122_) -> 0 | O100: =DSUM(SEP_2013_A,27,CL_122_) -> 0 | P100: =DSUM(SEP_2013_A,28,CL_122_) -> 0 | Q100: =DSUM(SEP_2013_A,29,CL_122_) -> 0 | R100: =DSUM(SEP_2013_A,30,CL_122_) -> 0 | S100: =DSUM(SEP_2013_A,31,CL_122_) -> 0 | T100: =DSUM(SEP_2013_A,32,CL_122_) -> 0 | U100: =DSUM(SEP_2013_A,33,CL_122_) -> 0 | V100: =DSUM(SEP_2013_A,34,CL_122_) -> 0
B101: CL_125_ | C101: =VLOOKUP(B101,BASE_A,6,FALSE) -> Rancho La Cuchilla No. 125 | D101: =VLOOKUP(B101,BASE_A,8,FALSE) -> Ordoñez Villalpando | E101: =VLOOKUP(B101,BASE_A,9,FALSE) -> 300 | F101: =DSUM(SEP_2013_A,AA,CL_125_) -> 0 | G101: =H101-F101 -> 0 | H101: =DSUM(SEP_2013_A,importe,CL_125_) -> 0 | I101: =IF(VLOOKUP(B101,BASE_A,9,FALSE)=0,0,G101/VLOOKUP(B101,BASE_A,9,FALSE)) -> 0 | J101: Cuchilla | K101: =DSUM(SEP_2013_A,23,CL_125_) -> 0 | L101: =DSUM(SEP_2013_A,24,CL_125_) -> 0 | M101: =DSUM(SEP_2013_A,25,CL_125_) -> 0 | N101: =DSUM(SEP_2013_A,26,CL_125_) -> 0 | O101: =DSUM(SEP_2013_A,27,CL_125_) -> 0 | P101: =DSUM(SEP_2013_A,28,CL_125_) -> 0 | Q101: =DSUM(SEP_2013_A,29,CL_125_) -> 0 | R101: =DSUM(SEP_2013_A,30,CL_125_) -> 0 | S101: =DSUM(SEP_2013_A,31,CL_125_) -> 0 | T101: =DSUM(SEP_2013_A,32,CL_125_) -> 0 | U101: =DSUM(SEP_2013_A,33,CL_125_) -> 0 | V101: =DSUM(SEP_2013_A,34,CL_125_) -> 0
...

Sheet financiero
B1: Asociación de Colonos HACIENDAS DE COYOACÁN
B3: REPORTE FINANCIERO
B4: AÑO: 2013
B6: CONCEPTO / MES | C6: DICIEMBRE 2012 | D6: ANUAL 2013 | E6: ENERO | F6: FEBRERO | G6: MARZO | H6: ABRIL | I6: MAYO | J6: JUNIO | K6: JULIO | L6: AGOSTO | M6: SEPTIEMBRE
B7: INGRESOS
B8: Cuotas de vigilancia | C8: =DSUM(DIC_2012,importe,ING_CUOTAS) -> 81975 | D8: =SUM(E8:M8) -> 697345 | E8: =DSUM(ENE_2013,importe,ING_CUOTAS) -> 127225 | F8: =DSUM(FEB_2013,importe,ING_CUOTAS) -> 87575 | G8: =DSUM(MAR_2013,importe,ING_CUOTAS) -> 81975 | H8: =DSUM(ABR_2013,importe,ING_CUOTAS) -> 57925 | I8: =DSUM(MAY_2013,importe,ING_CUOTAS) -> 68095 | J8: =DSUM(JUN_2013,importe,ING_CUOTAS) -> 70775 | K8: =DSUM(JUL_2013,importe,ING_CUOTAS) -> 68325 | L8: =DSUM(AGO_2013,importe,ING_CUOTAS) -> 58975 | M8: =DSUM(SEP_2013,importe,ING_CUOTAS) -> 76475 | N8: 64075 | O8: =M8-N8 -> 12400
B9: Cuotas extraordinarias | C9: =DSUM(DIC_2012,importe,ING_EXTRA) -> 8750 | D9: =SUM(E9:M9) -> 5660.71 | E9: =DSUM(ENE_2013,importe,ING_EXTRA) -> 900 | F9: =DSUM(FEB_2013,importe,ING_EXTRA) -> 1100 | G9: =DSUM(MAR_2013,importe,ING_EXTRA) -> 300 | H9: =DSUM(ABR_2013,importe,ING_EXTRA) -> 0 | I9: =DSUM(MAY_2013,importe,ING_EXTRA) -> 0 | J9: =DSUM(JUN_2013,importe,ING_EXTRA) -> 0 | K9: =DSUM(JUL_2013,importe,ING_EXTRA) -> 0 | L9: =DSUM(AGO_2013,importe,ING_EXTRA) -> 3360.71 | M9: =DSUM(SEP_2013,importe,ING_EXTRA) -> 0 | N9: 0
B10: Venta de llaves | C10: =DSUM(DIC_2012,importe,ING_LLAVES) -> 1500 | D10: =SUM(E10:M10) -> 17680 | E10: =DSUM(ENE_2013,importe,ING_LLAVES) -> 3180 | F10: =DSUM(FEB_2013,importe,ING_LLAVES) -> 2280 | G10: =DSUM(MAR_2013,importe,ING_LLAVES) -> 1650 | H10: =DSUM(ABR_2013,importe,ING_LLAVES) -> 1390 | I10: =DSUM(MAY_2013,importe,ING_LLAVES) -> 1650 | J10: =DSUM(JUN_2013,importe,ING_LLAVES) -> 1500 | K10: =DSUM(JUL_2013,importe,ING_LLAVES) -> 2550 | L10: =DSUM(AGO_2013,importe,ING_LLAVES) -> 1080 | M10: =DSUM(SEP_2013,importe,ING_LLAVES) -> 2400 | N10: 2400
B11: Venta de tarjetas electrónicas | C11: =DSUM(DIC_2012,importe,ING_TELE) -> 2080 | D11: =SUM(E11:M11) -> 17120 | E11: =DSUM(ENE_2013,importe,ING_TELE) -> 1920 | F11: =DSUM(FEB_2013,importe,ING_TELE) -> 800 | G11: =DSUM(MAR_2013,importe,ING_TELE) -> 2560 | H11: =DSUM(ABR_2013,importe,ING_TELE) -> 2240 | I11: =DSUM(MAY_2013,importe,ING_TELE) -> 2880 | J11: =DSUM(JUN_2013,importe,ING_TELE) -> 2560 | K11: =DSUM(JUL_2013,importe,ING_TELE) -> 800 | L11: =DSUM(AGO_2013,importe,ING_TELE) -> 1440 | M11: =DSUM(SEP_2013,importe,ING_TELE) -> 1920 | N11: 1920
B12: Venta de tarjetones | C12: =DSUM(DIC_2012,importe,ING_TAR) -> 320 | D12: =SUM(E12:M12) -> 1680 | E12: =DSUM(ENE_2013,importe,ING_TAR) -> 20 | F12: =DSUM(FEB_2013,importe,ING_TAR) -> 300 | G12: =DSUM(MAR_2013,importe,ING_TAR) -> 320 | H12: =DSUM(ABR_2013,importe,ING_TAR) -> 240 | I12: =DSUM(MAY_2013,importe,ING_TAR) -> 60 | J12: =DSUM(JUN_2013,importe,ING_TAR) -> 80 | K12: =DSUM(JUL_2013,importe,ING_TAR) -> 460 | L12: =DSUM(AGO_2013,importe,ING_TAR) -> 100 | M12: =DSUM(SEP_2013,importe,ING_TAR) -> 100 | N12: 100
B13: Aportación Colegio Carmel y otros depósitos | D13: =SUM(E13:M13) -> 87200 | E13: =DSUM(BCO_ENE13,deposito,DTE_01)+DSUM(BCO_ENE13,deposito,DTE_02)+DSUM(BCO_ENE13,deposito,DTE_03)+DSUM(BCO_ENE13,deposito,DTE_04)+DSUM(BCO_ENE13,deposito,DTE_05) -> 10600 | F13: =DSUM(BCO_FEB13,deposito,DTE_01)+DSUM(BCO_FEB13,deposito,DTE_02)+DSUM(BCO_FEB13,deposito,DTE_03)+DSUM(BCO_FEB13,deposito,DTE_04)+DSUM(BCO_FEB13,deposito,DTE_05) -> 11200 | G13: =DSUM(BCO_MAR13,deposito,DTE_01)+DSUM(BCO_MAR13,deposito,DTE_02)+DSUM(BCO_MAR13,deposito,DTE_03)+DSUM(BCO_MAR13,deposito,DTE_04)+DSUM(BCO_MAR13,deposito,DTE_05) -> 11200 | H13: =DSUM(BCO_ABR13,deposito,DTE_01)+DSUM(BCO_ABR13,deposito,DTE_02)+DSUM(BCO_ABR13,deposito,DTE_03)+DSUM(BCO_ABR13,deposito,DTE_04)+DSUM(BCO_ABR13,deposito,DTE_05) -> 1200 | I13: =DSUM(BCO_MAY13,deposito,DTE_01)+DSUM(BCO_MAY13,deposito,DTE_02)+DSUM(BCO_MAY13,deposito,DTE_03)+DSUM(BCO_MAY13,deposito,DTE_04)+DSUM(BCO_MAY13,deposito,DTE_05) -> 20900 | J13: =DSUM(BCO_JUN13,deposito,DTE_01)+DSUM(BCO_JUN13,deposito,DTE_02)+DSUM(BCO_JUN13,deposito,DTE_03)+DSUM(BCO_JUN13,deposito,DTE_04)+DSUM(BCO_JUN13,deposito,DTE_05) -> 10600 | K13: =DSUM(BCO_JUL13,deposito,DTE_01)+DSUM(BCO_JUL13,deposito,DTE_02)+DSUM(BCO_JUL13,deposito,DTE_03)+DSUM(BCO_JUL13,deposito,DTE_04)+DSUM(BCO_JUL13,deposito,DTE_05) -> 10900 | L13: =DSUM(BCO_AGO13,deposito,DTE_01)+DSUM(BCO_AGO13,deposito,DTE_02)+DSUM(BCO_AGO13,deposito,DTE_03)+DSUM(BCO_AGO13,deposito,DTE_04)+DSUM(BCO_AGO13,deposito,DTE_05) -> 10600 | M13: =DSUM(BCO_SEP13,deposito,DTE_01)+DSUM(BCO_SEP13,deposito,DTE_02)+DSUM(BCO_SEP13,deposito,DTE_03)+DSUM(BCO_SEP13,deposito,DTE_04)+DSUM(BCO_SEP13,deposito,DTE_05) -> 0 | N13: 0
B14: Otros ingresos | C14: =DSUM(DIC_2012,importe,ING_OTROS) -> 1000 | D14: =SUM(E14:M14) -> 250 | E14: =DSUM(ENE_2013,importe,ING_OTROS) -> 200 | F14: =DSUM(FEB_2013,importe,ING_OTROS) -> 0 | G14: =DSUM(MAR_2013,importe,ING_OTROS) -> 50 | H14: =DSUM(ABR_2013,importe,ING_OTROS) -> 0 | I14: =DSUM(MAY_2013,importe,ING_OTROS) -> 0 | J14: =DSUM(JUN_2013,importe,ING_OTROS) -> 0 | K14: =DSUM(JUL_2013,importe,ING_OTROS) -> 0 | L14: =DSUM(AGO_2013,importe,ING_OTROS) -> 0 | M14: =DSUM(SEP_2013,importe,ING_OTROS) -> 0 | N14: 0
B16: SUMA INGRESOS | C16: =SUM(C8:C14) -> 95625 | D16: =SUM(D8:D14) -> 826935.71 | E16: =SUM(E8:E14) -> 144045 | F16: =SUM(F8:F14) -> 103255 | G16: =SUM(G8:G14) -> 98055 | H16: =SUM(H8:H14) -> 62995 | I16: =SUM(I8:I14) -> 93585 | J16: =SUM(J8:J14) -> 85515 | ... M16: =SUM(M8:M14) -> 80895 | N16: 68495
D17: =SUM(C16:D16) -> 922560.71
B18: EGRESOS
B19: COSTO DE VIGILANCIA | E19: =SUM(E20:E26) -> 59769.5 | F19: =SUM(F20:F26) -> 57058.52 | G19: =SUM(G20:G26) -> 61345.5 | H19: =SUM(H20:H26) -> 58909 | I19: =SUM(I20:I26) -> 55230.92 | J19: =SUM(J20:J26) -> 48437.84 | K19: =SUM(K20:K26) -> 51489.568 | L19: =SUM(L20:L26) -> 54106.62 | M19: =SUM(M20:M26) -> 0
A20: G_NMNVG | B20: Sueldos y bono de puntualidad | E20: =DSUM(G_ENE_2013,GASTO,G_NMNVG) -> 56500 | F20: =DSUM(G_FEB_2013,GASTO,G_NMNVG) -> 54400 | G20: =DSUM(G_MAR_2013,GASTO,G_NMNVG) -> 57023 | H20: =DSUM(G_ABR_2013,GASTO,G_NMNVG) -> 55120 | I20: =DSUM(G_MAY_2013,GASTO,G_NMNVG) -> 51790 | J20: =DSUM(G_JUN_2013,GASTO,G_NMNVG) -> 46400 | K20: =DSUM(G_JUL_2013,GASTO,G_NMNVG) -> 46150 | L20: =DSUM(G_AGO_2013,GASTO,G_NMNVG) -> 51353.34
A21: G_AGUA | B21: Agua | E21: =DSUM(G_ENE_2013,GASTO,G_AGUA) -> 689.5 | F21: =DSUM(G_FEB_2013,GASTO,G_AGUA) -> 478.52 | G21: =DSUM(G_MAR_2013,GASTO,G_AGUA) -> 420 | H21: =DSUM(G_ABR_2013,GASTO,G_AGUA) -> 501 | I21: =DSUM(G_MAY_2013,GASTO,G_AGUA) -> 678 | J21: =DSUM(G_JUN_2013,GASTO,G_AGUA) -> 300 | K21: =DSUM(G_JUL_2013,GASTO,G_AGUA) -> 390 | L21: =DSUM(G_AGO_2013,GASTO,G_AGUA) -> 270
A22: G_ALMVG | B22: Alimentos | E22: =DSUM(G_ENE_2013,GASTO,G_ALMVG) -> 2580 | F22: =DSUM(G_FEB_2013,GASTO,G_ALMVG) -> 2180 | G22: =DSUM(G_MAR_2013,GASTO,G_ALMVG) -> 2320 | H22: =DSUM(G_ABR_2013,GASTO,G_ALMVG) -> 2200 | I22: =DSUM(G_MAY_2013,GASTO,G_ALMVG) -> 2000 | J22: =DSUM(G_JUN_2013,GASTO,G_ALMVG) -> 1600 | K22: =DSUM(G_JUL_2013,GASTO,G_ALMVG) -> 1600 | L22: =DSUM(G_AGO_2013,GASTO,G_ALMVG) -> 1800
A23: G_MTLPZ | B23: Artículos de limpieza | E23: =DSUM(G_ENE_2013,GASTO,G_MTLPZ) -> 0 | F23: =DSUM(G_FEB_2013,GASTO,G_MTLPZ) -> 0 | G23: =DSUM(G_MAR_2013,GASTO,G_MTLPZ) -> 0 | H23: =DSUM(G_ABR_2013,GASTO,G_MTLPZ) -> 0 | I23: =DSUM(G_MAY_2013,GASTO,G_MTLPZ) -> 0 | J23: =DSUM(G_JUN_2013,GASTO,G_MTLPZ) -> 137.84 | K23: =DSUM(G_JUL_2013,GASTO,G_MTLPZ) -> 151.63793 | L23: =DSUM(G_AGO_2013,GASTO,G_MTLPZ) -> 213.28
A24: G_MDC | B24: Atención médica | E24: =DSUM(G_ENE_2013,GASTO,G_MDC) -> 0 | F24: =DSUM(G_FEB_2013,GASTO,G_MDC) -> 0 | G24: =DSUM(G_MAR_2013,GASTO,G_MDC) -> 0 | H24: =DSUM(G_ABR_2013,GASTO,G_MDC) -> 1088 | I24: =DSUM(G_MAY_2013,GASTO,G_MDC) -> 0 | J24: =DSUM(G_JUN_2013,GASTO,G_MDC) -> 0 | K24: =DSUM(G_JUL_2013,GASTO,G_MDC) -> 864.55 | L24: =DSUM(G_AGO_2013,GASTO,G_MDC) -> 0
A25: G_TRSP | B25: Mantenimiento de bicicletas | E25: =DSUM(G_ENE_2013,GASTO,G_TRSP) -> 0 | F25: =DSUM(G_FEB_2013,GASTO,G_TRSP) -> 0 | G25: =DSUM(G_MAR_2013,GASTO,G_TRSP) -> 0 | H25: =DSUM(G_ABR_2013,GASTO,G_TRSP) -> 0 | I25: =DSUM(G_MAY_2013,GASTO,G_TRSP) -> 762.92 | J25: =DSUM(G_JUN_2013,GASTO,G_TRSP) -> 0 | K25: =DSUM(G_JUL_2013,GASTO,G_TRSP) -> 323.26 | L25: =DSUM(G_AGO_2013,GASTO,G_TRSP) -> 0
A26: G_UNF | B26: Uniformes | E26: =DSUM(G_ENE_2013,GASTO,G_UNF) -> 0 | F26: =DSUM(G_FEB_2013,GASTO,G_UNF) -> 0 | G26: =DSUM(G_MAR_2013,GASTO,G_UNF) -> 1582.5 | H26: =DSUM(G_ABR_2013,GASTO,G_UNF) -> 0 | I26: =DSUM(G_MAY_2013,GASTO,G_UNF) -> 0 | J26: =DSUM(G_JUN_2013,GASTO,G_UNF) -> 0 | K26: =DSUM(G_JUL_2013,GASTO,G_UNF) -> 2010.12 | L26: =DSUM(G_AGO_2013,GASTO,G_UNF) -> 470
B27: INFRAESTRUCTURA Y SUMINISTROS | E27: =SUM(E28:E31) -> 42712 | F27: =SUM(F28:F31) -> 21000 | G27: =SUM(G28:G31) -> 4950 | H27: =SUM(H28:H31) -> 2400 | I27: =SUM(I28:I31) -> 22400 | J27: =SUM(J28:J31) -> 13800 | K27: =SUM(K28:K31) -> 2540.52 | L27: =SUM(L28:L31) -> 783.63 | M27: =SUM(M28:M31) -> 0
A28: G_INFRA | B28: Cámaras de vigilancia | E28: =DSUM(G_ENE_2013,GASTO,G_INFRA) -> 35000 | F28: =DSUM(G_FEB_2013,GASTO,G_INFRA) -> 21000 | G28: =DSUM(G_MAR_2013,GASTO,G_INFRA) -> 0 | H28: =DSUM(G_ABR_2013,GASTO,G_INFRA) -> 0 | I28: =DSUM(G_MAY_2013,GASTO,G_INFRA)+DSUM(BCO_MAY13,8,INFRA) -> 20000 | J28: =DSUM(G_JUN_2013,GASTO,G_INFRA)+DSUM(BCO_JUN13,retiro,INFRA) -> 12000 | K28: =DSUM(G_JUL_2013,GASTO,G_INFRA) -> 1200 | L28: =DSUM(G_AGO_2013,GASTO,G_INFRA) -> 0
A29: G_USB | B29: Dispositivos USB | E29: =DSUM(G_ENE_2013,GASTO,G_USB) -> 0 | F29: =DSUM(G_FEB_2013,GASTO,G_USB) -> 0 | G29: =DSUM(G_MAR_2013,GASTO,G_USB) -> 0 | H29: =DSUM(G_ABR_2013,GASTO,G_USB) -> 0 | I29: =DSUM(G_MAY_2013,GASTO,G_USB) -> 0 | J29: =DSUM(G_JUN_2013,GASTO,G_USB) -> 0 | K29: =DSUM(G_JUL_2013,GASTO,G_USB) -> 240.52 | L29: =DSUM(G_AGO_2013,GASTO,G_USB) -> 0
A30: G_ADQ | B30: Llaves electrónicas y de acceso peatonal | E30: =DSUM(G_ENE_2013,GASTO,G_ADQ) -> 7712 | F30: =DSUM(G_FEB_2013,GASTO,G_ADQ) -> 0 | G30: =DSUM(G_MAR_2013,GASTO,G_ADQ) -> 4950 | H30: =DSUM(G_ABR_2013,GASTO,G_ADQ) -> 2400 | I30: =DSUM(G_MAY_2013,GASTO,G_ADQ) -> 2400 | J30: =DSUM(G_JUN_2013,GASTO,G_ADQ) -> 1800 | K30: =DSUM(G_JUL_2013,GASTO,G_ADQ) -> 1100 | L30: =DSUM(G_AGO_2013,GASTO,G_ADQ) -> 150
A31: G_SÑ | B31: Señalización en calles | L31: =DSUM(G_AGO_2013,GASTO,G_SÑ) -> 633.63
B32: MANTENIMIENTO | E32: =SUM(E33:E38) -> 23851.15 | F32: =SUM(F33:F38) -> 17379.89 | G32: =SUM(G33:G38) -> 9092.5 | H32: =SUM(H33:H38) -> 3550 | I32: =SUM(I33:I38) -> 3670 | J32: =SUM(J33:J38) -> 2000 | K32: =SUM(K33:K38) -> 8562.47 | L32: =SUM(L33:L38) -> 9893.3955 | M32: =SUM(M33:M38) -> 0
A33: G_MTCBQ | B33: A calles y banquetas | L33: =DSUM(G_AGO_2013,GASTO,G_MTCBQ) -> 1898.1
A34: G_MTCYP | B34: A cámaras de vigilancia y plumas de acceso | E34: =DSUM(G_ENE_2013,GASTO,G_MTCYP) -> 0 | F34: =DSUM(G_FEB_2013,GASTO,G_MTCYP) -> 0 | G34: =DSUM(G_MAR_2013,GASTO,G_MTCYP) -> 0 | H34: =DSUM(G_ABR_2013,GASTO,G_MTCYP) -> 2500 | I34: =DSUM(G_MAY_2013,GASTO,G_MTCYP) -> 2500 | J34: =DSUM(G_JUN_2013,GASTO,G_MTCYP) -> 0 | K34: =DSUM(G_JUL_2013,GASTO,G_MTCYP) -> 1600 | L34: =DSUM(G_AGO_2013,GASTO,G_MTCYP) -> 3955
A35: G_MTCST | B35: A casetas | E35: =DSUM(G_ENE_2013,GASTO,G_MTCST) -> 8625.15 | F35: =DSUM(G_FEB_2013,GASTO,G_MTCST) -> 7389.89 | G35: =DSUM(G_MAR_2013,GASTO,G_MTCST) -> 8092.5 | H35: =DSUM(G_ABR_2013,GASTO,G_MTCST) -> 300 | I35: =DSUM(G_MAY_2013,GASTO,G_MTCST) -> 0 | J35: =DSUM(G_JUN_2013,GASTO,G_MTCST) -> 0 | K35: =DSUM(G_JUL_2013,GASTO,G_MTCST) -> 0 | L35: =DSUM(G_AGO_2013,GASTO,G_MTCST) -> 1057.58
A36: G_MTPTA | B36: A las puertas de acceso peatonal | E36: =DSUM(G_ENE_2013,GASTO,G_MTPTA) -> 8500 | F36: =DSUM(G_FEB_2013,GASTO,G_MTPTA) -> 0 | G36: =DSUM(G_MAR_2013,GASTO,G_MTPTA) -> 0 | H36: =DSUM(G_ABR_2013,GASTO,G_MTPTA) -> 750 | I36: =DSUM(G_MAY_2013,GASTO,G_MTPTA) -> 0 | J36: =DSUM(G_JUN_2013,GASTO,G_MTPTA) -> 350 | K36: =DSUM(G_JUL_2013,GASTO,G_MTPTA) -> 6087.47 | L36: =DSUM(G_AGO_2013,GASTO,G_MTPTA) -> 1607.7155
A37: G_MTILM | B37: A luminarias | E37: =DSUM(G_ENE_2013,GASTO,G_MTILM) -> 1000 | F37: =DSUM(G_FEB_2013,GASTO,G_MTILM) -> 9500 | G37: =DSUM(G_MAR_2013,GASTO,G_MTILM) -> 1000 | H37: =DSUM(G_ABR_2013,GASTO,G_MTILM) -> 0 | I37: =DSUM(G_MAY_2013,GASTO,G_MTILM) -> 0 | J37: =DSUM(G_JUN_2013,GASTO,G_MTILM) -> 1200 | K37: =DSUM(G_JUL_2013,GASTO,G_MTILM) -> 200 | L37: =DSUM(G_AGO_2013,GASTO,G_MTILM) -> 0
A38: G_JDN | B38: Al jardín del fraccionamiento | E38: =DSUM(G_ENE_2013,GASTO,G_JDN) -> 5726 | F38: =DSUM(G_FEB_2013,GASTO,G_JDN) -> 490 | G38: =DSUM(G_MAR_2013,GASTO,G_JDN) -> 0 | H38: =DSUM(G_ABR_2013,GASTO,G_JDN) -> 0 | I38: =DSUM(G_MAY_2013,GASTO,G_JDN) -> 1170 | J38: =DSUM(G_JUN_2013,GASTO,G_JDN) -> 450 | K38: =DSUM(G_JUL_2013,GASTO,G_JDN) -> 675 | L38: =DSUM(G_AGO_2013,GASTO,G_JDN) -> 1375
B39: GASTOS ADMINISTRATIVOS | E39: =SUM(E40:E48) -> 11671.56 | F39: =SUM(F40:F48) -> 14137.71 | G39: =SUM(G40:G48) -> 9807 | H39: =SUM(H40:H48) -> 8808.77 | I39: =SUM(I40:I48) -> 13259.93 | J39: =SUM(J40:J48) -> 578.48 | K39: =SUM(K40:K48) -> 2279.84 | L39: =SUM(L40:L48) -> 341.76 | M39: =SUM(M40:M48) -> 0
A40: G_CBR | B40: Cobranza | E40: =DSUM(G_ENE_2013,GASTO,G_CBR) -> 1700 | F40: =DSUM(G_FEB_2013,GASTO,G_CBR) -> 1120 | G40: =DSUM(G_MAR_2013,GASTO,G_CBR) -> 1000 | H40: =DSUM(G_ABR_2013,GASTO,G_CBR) -> 520 | I40: =DSUM(G_MAY_2013,GASTO,G_CBR)+DSUM(BCO_MAY13,8,G_CBR) -> 0 | J40: =DSUM(G_JUN_2013,GASTO,G_CBR) -> 0 | K40: =DSUM(G_JUL_2013,GASTO,G_CBR) -> 0 | L40: =DSUM(G_AGO_2013,GASTO,G_CBR) -> 0
A41: G_ORG | B41: Gastos de organización | E41: =DSUM(G_ENE_2013,GASTO,G_ORG) -> 6481.39 | F41: =DSUM(G_FEB_2013,GASTO,G_ORG) -> 6605.32 | G41: =DSUM(G_MAR_2013,GASTO,G_ORG) -> 4579.51 | H41: =DSUM(G_ABR_2013,GASTO,G_ORG) -> 5100 | I41: =DSUM(G_MAY_2013,GASTO,G_ORG)+DSUM(BCO_MAY13,8,G_ORG) -> 3008.19 | J41: =DSUM(G_JUN_2013,GASTO,G_ORG) -> 53.92 | K41: =DSUM(G_JUL_2013,GASTO,G_ORG) -> 0 | L41: =DSUM(G_AGO_2013,GASTO,G_ORG) -> 0
A42: G_P_Fin | B42: Gastos y productos financieros | E42: =DSUM(BCO_ENE13,8,G_P_Fin)-DSUM(BCO_ENE13,7,G_P_Fin) -> 13.17 | F42: =DSUM(BCO_FEB13,8,G_P_Fin)-DSUM(BCO_FEB13,7,G_P_Fin) -> 26.89 | G42: =DSUM(BCO_MAR13,8,G_P_Fin)-DSUM(BCO_MAR13,7,G_P_Fin) -> 33.8 | H42: =DSUM(BCO_ABR13,8,G_P_Fin)-DSUM(BCO_ABR13,7,G_P_Fin) -> -0.54 | I42: =DSUM(BCO_MAY13,8,G_P_Fin)-DSUM(BCO_MAY13,7,G_P_Fin) -> 17.71 | J42: =DSUM(BCO_JUN13,8,G_P_Fin)-DSUM(BCO_JUN13,7,G_P_Fin) -> 8.53 | K42: =DSUM(BCO_JUL13,8,G_P_Fin)-DSUM(BCO_JUL13,7,G_P_Fin) -> -0.61 | L42: =DSUM(BCO_AGO13,8,G_P_Fin)-DSUM(BCO_AGO13,7,G_P_Fin) -> -0.75
A43: G_HCTB | B43: Honorarios contables | E43: =DSUM(G_ENE_2013,GASTO,G_HCTB) -> 1160 | F43: =DSUM(G_FEB_2013,GASTO,G_HCTB) -> 1160 | G43: =DSUM(G_MAR_2013,GASTO,G_HCTB) -> 2320 | H43: =DSUM(G_ABR_2013,GASTO,G_HCTB) -> 1160 | I43: =DSUM(G_MAY_2013,GASTO,G_HCTB)+DSUM(BCO_MAY13,8,G_HCTB) -> 0 | J43: =DSUM(G_JUN_2013,GASTO,G_HCTB) -> 0 | K43: =DSUM(G_JUL_2013,GASTO,G_HCTB) -> 0 | L43: =DSUM(G_AGO_2013,GASTO,G_HCTB) -> 0
A44: G_HJRD | B44: Honorarios jurídicos | E44: =DSUM(G_ENE_2013,GASTO,G_HJRD) -> 0 | F44: =DSUM(G_FEB_2013,GASTO,G_HJRD) -> 0 | G44: =DSUM(G_MAR_2013,GASTO,G_HJRD) -> 0 | H44: =DSUM(G_ABR_2013,GASTO,G_HJRD) -> 0 | I44: =DSUM(G_MAY_2013,GASTO,G_HJRD)+DSUM(BCO_MAY13,8,HJRD) -> 8052 | J44: =DSUM(G_JUN_2013,GASTO,G_HJRD) -> 0 | K44: =DSUM(G_JUL_2013,GASTO,G_HJRD) -> 0 | L44: =DSUM(G_AGO_2013,GASTO,G_HJRD) -> 0
A45: G_ASLE | B45: Asesoría Legal | E45: =DSUM(G_ENE_2013,GASTO,G_ASLE) -> 0 | F45: =DSUM(G_FEB_2013,GASTO,G_ASLE) -> 4000 | G45: =DSUM(G_MAR_2013,GASTO,G_ASLE) -> 0 | H45: =DSUM(G_ABR_2013,GASTO,G_ASLE) -> 0 | I45: =DSUM(G_MAY_2013,GASTO,G_ASLE) -> 0 | J45: =DSUM(G_JUN_2013,GASTO,G_ASLE) -> 0 | K45: =DSUM(G_JUL_2013,GASTO,G_ASLE) -> 0 | L45: =DSUM(G_AGO_2013,GASTO,G_ASLE) -> 0
A46: G_PAPE | B46: Papelería y fotocopiado | E46: =DSUM(G_ENE_2013,GASTO,G_PAPE) -> 1438 | F46: =DSUM(G_FEB_2013,GASTO,G_PAPE) -> 287.5 | G46: =DSUM(G_MAR_2013,GASTO,G_PAPE) -> 1002.69 | H46: =DSUM(G_ABR_2013,GASTO,G_PAPE) -> 1217.31 | I46: =DSUM(G_MAY_2013,GASTO,G_PAPE)+DSUM(BCO_MAY13,8,G_PAPE) -> 1497 | J46: =DSUM(G_JUN_2013,GASTO,G_PAPE) -> 124.03 | K46: =DSUM(G_JUL_2013,GASTO,G_PAPE) -> 686.36 | L46: =DSUM(G_AGO_2013,GASTO,G_PAPE) -> 342.51
A47: G_DIF | B47: Publicidad | E47: =DSUM(G_ENE_2013,GASTO,G_DIF) -> 0 | F47: =DSUM(G_FEB_2013,GASTO,G_DIF) -> 0 | G47: =DSUM(G_MAR_2013,GASTO,G_DIF) -> 0 | H47: =DSUM(G_ABR_2013,GASTO,G_DIF) -> 0 | I47: =DSUM(G_MAY_2013,GASTO,G_DIF) -> 0 | J47: =DSUM(G_JUN_2013,GASTO,G_DIF) -> 392 | K47: =DSUM(G_JUL_2013,GASTO,G_DIF) -> 0 | L47: =DSUM(G_AGO_2013,GASTO,G_DIF) -> 0
A48: G_TLF | B48: Teléfono e Internet | E48: =DSUM(G_ENE_2013,GASTO,G_TLF) -> 879 | F48: =DSUM(G_FEB_2013,GASTO,G_TLF) -> 938 | G48: =DSUM(G_MAR_2013,GASTO,G_TLF) -> 871 | H48: =DSUM(G_ABR_2013,GASTO,G_TLF) -> 812 | I48: =DSUM(G_MAY_2013,GASTO,G_TLF)+DSUM(BCO_MAY13,8,G_TLF) -> 685.03 | J48: =DSUM(G_JUN_2013,GASTO,G_TLF) -> 0 | K48: =DSUM(G_JUL_2013,GASTO,G_TLF) -> 1594.09 | L48: =DSUM(G_AGO_2013,GASTO,G_TLF) -> 0
B49: IMPUESTOS Y CONTRIBUCIONES | E49: =SUM(E50) -> 0 | F49: =SUM(F50) -> 0 | G49: =SUM(G50) -> 0 | H49: =SUM(H50) -> 37.33 | I49: =SUM(I50) -> 230.19 | J49: =SUM(J50) -> 107.24 | K49: =SUM(K50) -> 968.88207 | L49: =SUM(L50) -> 432.42448 | M49: =SUM(M50) -> 0
A50: G_TOTAL | B50: I.V.A. Pagado | E50: =DSUM(G_ENE_2013,IVA,G_TOTAL) -> 0 | F50: =DSUM(G_FEB_2013,IVA,G_TOTAL) -> 0 | G50: =DSUM(G_MAR_2013,IVA,G_TOTAL) -> 0 | H50: =DSUM(G_ABR_2013,IVA,G_TOTAL) -> 37.33 | I50: =DSUM(G_MAY_2013,IVA,G_TOTAL) -> 230.19 | J50: =DSUM(G_JUN_2013,IVA,G_TOTAL) -> 107.24 | K50: =DSUM(G_JUL_2013,IVA,G_TOTAL) -> 968.88207 | L50: =DSUM(G_AGO_2013,IVA,G_TOTAL) -> 432.42448
B52: SUMA EGRESOS | C52: =SUM(C38:C50) -> 0 | D52: =SUM(D38:D50) -> 0 | E52: =SUM(E19,E27,E32,E39,E49) -> 138004.21 | F52: =SUM(F19,F27,F32,F39,F49) -> 109576.12 | G52: =SUM(G19,G27,G32,G39,G49) -> 85195 | H52: =SUM(H19,H27,H32,H39,H49) -> 73705.1 | I52: =SUM(I19,I27,I32,I39,I49) -> 94791.04 | J52: =SUM(J19,J27,J32,J39,J49) -> 64923.56 | K52: =SUM(K19,K27,K32,K39,K49) -> 65841.28 | L52: =SUM(L19,L27,L32,L39,L49) -> 65557.83 | M52: =SUM(M19,M27,M32,M39,M49) -> 0
B54: DÉFICIT / SUPERAVIT DEL MES | E54: =E16-E52 -> 6040.79 | F54: =F16-F52 -> -6321.12 | G54: =G16-G52 -> 12860 | H54: =H16-H52 -> -10710.1 | I54: =I16-I52 -> -1206.04 | J54: =J16-J52 -> 20591.44 | K54: =K16-K52 -> 17193.72 | L54: =L16-L52 -> 9997.88 | M54: =M16-M52 -> 80895
B56: REMANENTE DEL PERÍODO ANTERIOR
B57: Caja | G57: 8240.42 | H57: =G60 -> 9934.22 | I57: =H60 -> 8023.12 | J57: =I60 -> 15934.79 | K57: =J60 -> 37934.76 | L57: =K60 -> 43027.87 | M57: =L60 -> 42425
B58: Banco | G58: 21140.39 | H58: =G61 -> 32306.59 | I58: =H61 -> 33507.59 | J58: =I61 -> 24389.88 | K58: =J61 -> 22981.35 | L58: =K61 -> 35081.96 | M58: =L61 -> 45682.71
B59: REMANENTE AL CIERRE DEL PERÍODO
B60: Caja | F60: 8240.42 | G60: =SUM(G57:G58,G54,-G61) -> 9934.22 | H60: =SUM(H57:H58,H54,-H61)+10000 -> 8023.12 | I60: =SUM(I57:I58,I54,-I61) -> 15934.79 | J60: =SUM(J57:J58,J54,-J61) -> 37934.76 | K60: =SUM(K57:K58,K54,-K61) -> 43027.87 | L60: =SUM(L57:L58,L54,-L61) -> 42425 | M60: =SUM(M57:M58,M54,-M61) -> 123320
B61: Banco | F61: 21140.39 | G61: 32306.59 | H61: 33507.59 | I61: 24389.88 | J61: 22981.35 | K61: 35081.96 | L61: 45682.71 | M61: 45682.71

Sheet estadística
C1: Asociación de Colonos HACIENDAS DE COYOACÁN
C2: Índices de cobranza. | K2: ENERO - SEPTIEMBRE 2013
C3: Actualización: | E3: =TODAY() -> 41985
F5: Fraccionamiento
F6: CASAS | G6: PAGAN | H6: CUOTAS | I6: COBRADO
F7: =SUM(C13,C18,C33,H13,H18,H23,C23,H28,C28,H33) -> 441 | G7: =SUM(D13,D18,D33,I13,I18,I23,D23,I28,D28,I33) -> 312 | H7: =SUM(E13,E18,J13,E33,J18,J23,E23,J28,E28,J33) -> 1194.075 | I7: =SUM(F13,F18,F33,K13,K18,K23,F23,K28,F28,K33) -> 763.495
F8: =F7/$F$7 -> 1 | G8: =G7/F7 -> 0.70748299 | I8: =I7/H7 -> 0.63940289
C11: Cuchilla | H11: Estanzuela
C12: CASAS | D12: PAGAN | E12: CUOTAS | F12: COBRADO | H12: CASAS | I12: PAGAN | J12: CUOTAS | K12: COBRADO
C13: =DCOUNTA(CALLES,1,CL_TODO) -> 111 | D13: =DCOUNTA(CALLES,1,CL_PAGA) -> 77 | E13: =(DSUM(BASE_A,9,CUCHILLA)/1000)*SEP -> 279.225 | F13: =DSUM(CALLES,6,CL)/1000 -> 173.495 | H13: =DCOUNTA(CALLES,1,EZ_TODO) -> 78 | I13: =DCOUNTA(CALLES,1,EZ_PAGA) -> 50 | J13: =(DSUM(BASE_A,9,ESTANZUELA)/1000)*SEP -> 178.2 | K13: =DSUM(CALLES,6,EZ)/1000 -> 106.95
C14: =C13/$F$7 -> 0.25170068 | D14: =D13/C13 -> 0.69369369 | F14: =F13/E13 -> 0.62134479 | H14: =H13/$F$7 -> 0.17687075 | I14: =I13/H13 -> 0.64102564 | K14: =K13/J13 -> 0.60016835
C16: Estopila | H16: Hueso
C17: CASAS | D17: PAGAN | E17: CUOTAS | F17: COBRADO | H17: CASAS | I17: PAGAN | J17: CUOTAS | K17: COBRADO
C18: =DCOUNTA(CALLES,1,EP_TODO) -> 5 | D18: =DCOUNTA(CALLES,1,EP_PAGA) -> 3 | E18: =(DSUM(BASE_A,9,ESTOPILA)/1000)*SEP -> 10.8 | F18: =DSUM(CALLES,6,EP)/1000 -> 4.05 | H18: =DCOUNTA(CALLES,1,HS_TODO) -> 5 | I18: =DCOUNTA(CALLES,1,HS_PAGA) -> 3 | J18: =(DSUM(BASE_A,9,HUESO)/1000)*SEP -> 19.8 | K18: =DSUM(CALLES,6,HS)/1000 -> 10.4
C19: =C18/$F$7 -> 0.011337868 | D19: =D18/C18 -> 0.6 | F19: =F18/E18 -> 0.375 | H19: =H18/$F$7 -> 0.011337868 | I19: =I18/H18 -> 0.6 | K19: =K18/J18 -> 0.52525253
C21: Romeral | H21: Landero
C22: CASAS | D22: PAGAN | E22: CUOTAS | F22: COBRADO | H22: CASAS | I22: PAGAN | J22: CUOTAS | K22: COBRADO
C23: =DCOUNTA(CALLES,1,RM_TODO) -> 10 | D23: =DCOUNTA(CALLES,1,RM_PAGA) -> 7 | E23: =(DSUM(BASE_A,9,ROMERAL)/1000)*SEP -> 22.95 | F23: =DSUM(CALLES,6,RM)/1000 -> 13.65 | H23: =DCOUNTA(CALLES,1,LD_TODO) -> 82 | I23: =DCOUNTA(CALLES,1,LD_PAGA) -> 61 | J23: =(DSUM(BASE_A,9,LANDERO)/1000)*SEP -> 205.65 | K23: =DSUM(CALLES,6,LD)/1000 -> 119.35
C24: =C23/$F$7 -> 0.022675737 | D24: =D23/C23 -> 0.7 | F24: =F23/E23 -> 0.59477124 | H24: =H23/$F$7 -> 0.18594104 | I24: =I23/H23 -> 0.74390244 | K24: =K23/J23 -> 0.58035497
C26: Upácuaro | H26: Recoveco
C27: CASAS | D27: PAGAN | E27: CUOTAS | F27: COBRADO | H27: CASAS | I27: PAGAN | J27: CUOTAS | K27: COBRADO
C28: =DCOUNTA(CALLES,1,UP_TODO) -> 101 | D28: =DCOUNTA(CALLES,1,UP_PAGA) -> 72 | E28: =(DSUM(BASE_A,9,UPACUARO)/1000)*SEP -> 261.9 | F28: =DSUM(CALLES,6,UP)/1000 -> 166.45 | H28: =DCOUNTA(CALLES,1,RV_TODO) -> 15 | I28: =DCOUNTA(CALLES,1,RV_PAGA) -> 13 | J28: =(DSUM(BASE_A,9,RECOVECO)/1000)*SEP -> 39.15 | K28: =DSUM(CALLES,6,RV)/1000 -> 32.1
C29: =C28/$F$7 -> 0.22902494 | D29: =D28/C28 -> 0.71287129 | F29: =F28/E28 -> 0.63554792 | H29: =H28/$F$7 -> 0.034013605 | I29: =I28/H28 -> 0.86666667 | K29: =K28/J28 -> 0.81992337
C31: Colegio Carmel | H31: Zinamba
C32: CASAS | D32: PAGAN | E32: CUOTAS | F32: COBRADO | H32: CASAS | I32: PAGAN | J32: CUOTAS | K32: COBRADO
C33: =DCOUNTA(CALLES,1,CM_TODO) -> 1 | D33: =DCOUNTA(CALLES,1,CM_PAGA) -> 1 | E33: =(DSUM(BASE_A,9,Carmel)/1000)*SEP -> 90 | F33: =DSUM(CALLES,6,CM)/1000 -> 80 | H33: =DCOUNTA(CALLES,1,ZB_TODO) -> 33 | I33: =DCOUNTA(CALLES,1,ZB_PAGA) -> 25 | J33: =(DSUM(BASE_A,9,ZINAMBA)/1000)*SEP -> 86.4 | K33: =DSUM(CALLES,6,ZB)/1000 -> 57.05
C34: =C33/$F$7 -> 0.0022675737 | D34: =D33/C33 -> 1 | F34: =F33/E33 -> 0.88888889 | H34: =H33/$F$7 -> 0.074829932 | I34: =I33/H33 -> 0.75757576 | K34: =K33/J33 -> 0.66030093
K36: CUOTAS Y COBRADO en miles de pesos.
D37: Cuota mensual asignada
D38: Cuchilla | E38: =DSUM(BASE_A,9,CUCHILLA) -> 31025 | F38: =E38/$E$48 -> 0.2338421
D39: Estanzuela | E39: =DSUM(BASE_A,9,ESTANZUELA) -> 19800 | F39: =E39/$E$48 -> 0.14923686
D40: Colegio Carmel | E40: =DSUM(BASE_A,9,Carmel) -> 10000 | F40: =E40/$E$48 -> 0.07537215
D41: Upácuaro | E41: =DSUM(BASE_A,9,UPACUARO) -> 29100 | F41: =E41/$E$48 -> 0.21933296
D42: Landero | E42: =DSUM(BASE_A,9,LANDERO) -> 22850 | F42: =E42/$E$48 -> 0.17222536
D43: Zinamba | E43: =DSUM(BASE_A,9,ZINAMBA) -> 9600 | F43: =E43/$E$48 -> 0.072357264
D44: Recoveco | E44: =DSUM(BASE_A,9,RECOVECO) -> 4350 | F44: =E44/$E$48 -> 0.032786885
D45: Romeral | E45: =DSUM(BASE_A,9,ROMERAL) -> 2550 | F45: =E45/$E$48 -> 0.019219898
D46: Hueso | E46: =DSUM(BASE_A,9,HUESO) -> 2200 | F46: =E46/$E$48 -> 0.016581873
D47: Estopila | E47: =DSUM(BASE_A,9,ESTOPILA) -> 1200 | F47: =E47/$E$48 -> 0.009044658
D48: Haciendas de Coyoacán | E48: =SUM(E38:E47) -> 132675 | F48: =E48/$E$48 -> 1

Sheet consulta
A1: CASA | B1: C_ING
A2: =VLOOKUP(A4,BASE_B,2,FALSE) -> CL_29_ | B2: 1
A4: 19
D5: Asociación de Colonos HACIENDAS DE COYOACÁN
D7: FAMILIA | G7: =VLOOKUP(A2,BASE_A,8,FALSE) -> Vega Sánchez C.
D8: DOMICILIO | G8: =VLOOKUP(A2,BASE_A,6,FALSE) -> Rancho La Cuchilla No. 29
D9: CUOTA MENSUAL | G9: =(VLOOKUP(A2,BASE_A,9,FALSE)) -> 300
F10: COBRO DEL AÑO
F11: IDEAL | G11: ALCANZADO
F12: =G9*COUNT(A19:A30) -> 2400 | G12: =SUM(I18:I30)-SUM(G18:G30) -> 0
D13: NÚMERO DE MESES COBRADOS | G13: =G12/G9 -> 0
D16: CUOTAS REGISTRADAS
D17: MES | E17: RECIBO N° | F17: FECHA | G17: DEL AÑO ANTERIOR | H17: DEL AÑO 2013 | I17: TOTAL
D18: DIC_2012 | E18: =IF(DSUM(DIC_2012,1,INDICE)=0,"",DSUM(DIC_2012,1,INDICE)) | F18: =IF(DSUM(DIC_2012,8,INDICE)=0,"",DSUM(DIC_2012,8,INDICE)) | G18: =IF(DSUM(DIC_2012,7,INDICE)=0,0,(DSUM(DIC_2012,AA,INDICE))*(VLOOKUP(A2,BASE_A,9,FALSE))) -> 0 | H18: =I18-G18 -> 0 | I18: =IF(DSUM(DIC_2012,7,INDICE)=0,0,DSUM(DIC_2012,7,INDICE)) -> 0 | J18: =IF(OR(E18="",AND(E18>=recibos!B5,E18<=recibos!B263)),"OK","NO") -> OK
A19: =IF(D19=0,"",1) -> 1 | D19: ENE_2013 | E19: =IF(DSUM(ENE_2013,1,INDICE)=0,"",DSUM(ENE_2013,1,INDICE)) | F19: =IF(DSUM(ENE_2013,8,INDICE)=0,"",DSUM(ENE_2013,8,INDICE)) | G19: =IF(DSUM(ENE_2013,7,INDICE)=0,0,(DSUM(ENE_2013,22,INDICE))*(VLOOKUP(A2,BASE_A,9,FALSE))) -> 0 | H19: =I19-G19 -> 0 | I19: =IF(DSUM(ENE_2013,7,INDICE)=0,0,DSUM(ENE_2013,7,INDICE)) -> 0 | J19: =IF(OR(E19="",AND(E19>=recibos!B265,E19<=recibos!B519)),"OK","NO") -> OK
A20: =IF(D20=0,"",1) -> 1 | D20: FEB_2013 | E20: =IF(DSUM(FEB_2013,1,INDICE)=0,"",DSUM(FEB_2013,1,INDICE)) | F20: =IF(DSUM(FEB_2013,8,INDICE)=0,"",DSUM(FEB_2013,8,INDICE)) | G20: =IF(DSUM(FEB_2013,7,INDICE)=0,0,(DSUM(FEB_2013,22,INDICE))*(VLOOKUP(A$2,BASE_A,9,FALSE))) -> 0 | H20: =I20-G20 -> 0 | I20: =IF(DSUM(FEB_2013,7,INDICE)=0,0,DSUM(FEB_2013,7,INDICE)) -> 0 | J20: =IF(OR(E20="",AND(E20>=recibos!B521,E20<=recibos!B740)),"OK","NO") -> OK
A21: =IF(D21=0,"",1) -> 1 | D21: MAR_2013 | E21: =IF(DSUM(MAR_2013,1,INDICE)=0,"",DSUM(MAR_2013,1,INDICE)) | F21: =IF(DSUM(MAR_2013,8,INDICE)=0,"",DSUM(MAR_2013,8,INDICE)) | G21: =IF(DSUM(MAR_2013,7,INDICE)=0,0,(DSUM(MAR_2013,22,INDICE))*(VLOOKUP(A$2,BASE_A,9,FALSE))) -> 0 | H21: =I21-G21 -> 0 | I21: =IF(DSUM(MAR_2013,7,INDICE)=0,0,DSUM(MAR_2013,7,INDICE)) -> 0 | J21: =IF(OR(E21="",AND(E21>=recibos!B742,E21<=recibos!B977)),"OK","NO") -> OK
A22: =IF(D22=0,"",1) -> 1 | D22: ABR_2013 | E22: =IF(DSUM(ABR_2013,1,INDICE)=0,"",DSUM(ABR_2013,1,INDICE)) | F22: =IF(DSUM(ABR_2013,8,INDICE)=0,"",DSUM(ABR_2013,8,INDICE)) | G22: =IF(DSUM(ABR_2013,7,INDICE)=0,0,(DSUM(ABR_2013,22,INDICE))*(VLOOKUP(A$2,BASE_A,9,FALSE))) -> 0 | H22: =I22-G22 -> 0 | I22: =IF(DSUM(ABR_2013,7,INDICE)=0,0,DSUM(ABR_2013,7,INDICE)) -> 0 | J22: =IF(OR(E22="",AND(E22>=recibos!B979,E22<=recibos!B1162)),"OK","NO") -> OK
A23: =IF(D23=0,"",1) -> 1 | D23: MAY_2013 | E23: =IF(DSUM(MAY_2013,1,INDICE)=0,"",DSUM(MAY_2013,1,INDICE)) | F23: =IF(DSUM(MAY_2013,8,INDICE)=0,"",DSUM(MAY_2013,8,INDICE)) | G23: =IF(DSUM(MAY_2013,7,INDICE)=0,0,(DSUM(MAY_2013,22,INDICE))*(VLOOKUP(A$2,BASE_A,9,FALSE))) -> 0 | H23: =I23-G23 -> 0 | I23: =IF(DSUM(MAY_2013,7,INDICE)=0,0,DSUM(MAY_2013,7,INDICE)) -> 0 | J23: =IF(OR(E23="",AND(E23>=recibos!B1164,E23<=recibos!B1356)),"OK","NO") -> OK
A24: =IF(D24=0,"",1) -> 1 | D24: JUN_2013 | E24: =IF(DSUM(JUN_2013,1,INDICE)=0,"",DSUM(JUN_2013,1,INDICE)) | F24: =IF(DSUM(JUN_2013,8,INDICE)=0,"",DSUM(JUN_2013,8,INDICE)) | G24: =IF(DSUM(JUN_2013,7,INDICE)=0,0,(DSUM(JUN_2013,22,INDICE))*(VLOOKUP(A$2,BASE_A,9,FALSE))) -> 0 | H24: =I24-G24 -> 0 | I24: =IF(DSUM(JUN_2013,7,INDICE)=0,0,DSUM(JUN_2013,7,INDICE)) -> 0 | J24: =IF(OR(E24="",AND(E24>=recibos!B1358,E24<=recibos!B1571)),"OK","NO") -> OK
A25: =IF(D25=0,"",1) -> 1 | D25: JUL_2013 | E25: =IF(DSUM(JUL_2013,1,INDICE)=0,"",DSUM(JUL_2013,1,INDICE)) | F25: =IF(DSUM(JUL_2013,8,INDICE)=0,"",DSUM(JUL_2013,8,INDICE)) | G25: =IF(DSUM(JUL_2013,7,INDICE)=0,0,(DSUM(JUL_2013,22,INDICE))*(VLOOKUP(A$2,BASE_A,9,FALSE))) -> 0 | H25: =I25-G25 -> 0 | I25: =IF(DSUM(JUL_2013,7,INDICE)=0,0,DSUM(JUL_2013,7,INDICE)) -> 0 | J25: =IF(OR(E25="",AND(E25>=recibos!B1573,E25<=recibos!B1762)),"OK","NO") -> OK
A26: =IF(D26=0,"",1) -> 1 | D26: AGO_2013 | E26: =IF(DSUM(AGO_2013,1,INDICE)=0,"",DSUM(AGO_2013,1,INDICE)) | F26: =IF(DSUM(AGO_2013,8,INDICE)=0,"",DSUM(AGO_2013,8,INDICE)) | G26: =IF(DSUM(AGO_2013,7,INDICE)=0,0,(DSUM(AGO_2013,22,INDICE))*(VLOOKUP(A$2,BASE_A,9,FALSE))) -> 0 | H26: =I26-G26 -> 0 | I26: =IF(DSUM(AGO_2013,7,INDICE)=0,0,DSUM(AGO_2013,7,INDICE)) -> 0 | J26: =IF(OR(E26="",AND(E26>=recibos!B1764,E26<=recibos!B1930)),"OK","NO") -> OK
A27: =IF(D27=0,"",1)
A28: =IF(D28=0,"",1)
A29: =IF(D29=0,"",1)
A30: =IF(D30=0,"",1)

Sheet chequera
H1: 813034795
H2: =SUBTOTAL(9,H6:H80) -> 115805.58
B3: FECHA EMISIÓN | C3: FECHA OPERACIÓN | D3: CHEQUE No. | F3: CONCEPTO | G3: CASA | H3: DEPÓSITO | I3: RETIRO | J3: SALDO
J4: 1280.17
C5: 41281 | F5: Depósito en efectivo | H5: 6000 | J5: =J4+H5-I5 -> 7280.17
C6: 41284 | G6: UP_46_ | H6: 300 | J6: =J5+H6-I6 -> 7580.17
G7: G_P_Fin | H7: 0.46 | J7: =J6+H7-I7 -> 7580.63
C8: 41284 | G8: CL_29_ | H8: 300 | J8: =J7+H8-I8 -> 7880.63
G9: G_P_Fin | H9: 0.29 | J9: =J8+H9-I9 -> 7880.92
C10: 41288 | H10: 13000 | J10: =J9+H10-I10 -> 20880.92
C11: 41288 | H11: 3600 | J11: =J10+H11-I11 -> 24480.92
C12: 41288 | H12: 2000 | J12: =J11+H12-I12 -> 26480.92
C13: 41288 | H13: 2000 | J13: =J12+H13-I13 -> 28480.92
C14: 41291 | D14: 40 | E14: Sistemas inteligentes en Seguridad | F14: Instalación de cámaras | I14: 20000 | J14: =J13+H14-I14 -> 8480.92
C15: 41291 | H15: 1500 | J15: =J14+H15-I15 -> 9980.92
C16: 41291 | H16: 3300 | J16: =J15+H16-I16 -> 13280.92
C17: 41291 | G17: CM_130_A | H17: 10000 | J17: =J16+H17-I17 -> 23280.92
C18: 41302 | H18: 15000 | J18: =J17+H18-I18 -> 38280.92
C19: 41302 | H19: 600 | J19: =J18+H19-I19 -> 38880.92
C20: 41303 | D20: 41 | E20: Sistemas inteligentes en Seguridad | F20: Instalación de cámaras | I20: 13000 | J20: =J19+H20-I20 -> 25880.92
C21: 41305 | F21: Comisión por cheques expedidos | G21: G_P_Fin | I21: 12 | J21: =J20+H21-I21 -> 25868.92
C22: 41305 | F22: I.V.A. sobre comisiones | G22: G_P_Fin | I22: 1.92 | J22: =J21+H22-I22 -> 25867
B23: FECHA EMISIÓN | C23: FECHA OPERACIÓN | D23: CHEQUE No. | F23: CONCEPTO | G23: CASA | H23: DEPÓSITO | I23: RETIRO | J23: SALDO
C24: 41310 | H24: 4000 | J24: =J22+H24-I24 -> 29867
C25: 41310 | H25: 1200 | J25: =J24+H25-I25 -> 31067
C26: 41310 | H26: 600 | J26: =J25+H26-I26 -> 31667
C27: 41313 | D27: 42 | E27: Sistemas inteligentes en Seguridad | F27: Instalación de cámaras | I27: 15000 | J27: =J26+H27-I27 -> 16667
C28: 41313 | G28: UP_86_ | H28: 600 | J28: =J27+H28-I28 -> 17267
C29: 41313 | G29: G_P_Fin | H29: 0.2 | J29: =J28+H29-I29 -> 17267.2
C30: 41313 | G30: CL_29_ | H30: 300 | J30: =J29+H30-I30 -> 17567.2
C31: 41313 | G31: G_P_Fin | H31: 0.29 | J31: =J30+H31-I31 -> 17567.49
C32: 41318 | G32: UP_46_ | H32: 300 | J32: =J31+H32-I32 -> 17867.49
C33: 41318 | G33: G_P_Fin | H33: 0.46 | J33: =J32+H33-I33 -> 17867.95
C34: 41319 | G34: CL_28_ | H34: 3300.28 | J34: =J33+H34-I34 -> 21168.23
C35: 41320 | G35: CM_130_A | H35: 10000 | J35: =J34+H35-I35 -> 31168.23
C36: 41331 | D36: 43 | E36: Sistemas inteligentes en Seguridad | F36: Instalación de cámaras | I36: 6000 | J36: =J35+H36-I36 -> 25168.23
C37: 41332 | D37: 44 | E37: Lic. Manuel García | F37: Notaría | I37: 4000 | J37: =J36+H37-I37 -> 21168.23
C38: 41333 | F38: Comisión por cheques expedidos | G38: G_P_Fin | I38: 24 | J38: =J37+H38-I38 -> 21144.23
C39: 41333 | F39: I.V.A. sobre comisiones | G39: G_P_Fin | I39: 3.84 | J39: =J38+H39-I39 -> 21140.39
B40: FECHA EMISIÓN | C40: FECHA OPERACIÓN | D40: CHEQUE No. | F40: CONCEPTO | G40: CASA | H40: DEPÓSITO | I40: RETIRO | J40: SALDO
C41: 41334 | G41: EZ_15_A | H41: 300 | J41: =J39+H41-I41 -> 21440.39
C42: 41334 | G42: G_P_Fin | H42: 0.15 | J42: =J41+H42-I42 -> 21440.54
C43: 41338 | G43: UP_86_ | H43: 300 | J43: =J42+H43-I43 -> 21740.54
C44: 41338 | G44: G_P_Fin | H44: 0.1 | J44: =J43+H44-I44 -> 21740.64
C45: 41340 | F45: Comisión por expedición de estado de cuenta | G45: G_P_Fin | I45: 30 | J45: =J44+H45-I45 -> 21710.64
C46: 41340 | F46: I.V.A. sobre comisiones | G46: G_P_Fin | I46: 4.8 | J46: =J45+H46-I46 -> 21705.84
C47: 41344 | G47: CL_29_ | H47: 300 | J47: =J46+H47-I47 -> 22005.84
C48: 41344 | G48: G_P_Fin | H48: 0.29 | J48: =J47+H48-I48 -> 22006.13
C49: 41349 | G49: UP_46_ | H49: 300 | J49: =J48+H49-I49 -> 22306.13
C50: 41349 | G50: G_P_Fin | H50: 0.46 | J50: =J49+H50-I50 -> 22306.59
C51: 41354 | G51: CM_130_A | H51: 10000 | J51: =J50+H51-I51 -> 32306.59
B52: FECHA EMISIÓN | C52: FECHA OPERACIÓN | D52: CHEQUE No. | F52: CONCEPTO | G52: CASA | H52: DEPÓSITO | I52: RETIRO | J52: SALDO
C53: 41372 | G53: UP_86_ | H53: 300 | J53: =J51+H53-I53 -> 32606.59
C54: 41372 | G54: G_P_Fin | H54: 0.1 | J54: =J53+H54-I54 -> 32606.69
C55: 41373 | G55: CL_29_ | H55: 300 | J55: =J54+H55-I55 -> 32906.69
C56: 41373 | G56: G_P_Fin | H56: 0.29 | J56: =J55+H56-I56 -> 32906.98
C57: 41390 | G57: EZ_15_A | H57: 300 | J57: =J56+H57-I57 -> 33206.98
C58: 41390 | G58: G_P_Fin | H58: 0.15 | J58: =J57+H58-I58 -> 33207.13
C59: 41390 | G59: UP_46_ | H59: 300 | J59: =J58+H59-I59 -> 33507.13
C60: 41390 | G60: G_P_Fin | H60: 0.46 | J60: =J59+H60-I60 -> 33507.59
B61: FECHA EMISIÓN | C61: FECHA OPERACIÓN | D61: CHEQUE No. | F61: CONCEPTO | G61: CASA | H61: DEPÓSITO | I61: RETIRO | J61: SALDO
C62: 41401 | G62: UP_46_ | H62: 300 | J62: =J60+H62-I62 -> 33807.59
C63: 41401 | G63: G_P_Fin | H63: 0.46 | J63: =J62+H63-I63 -> 33808.05
C64: 41403 | G64: CM_130_A | H64: 10000 | J64: =J63+H64-I64 -> 43808.05
C65: 41403 | G65: UP_86_ | H65: 300 | J65: =J64+H65-I65 -> 44108.05
C66: 41403 | G66: G_P_Fin | H66: 0.1 | J66: =J65+H66-I66 -> 44108.15
C67: 41409 | G67: CL_29_ | H67: 300 | J67: =J66+H67-I67 -> 44408.15
C68: 41409 | G68: G_P_Fin | H68: 0.29 | J68: =J67+H68-I68 -> 44408.44
C69: 41418 | D69: 46 | E69: Lic. Manuel Ruiz | F69: Gastos de notaría | I69: 10000 | J69: =J68+H69-I69 -> 34408.44
C70: 41422 | D70: 45 | E70: Sistemas inteligentes en Seguridad | F70: Instalación de cámaras | G70: INFRA | I70: 20000 | J70: =J69+H70-I70 -> 14408.44
C71: 41423 | G71: CM_130_A | H71: 10000 | J71: =J70+H71-I71 -> 24408.44
C72: 41425 | F72: Comisión por cheques expedidos | G72: G_P_Fin | I72: 16 | J72: =J71+H72-I72 -> 24392.44
C73: 41425 | F73: I.V.A. sobre comisiones | G73: G_P_Fin | I73: 2.56 | J73: =J72+H73-I73 -> 24389.88
B74: FECHA EMISIÓN | C74: FECHA OPERACIÓN | D74: CHEQUE No. | F74: CONCEPTO | G74: CASA | H74: DEPÓSITO | I74: RETIRO | J74: SALDO
C75: 41428 | D75: 47 | E75: Sistemas inteligentes en Seguridad | F75: Instalación de 16 cámaras (3era. etapa) | G75: INFRA | I75: 12000 | J75: =J73+H75-I75 -> 12389.88
C76: 41432 | G76: CL_29_ | H76: 300 | J76: =J75+H76-I76 -> 12689.88
C77: 41432 | G77: G_P_Fin | H77: 0.29 | J77: =J76+H77-I77 -> 12690.17
C78: 41439 | G78: UP_46_ | H78: 300 | J78: =J77+H78-I78 -> 12990.17
C79: 41439 | G79: G_P_Fin | H79: 0.46 | J79: =J78+H79-I79 -> 12990.63
