Workbook
Name ABR_2016: Recibos!$B$590:$H$785
Name ABR_2017: Recibos!$B$3786:$AX$4044
Name ABR_2018: Recibos!$B$6111:$AW$6361
Name AGO_2016: Recibos!$B$1806:$H$2081
Name AGO_2017: Recibos!$B$4571:$AX$4736
Name AGO_2018: Recibos!$B$6906:$AW$7093
Name BASE: base!$B$5:$D$469
Name DIC_2016: Recibos!$B$2779:$AJ$2975
Name DIC_2017: Recibos!$B$5278:$AW$5478
Name ENE_2016: Recibos!$B$24:$H$274
Name ENE_2017: Recibos!$B$2976:$AJ$3245
Name ENE_2018: Recibos!$B$5479:$AW$5691
Name FEB_2016: Recibos!$B$275:$H$432
Name FEB_2017: Recibos!$B$3246:$AJ$3491
Name FEB_2018: Recibos!$B$5692:$AW$5901
Name G_ABR_2016: Gasto!$B$321:$H$414
Name G_ABR_2017: Gasto!$B$1861:$H$2020
Name G_ABR_2018: Gasto!$B$3256:$H$3352
Name G_ADQ: criterios!$P$3:$P$4
Name G_AGO_2016: Gasto!$B$748:$H$875
Name G_AGO_2017: Gasto!$B$2361:$H$2497
Name G_AGO_2018: Gasto!$B$3681:$H$3780
Name G_AGUA: criterios!$Q$3:$Q$4
Name G_ALMVG: criterios!$R$3:$R$4
Name G_ASLE: criterios!$S$3:$S$4
Name G_CBR: criterios!$T$3:$T$4
Name G_DIC_2016: Gasto!$B$1277:$H$1434
Name G_DIC_2017: Gasto!$B$2802:$H$2932
Name G_DIF: criterios!$U$3:$U$4
Name G_ENE_2016: Gasto!$B$3:$H$96
Name G_ENE_2017: Gasto!$B$1435:$H$1569
Name G_ENE_2018: Gasto!$B$2933:$H$3058
Name G_FEB_2016: Gasto!$B$97:$H$204
Name G_FEB_2017: Gasto!$B$1570:$H$1710
Name G_FEB_2018: Gasto!$B$3059:$H$3156
Name G_HCTB: criterios!$V$3:$V$4
Name G_HJRD: criterios!$W$3:$W$4
Name G_INFRA: criterios!$X$3:$X$4
Name G_IVA: criterios!$Y$3:$Y$4
Name G_JDN: criterios!$Z$3:$Z$4
Name G_JUL_2016: Gasto!$B$629:$H$747
Name G_JUL_2017: Gasto!$B$2257:$H$2360
Name G_JUL_2018: Gasto!$B$3567:$H$3680
Name G_JUN_2016: Gasto!$B$514:$H$628
Name G_JUN_2017: Gasto!$B$2159:$H$2256
Name G_JUN_2018: Gasto!$B$3449:$H$3566
Name G_MAR_2016: Gasto!$B$205:$H$320
Name G_MAR_2017: Gasto!$B$1711:$H$1860
Name G_MAR_2018: Gasto!$B$3157:$H$3255
Name G_MAY_2016: Gasto!$B$415:$H$513
Name G_MAY_2017: Gasto!$B$2021:$H$2158
Name G_MAY_2018: Gasto!$B$3353:$H$3448
Name G_MDC: criterios!$AA$3:$AA$4
Name G_MTCBQ: criterios!$AB$3:$AB$4
Name G_MTCP: criterios!$AC$3:$AC$4
Name G_MTCST: criterios!$AD$3:$AD$4
Name G_MTCYP: criterios!$AE$3:$AE$4
Name G_MTILM: criterios!$AF$3:$AF$4
Name G_MTLPZ: criterios!$AG$3:$AG$4
Name G_MTPTA: criterios!$AH$3:$AH$4

Sheet base
B4: 1 | C4: 2 | D4: 3 | E4: 4 | F4: 5
A5: N° | B5: CASA | C5: DOMICILIO | D5: FAMILIA
A6: 1 | B6: CL_7_101 | C6: Rancho La Cuchilla No. 7, 101 | D6: Olivares
A7: 2 | B7: CL_7_102 | C7: Rancho La Cuchilla No. 7, 102 | D7: García Moreno
A8: 3 | B8: CL_7_201 | C8: Rancho La Cuchilla No. 7, 201 | D8: Solís Susana
A9: 4 | B9: CL_7_202 | C9: Rancho La Cuchilla No. 7, 202 | D9: Carbajal Zayas
A10: 5 | B10: CL_9_ | C10: Rancho La Cuchilla No. 9 | D10: Martín del Campo
A11: 6 | B11: CL_11_ | C11: Rancho La Cuchilla No. 11 | D11: Santiago
A12: 7 | B12: CL_12_ | C12: Rancho La Cuchilla No. 12 | D12: Rivera Flores
A13: 8 | B13: CL_13_ | C13: Rancho La Cuchilla No. 13 | D13: Torres
A14: 9 | B14: CL_14_ | C14: Rancho La Cuchilla No. 14 | D14: Chávez Lara
A15: 10 | B15: CL_15_ | C15: Rancho La Cuchilla No. 15 | D15: Guerrero Ponce
A16: 11 | B16: CL_17_A | C16: Rancho La Cuchilla No. 17, A
A17: 12 | B17: CL_18_ | C17: Rancho La Cuchilla No. 18 | D17: Aldana Sánchez
A18: 13 | B18: CL_19_ | C18: Rancho La Cuchilla No. 19 | D18: Tapia Vázquez
A19: 14 | B19: CL_20_ | C19: Rancho La Cuchilla No. 20 | D19: Sánchez López
A20: 15 | B20: CL_21_ | C20: Rancho La Cuchilla No. 21 | D20: Solórzano Calderón
A21: 16 | B21: CL_23_ | C21: Rancho La Cuchilla No. 23 | D21: Ocampo
A22: 17 | B22: CL_25_ | C22: Rancho La Cuchilla No. 25 | D22: García de León
A23: 18 | B23: CL_27_ | C23: Rancho La Cuchilla No. 27 | D23: Montoya
A24: 19 | B24: CL_28_ | C24: Rancho La Cuchilla No. 28 | D24: Prado de los S. | E24: Cambio de número de vivienda de 2 a 28. BS 14JUN13
A25: 20 | B25: CL_29_ | C25: Rancho La Cuchilla No. 29 | D25: Vega Sánchez C.
A26: 21 | B26: CL_30_ | C26: Rancho La Cuchilla No. 30 | D26: Ruiz Navarrete
A27: 22 | B27: CL_31_ | C27: Rancho La Cuchilla No. 31 | D27: Lince
A28: 23 | B28: CL_32_ | C28: Rancho La Cuchilla No. 32 | D28: Hernández
A29: 24 | B29: CL_33_ | C29: Rancho La Cuchilla No. 33 | D29: Tanús
A30: 25 | B30: CL_35_ | C30: Rancho La Cuchilla No. 35 | D30: Mendoza
A31: 26 | B31: CL_36_ | C31: Rancho La Cuchilla No. 36 | D31: Castillo
A32: 27 | B32: CL_38_ | C32: Rancho La Cuchilla No. 38 | D32: Cerecedo
A33: 28 | B33: CL_39_ | C33: Rancho La Cuchilla No. 39 | D33: Arenas
A34: 29 | B34: CL_40_ | C34: Rancho La Cuchilla No. 40 | D34: López Pico
A35: 30 | B35: CL_41_ | C35: Rancho La Cuchilla No. 41 | D35: Arriaga Lemus
A36: 31 | B36: CL_42_ | C36: Rancho La Cuchilla No. 42 | D36: Mac Kinney
... A38: 33 | B38: CL_43_B | C38: Rancho La Cuchilla No. 43, B | D38: Luna Albertano
A39: 34 | B39: CL_44_ | C39: Rancho La Cuchilla No. 44 | D39: García Osorio | E39: Agregado el 16/abr/18 GMS antes Garduño
A40: 35 | B40: CL_45_ | C40: Rancho La Cuchilla No. 45 | D40: Estévez Hernández
A41: 36 | B41: CL_46_ | C41: Rancho La Cuchilla No. 46 | D41: Cruz López
A42: 37 | B42: CL_47_ | C42: Rancho La Cuchilla No. 47 | D42: López
A43: 38 | B43: CL_49_ | C43: Rancho La Cuchilla No. 49 | D43: Orozco Castelazo
A44: 39 | B44: CL_52_ | C44: Rancho La Cuchilla No. 52 | D44: Velázquez
A45: 40 | B45: CL_53_ | C45: Rancho La Cuchilla No. 53 | D45: Rivera Hernández
A46: 41 | B46: CL_54_ | C46: Rancho La Cuchilla No. 54 | D46: Mendoza León
A47: 42 | B47: CL_55_ | C47: Rancho La Cuchilla No. 55 | D47: López Velázquez
A48: 43 | B48: CL_57_ | C48: Rancho La Cuchilla No. 57 | E48: Agregado el 14JUN13. BS
A49: 44 | B49: CL_58_ | C49: Rancho La Cuchilla No. 58 | D49: Serdán
A50: 45 | B50: CL_59_ | C50: Rancho La Cuchilla No. 59 | D50: Ortega Vega
A51: 46 | B51: CL_60_ | C51: Rancho La Cuchilla No. 60 | D51: Moisen | E51: Agregado el 14JUN13. BS/ Se cambio fam antes Cedillo 11/3/18 | F51: GMS
A52: 47 | B52: CL_61_ | C52: Rancho La Cuchilla No. 61 | D52: Rivera
A53: 48 | B53: CL_62_ | C53: Rancho La Cuchilla No. 62 | D53: Frías
A54: 49 | B54: CL_63_ | C54: Rancho La Cuchilla No. 63 | D54: Díaz de la Rosa
A55: 50 | B55: CL_65_ | C55: Rancho La Cuchilla No. 65 | D55: Garduño | E55: Agregado el 14JUN13. BS
A56: 51 | B56: CL_66_ | C56: Rancho La Cuchilla No. 66 | D56: Prieto
A57: 52 | B57: CL_67_ | C57: Rancho La Cuchilla No. 67 | D57: Quezada Viruega
A58: 53 | B58: CL_68_ | C58: Rancho La Cuchilla No. 68 | D58: Montesinos
A59: 54 | B59: CL_69_ | C59: Rancho La Cuchilla No. 69 | D59: Romero
A60: 55 | B60: CL_70_ | C60: Rancho La Cuchilla No. 70 | E60: Agregado el 14JUN13. BS
A61: 56 | B61: CL_71_ | C61: Rancho La Cuchilla No. 71 | D61: Flores | E61: Se cambio nombre el dìa 24/jul/16 GM
A62: 57 | B62: CL_72_ | C62: Rancho La Cuchilla No. 72 | D62: Ortiz González
A63: 58 | B63: CL_73_ | C63: Rancho La Cuchilla No. 73 | D63: Cooper
A64: 59 | B64: CL_74_ | C64: Rancho La Cuchilla No. 74 | D64: Gil
A65: 60 | B65: CL_75_ | C65: Rancho La Cuchilla No. 75 | D65: Sosa Lucio
A66: 61 | B66: CL_76_ | C66: Rancho La Cuchilla No. 76 | E66: Agregado el 14JUN13. BS
A67: 62 | B67: CL_77_ | C67: Rancho La Cuchilla No. 77 | D67: Loperena
A68: 63 | B68: CL_78_ | C68: Rancho La Cuchilla No. 78 | D68: García | E68: Agregado el 16ENE15. GM
A69: 64 | B69: CL_79_ | C69: Rancho La Cuchilla No. 79 | D69: De la Rosa | E69: Se cambiaron familia nueva 02/08/15
A70: 65 | B70: CL_80_ | C70: Rancho La Cuchilla No. 80 | D70: Aparicio
A71: 66 | B71: CL_81_A | C71: Rancho La Cuchilla No. 81, A | D71: Barrientos López
A72: 67 | B72: CL_81_ | C72: Rancho La Cuchilla No. 81 | D72: Suárez
A73: 68 | B73: CL_82_ | C73: Rancho La Cuchilla No. 82 | D73: Cruz
A74: 69 | B74: CL_83_ | C74: Rancho La Cuchilla No. 83 | D74: Barradas
A75: 70 | B75: CL_86_ | C75: Rancho La Cuchilla No. 86 | D75: Del Villar
A76: 71 | B76: CL_87_ | C76: Rancho La Cuchilla No. 87 | D76: Villanueva S.
A77: 72 | B77: CL_88_ | C77: Rancho La Cuchilla No. 88 | E77: Agregado el 14JUN13. BS
A78: 73 | B78: CL_89_ | C78: Rancho La Cuchilla No. 89 | D78: Gálvez
A79: 74 | B79: CL_90_ | C79: Rancho La Cuchilla No. 90 | D79: Porras Fuentes
A80: 75 | B80: CL_91_ | C80: Rancho La Cuchilla No. 91 | D80: Roldán Flores
A81: 76 | B81: CL_92_ | C81: Rancho La Cuchilla No. 92 | D81: Cabrera
A82: 77 | B82: CL_93_ | C82: Rancho La Cuchilla No. 93 | D82: Alcántara Silva
A83: 78 | B83: CL_94_ | C83: Rancho La Cuchilla No. 94 | D83: Sánchez Márquez
A84: 79 | B84: CL_95_ | C84: Rancho La Cuchilla No. 95 | D84: Cruz Linares | E84: Cambio familia 01/01/17 GMS
A85: 80 | B85: CL_96_ | C85: Rancho La Cuchilla No. 96 | D85: Valdez Álvarez
A86: 81 | B86: CL_97_ | C86: Rancho La Cuchilla No. 97 | D86: López Ruiz
A87: 82 | B87: CL_101_ | C87: Rancho La Cuchilla No. 101 | D87: Rodríguez Ramírez
A88: 83 | B88: CL_103_ | C88: Rancho La Cuchilla No. 103 | D88: Bernal
A89: 84 | B89: CL_107_ | C89: Rancho La Cuchilla No. 107 | D89: Quiñones, Eduardo
A90: 85 | B90: CL_110_ | C90: Rancho La Cuchilla No. 110 | D90: Domínguez Canudas
A91: 86 | B91: CL_111_ | C91: Rancho La Cuchilla No. 111 | D91: García Santos Ofelia
A92: 87 | B92: CL_112_PA | C92: Rancho La Cuchilla No. 112, PA | D92: Villalpando Pineda
A93: 88 | B93: CL_112_PB | C93: Rancho La Cuchilla No. 112, PB | D93: Soreque
A94: 89 | B94: CL_115_ | C94: Rancho La Cuchilla No. 115 | D94: Alfaro
A95: 90 | B95: CL_116_ | C95: Rancho La Cuchilla No. 116 | D95: Miranda
A96: 91 | B96: CL_117_ | C96: Rancho La Cuchilla No. 117 | D96: Gómez
... A101: 96 | B101: CL_122_ | C101: Rancho La Cuchilla No. 122 | D101: Mendoza
A102: 97 | B102: CL_125_ | C102: Rancho La Cuchilla No. 125 | D102: Nisse | E102: Antes fam Ordoñez Vilalpando cambio 11/03/18 GMS
A103: 98 | B103: CL_127_ | C103: Rancho La Cuchilla No. 127 | D103: Quiñones
A104: 99 | B104: CL_129_ | C104: Rancho La Cuchilla No. 129 | D104: Gamboa Rueda
A105: 100 | B105: CL_130_ | C105: Rancho La Cuchilla No. 130 | D105: Gonzalez
A106: 101 | B106: CL_131_ | C106: Rancho La Cuchilla No. 131 | D106: Cabrera Marquez
A107: 102 | B107: CL_132_ | C107: Rancho La Cuchilla No. 132 | D107: Téllez Girón
A108: 103 | B108: CL_133_ | C108: Rancho La Cuchilla No. 133 | D108: Rivas
...

Sheet criterios
G2: INGRESOS | P2: EGRESOS
G3: C_ING | H3: C_ING | I3: C_ING | J3: C_ING | K3: C_ING | L3: C_ING | M3: C_ING | N3: C_ING | P3: clave | Q3: clave | R3: clave | S3: clave | T3: clave | U3: clave | V3: clave | W3: clave | X3: clave | Y3: clave | Z3: clave | AA3: clave | AB3: clave | AC3: clave | AD3: clave | AE3: clave | AF3: clave | AG3: clave | AH3: clave | AI3: clave | AJ3: clave | AK3: clave | AL3: clave | AM3: clave | AN3: clave | AO3: clave | AP3: clave | AQ3: clave | AR3: clave | AS3: clave | AT3: clave
G4: 1 | H4: 2 | I4: 3 | J4: 4 | K4: 5 | L4: 6 | M4: 7 | P4: G_ADQ | Q4: G_AGUA | R4: G_ALMVG | S4: G_ASLE | T4: G_CBR | U4: G_DIF | V4: G_HCTB | W4: G_HJRD | X4: G_INFRA | Y4: G_IVA | Z4: G_JDN | AA4: G_MDC | AB4: G_MTCBQ | AC4: G_MTCP | AD4: G_MTCST | AE4: G_MTCYP | AF4: G_MTILM | AG4: G_MTLPZ | AH4: G_MTPTA | AI4: G_NMNVG | AJ4: G_ORG | AK4: G_P_FIN | AL4: G_P_IVA | AM4: G_PAPE | AN4: G_SÑ | AO4: G_TLF | AP4: G_TRSP | AQ4: G_UNF | AR4: G_USB | AS4: G_VRS
B5: INGRESOS
B6: 1 | D6: ING_CUOTAS | E6: Cuotas de vigilancia
B7: 2 | D7: ING_EXTRA | E7: Cuotas extraordinarias
B8: 3 | D8: ING_LLAVES | E8: Venta de llaves
B9: 4 | D9: ING_TELE | E9: Venta de tarjetas electrónicas
B10: 5 | D10: ING_TAR | E10: Venta de tarjetones
B11: 6 | E11: Aportación Colegio Carmel
B12: 7 | D12: ING_OTROS | E12: Otros ingresos
B14: EGRESOS
C15: COSTO DE VIGILANCIA
D16: G_NMNVG | E16: Sueldos y bono de puntualidad
D17: G_AGUA | E17: Agua
D18: G_ALMVG | E18: Alimentos
D19: G_MTLPZ | E19: Artículos de limpieza
D20: G_MDC | E20: Atención médica
D21: G_TRSP | E21: Mantenimiento de bicicletas
D22: G_UNF | E22: Uniformes
C23: INFRAESTRUCTURA Y SUMINISTROS
D24: G_INFRA | E24: Cámaras de vigilancia
D25: G_USB | E25: Dispositivos, discos y USB
D26: G_ADQ | E26: Llaves electrónicas y de acceso peatonal
D27: G_SÑ | E27: Señalización en calles
C28: MANTENIMIENTO
D29: G_MTCBQ | E29: A calles y banquetas
D30: G_MTCYP | E30: A cámaras de vigilancia y plumas de acceso
D31: G_MTCST | E31: A casetas
D32: G_MTPTA | E32: A las puertas de acceso peatonal
D33: G_MTILM | E33: A luminarias
D34: G_JDN | E34: Al jardín, Kiosco, juegos y explanada
D35: G_VRS | E35: Varios
C36: GASTOS ADMINISTRATIVOS
D37: G_CBR | E37: Cobranza
D38: G_ORG | E38: Gastos de organización
D39: G_P_FIN | E39: Gastos y productos financieros
D40: G_HCTB | E40: Honorarios contables y captura
D41: G_HJRD | E41: Honorarios jurídicos
D42: G_ASLE | E42: Asesoría Legal
D43: G_PAPE | E43: Papelería y fotocopiado
D44: G_DIF | E44: Publicidad
D45: G_TLF | E45: Teléfono e Internet
C46: IMPUESTOS Y CONTRIBUCIONES
D47: G_TOTAL | E47: I.V.A. Pagado

Sheet Comprobación
C2: 2016
B3: mes | C3: financiero | D3: distribución
D4: 2015 | E4: 2016 | F4: 2017
B5: enero | C5: =SUMIF(Recibos!G25:G274,1,Recibos!H25:H274) -> 213050 | E5: =-Recibos!H274 -> -38000
B6: febrero | C6: =SUMIF(Recibos!G276:G432,1,Recibos!H276:H432) -> 94750 | E6: =-Recibos!H432 -> -5600
B7: marzo | C7: =SUMIF(Recibos!G434:G589,1,Recibos!H434:H589) -> 82625 | E7: =-Recibos!H589 -> -1000
B8: abril | C8: =SUMIF(Recibos!G591:G785,1,Recibos!H591:H785) -> 102075 | E8: =-Recibos!H785 -> -1200
B9: mayo | C9: =SUMIF(Recibos!G787:G1018,1,Recibos!H787:H1018) -> 108875 | E9: =-Recibos!H1018 -> 0
B10: junio | C10: =SUMIF(Recibos!G1019:G1423,1,Recibos!H1019:H1423) -> 117275 | E10: =-Recibos!H1423 -> -2550
B11: julio | C11: =SUMIF(Recibos!G1425:G1805,1,Recibos!H1425:H1805) -> 104575 | D11: =Recibos!H5 -> 900
B12: agosto | C12: =SUMIF(Recibos!G1807:G2081,1,Recibos!H1807:H2081) -> 106275 | D12: =Recibos!H7 -> 150
B13: septiembre | C13: =SUMIF(Recibos!G2083:G2341,1,Recibos!H2083:H2341) -> 95625
B14: octubre | C14: =SUMIF(Recibos!G2342:G2560,1,Recibos!H2342:H2560) -> 88925
B15: noviembre | D15: =Recibos!H10 -> 800
B16: diciembre | D16: =Recibos!H23 -> 23950
B17: suma | C17: =SUM(C5:C16) -> 1114050 | E17: =Recibos!W2 -> 1087600 | F17: =SUM(C5:F16) -> 1091500
F18: =IF(E17=F17,"ok",E17-F17) -> -3900

Sheet Cobranza
B1: Haciendas de Coyoacán
B2: Cuotas de vigilancia y mantenimiento
B3: Período: julio de 2012 - junio de 2017
K4: =SUM(K6:K469) -> 102125 | X4: =SUM(X6:X469) -> 1071865 | AK4: =SUM(AK6:AK469) -> 1244640 | AX4: =SUM(AX6:AX469) -> 1281550 | BK4: =SUM(BK6:BK469) -> 1349200 | BX4: =SUM(BX6:BX469) -> 1337550
B5: CASA | C5: Domicilio | D5: Familia | E5: JUL 2012 | F5: AGO 2012 | G5: SEP 2012 | H5: OCT 2012 | I5: NOV 2012 | J5: DIC 2012 | K5: SUMA 2012 | L5: ENE 2013 | M5: FEB 2013 | N5: MAR 2013 | O5: ABR 2013 | P5: MAY 2013 | Q5: JUN 2013 | R5: JUL 2013 | S5: AGO 2013 | T5: SEP 2013 | U5: OCT 2013 | V5: NOV 2013 | W5: DIC 2013 | X5: SUMA 2013 | Y5: ENE 2014 | Z5: FEB 2014 | AA5: MAR 2014 | AB5: ABR 2014 | AC5: MAY 2014 | AD5: JUN 2014 | AE5: JUL 2014 | AF5: AGO 2014 | AG5: SEP 2014 | AH5: OCT 2014 | AI5: NOV 2014 | AJ5: DIC 2014 | AK5: SUMA 2014 | AL5: ENE 2015 | AM5: FEB 2015 | AN5: MAR 2015 | AO5: ABR 2015 | AP5: MAY 2015 | AQ5: JUN 2015 | AR5: JUL 2015 | AS5: AGO 2015 | AT5: SEP 2015 | AU5: OCT 2015 | AV5: NOV 2015 | AW5: DIC 2015 | AX5: SUMA 2015 | AY5: ENE 2016 | AZ5: FEB 2016 | BA5: MAR 2016 | BB5: ABR 2016 | BC5: MAY 2016 | BD5: JUN 2016 | BE5: JUL 2016 | BF5: AGO 2016 | BG5: SEP 2016 | BH5: OCT 2016 | BI5: NOV 2016 | BJ5: DIC 2016 | BK5: SUMA 2016 | BL5: ENE 2017 | BM5: FEB 2017 | BN5: MAR 2017 | BO5: ABR 2017 | BP5: MAY 2017 | BQ5: JUN 2017 | BR5: JUL 2017 | BS5: AGO 2017 | BT5: SEP 2017 | BU5: OCT 2017 | BV5: NOV 2017 | BW5: DIC 2017 | BX5: SUMA 2017 | BY5: ENE 2018 | BZ5: FEB 2018 | CA5: MAR 2018 | CB5: ABR 2018 | CC5: MAY 2018 | CD5: JUN 2018 | CE5: JUL 2018 | CF5: AGO 2018 | CG5: SEP 2018 | CH5: OCT 2018 | CI5: NOV 2018 | CJ5: DIC 2018 | CK5: SUMA 2018
B6: CL_7_101 | C6: Rancho La Cuchilla No. 7, 101 | D6: Olivares | E6: 0 | F6: 0 | G6: 0 | H6: 0 | I6: 0 | J6: 100 | K6: =SUM(E6:J6) -> 100 | L6: 100 | M6: 100 | N6: 100 | O6: 100 | P6: 100 | Q6: 100 | R6: 100 | S6: 100 | T6: 100 | U6: 0 | V6: 0 | W6: 0 | X6: =SUM(L6:W6) -> 900 | Y6: 100 | Z6: 100 | AA6: 100 | AB6: 100 | AC6: 100 | AD6: 100 | AE6: 100 | AF6: 100 | AG6: 100 | AH6: 100 | AI6: 100 | AJ6: 100 | AK6: =SUM(Y6:AJ6) -> 1200 | AL6: 100 | AM6: 100 | AN6: 0 | AO6: 0 | AP6: 0 | AQ6: 0 | AR6: 0 | AS6: 0 | AT6: 0 | AU6: 0 | AV6: 0 | AW6: 0 | AX6: =SUM(AL6:AW6) -> 200 | AY6: =SUMIF(Recibos!$D$4:$D$7493,Cobranza!$B6,Recibos!K$4:K$7493) -> 0 | AZ6: =SUMIF(Recibos!$D$4:$D$7493,Cobranza!$B6,Recibos!L$4:L$7493) -> 0 | BA6: =SUMIF(Recibos!$D$4:$D$7493,Cobranza!$B6,Recibos!M$4:M$7493) -> 0 | BB6: =SUMIF(Recibos!$D$4:$D$7493,Cobranza!$B6,Recibos!N$4:N$7493) -> 0 | BC6: =SUMIF(Recibos!$D$4:$D$7493,Cobranza!$B6,Recibos!O$4:O$7493) -> 0 | BD6: =SUMIF(Recibos!$D$4:$D$7493,Cobranza!$B6,Recibos!P$4:P$7493) -> 0 | BE6: =SUMIF(Recibos!$D$4:$D$7493,Cobranza!$B6,Recibos!Q$4:Q$7493) -> 0 | BF6: =SUMIF(Recibos!$D$4:$D$7493,Cobranza!$B6,Recibos!R$4:R$7493) -> 100 | ... BJ6: =SUMIF(Recibos!$D$4:$D$7493,Cobranza!$B6,Recibos!V$4:V$7493) -> 100 | BK6: =SUM(AY6:BJ6) -> 500 | BL6: =SUMIF(Recibos!$D$4:$D$7493,Cobranza!$B6,Recibos!X$4:X$7493) -> 100 | BM6: =SUMIF(Recibos!$D$4:$D$7493,Cobranza!$B6,Recibos!Y$4:Y$7493) -> 100 | BN6: =SUMIF(Recibos!$D$4:$D$7493,Cobranza!$B6,Recibos!Z$4:Z$7493) -> 0 | BO6: =SUMIF(Recibos!$D$4:$D$7493,Cobranza!$B6,Recibos!AA$4:AA$7493) -> 0 | BP6: =SUMIF(Recibos!$D$4:$D$7493,Cobranza!$B6,Recibos!AB$4:AB$7493) -> 0 | BQ6: =SUMIF(Recibos!$D$4:$D$7493,Cobranza!$B6,Recibos!AC$4:AC$7493) -> 0 | BR6: =SUMIF(Recibos!$D$4:$D$7493,Cobranza!$B6,Recibos!AD$4:AD$7493) -> 0 | BS6: =SUMIF(Recibos!$D$4:$D$7493,Cobranza!$B6,Recibos!AE$4:AE$7493) -> 0 | ... BW6: =SUMIF(Recibos!$D$4:$D$7493,Cobranza!$B6,Recibos!AI$4:AI$7493) -> 0 | BX6: =SUM(BL6:BW6) -> 200 | BY6: =SUMIF(Recibos!$D$4:$D$7493,Cobranza!$B6,Recibos!AK$4:AK$7493) -> 0 | BZ6: =SUMIF(Recibos!$D$4:$D$7493,Cobranza!$B6,Recibos!AL$4:AL$7493) -> 0 | CA6: =SUMIF(Recibos!$D$4:$D$7493,Cobranza!$B6,Recibos!AM$4:AM$7493) -> 0 | CB6: =SUMIF(Recibos!$D$4:$D$7493,Cobranza!$B6,Recibos!AN$4:AN$7493) -> 0 | CC6: =SUMIF(Recibos!$D$4:$D$7493,Cobranza!$B6,Recibos!AO$4:AO$7493) -> 0 | CD6: =SUMIF(Recibos!$D$4:$D$7493,Cobranza!$B6,Recibos!AP$4:AP$7493) -> 0 | CE6: =SUMIF(Recibos!$D$4:$D$7493,Cobranza!$B6,Recibos!AQ$4:AQ$7493) -> 0 | CF6: =SUMIF(Recibos!$D$4:$D$7493,Cobranza!$B6,Recibos!AR$4:AR$7493) -> 0 | ... CJ6: =SUMIF(Recibos!$D$4:$D$7493,Cobranza!$B6,Recibos!AV$4:AV$7493) -> 0 | CK6: =SUM(BY6:CJ6) -> 0
B7: CL_7_102 | C7: Rancho La Cuchilla No. 7, 102 | D7: García Moreno | E7: 0 | F7: 0 | G7: 0 | H7: 100 | I7: 100 | J7: 100 | K7: =SUM(E7:J7) -> 300 | L7: 100 | M7: 100 | N7: 100 | O7: 100 | P7: 100 | Q7: 100 | R7: 100 | S7: 100 | T7: 100 | U7: 100 | V7: 100 | W7: 100 | X7: =SUM(L7:W7) -> 1200 | Y7: 100 | Z7: 100 | AA7: 100 | AB7: 100 | AC7: 100 | AD7: 100 | AE7: 100 | AF7: 100 | AG7: 100 | AH7: 100 | AI7: 100 | AJ7: 100 | AK7: =SUM(Y7:AJ7) -> 1200 | AL7: 100 | AM7: 100 | AN7: 100 | AO7: 100 | AP7: 100 | AQ7: 100 | AR7: 100 | AS7: 100 | AT7: 0 | AU7: 0 | AV7: 0 | AW7: 0 | AX7: =SUM(AL7:AW7) -> 800 | AY7: =SUMIF(Recibos!$D$4:$D$7493,Cobranza!$B7,Recibos!K$4:K$7493) -> 100 | AZ7: =SUMIF(Recibos!$D$4:$D$7493,Cobranza!$B7,Recibos!L$4:L$7493) -> 100 | BA7: =SUMIF(Recibos!$D$4:$D$7493,Cobranza!$B7,Recibos!M$4:M$7493) -> 100 | BB7: =SUMIF(Recibos!$D$4:$D$7493,Cobranza!$B7,Recibos!N$4:N$7493) -> 100 | BC7: =SUMIF(Recibos!$D$4:$D$7493,Cobranza!$B7,Recibos!O$4:O$7493) -> 100 | BD7: =SUMIF(Recibos!$D$4:$D$7493,Cobranza!$B7,Recibos!P$4:P$7493) -> 100 | BE7: =SUMIF(Recibos!$D$4:$D$7493,Cobranza!$B7,Recibos!Q$4:Q$7493) -> 100 | BF7: =SUMIF(Recibos!$D$4:$D$7493,Cobranza!$B7,Recibos!R$4:R$7493) -> 100 | ... BJ7: =SUMIF(Recibos!$D$4:$D$7493,Cobranza!$B7,Recibos!V$4:V$7493) -> 100 | BK7: =SUM(AY7:BJ7) -> 1200 | BL7: =SUMIF(Recibos!$D$4:$D$7493,Cobranza!$B7,Recibos!X$4:X$7493) -> 100 | BM7: =SUMIF(Recibos!$D$4:$D$7493,Cobranza!$B7,Recibos!Y$4:Y$7493) -> 100 | BN7: =SUMIF(Recibos!$D$4:$D$7493,Cobranza!$B7,Recibos!Z$4:Z$7493) -> 100 | BO7: =SUMIF(Recibos!$D$4:$D$7493,Cobranza!$B7,Recibos!AA$4:AA$7493) -> 100 | BP7: =SUMIF(Recibos!$D$4:$D$7493,Cobranza!$B7,Recibos!AB$4:AB$7493) -> 100 | BQ7: =SUMIF(Recibos!$D$4:$D$7493,Cobranza!$B7,Recibos!AC$4:AC$7493) -> 100 | BR7: =SUMIF(Recibos!$D$4:$D$7493,Cobranza!$B7,Recibos!AD$4:AD$7493) -> 100 | BS7: =SUMIF(Recibos!$D$4:$D$7493,Cobranza!$B7,Recibos!AE$4:AE$7493) -> 100 | ... BW7: =SUMIF(Recibos!$D$4:$D$7493,Cobranza!$B7,Recibos!AI$4:AI$7493) -> 100 | BX7: =SUM(BL7:BW7) -> 1200 | BY7: =SUMIF(Recibos!$D$4:$D$7493,Cobranza!$B7,Recibos!AK$4:AK$7493) -> 100 | BZ7: =SUMIF(Recibos!$D$4:$D$7493,Cobranza!$B7,Recibos!AL$4:AL$7493) -> 100 | CA7: =SUMIF(Recibos!$D$4:$D$7493,Cobranza!$B7,Recibos!AM$4:AM$7493) -> 100 | CB7: =SUMIF(Recibos!$D$4:$D$7493,Cobranza!$B7,Recibos!AN$4:AN$7493) -> 100 | CC7: =SUMIF(Recibos!$D$4:$D$7493,Cobranza!$B7,Recibos!AO$4:AO$7493) -> 100 | CD7: =SUMIF(Recibos!$D$4:$D$7493,Cobranza!$B7,Recibos!AP$4:AP$7493) -> 100 | CE7: =SUMIF(Recibos!$D$4:$D$7493,Cobranza!$B7,Recibos!AQ$4:AQ$7493) -> 0 | CF7: =SUMIF(Recibos!$D$4:$D$7493,Cobranza!$B7,Recibos!AR$4:AR$7493) -> 0 | ... CJ7: =SUMIF(Recibos!$D$4:$D$7493,Cobranza!$B7,Recibos!AV$4:AV$7493) -> 0 | CK7: =SUM(BY7:CJ7) -> 600
B8: CL_7_201 | C8: Rancho La Cuchilla No. 7, 201 | D8: Solís Susana | E8: 0 | F8: 0 | G8: 0 | H8: 0 | I8: 0 | J8: 0 | K8: =SUM(E8:J8) -> 0 | L8: 0 | M8: 0 | N8: 0 | O8: 0 | P8: 0 | Q8: 0 | R8: 0 | S8: 0 | T8: 0 | U8: 0 | V8: 0 | W8: 0 | X8: =SUM(L8:W8) -> 0 | Y8: 0 | Z8: 0 | AA8: 0 | AB8: 0 | AC8: 0 | AD8: 0 | AE8: 0 | AF8: 0 | AG8: 0 | AH8: 0 | AI8: 0 | AJ8: 0 | AK8: =SUM(Y8:AJ8) -> 0 | AL8: 0 | AM8: 0 | AN8: 0 | AO8: 0 | AP8: 0 | AQ8: 0 | AR8: 0 | AS8: 0 | AT8: 0 | AU8: 0 | AV8: 0 | AW8: 0 | AX8: =SUM(AL8:AW8) -> 0 | AY8: =SUMIF(Recibos!$D$4:$D$7493,Cobranza!$B8,Recibos!K$4:K$7493) -> 0 | AZ8: =SUMIF(Recibos!$D$4:$D$7493,Cobranza!$B8,Recibos!L$4:L$7493) -> 0 | BA8: =SUMIF(Recibos!$D$4:$D$7493,Cobranza!$B8,Recibos!M$4:M$7493) -> 0 | BB8: =SUMIF(Recibos!$D$4:$D$7493,Cobranza!$B8,Recibos!N$4:N$7493) -> 0 | BC8: =SUMIF(Recibos!$D$4:$D$7493,Cobranza!$B8,Recibos!O$4:O$7493) -> 0 | BD8: =SUMIF(Recibos!$D$4:$D$7493,Cobranza!$B8,Recibos!P$4:P$7493) -> 0 | BE8: =SUMIF(Recibos!$D$4:$D$7493,Cobranza!$B8,Recibos!Q$4:Q$7493) -> 0 | BF8: =SUMIF(Recibos!$D$4:$D$7493,Cobranza!$B8,Recibos!R$4:R$7493) -> 100 | ... BJ8: =SUMIF(Recibos!$D$4:$D$7493,Cobranza!$B8,Recibos!V$4:V$7493) -> 0 | BK8: =SUM(AY8:BJ8) -> 100 | BL8: =SUMIF(Recibos!$D$4:$D$7493,Cobranza!$B8,Recibos!X$4:X$7493) -> 0 | BM8: =SUMIF(Recibos!$D$4:$D$7493,Cobranza!$B8,Recibos!Y$4:Y$7493) -> 0 | BN8: =SUMIF(Recibos!$D$4:$D$7493,Cobranza!$B8,Recibos!Z$4:Z$7493) -> 0 | BO8: =SUMIF(Recibos!$D$4:$D$7493,Cobranza!$B8,Recibos!AA$4:AA$7493) -> 0 | BP8: =SUMIF(Recibos!$D$4:$D$7493,Cobranza!$B8,Recibos!AB$4:AB$7493) -> 0 | BQ8: =SUMIF(Recibos!$D$4:$D$7493,Cobranza!$B8,Recibos!AC$4:AC$7493) -> 0 | BR8: =SUMIF(Recibos!$D$4:$D$7493,Cobranza!$B8,Recibos!AD$4:AD$7493) -> 0 | BS8: =SUMIF(Recibos!$D$4:$D$7493,Cobranza!$B8,Recibos!AE$4:AE$7493) -> 0 | ... BW8: =SUMIF(Recibos!$D$4:$D$7493,Cobranza!$B8,Recibos!AI$4:AI$7493) -> 0 | BX8: =SUM(BL8:BW8) -> 0 | BY8: =SUMIF(Recibos!$D$4:$D$7493,Cobranza!$B8,Recibos!AK$4:AK$7493) -> 0 | BZ8: =SUMIF(Recibos!$D$4:$D$7493,Cobranza!$B8,Recibos!AL$4:AL$7493) -> 0 | CA8: =SUMIF(Recibos!$D$4:$D$7493,Cobranza!$B8,Recibos!AM$4:AM$7493) -> 0 | CB8: =SUMIF(Recibos!$D$4:$D$7493,Cobranza!$B8,Recibos!AN$4:AN$7493) -> 0 | CC8: =SUMIF(Recibos!$D$4:$D$7493,Cobranza!$B8,Recibos!AO$4:AO$7493) -> 0 | CD8: =SUMIF(Recibos!$D$4:$D$7493,Cobranza!$B8,Recibos!AP$4:AP$7493) -> 0 | CE8: =SUMIF(Recibos!$D$4:$D$7493,Cobranza!$B8,Recibos!AQ$4:AQ$7493) -> 0 | CF8: =SUMIF(Recibos!$D$4:$D$7493,Cobranza!$B8,Recibos!AR$4:AR$7493) -> 0 | ... CJ8: =SUMIF(Recibos!$D$4:$D$7493,Cobranza!$B8,Recibos!AV$4:AV$7493) -> 0 | CK8: =SUM(BY8:CJ8) -> 0
B9: CL_7_202 | C9: Rancho La Cuchilla No. 7, 202 | D9: Carbajal Zayas | E9: 0 | F9: 0 | G9: 100 | H9: 100 | I9: 100 | J9: 100 | K9: =SUM(E9:J9) -> 400 | L9: 100 | M9: 100 | N9: 100 | O9: 100 | P9: 100 | Q9: 100 | R9: 100 | S9: 100 | T9: 100 | U9: 100 | V9: 100 | W9: 100 | X9: =SUM(L9:W9) -> 1200 | Y9: 100 | Z9: 100 | AA9: 0 | AB9: 0 | AC9: 100 | AD9: 100 | AE9: 100 | AF9: 100 | AG9: 100 | AH9: 100 | AI9: 100 | AJ9: 100 | AK9: =SUM(Y9:AJ9) -> 1000 | AL9: 100 | AM9: 100 | AN9: 100 | AO9: 100 | AP9: 100 | AQ9: 100 | AR9: 100 | AS9: 100 | AT9: 100 | AU9: 0 | AV9: 0 | AW9: 0 | AX9: =SUM(AL9:AW9) -> 900 | AY9: =SUMIF(Recibos!$D$4:$D$7493,Cobranza!$B9,Recibos!K$4:K$7493) -> 100 | AZ9: =SUMIF(Recibos!$D$4:$D$7493,Cobranza!$B9,Recibos!L$4:L$7493) -> 100 | BA9: =SUMIF(Recibos!$D$4:$D$7493,Cobranza!$B9,Recibos!M$4:M$7493) -> 100 | BB9: =SUMIF(Recibos!$D$4:$D$7493,Cobranza!$B9,Recibos!N$4:N$7493) -> 100 | BC9: =SUMIF(Recibos!$D$4:$D$7493,Cobranza!$B9,Recibos!O$4:O$7493) -> 100 | BD9: =SUMIF(Recibos!$D$4:$D$7493,Cobranza!$B9,Recibos!P$4:P$7493) -> 100 | BE9: =SUMIF(Recibos!$D$4:$D$7493,Cobranza!$B9,Recibos!Q$4:Q$7493) -> 100 | BF9: =SUMIF(Recibos!$D$4:$D$7493,Cobranza!$B9,Recibos!R$4:R$7493) -> 100 | ... BJ9: =SUMIF(Recibos!$D$4:$D$7493,Cobranza!$B9,Recibos!V$4:V$7493) -> 0 | BK9: =SUM(AY9:BJ9) -> 1100 | BL9: =SUMIF(Recibos!$D$4:$D$7493,Cobranza!$B9,Recibos!X$4:X$7493) -> 0 | BM9: =SUMIF(Recibos!$D$4:$D$7493,Cobranza!$B9,Recibos!Y$4:Y$7493) -> 0 | BN9: =SUMIF(Recibos!$D$4:$D$7493,Cobranza!$B9,Recibos!Z$4:Z$7493) -> 0 | BO9: =SUMIF(Recibos!$D$4:$D$7493,Cobranza!$B9,Recibos!AA$4:AA$7493) -> 0 | BP9: =SUMIF(Recibos!$D$4:$D$7493,Cobranza!$B9,Recibos!AB$4:AB$7493) -> 0 | BQ9: =SUMIF(Recibos!$D$4:$D$7493,Cobranza!$B9,Recibos!AC$4:AC$7493) -> 0 | BR9: =SUMIF(Recibos!$D$4:$D$7493,Cobranza!$B9,Recibos!AD$4:AD$7493) -> 0 | BS9: =SUMIF(Recibos!$D$4:$D$7493,Cobranza!$B9,Recibos!AE$4:AE$7493) -> 0 | ... BW9: =SUMIF(Recibos!$D$4:$D$7493,Cobranza!$B9,Recibos!AI$4:AI$7493) -> 0 | BX9: =SUM(BL9:BW9) -> 0 | BY9: =SUMIF(Recibos!$D$4:$D$7493,Cobranza!$B9,Recibos!AK$4:AK$7493) -> 0 | BZ9: =SUMIF(Recibos!$D$4:$D$7493,Cobranza!$B9,Recibos!AL$4:AL$7493) -> 0 | CA9: =SUMIF(Recibos!$D$4:$D$7493,Cobranza!$B9,Recibos!AM$4:AM$7493) -> 0 | CB9: =SUMIF(Recibos!$D$4:$D$7493,Cobranza!$B9,Recibos!AN$4:AN$7493) -> 0 | CC9: =SUMIF(Recibos!$D$4:$D$7493,Cobranza!$B9,Recibos!AO$4:AO$7493) -> 0 | CD9: =SUMIF(Recibos!$D$4:$D$7493,Cobranza!$B9,Recibos!AP$4:AP$7493) -> 0 | CE9: =SUMIF(Recibos!$D$4:$D$7493,Cobranza!$B9,Recibos!AQ$4:AQ$7493) -> 0 | CF9: =SUMIF(Recibos!$D$4:$D$7493,Cobranza!$B9,Recibos!AR$4:AR$7493) -> 0 | ... CJ9: =SUMIF(Recibos!$D$4:$D$7493,Cobranza!$B9,Recibos!AV$4:AV$7493) -> 0 | CK9: =SUM(BY9:CJ9) -> 0
B10: CL_9_ | C10: Rancho La Cuchilla No. 9 | D10: Martín del Campo | E10: 0 | F10: 0 | G10: 0 | H10: 0 | I10: 300 | J10: 300 | K10: =SUM(E10:J10) -> 600 | L10: 300 | M10: 0 | N10: 0 | O10: 0 | P10: 0 | Q10: 0 | R10: 0 | S10: 0 | T10: 0 | U10: 0 | V10: 0 | W10: 0 | X10: =SUM(L10:W10) -> 300 | Y10: 0 | Z10: 0 | AA10: 0 | AB10: 0 | AC10: 0 | AD10: 0 | AE10: 0 | AF10: 0 | AG10: 0 | AH10: 0 | AI10: 0 | AJ10: 0 | AK10: =SUM(Y10:AJ10) -> 0 | AL10: 0 | AM10: 0 | AN10: 0 | AO10: 0 | AP10: 0 | AQ10: 0 | AR10: 0 | AS10: 0 | AT10: 0 | AU10: 0 | AV10: 0 | AW10: 0 | AX10: =SUM(AL10:AW10) -> 0 | AY10: =SUMIF(Recibos!$D$4:$D$7493,Cobranza!$B10,Recibos!K$4:K$7493) -> 0 | AZ10: =SUMIF(Recibos!$D$4:$D$7493,Cobranza!$B10,Recibos!L$4:L$7493) -> 0 | BA10: =SUMIF(Recibos!$D$4:$D$7493,Cobranza!$B10,Recibos!M$4:M$7493) -> 0 | BB10: =SUMIF(Recibos!$D$4:$D$7493,Cobranza!$B10,Recibos!N$4:N$7493) -> 0 | BC10: =SUMIF(Recibos!$D$4:$D$7493,Cobranza!$B10,Recibos!O$4:O$7493) -> 0 | BD10: =SUMIF(Recibos!$D$4:$D$7493,Cobranza!$B10,Recibos!P$4:P$7493) -> 0 | BE10: =SUMIF(Recibos!$D$4:$D$7493,Cobranza!$B10,Recibos!Q$4:Q$7493) -> 0 | BF10: =SUMIF(Recibos!$D$4:$D$7493,Cobranza!$B10,Recibos!R$4:R$7493) -> 0 | ... BJ10: =SUMIF(Recibos!$D$4:$D$7493,Cobranza!$B10,Recibos!V$4:V$7493) -> 0 | BK10: =SUM(AY10:BJ10) -> 0 | BL10: =SUMIF(Recibos!$D$4:$D$7493,Cobranza!$B10,Recibos!X$4:X$7493) -> 0 | BM10: =SUMIF(Recibos!$D$4:$D$7493,Cobranza!$B10,Recibos!Y$4:Y$7493) -> 0 | BN10: =SUMIF(Recibos!$D$4:$D$7493,Cobranza!$B10,Recibos!Z$4:Z$7493) -> 0 | BO10: =SUMIF(Recibos!$D$4:$D$7493,Cobranza!$B10,Recibos!AA$4:AA$7493) -> 0 | BP10: =SUMIF(Recibos!$D$4:$D$7493,Cobranza!$B10,Recibos!AB$4:AB$7493) -> 0 | BQ10: =SUMIF(Recibos!$D$4:$D$7493,Cobranza!$B10,Recibos!AC$4:AC$7493) -> 0 | BR10: =SUMIF(Recibos!$D$4:$D$7493,Cobranza!$B10,Recibos!AD$4:AD$7493) -> 0 | BS10: =SUMIF(Recibos!$D$4:$D$7493,Cobranza!$B10,Recibos!AE$4:AE$7493) -> 0 | ... BW10: =SUMIF(Recibos!$D$4:$D$7493,Cobranza!$B10,Recibos!AI$4:AI$7493) -> 0 | BX10: =SUM(BL10:BW10) -> 0 | BY10: =SUMIF(Recibos!$D$4:$D$7493,Cobranza!$B10,Recibos!AK$4:AK$7493) -> 0 | BZ10: =SUMIF(Recibos!$D$4:$D$7493,Cobranza!$B10,Recibos!AL$4:AL$7493) -> 0 | CA10: =SUMIF(Recibos!$D$4:$D$7493,Cobranza!$B10,Recibos!AM$4:AM$7493) -> 0 | CB10: =SUMIF(Recibos!$D$4:$D$7493,Cobranza!$B10,Recibos!AN$4:AN$7493) -> 0 | CC10: =SUMIF(Recibos!$D$4:$D$7493,Cobranza!$B10,Recibos!AO$4:AO$7493) -> 0 | CD10: =SUMIF(Recibos!$D$4:$D$7493,Cobranza!$B10,Recibos!AP$4:AP$7493) -> 0 | CE10: =SUMIF(Recibos!$D$4:$D$7493,Cobranza!$B10,Recibos!AQ$4:AQ$7493) -> 0 | CF10: =SUMIF(Recibos!$D$4:$D$7493,Cobranza!$B10,Recibos!AR$4:AR$7493) -> 0 | ... CJ10: =SUMIF(Recibos!$D$4:$D$7493,Cobranza!$B10,Recibos!AV$4:AV$7493) -> 0 | CK10: =SUM(BY10:CJ10) -> 0
B11: CL_11_ | C11: Rancho La Cuchilla No. 11 | D11: Santiago | E11: 0 | F11: 0 | G11: 0 | H11: 0 | I11: 0 | J11: 0 | K11: =SUM(E11:J11) -> 0 | L11: 100 | M11: 100 | N11: 100 | O11: 100 | P11: 100 | Q11: 100 | R11: 100 | S11: 100 | T11: 100 | U11: 100 | V11: 0 | W11: 0 | X11: =SUM(L11:W11) -> 1000 | Y11: 0 | Z11: 100 | AA11: 100 | AB11: 100 | AC11: 100 | AD11: 100 | AE11: 100 | AF11: 100 | AG11: 100 | AH11: 100 | AI11: 100 | AJ11: 100 | AK11: =SUM(Y11:AJ11) -> 1100 | AL11: 100 | AM11: 100 | AN11: 100 | AO11: 0 | AP11: 0 | AQ11: 0 | AR11: 0 | AS11: 0 | AT11: 0 | AU11: 0 | AV11: 0 | AW11: 0 | AX11: =SUM(AL11:AW11) -> 300 | AY11: =SUMIF(Recibos!$D$4:$D$7493,Cobranza!$B11,Recibos!K$4:K$7493) -> 0 | AZ11: =SUMIF(Recibos!$D$4:$D$7493,Cobranza!$B11,Recibos!L$4:L$7493) -> 0 | BA11: =SUMIF(Recibos!$D$4:$D$7493,Cobranza!$B11,Recibos!M$4:M$7493) -> 0 | BB11: =SUMIF(Recibos!$D$4:$D$7493,Cobranza!$B11,Recibos!N$4:N$7493) -> 0 | BC11: =SUMIF(Recibos!$D$4:$D$7493,Cobranza!$B11,Recibos!O$4:O$7493) -> 0 | BD11: =SUMIF(Recibos!$D$4:$D$7493,Cobranza!$B11,Recibos!P$4:P$7493) -> 0 | BE11: =SUMIF(Recibos!$D$4:$D$7493,Cobranza!$B11,Recibos!Q$4:Q$7493) -> 0 | BF11: =SUMIF(Recibos!$D$4:$D$7493,Cobranza!$B11,Recibos!R$4:R$7493) -> 0 | ... BJ11: =SUMIF(Recibos!$D$4:$D$7493,Cobranza!$B11,Recibos!V$4:V$7493) -> 0 | BK11: =SUM(AY11:BJ11) -> 0 | BL11: =SUMIF(Recibos!$D$4:$D$7493,Cobranza!$B11,Recibos!X$4:X$7493) -> 0 | BM11: =SUMIF(Recibos!$D$4:$D$7493,Cobranza!$B11,Recibos!Y$4:Y$7493) -> 0 | BN11: =SUMIF(Recibos!$D$4:$D$7493,Cobranza!$B11,Recibos!Z$4:Z$7493) -> 0 | BO11: =SUMIF(Recibos!$D$4:$D$7493,Cobranza!$B11,Recibos!AA$4:AA$7493) -> 0 | BP11: =SUMIF(Recibos!$D$4:$D$7493,Cobranza!$B11,Recibos!AB$4:AB$7493) -> 0 | BQ11: =SUMIF(Recibos!$D$4:$D$7493,Cobranza!$B11,Recibos!AC$4:AC$7493) -> 0 | BR11: =SUMIF(Recibos!$D$4:$D$7493,Cobranza!$B11,Recibos!AD$4:AD$7493) -> 0 | BS11: =SUMIF(Recibos!$D$4:$D$7493,Cobranza!$B11,Recibos!AE$4:AE$7493) -> 0 | ... BW11: =SUMIF(Recibos!$D$4:$D$7493,Cobranza!$B11,Recibos!AI$4:AI$7493) -> 0 | BX11: =SUM(BL11:BW11) -> 0 | BY11: =SUMIF(Recibos!$D$4:$D$7493,Cobranza!$B11,Recibos!AK$4:AK$7493) -> 0 | BZ11: =SUMIF(Recibos!$D$4:$D$7493,Cobranza!$B11,Recibos!AL$4:AL$7493) -> 0 | CA11: =SUMIF(Recibos!$D$4:$D$7493,Cobranza!$B11,Recibos!AM$4:AM$7493) -> 0 | CB11: =SUMIF(Recibos!$D$4:$D$7493,Cobranza!$B11,Recibos!AN$4:AN$7493) -> 400 | CC11: =SUMIF(Recibos!$D$4:$D$7493,Cobranza!$B11,Recibos!AO$4:AO$7493) -> 400 | CD11: =SUMIF(Recibos!$D$4:$D$7493,Cobranza!$B11,Recibos!AP$4:AP$7493) -> 400 | CE11: =SUMIF(Recibos!$D$4:$D$7493,Cobranza!$B11,Recibos!AQ$4:AQ$7493) -> 400 | CF11: =SUMIF(Recibos!$D$4:$D$7493,Cobranza!$B11,Recibos!AR$4:AR$7493) -> 400 | ... CJ11: =SUMIF(Recibos!$D$4:$D$7493,Cobranza!$B11,Recibos!AV$4:AV$7493) -> 0 | CK11: =SUM(BY11:CJ11) -> 2400
B12: CL_12_ | C12: Rancho La Cuchilla No. 12 | D12: Rivera Flores | E12: 0 | F12: 0 | G12: 0 | H12: 0 | I12: 0 | J12: 250 | K12: =SUM(E12:J12) -> 250 | L12: 300 | M12: 300 | N12: 300 | O12: 300 | P12: 300 | Q12: 300 | R12: 300 | S12: 300 | T12: 300 | U12: 350 | V12: 350 | W12: 350 | X12: =SUM(L12:W12) -> 3750 | Y12: 300 | Z12: 300 | AA12: 300 | AB12: 300 | AC12: 300 | AD12: 300 | AE12: 300 | AF12: 300 | AG12: 300 | AH12: 300 | AI12: 300 | AJ12: 300 | AK12: =SUM(Y12:AJ12) -> 3600 | AL12: 300 | AM12: 300 | AN12: 300 | AO12: 300 | AP12: 300 | AQ12: 300 | AR12: 300 | AS12: 300 | AT12: 300 | AU12: 300 | AV12: 300 | AW12: 300 | AX12: =SUM(AL12:AW12) -> 3600 | AY12: =SUMIF(Recibos!$D$4:$D$7493,Cobranza!$B12,Recibos!K$4:K$7493) -> 300 | AZ12: =SUMIF(Recibos!$D$4:$D$7493,Cobranza!$B12,Recibos!L$4:L$7493) -> 300 | BA12: =SUMIF(Recibos!$D$4:$D$7493,Cobranza!$B12,Recibos!M$4:M$7493) -> 300 | BB12: =SUMIF(Recibos!$D$4:$D$7493,Cobranza!$B12,Recibos!N$4:N$7493) -> 300 | BC12: =SUMIF(Recibos!$D$4:$D$7493,Cobranza!$B12,Recibos!O$4:O$7493) -> 300 | BD12: =SUMIF(Recibos!$D$4:$D$7493,Cobranza!$B12,Recibos!P$4:P$7493) -> 300 | BE12: =SUMIF(Recibos!$D$4:$D$7493,Cobranza!$B12,Recibos!Q$4:Q$7493) -> 300 | BF12: =SUMIF(Recibos!$D$4:$D$7493,Cobranza!$B12,Recibos!R$4:R$7493) -> 300 | ... BJ12: =SUMIF(Recibos!$D$4:$D$7493,Cobranza!$B12,Recibos!V$4:V$7493) -> 300 | BK12: =SUM(AY12:BJ12) -> 3600 | BL12: =SUMIF(Recibos!$D$4:$D$7493,Cobranza!$B12,Recibos!X$4:X$7493) -> 350 | BM12: =SUMIF(Recibos!$D$4:$D$7493,Cobranza!$B12,Recibos!Y$4:Y$7493) -> 350 | BN12: =SUMIF(Recibos!$D$4:$D$7493,Cobranza!$B12,Recibos!Z$4:Z$7493) -> 350 | BO12: =SUMIF(Recibos!$D$4:$D$7493,Cobranza!$B12,Recibos!AA$4:AA$7493) -> 350 | BP12: =SUMIF(Recibos!$D$4:$D$7493,Cobranza!$B12,Recibos!AB$4:AB$7493) -> 0 | BQ12: =SUMIF(Recibos!$D$4:$D$7493,Cobranza!$B12,Recibos!AC$4:AC$7493) -> 0 | BR12: =SUMIF(Recibos!$D$4:$D$7493,Cobranza!$B12,Recibos!AD$4:AD$7493) -> 0 | BS12: =SUMIF(Recibos!$D$4:$D$7493,Cobranza!$B12,Recibos!AE$4:AE$7493) -> 0 | ... BW12: =SUMIF(Recibos!$D$4:$D$7493,Cobranza!$B12,Recibos!AI$4:AI$7493) -> 0 | BX12: =SUM(BL12:BW12) -> 1400 | BY12: =SUMIF(Recibos!$D$4:$D$7493,Cobranza!$B12,Recibos!AK$4:AK$7493) -> 350 | BZ12: =SUMIF(Recibos!$D$4:$D$7493,Cobranza!$B12,Recibos!AL$4:AL$7493) -> 350 | CA12: =SUMIF(Recibos!$D$4:$D$7493,Cobranza!$B12,Recibos!AM$4:AM$7493) -> 350 | CB12: =SUMIF(Recibos!$D$4:$D$7493,Cobranza!$B12,Recibos!AN$4:AN$7493) -> 350 | CC12: =SUMIF(Recibos!$D$4:$D$7493,Cobranza!$B12,Recibos!AO$4:AO$7493) -> 350 | CD12: =SUMIF(Recibos!$D$4:$D$7493,Cobranza!$B12,Recibos!AP$4:AP$7493) -> 350 | CE12: =SUMIF(Recibos!$D$4:$D$7493,Cobranza!$B12,Recibos!AQ$4:AQ$7493) -> 350 | CF12: =SUMIF(Recibos!$D$4:$D$7493,Cobranza!$B12,Recibos!AR$4:AR$7493) -> 350 | ... CJ12: =SUMIF(Recibos!$D$4:$D$7493,Cobranza!$B12,Recibos!AV$4:AV$7493) -> 350 | CK12: =SUM(BY12:CJ12) -> 4200
B13: CL_13_ | C13: Rancho La Cuchilla No. 13 | D13: Torres | E13: 0 | F13: 0 | G13: 0 | H13: 0 | I13: 0 | J13: 0 | K13: =SUM(E13:J13) -> 0 | L13: 0 | M13: 0 | N13: 0 | O13: 0 | P13: 0 | Q13: 0 | R13: 0 | S13: 0 | T13: 0 | U13: 0 | V13: 0 | W13: 0 | X13: =SUM(L13:W13) -> 0 | Y13: 0 | Z13: 0 | AA13: 0 | AB13: 0 | AC13: 0 | AD13: 0 | AE13: 0 | AF13: 0 | AG13: 0 | AH13: 0 | AI13: 0 | AJ13: 0 | AK13: =SUM(Y13:AJ13) -> 0 | AL13: 0 | AM13: 0 | AN13: 0 | AO13: 0 | AP13: 0 | AQ13: 0 | AR13: 0 | AS13: 0 | AT13: 0 | AU13: 0 | AV13: 0 | AW13: 0 | AX13: =SUM(AL13:AW13) -> 0 | AY13: =SUMIF(Recibos!$D$4:$D$7493,Cobranza!$B13,Recibos!K$4:K$7493) -> 0 | AZ13: =SUMIF(Recibos!$D$4:$D$7493,Cobranza!$B13,Recibos!L$4:L$7493) -> 0 | BA13: =SUMIF(Recibos!$D$4:$D$7493,Cobranza!$B13,Recibos!M$4:M$7493) -> 0 | BB13: =SUMIF(Recibos!$D$4:$D$7493,Cobranza!$B13,Recibos!N$4:N$7493) -> 0 | BC13: =SUMIF(Recibos!$D$4:$D$7493,Cobranza!$B13,Recibos!O$4:O$7493) -> 0 | BD13: =SUMIF(Recibos!$D$4:$D$7493,Cobranza!$B13,Recibos!P$4:P$7493) -> 0 | BE13: =SUMIF(Recibos!$D$4:$D$7493,Cobranza!$B13,Recibos!Q$4:Q$7493) -> 0 | BF13: =SUMIF(Recibos!$D$4:$D$7493,Cobranza!$B13,Recibos!R$4:R$7493) -> 200 | ... BJ13: =SUMIF(Recibos!$D$4:$D$7493,Cobranza!$B13,Recibos!V$4:V$7493) -> 0 | BK13: =SUM(AY13:BJ13) -> 200 | BL13: =SUMIF(Recibos!$D$4:$D$7493,Cobranza!$B13,Recibos!X$4:X$7493) -> 0 | BM13: =SUMIF(Recibos!$D$4:$D$7493,Cobranza!$B13,Recibos!Y$4:Y$7493) -> 0 | BN13: =SUMIF(Recibos!$D$4:$D$7493,Cobranza!$B13,Recibos!Z$4:Z$7493) -> 0 | BO13: =SUMIF(Recibos!$D$4:$D$7493,Cobranza!$B13,Recibos!AA$4:AA$7493) -> 0 | BP13: =SUMIF(Recibos!$D$4:$D$7493,Cobranza!$B13,Recibos!AB$4:AB$7493) -> 0 | BQ13: =SUMIF(Recibos!$D$4:$D$7493,Cobranza!$B13,Recibos!AC$4:AC$7493) -> 0 | BR13: =SUMIF(Recibos!$D$4:$D$7493,Cobranza!$B13,Recibos!AD$4:AD$7493) -> 0 | BS13: =SUMIF(Recibos!$D$4:$D$7493,Cobranza!$B13,Recibos!AE$4:AE$7493) -> 0 | ... BW13: =SUMIF(Recibos!$D$4:$D$7493,Cobranza!$B13,Recibos!AI$4:AI$7493) -> 0 | BX13: =SUM(BL13:BW13) -> 0 | BY13: =SUMIF(Recibos!$D$4:$D$7493,Cobranza!$B13,Recibos!AK$4:AK$7493) -> 0 | BZ13: =SUMIF(Recibos!$D$4:$D$7493,Cobranza!$B13,Recibos!AL$4:AL$7493) -> 0 | CA13: =SUMIF(Recibos!$D$4:$D$7493,Cobranza!$B13,Recibos!AM$4:AM$7493) -> 0 | CB13: =SUMIF(Recibos!$D$4:$D$7493,Cobranza!$B13,Recibos!AN$4:AN$7493) -> 0 | CC13: =SUMIF(Recibos!$D$4:$D$7493,Cobranza!$B13,Recibos!AO$4:AO$7493) -> 0 | CD13: =SUMIF(Recibos!$D$4:$D$7493,Cobranza!$B13,Recibos!AP$4:AP$7493) -> 0 | CE13: =SUMIF(Recibos!$D$4:$D$7493,Cobranza!$B13,Recibos!AQ$4:AQ$7493) -> 0 | CF13: =SUMIF(Recibos!$D$4:$D$7493,Cobranza!$B13,Recibos!AR$4:AR$7493) -> 0 | ... CJ13: =SUMIF(Recibos!$D$4:$D$7493,Cobranza!$B13,Recibos!AV$4:AV$7493) -> 0 | CK13: =SUM(BY13:CJ13) -> 0
B14: CL_14_ | C14: Rancho La Cuchilla No. 14 | D14: Chávez Lara | E14: 0 | F14: 0 | G14: 0 | H14: 0 | I14: 0 | J14: 0 | K14: =SUM(E14:J14) -> 0 | L14: 0 | M14: 0 | N14: 0 | O14: 0 | P14: 300 | Q14: 300 | R14: 300 | S14: 300 | T14: 300 | U14: 300 | V14: 400 | W14: 400 | X14: =SUM(L14:W14) -> 2600 | Y14: 400 | Z14: 400 | AA14: 400 | AB14: 400 | AC14: 400 | AD14: 400 | AE14: 400 | AF14: 400 | AG14: 400 | AH14: 400 | AI14: 400 | AJ14: 400 | AK14: =SUM(Y14:AJ14) -> 4800 | AL14: 400 | AM14: 400 | AN14: 400 | AO14: 400 | AP14: 400 | AQ14: 400 | AR14: 400 | AS14: 400 | AT14: 400 | AU14: 400 | AV14: 400 | AW14: 400 | AX14: =SUM(AL14:AW14) -> 4800 | AY14: =SUMIF(Recibos!$D$4:$D$7493,Cobranza!$B14,Recibos!K$4:K$7493) -> 400 | AZ14: =SUMIF(Recibos!$D$4:$D$7493,Cobranza!$B14,Recibos!L$4:L$7493) -> 400 | BA14: =SUMIF(Recibos!$D$4:$D$7493,Cobranza!$B14,Recibos!M$4:M$7493) -> 400 | BB14: =SUMIF(Recibos!$D$4:$D$7493,Cobranza!$B14,Recibos!N$4:N$7493) -> 400 | BC14: =SUMIF(Recibos!$D$4:$D$7493,Cobranza!$B14,Recibos!O$4:O$7493) -> 400 | BD14: =SUMIF(Recibos!$D$4:$D$7493,Cobranza!$B14,Recibos!P$4:P$7493) -> 400 | BE14: =SUMIF(Recibos!$D$4:$D$7493,Cobranza!$B14,Recibos!Q$4:Q$7493) -> 400 | BF14: =SUMIF(Recibos!$D$4:$D$7493,Cobranza!$B14,Recibos!R$4:R$7493) -> 400 | ... BJ14: =SUMIF(Recibos!$D$4:$D$7493,Cobranza!$B14,Recibos!V$4:V$7493) -> 0 | BK14: =SUM(AY14:BJ14) -> 4400 | BL14: =SUMIF(Recibos!$D$4:$D$7493,Cobranza!$B14,Recibos!X$4:X$7493) -> 400 | BM14: =SUMIF(Recibos!$D$4:$D$7493,Cobranza!$B14,Recibos!Y$4:Y$7493) -> 400 | BN14: =SUMIF(Recibos!$D$4:$D$7493,Cobranza!$B14,Recibos!Z$4:Z$7493) -> 400 | BO14: =SUMIF(Recibos!$D$4:$D$7493,Cobranza!$B14,Recibos!AA$4:AA$7493) -> 400 | BP14: =SUMIF(Recibos!$D$4:$D$7493,Cobranza!$B14,Recibos!AB$4:AB$7493) -> 400 | BQ14: =SUMIF(Recibos!$D$4:$D$7493,Cobranza!$B14,Recibos!AC$4:AC$7493) -> 400 | BR14: =SUMIF(Recibos!$D$4:$D$7493,Cobranza!$B14,Recibos!AD$4:AD$7493) -> 400 | BS14: =SUMIF(Recibos!$D$4:$D$7493,Cobranza!$B14,Recibos!AE$4:AE$7493) -> 400 | ... BW14: =SUMIF(Recibos!$D$4:$D$7493,Cobranza!$B14,Recibos!AI$4:AI$7493) -> 0 | BX14: =SUM(BL14:BW14) -> 4400 | BY14: =SUMIF(Recibos!$D$4:$D$7493,Cobranza!$B14,Recibos!AK$4:AK$7493) -> 400 | BZ14: =SUMIF(Recibos!$D$4:$D$7493,Cobranza!$B14,Recibos!AL$4:AL$7493) -> 400 | CA14: =SUMIF(Recibos!$D$4:$D$7493,Cobranza!$B14,Recibos!AM$4:AM$7493) -> 400 | CB14: =SUMIF(Recibos!$D$4:$D$7493,Cobranza!$B14,Recibos!AN$4:AN$7493) -> 400 | CC14: =SUMIF(Recibos!$D$4:$D$7493,Cobranza!$B14,Recibos!AO$4:AO$7493) -> 400 | CD14: =SUMIF(Recibos!$D$4:$D$7493,Cobranza!$B14,Recibos!AP$4:AP$7493) -> 400 | CE14: =SUMIF(Recibos!$D$4:$D$7493,Cobranza!$B14,Recibos!AQ$4:AQ$7493) -> 400 | CF14: =SUMIF(Recibos!$D$4:$D$7493,Cobranza!$B14,Recibos!AR$4:AR$7493) -> 400 | ... CJ14: =SUMIF(Recibos!$D$4:$D$7493,Cobranza!$B14,Recibos!AV$4:AV$7493) -> 0 | CK14: =SUM(BY14:CJ14) -> 4400
B15: CL_15_ | C15: Rancho La Cuchilla No. 15 | D15: Guerrero Ponce | E15: 0 | F15: 0 | G15: 0 | H15: 300 | I15: 300 | J15: 300 | K15: =SUM(E15:J15) -> 900 | L15: 300 | M15: 300 | N15: 300 | O15: 300 | P15: 300 | Q15: 300 | R15: 300 | S15: 300 | T15: 300 | U15: 300 | V15: 300 | W15: 300 | X15: =SUM(L15:W15) -> 3600 | Y15: 300 | Z15: 300 | AA15: 300 | AB15: 300 | AC15: 300 | AD15: 300 | AE15: 300 | AF15: 300 | AG15: 300 | AH15: 300 | AI15: 300 | AJ15: 300 | AK15: =SUM(Y15:AJ15) -> 3600 | AL15: 300 | AM15: 300 | AN15: 300 | AO15: 300 | AP15: 300 | AQ15: 300 | AR15: 300 | AS15: 300 | AT15: 300 | AU15: 300 | AV15: 300 | AW15: 300 | AX15: =SUM(AL15:AW15) -> 3600 | AY15: =SUMIF(Recibos!$D$4:$D$7493,Cobranza!$B15,Recibos!K$4:K$7493) -> 0 | AZ15: =SUMIF(Recibos!$D$4:$D$7493,Cobranza!$B15,Recibos!L$4:L$7493) -> 0 | BA15: =SUMIF(Recibos!$D$4:$D$7493,Cobranza!$B15,Recibos!M$4:M$7493) -> 300 | BB15: =SUMIF(Recibos!$D$4:$D$7493,Cobranza!$B15,Recibos!N$4:N$7493) -> 300 | BC15: =SUMIF(Recibos!$D$4:$D$7493,Cobranza!$B15,Recibos!O$4:O$7493) -> 0 | BD15: =SUMIF(Recibos!$D$4:$D$7493,Cobranza!$B15,Recibos!P$4:P$7493) -> 300 | BE15: =SUMIF(Recibos!$D$4:$D$7493,Cobranza!$B15,Recibos!Q$4:Q$7493) -> 300 | BF15: =SUMIF(Recibos!$D$4:$D$7493,Cobranza!$B15,Recibos!R$4:R$7493) -> 300 | ... BJ15: =SUMIF(Recibos!$D$4:$D$7493,Cobranza!$B15,Recibos!V$4:V$7493) -> 300 | BK15: =SUM(AY15:BJ15) -> 2700 | BL15: =SUMIF(Recibos!$D$4:$D$7493,Cobranza!$B15,Recibos!X$4:X$7493) -> 300 | BM15: =SUMIF(Recibos!$D$4:$D$7493,Cobranza!$B15,Recibos!Y$4:Y$7493) -> 300 | BN15: =SUMIF(Recibos!$D$4:$D$7493,Cobranza!$B15,Recibos!Z$4:Z$7493) -> 300 | BO15: =SUMIF(Recibos!$D$4:$D$7493,Cobranza!$B15,Recibos!AA$4:AA$7493) -> 300 | BP15: =SUMIF(Recibos!$D$4:$D$7493,Cobranza!$B15,Recibos!AB$4:AB$7493) -> 300 | BQ15: =SUMIF(Recibos!$D$4:$D$7493,Cobranza!$B15,Recibos!AC$4:AC$7493) -> 300 | BR15: =SUMIF(Recibos!$D$4:$D$7493,Cobranza!$B15,Recibos!AD$4:AD$7493) -> 300 | BS15: =SUMIF(Recibos!$D$4:$D$7493,Cobranza!$B15,Recibos!AE$4:AE$7493) -> 300 | ... BW15: =SUMIF(Recibos!$D$4:$D$7493,Cobranza!$B15,Recibos!AI$4:AI$7493) -> 300 | BX15: =SUM(BL15:BW15) -> 3600 | BY15: =SUMIF(Recibos!$D$4:$D$7493,Cobranza!$B15,Recibos!AK$4:AK$7493) -> 300 | BZ15: =SUMIF(Recibos!$D$4:$D$7493,Cobranza!$B15,Recibos!AL$4:AL$7493) -> 300 | CA15: =SUMIF(Recibos!$D$4:$D$7493,Cobranza!$B15,Recibos!AM$4:AM$7493) -> 300 | CB15: =SUMIF(Recibos!$D$4:$D$7493,Cobranza!$B15,Recibos!AN$4:AN$7493) -> 300 | CC15: =SUMIF(Recibos!$D$4:$D$7493,Cobranza!$B15,Recibos!AO$4:AO$7493) -> 300 | CD15: =SUMIF(Recibos!$D$4:$D$7493,Cobranza!$B15,Recibos!AP$4:AP$7493) -> 300 | CE15: =SUMIF(Recibos!$D$4:$D$7493,Cobranza!$B15,Recibos!AQ$4:AQ$7493) -> 300 | CF15: =SUMIF(Recibos!$D$4:$D$7493,Cobranza!$B15,Recibos!AR$4:AR$7493) -> 300 | ... CJ15: =SUMIF(Recibos!$D$4:$D$7493,Cobranza!$B15,Recibos!AV$4:AV$7493) -> 0 | CK15: =SUM(BY15:CJ15) -> 2400
B16: CL_17_A | E16: 0 | F16: 0 | G16: 0 | H16: 0 | I16: 0 | J16: 0 | K16: =SUM(E16:J16) -> 0 | L16: 0 | M16: 0 | N16: 0 | O16: 0 | P16: 0 | Q16: 0 | R16: 0 | S16: 0 | T16: 0 | U16: 0 | V16: 0 | W16: 0 | X16: =SUM(L16:W16) -> 0 | AX16: =SUM(AL16:AW16) -> 0 | AY16: =SUMIF(Recibos!$D$4:$D$7493,Cobranza!$B16,Recibos!K$4:K$7493) -> 0 | AZ16: =SUMIF(Recibos!$D$4:$D$7493,Cobranza!$B16,Recibos!L$4:L$7493) -> 0 | BA16: =SUMIF(Recibos!$D$4:$D$7493,Cobranza!$B16,Recibos!M$4:M$7493) -> 0 | BB16: =SUMIF(Recibos!$D$4:$D$7493,Cobranza!$B16,Recibos!N$4:N$7493) -> 0 | BC16: =SUMIF(Recibos!$D$4:$D$7493,Cobranza!$B16,Recibos!O$4:O$7493) -> 0 | BD16: =SUMIF(Recibos!$D$4:$D$7493,Cobranza!$B16,Recibos!P$4:P$7493) -> 0 | BE16: =SUMIF(Recibos!$D$4:$D$7493,Cobranza!$B16,Recibos!Q$4:Q$7493) -> 0 | BF16: =SUMIF(Recibos!$D$4:$D$7493,Cobranza!$B16,Recibos!R$4:R$7493) -> 0 | ... BJ16: =SUMIF(Recibos!$D$4:$D$7493,Cobranza!$B16,Recibos!V$4:V$7493) -> 0 | BK16: =SUM(AY16:BJ16) -> 0 | BL16: =SUMIF(Recibos!$D$4:$D$7493,Cobranza!$B16,Recibos!X$4:X$7493) -> 0 | BM16: =SUMIF(Recibos!$D$4:$D$7493,Cobranza!$B16,Recibos!Y$4:Y$7493) -> 0 | BN16: =SUMIF(Recibos!$D$4:$D$7493,Cobranza!$B16,Recibos!Z$4:Z$7493) -> 0 | BO16: =SUMIF(Recibos!$D$4:$D$7493,Cobranza!$B16,Recibos!AA$4:AA$7493) -> 0 | BP16: =SUMIF(Recibos!$D$4:$D$7493,Cobranza!$B16,Recibos!AB$4:AB$7493) -> 0 | BQ16: =SUMIF(Recibos!$D$4:$D$7493,Cobranza!$B16,Recibos!AC$4:AC$7493) -> 0 | BR16: =SUMIF(Recibos!$D$4:$D$7493,Cobranza!$B16,Recibos!AD$4:AD$7493) -> 0 | BS16: =SUMIF(Recibos!$D$4:$D$7493,Cobranza!$B16,Recibos!AE$4:AE$7493) -> 0 | ... BW16: =SUMIF(Recibos!$D$4:$D$7493,Cobranza!$B16,Recibos!AI$4:AI$7493) -> 0 | BX16: =SUM(BL16:BW16) -> 0 | BY16: =SUMIF(Recibos!$D$4:$D$7493,Cobranza!$B16,Recibos!AK$4:AK$7493) -> 0 | BZ16: =SUMIF(Recibos!$D$4:$D$7493,Cobranza!$B16,Recibos!AL$4:AL$7493) -> 0 | CA16: =SUMIF(Recibos!$D$4:$D$7493,Cobranza!$B16,Recibos!AM$4:AM$7493) -> 0 | CB16: =SUMIF(Recibos!$D$4:$D$7493,Cobranza!$B16,Recibos!AN$4:AN$7493) -> 0 | CC16: =SUMIF(Recibos!$D$4:$D$7493,Cobranza!$B16,Recibos!AO$4:AO$7493) -> 0 | CD16: =SUMIF(Recibos!$D$4:$D$7493,Cobranza!$B16,Recibos!AP$4:AP$7493) -> 0 | CE16: =SUMIF(Recibos!$D$4:$D$7493,Cobranza!$B16,Recibos!AQ$4:AQ$7493) -> 0 | CF16: =SUMIF(Recibos!$D$4:$D$7493,Cobranza!$B16,Recibos!AR$4:AR$7493) -> 0 | ... CJ16: =SUMIF(Recibos!$D$4:$D$7493,Cobranza!$B16,Recibos!AV$4:AV$7493) -> 0 | CK16: =SUM(BY16:CJ16) -> 0
B17: CL_18_ | C17: Rancho La Cuchilla No. 18 | D17: Aldana Sánchez | E17: 0 | F17: 0 | G17: 0 | H17: 0 | I17: 0 | J17: 300 | K17: =SUM(E17:J17) -> 300 | L17: 300 | M17: 300 | N17: 300 | O17: 300 | P17: 300 | Q17: 300 | R17: 300 | S17: 300 | T17: 300 | U17: 400 | V17: 400 | W17: 400 | X17: =SUM(L17:W17) -> 3900 | Y17: 400 | Z17: 400 | AA17: 400 | AB17: 400 | AC17: 400 | AD17: 400 | AE17: 400 | AF17: 400 | AG17: 400 | AH17: 400 | AI17: 400 | AJ17: 400 | AK17: =SUM(Y17:AJ17) -> 4800 | AL17: 400 | AM17: 400 | AN17: 400 | AO17: 400 | AP17: 400 | AQ17: 400 | AR17: 400 | AS17: 400 | AT17: 400 | AU17: 400 | AV17: 400 | AW17: 400 | AX17: =SUM(AL17:AW17) -> 4800 | AY17: =SUMIF(Recibos!$D$4:$D$7493,Cobranza!$B17,Recibos!K$4:K$7493) -> 400 | AZ17: =SUMIF(Recibos!$D$4:$D$7493,Cobranza!$B17,Recibos!L$4:L$7493) -> 400 | BA17: =SUMIF(Recibos!$D$4:$D$7493,Cobranza!$B17,Recibos!M$4:M$7493) -> 400 | BB17: =SUMIF(Recibos!$D$4:$D$7493,Cobranza!$B17,Recibos!N$4:N$7493) -> 400 | BC17: =SUMIF(Recibos!$D$4:$D$7493,Cobranza!$B17,Recibos!O$4:O$7493) -> 400 | BD17: =SUMIF(Recibos!$D$4:$D$7493,Cobranza!$B17,Recibos!P$4:P$7493) -> 400 | BE17: =SUMIF(Recibos!$D$4:$D$7493,Cobranza!$B17,Recibos!Q$4:Q$7493) -> 400 | BF17: =SUMIF(Recibos!$D$4:$D$7493,Cobranza!$B17,Recibos!R$4:R$7493) -> 400 | ... BJ17: =SUMIF(Recibos!$D$4:$D$7493,Cobranza!$B17,Recibos!V$4:V$7493) -> 400 | BK17: =SUM(AY17:BJ17) -> 4800 | BL17: =SUMIF(Recibos!$D$4:$D$7493,Cobranza!$B17,Recibos!X$4:X$7493) -> 400 | BM17: =SUMIF(Recibos!$D$4:$D$7493,Cobranza!$B17,Recibos!Y$4:Y$7493) -> 400 | BN17: =SUMIF(Recibos!$D$4:$D$7493,Cobranza!$B17,Recibos!Z$4:Z$7493) -> 400 | BO17: =SUMIF(Recibos!$D$4:$D$7493,Cobranza!$B17,Recibos!AA$4:AA$7493) -> 400 | BP17: =SUMIF(Recibos!$D$4:$D$7493,Cobranza!$B17,Recibos!AB$4:AB$7493) -> 400 | BQ17: =SUMIF(Recibos!$D$4:$D$7493,Cobranza!$B17,Recibos!AC$4:AC$7493) -> 400 | BR17: =SUMIF(Recibos!$D$4:$D$7493,Cobranza!$B17,Recibos!AD$4:AD$7493) -> 400 | BS17: =SUMIF(Recibos!$D$4:$D$7493,Cobranza!$B17,Recibos!AE$4:AE$7493) -> 400 | ... BW17: =SUMIF(Recibos!$D$4:$D$7493,Cobranza!$B17,Recibos!AI$4:AI$7493) -> 400 | BX17: =SUM(BL17:BW17) -> 4800 | BY17: =SUMIF(Recibos!$D$4:$D$7493,Cobranza!$B17,Recibos!AK$4:AK$7493) -> 400 | BZ17: =SUMIF(Recibos!$D$4:$D$7493,Cobranza!$B17,Recibos!AL$4:AL$7493) -> 400 | CA17: =SUMIF(Recibos!$D$4:$D$7493,Cobranza!$B17,Recibos!AM$4:AM$7493) -> 400 | CB17: =SUMIF(Recibos!$D$4:$D$7493,Cobranza!$B17,Recibos!AN$4:AN$7493) -> 400 | CC17: =SUMIF(Recibos!$D$4:$D$7493,Cobranza!$B17,Recibos!AO$4:AO$7493) -> 400 | CD17: =SUMIF(Recibos!$D$4:$D$7493,Cobranza!$B17,Recibos!AP$4:AP$7493) -> 400 | CE17: =SUMIF(Recibos!$D$4:$D$7493,Cobranza!$B17,Recibos!AQ$4:AQ$7493) -> 400 | CF17: =SUMIF(Recibos!$D$4:$D$7493,Cobranza!$B17,Recibos!AR$4:AR$7493) -> 400 | ... CJ17: =SUMIF(Recibos!$D$4:$D$7493,Cobranza!$B17,Recibos!AV$4:AV$7493) -> 0 | CK17: =SUM(BY17:CJ17) -> 4000
B18: CL_19_ | C18: Rancho La Cuchilla No. 19 | D18: Tapia Vázquez | E18: 0 | F18: 0 | G18: 0 | H18: 0 | I18: 0 | J18: 300 | K18: =SUM(E18:J18) -> 300 | L18: 300 | M18: 300 | N18: 300 | O18: 300 | P18: 300 | Q18: 300 | R18: 300 | S18: 300 | T18: 300 | U18: 300 | V18: 300 | W18: 300 | X18: =SUM(L18:W18) -> 3600 | Y18: 300 | Z18: 300 | AA18: 300 | AB18: 300 | AC18: 300 | AD18: 300 | AE18: 300 | AF18: 300 | AG18: 300 | AH18: 300 | AI18: 300 | AJ18: 300 | AK18: =SUM(Y18:AJ18) -> 3600 | AL18: 300 | AM18: 300 | AN18: 300 | AO18: 300 | AP18: 300 | AQ18: 300 | AR18: 300 | AS18: 300 | AT18: 300 | AU18: 300 | AV18: 300 | AW18: 300 | AX18: =SUM(AL18:AW18) -> 3600 | AY18: =SUMIF(Recibos!$D$4:$D$7493,Cobranza!$B18,Recibos!K$4:K$7493) -> 300 | AZ18: =SUMIF(Recibos!$D$4:$D$7493,Cobranza!$B18,Recibos!L$4:L$7493) -> 300 | BA18: =SUMIF(Recibos!$D$4:$D$7493,Cobranza!$B18,Recibos!M$4:M$7493) -> 300 | BB18: =SUMIF(Recibos!$D$4:$D$7493,Cobranza!$B18,Recibos!N$4:N$7493) -> 300 | BC18: =SUMIF(Recibos!$D$4:$D$7493,Cobranza!$B18,Recibos!O$4:O$7493) -> 300 | BD18: =SUMIF(Recibos!$D$4:$D$7493,Cobranza!$B18,Recibos!P$4:P$7493) -> 300 | BE18: =SUMIF(Recibos!$D$4:$D$7493,Cobranza!$B18,Recibos!Q$4:Q$7493) -> 300 | BF18: =SUMIF(Recibos!$D$4:$D$7493,Cobranza!$B18,Recibos!R$4:R$7493) -> 300 | ... BJ18: =SUMIF(Recibos!$D$4:$D$7493,Cobranza!$B18,Recibos!V$4:V$7493) -> 0 | BK18: =SUM(AY18:BJ18) -> 3300 | BL18: =SUMIF(Recibos!$D$4:$D$7493,Cobranza!$B18,Recibos!X$4:X$7493) -> 300 | BM18: =SUMIF(Recibos!$D$4:$D$7493,Cobranza!$B18,Recibos!Y$4:Y$7493) -> 300 | BN18: =SUMIF(Recibos!$D$4:$D$7493,Cobranza!$B18,Recibos!Z$4:Z$7493) -> 300 | BO18: =SUMIF(Recibos!$D$4:$D$7493,Cobranza!$B18,Recibos!AA$4:AA$7493) -> 300 | BP18: =SUMIF(Recibos!$D$4:$D$7493,Cobranza!$B18,Recibos!AB$4:AB$7493) -> 300 | BQ18: =SUMIF(Recibos!$D$4:$D$7493,Cobranza!$B18,Recibos!AC$4:AC$7493) -> 300 | BR18: =SUMIF(Recibos!$D$4:$D$7493,Cobranza!$B18,Recibos!AD$4:AD$7493) -> 300 | BS18: =SUMIF(Recibos!$D$4:$D$7493,Cobranza!$B18,Recibos!AE$4:AE$7493) -> 300 | ... BW18: =SUMIF(Recibos!$D$4:$D$7493,Cobranza!$B18,Recibos!AI$4:AI$7493) -> 0 | BX18: =SUM(BL18:BW18) -> 3300 | BY18: =SUMIF(Recibos!$D$4:$D$7493,Cobranza!$B18,Recibos!AK$4:AK$7493) -> 300 | BZ18: =SUMIF(Recibos!$D$4:$D$7493,Cobranza!$B18,Recibos!AL$4:AL$7493) -> 300 | CA18: =SUMIF(Recibos!$D$4:$D$7493,Cobranza!$B18,Recibos!AM$4:AM$7493) -> 300 | CB18: =SUMIF(Recibos!$D$4:$D$7493,Cobranza!$B18,Recibos!AN$4:AN$7493) -> 300 | CC18: =SUMIF(Recibos!$D$4:$D$7493,Cobranza!$B18,Recibos!AO$4:AO$7493) -> 300 | CD18: =SUMIF(Recibos!$D$4:$D$7493,Cobranza!$B18,Recibos!AP$4:AP$7493) -> 300 | CE18: =SUMIF(Recibos!$D$4:$D$7493,Cobranza!$B18,Recibos!AQ$4:AQ$7493) -> 300 | CF18: =SUMIF(Recibos!$D$4:$D$7493,Cobranza!$B18,Recibos!AR$4:AR$7493) -> 300 | ... CJ18: =SUMIF(Recibos!$D$4:$D$7493,Cobranza!$B18,Recibos!AV$4:AV$7493) -> 0 | CK18: =SUM(BY18:CJ18) -> 3300
B19: CL_20_ | C19: Rancho La Cuchilla No. 20 | D19: Sánchez López | E19: 0 | F19: 0 | G19: 0 | H19: 0 | I19: 0 | J19: 300 | K19: =SUM(E19:J19) -> 300 | L19: 300 | M19: 300 | N19: 300 | O19: 300 | P19: 300 | Q19: 300 | R19: 300 | S19: 300 | T19: 300 | U19: 400 | V19: 400 | W19: 400 | X19: =SUM(L19:W19) -> 3900 | Y19: 400 | Z19: 400 | AA19: 0 | AB19: 400 | AC19: 400 | AD19: 400 | AE19: 400 | AF19: 400 | AG19: 400 | AH19: 400 | AI19: 400 | AJ19: 400 | AK19: =SUM(Y19:AJ19) -> 4400 | AL19: 400 | AM19: 400 | AN19: 400 | AO19: 400 | AP19: 400 | AQ19: 400 | AR19: 400 | AS19: 400 | AT19: 400 | AU19: 400 | AV19: 400 | AW19: 400 | AX19: =SUM(AL19:AW19) -> 4800 | AY19: =SUMIF(Recibos!$D$4:$D$7493,Cobranza!$B19,Recibos!K$4:K$7493) -> 400 | AZ19: =SUMIF(Recibos!$D$4:$D$7493,Cobranza!$B19,Recibos!L$4:L$7493) -> 400 | BA19: =SUMIF(Recibos!$D$4:$D$7493,Cobranza!$B19,Recibos!M$4:M$7493) -> 400 | BB19: =SUMIF(Recibos!$D$4:$D$7493,Cobranza!$B19,Recibos!N$4:N$7493) -> 400 | BC19: =SUMIF(Recibos!$D$4:$D$7493,Cobranza!$B19,Recibos!O$4:O$7493) -> 400 | BD19: =SUMIF(Recibos!$D$4:$D$7493,Cobranza!$B19,Recibos!P$4:P$7493) -> 400 | BE19: =SUMIF(Recibos!$D$4:$D$7493,Cobranza!$B19,Recibos!Q$4:Q$7493) -> 400 | BF19: =SUMIF(Recibos!$D$4:$D$7493,Cobranza!$B19,Recibos!R$4:R$7493) -> 400 | ... BJ19: =SUMIF(Recibos!$D$4:$D$7493,Cobranza!$B19,Recibos!V$4:V$7493) -> 400 | BK19: =SUM(AY19:BJ19) -> 4800 | BL19: =SUMIF(Recibos!$D$4:$D$7493,Cobranza!$B19,Recibos!X$4:X$7493) -> 400 | BM19: =SUMIF(Recibos!$D$4:$D$7493,Cobranza!$B19,Recibos!Y$4:Y$7493) -> 400 | BN19: =SUMIF(Recibos!$D$4:$D$7493,Cobranza!$B19,Recibos!Z$4:Z$7493) -> 400 | BO19: =SUMIF(Recibos!$D$4:$D$7493,Cobranza!$B19,Recibos!AA$4:AA$7493) -> 400 | BP19: =SUMIF(Recibos!$D$4:$D$7493,Cobranza!$B19,Recibos!AB$4:AB$7493) -> 400 | BQ19: =SUMIF(Recibos!$D$4:$D$7493,Cobranza!$B19,Recibos!AC$4:AC$7493) -> 400 | BR19: =SUMIF(Recibos!$D$4:$D$7493,Cobranza!$B19,Recibos!AD$4:AD$7493) -> 400 | BS19: =SUMIF(Recibos!$D$4:$D$7493,Cobranza!$B19,Recibos!AE$4:AE$7493) -> 400 | ... BW19: =SUMIF(Recibos!$D$4:$D$7493,Cobranza!$B19,Recibos!AI$4:AI$7493) -> 400 | BX19: =SUM(BL19:BW19) -> 4800 | BY19: =SUMIF(Recibos!$D$4:$D$7493,Cobranza!$B19,Recibos!AK$4:AK$7493) -> 400 | BZ19: =SUMIF(Recibos!$D$4:$D$7493,Cobranza!$B19,Recibos!AL$4:AL$7493) -> 400 | CA19: =SUMIF(Recibos!$D$4:$D$7493,Cobranza!$B19,Recibos!AM$4:AM$7493) -> 400 | CB19: =SUMIF(Recibos!$D$4:$D$7493,Cobranza!$B19,Recibos!AN$4:AN$7493) -> 400 | CC19: =SUMIF(Recibos!$D$4:$D$7493,Cobranza!$B19,Recibos!AO$4:AO$7493) -> 400 | CD19: =SUMIF(Recibos!$D$4:$D$7493,Cobranza!$B19,Recibos!AP$4:AP$7493) -> 400 | CE19: =SUMIF(Recibos!$D$4:$D$7493,Cobranza!$B19,Recibos!AQ$4:AQ$7493) -> 400 | CF19: =SUMIF(Recibos!$D$4:$D$7493,Cobranza!$B19,Recibos!AR$4:AR$7493) -> 400 | ... CJ19: =SUMIF(Recibos!$D$4:$D$7493,Cobranza!$B19,Recibos!AV$4:AV$7493) -> 0 | CK19: =SUM(BY19:CJ19) -> 4000
B20: CL_21_ | C20: Rancho La Cuchilla No. 21 | D20: Solórzano Calderón | E20: 0 | F20: 0 | G20: 0 | H20: 0 | I20: 0 | J20: 0 | K20: =SUM(E20:J20) -> 0 | L20: 300 | M20: 300 | N20: 300 | O20: 300 | P20: 300 | Q20: 300 | R20: 300 | S20: 300 | T20: 300 | U20: 300 | V20: 300 | W20: 0 | X20: =SUM(L20:W20) -> 3300 | Y20: 400 | Z20: 400 | AA20: 400 | AB20: 400 | AC20: 400 | AD20: 400 | AE20: 400 | AF20: 400 | AG20: 800 | AH20: 400 | AI20: 400 | AJ20: 0 | AK20: =SUM(Y20:AJ20) -> 4800 | AL20: 400 | AM20: 400 | AN20: 400 | AO20: 400 | AP20: 400 | AQ20: 400 | AR20: 400 | AS20: 400 | AT20: 400 | AU20: 400 | AV20: 400 | AW20: 0 | AX20: =SUM(AL20:AW20) -> 4400 | AY20: =SUMIF(Recibos!$D$4:$D$7493,Cobranza!$B20,Recibos!K$4:K$7493) -> 400 | AZ20: =SUMIF(Recibos!$D$4:$D$7493,Cobranza!$B20,Recibos!L$4:L$7493) -> 400 | BA20: =SUMIF(Recibos!$D$4:$D$7493,Cobranza!$B20,Recibos!M$4:M$7493) -> 400 | BB20: =SUMIF(Recibos!$D$4:$D$7493,Cobranza!$B20,Recibos!N$4:N$7493) -> 400 | BC20: =SUMIF(Recibos!$D$4:$D$7493,Cobranza!$B20,Recibos!O$4:O$7493) -> 400 | BD20: =SUMIF(Recibos!$D$4:$D$7493,Cobranza!$B20,Recibos!P$4:P$7493) -> 400 | BE20: =SUMIF(Recibos!$D$4:$D$7493,Cobranza!$B20,Recibos!Q$4:Q$7493) -> 400 | BF20: =SUMIF(Recibos!$D$4:$D$7493,Cobranza!$B20,Recibos!R$4:R$7493) -> 400 | ... BJ20: =SUMIF(Recibos!$D$4:$D$7493,Cobranza!$B20,Recibos!V$4:V$7493) -> 0 | BK20: =SUM(AY20:BJ20) -> 4400 | BL20: =SUMIF(Recibos!$D$4:$D$7493,Cobranza!$B20,Recibos!X$4:X$7493) -> 400 | BM20: =SUMIF(Recibos!$D$4:$D$7493,Cobranza!$B20,Recibos!Y$4:Y$7493) -> 400 | BN20: =SUMIF(Recibos!$D$4:$D$7493,Cobranza!$B20,Recibos!Z$4:Z$7493) -> 400 | BO20: =SUMIF(Recibos!$D$4:$D$7493,Cobranza!$B20,Recibos!AA$4:AA$7493) -> 400 | BP20: =SUMIF(Recibos!$D$4:$D$7493,Cobranza!$B20,Recibos!AB$4:AB$7493) -> 400 | BQ20: =SUMIF(Recibos!$D$4:$D$7493,Cobranza!$B20,Recibos!AC$4:AC$7493) -> 400 | BR20: =SUMIF(Recibos!$D$4:$D$7493,Cobranza!$B20,Recibos!AD$4:AD$7493) -> 400 | BS20: =SUMIF(Recibos!$D$4:$D$7493,Cobranza!$B20,Recibos!AE$4:AE$7493) -> 400 | ... BW20: =SUMIF(Recibos!$D$4:$D$7493,Cobranza!$B20,Recibos!AI$4:AI$7493) -> 0 | BX20: =SUM(BL20:BW20) -> 4400 | BY20: =SUMIF(Recibos!$D$4:$D$7493,Cobranza!$B20,Recibos!AK$4:AK$7493) -> 400 | BZ20: =SUMIF(Recibos!$D$4:$D$7493,Cobranza!$B20,Recibos!AL$4:AL$7493) -> 400 | CA20: =SUMIF(Recibos!$D$4:$D$7493,Cobranza!$B20,Recibos!AM$4:AM$7493) -> 400 | CB20: =SUMIF(Recibos!$D$4:$D$7493,Cobranza!$B20,Recibos!AN$4:AN$7493) -> 400 | CC20: =SUMIF(Recibos!$D$4:$D$7493,Cobranza!$B20,Recibos!AO$4:AO$7493) -> 400 | CD20: =SUMIF(Recibos!$D$4:$D$7493,Cobranza!$B20,Recibos!AP$4:AP$7493) -> 400 | CE20: =SUMIF(Recibos!$D$4:$D$7493,Cobranza!$B20,Recibos!AQ$4:AQ$7493) -> 400 | CF20: =SUMIF(Recibos!$D$4:$D$7493,Cobranza!$B20,Recibos!AR$4:AR$7493) -> 400 | ... CJ20: =SUMIF(Recibos!$D$4:$D$7493,Cobranza!$B20,Recibos!AV$4:AV$7493) -> 0 | CK20: =SUM(BY20:CJ20) -> 4400
B21: CL_23_ | C21: Rancho La Cuchilla No. 23 | D21: Ocampo | E21: 0 | F21: 0 | G21: 0 | H21: 0 | I21: 0 | J21: 200 | K21: =SUM(E21:J21) -> 200 | L21: 200 | M21: 200 | N21: 200 | O21: 0 | P21: 0 | Q21: 0 | R21: 0 | S21: 0 | T21: 0 | U21: 0 | V21: 0 | W21: 0 | X21: =SUM(L21:W21) -> 600 | Y21: 0 | Z21: 0 | AA21: 0 | AB21: 0 | AC21: 0 | AD21: 0 | AE21: 0 | AF21: 0 | AG21: 0 | AH21: 0 | AI21: 0 | AJ21: 0 | AK21: =SUM(Y21:AJ21) -> 0 | AL21: 0 | AM21: 0 | AN21: 0 | AO21: 0 | AP21: 0 | AQ21: 0 | AR21: 0 | AS21: 0 | AT21: 0 | AU21: 0 | AV21: 0 | AW21: 0 | AX21: =SUM(AL21:AW21) -> 0 | AY21: =SUMIF(Recibos!$D$4:$D$7493,Cobranza!$B21,Recibos!K$4:K$7493) -> 0 | AZ21: =SUMIF(Recibos!$D$4:$D$7493,Cobranza!$B21,Recibos!L$4:L$7493) -> 0 | BA21: =SUMIF(Recibos!$D$4:$D$7493,Cobranza!$B21,Recibos!M$4:M$7493) -> 0 | BB21: =SUMIF(Recibos!$D$4:$D$7493,Cobranza!$B21,Recibos!N$4:N$7493) -> 0 | BC21: =SUMIF(Recibos!$D$4:$D$7493,Cobranza!$B21,Recibos!O$4:O$7493) -> 0 | BD21: =SUMIF(Recibos!$D$4:$D$7493,Cobranza!$B21,Recibos!P$4:P$7493) -> 200 | BE21: =SUMIF(Recibos!$D$4:$D$7493,Cobranza!$B21,Recibos!Q$4:Q$7493) -> 200 | BF21: =SUMIF(Recibos!$D$4:$D$7493,Cobranza!$B21,Recibos!R$4:R$7493) -> 200 | ... BJ21: =SUMIF(Recibos!$D$4:$D$7493,Cobranza!$B21,Recibos!V$4:V$7493) -> 200 | BK21: =SUM(AY21:BJ21) -> 1400 | BL21: =SUMIF(Recibos!$D$4:$D$7493,Cobranza!$B21,Recibos!X$4:X$7493) -> 200 | BM21: =SUMIF(Recibos!$D$4:$D$7493,Cobranza!$B21,Recibos!Y$4:Y$7493) -> 200 | BN21: =SUMIF(Recibos!$D$4:$D$7493,Cobranza!$B21,Recibos!Z$4:Z$7493) -> 200 | BO21: =SUMIF(Recibos!$D$4:$D$7493,Cobranza!$B21,Recibos!AA$4:AA$7493) -> 200 | BP21: =SUMIF(Recibos!$D$4:$D$7493,Cobranza!$B21,Recibos!AB$4:AB$7493) -> 200 | BQ21: =SUMIF(Recibos!$D$4:$D$7493,Cobranza!$B21,Recibos!AC$4:AC$7493) -> 200 | BR21: =SUMIF(Recibos!$D$4:$D$7493,Cobranza!$B21,Recibos!AD$4:AD$7493) -> 0 | BS21: =SUMIF(Recibos!$D$4:$D$7493,Cobranza!$B21,Recibos!AE$4:AE$7493) -> 0 | ... BW21: =SUMIF(Recibos!$D$4:$D$7493,Cobranza!$B21,Recibos!AI$4:AI$7493) -> 0 | BX21: =SUM(BL21:BW21) -> 1200 | BY21: =SUMIF(Recibos!$D$4:$D$7493,Cobranza!$B21,Recibos!AK$4:AK$7493) -> 0 | BZ21: =SUMIF(Recibos!$D$4:$D$7493,Cobranza!$B21,Recibos!AL$4:AL$7493) -> 0 | CA21: =SUMIF(Recibos!$D$4:$D$7493,Cobranza!$B21,Recibos!AM$4:AM$7493) -> 0 | CB21: =SUMIF(Recibos!$D$4:$D$7493,Cobranza!$B21,Recibos!AN$4:AN$7493) -> 0 | CC21: =SUMIF(Recibos!$D$4:$D$7493,Cobranza!$B21,Recibos!AO$4:AO$7493) -> 0 | CD21: =SUMIF(Recibos!$D$4:$D$7493,Cobranza!$B21,Recibos!AP$4:AP$7493) -> 0 | CE21: =SUMIF(Recibos!$D$4:$D$7493,Cobranza!$B21,Recibos!AQ$4:AQ$7493) -> 0 | CF21: =SUMIF(Recibos!$D$4:$D$7493,Cobranza!$B21,Recibos!AR$4:AR$7493) -> 0 | ... CJ21: =SUMIF(Recibos!$D$4:$D$7493,Cobranza!$B21,Recibos!AV$4:AV$7493) -> 0 | CK21: =SUM(BY21:CJ21) -> 0
B22: CL_25_ | C22: Rancho La Cuchilla No. 25 | D22: García de León | E22: 0 | F22: 0 | G22: 0 | H22: 0 | I22: 0 | J22: 0 | K22: =SUM(E22:J22) -> 0 | L22: 0 | M22: 0 | N22: 0 | O22: 0 | P22: 0 | Q22: 0 | R22: 0 | S22: 0 | T22: 0 | U22: 0 | V22: 0 | W22: 0 | X22: =SUM(L22:W22) -> 0 | Y22: 0 | Z22: 0 | AA22: 0 | AB22: 0 | AC22: 0 | AD22: 0 | AE22: 0 | AF22: 0 | AG22: 0 | AH22: 0 | AI22: 0 | AJ22: 0 | AK22: =SUM(Y22:AJ22) -> 0 | AL22: 0 | AM22: 0 | AN22: 0 | AO22: 0 | AP22: 0 | AQ22: 0 | AR22: 0 | AS22: 0 | AT22: 0 | AU22: 0 | AV22: 0 | AW22: 0 | AX22: =SUM(AL22:AW22) -> 0 | AY22: =SUMIF(Recibos!$D$4:$D$7493,Cobranza!$B22,Recibos!K$4:K$7493) -> 0 | AZ22: =SUMIF(Recibos!$D$4:$D$7493,Cobranza!$B22,Recibos!L$4:L$7493) -> 0 | BA22: =SUMIF(Recibos!$D$4:$D$7493,Cobranza!$B22,Recibos!M$4:M$7493) -> 0 | BB22: =SUMIF(Recibos!$D$4:$D$7493,Cobranza!$B22,Recibos!N$4:N$7493) -> 0 | BC22: =SUMIF(Recibos!$D$4:$D$7493,Cobranza!$B22,Recibos!O$4:O$7493) -> 0 | BD22: =SUMIF(Recibos!$D$4:$D$7493,Cobranza!$B22,Recibos!P$4:P$7493) -> 0 | BE22: =SUMIF(Recibos!$D$4:$D$7493,Cobranza!$B22,Recibos!Q$4:Q$7493) -> 0 | BF22: =SUMIF(Recibos!$D$4:$D$7493,Cobranza!$B22,Recibos!R$4:R$7493) -> 0 | ... BJ22: =SUMIF(Recibos!$D$4:$D$7493,Cobranza!$B22,Recibos!V$4:V$7493) -> 0 | BK22: =SUM(AY22:BJ22) -> 0 | BL22: =SUMIF(Recibos!$D$4:$D$7493,Cobranza!$B22,Recibos!X$4:X$7493) -> 0 | BM22: =SUMIF(Recibos!$D$4:$D$7493,Cobranza!$B22,Recibos!Y$4:Y$7493) -> 0 | BN22: =SUMIF(Recibos!$D$4:$D$7493,Cobranza!$B22,Recibos!Z$4:Z$7493) -> 0 | BO22: =SUMIF(Recibos!$D$4:$D$7493,Cobranza!$B22,Recibos!AA$4:AA$7493) -> 0 | BP22: =SUMIF(Recibos!$D$4:$D$7493,Cobranza!$B22,Recibos!AB$4:AB$7493) -> 0 | BQ22: =SUMIF(Recibos!$D$4:$D$7493,Cobranza!$B22,Recibos!AC$4:AC$7493) -> 0 | BR22: =SUMIF(Recibos!$D$4:$D$7493,Cobranza!$B22,Recibos!AD$4:AD$7493) -> 0 | BS22: =SUMIF(Recibos!$D$4:$D$7493,Cobranza!$B22,Recibos!AE$4:AE$7493) -> 0 | ... BW22: =SUMIF(Recibos!$D$4:$D$7493,Cobranza!$B22,Recibos!AI$4:AI$7493) -> 0 | BX22: =SUM(BL22:BW22) -> 0 | BY22: =SUMIF(Recibos!$D$4:$D$7493,Cobranza!$B22,Recibos!AK$4:AK$7493) -> 0 | BZ22: =SUMIF(Recibos!$D$4:$D$7493,Cobranza!$B22,Recibos!AL$4:AL$7493) -> 0 | CA22: =SUMIF(Recibos!$D$4:$D$7493,Cobranza!$B22,Recibos!AM$4:AM$7493) -> 0 | CB22: =SUMIF(Recibos!$D$4:$D$7493,Cobranza!$B22,Recibos!AN$4:AN$7493) -> 0 | CC22: =SUMIF(Recibos!$D$4:$D$7493,Cobranza!$B22,Recibos!AO$4:AO$7493) -> 0 | CD22: =SUMIF(Recibos!$D$4:$D$7493,Cobranza!$B22,Recibos!AP$4:AP$7493) -> 0 | CE22: =SUMIF(Recibos!$D$4:$D$7493,Cobranza!$B22,Recibos!AQ$4:AQ$7493) -> 0 | CF22: =SUMIF(Recibos!$D$4:$D$7493,Cobranza!$B22,Recibos!AR$4:AR$7493) -> 0 | ... CJ22: =SUMIF(Recibos!$D$4:$D$7493,Cobranza!$B22,Recibos!AV$4:AV$7493) -> 0 | CK22: =SUM(BY22:CJ22) -> 0
B23: CL_27_ | C23: Rancho La Cuchilla No. 27 | D23: Montoya | E23: 0 | F23: 0 | G23: 0 | H23: 0 | I23: 0 | J23: 0 | K23: =SUM(E23:J23) -> 0 | L23: 0 | M23: 0 | N23: 0 | O23: 0 | P23: 0 | Q23: 0 | R23: 0 | S23: 0 | T23: 0 | U23: 0 | V23: 0 | W23: 0 | X23: =SUM(L23:W23) -> 0 | Y23: 0 | Z23: 0 | AA23: 0 | AB23: 0 | AC23: 0 | AD23: 0 | AE23: 0 | AF23: 0 | AG23: 0 | AH23: 0 | AI23: 0 | AJ23: 0 | AK23: =SUM(Y23:AJ23) -> 0 | AL23: 0 | AM23: 0 | AN23: 0 | AO23: 0 | AP23: 0 | AQ23: 0 | AR23: 0 | AS23: 0 | AT23: 0 | AU23: 0 | AV23: 0 | AW23: 0 | AX23: =SUM(AL23:AW23) -> 0 | AY23: =SUMIF(Recibos!$D$4:$D$7493,Cobranza!$B23,Recibos!K$4:K$7493) -> 0 | AZ23: =SUMIF(Recibos!$D$4:$D$7493,Cobranza!$B23,Recibos!L$4:L$7493) -> 0 | BA23: =SUMIF(Recibos!$D$4:$D$7493,Cobranza!$B23,Recibos!M$4:M$7493) -> 0 | BB23: =SUMIF(Recibos!$D$4:$D$7493,Cobranza!$B23,Recibos!N$4:N$7493) -> 0 | BC23: =SUMIF(Recibos!$D$4:$D$7493,Cobranza!$B23,Recibos!O$4:O$7493) -> 0 | BD23: =SUMIF(Recibos!$D$4:$D$7493,Cobranza!$B23,Recibos!P$4:P$7493) -> 0 | BE23: =SUMIF(Recibos!$D$4:$D$7493,Cobranza!$B23,Recibos!Q$4:Q$7493) -> 0 | BF23: =SUMIF(Recibos!$D$4:$D$7493,Cobranza!$B23,Recibos!R$4:R$7493) -> 0 | ... BJ23: =SUMIF(Recibos!$D$4:$D$7493,Cobranza!$B23,Recibos!V$4:V$7493) -> 0 | BK23: =SUM(AY23:BJ23) -> 0 | BL23: =SUMIF(Recibos!$D$4:$D$7493,Cobranza!$B23,Recibos!X$4:X$7493) -> 0 | BM23: =SUMIF(Recibos!$D$4:$D$7493,Cobranza!$B23,Recibos!Y$4:Y$7493) -> 0 | BN23: =SUMIF(Recibos!$D$4:$D$7493,Cobranza!$B23,Recibos!Z$4:Z$7493) -> 0 | BO23: =SUMIF(Recibos!$D$4:$D$7493,Cobranza!$B23,Recibos!AA$4:AA$7493) -> 0 | BP23: =SUMIF(Recibos!$D$4:$D$7493,Cobranza!$B23,Recibos!AB$4:AB$7493) -> 0 | BQ23: =SUMIF(Recibos!$D$4:$D$7493,Cobranza!$B23,Recibos!AC$4:AC$7493) -> 0 | BR23: =SUMIF(Recibos!$D$4:$D$7493,Cobranza!$B23,Recibos!AD$4:AD$7493) -> 0 | BS23: =SUMIF(Recibos!$D$4:$D$7493,Cobranza!$B23,Recibos!AE$4:AE$7493) -> 0 | ... BW23: =SUMIF(Recibos!$D$4:$D$7493,Cobranza!$B23,Recibos!AI$4:AI$7493) -> 0 | BX23: =SUM(BL23:BW23) -> 0 | BY23: =SUMIF(Recibos!$D$4:$D$7493,Cobranza!$B23,Recibos!AK$4:AK$7493) -> 0 | BZ23: =SUMIF(Recibos!$D$4:$D$7493,Cobranza!$B23,Recibos!AL$4:AL$7493) -> 0 | CA23: =SUMIF(Recibos!$D$4:$D$7493,Cobranza!$B23,Recibos!AM$4:AM$7493) -> 0 | CB23: =SUMIF(Recibos!$D$4:$D$7493,Cobranza!$B23,Recibos!AN$4:AN$7493) -> 0 | CC23: =SUMIF(Recibos!$D$4:$D$7493,Cobranza!$B23,Recibos!AO$4:AO$7493) -> 0 | CD23: =SUMIF(Recibos!$D$4:$D$7493,Cobranza!$B23,Recibos!AP$4:AP$7493) -> 0 | CE23: =SUMIF(Recibos!$D$4:$D$7493,Cobranza!$B23,Recibos!AQ$4:AQ$7493) -> 0 | CF23: =SUMIF(Recibos!$D$4:$D$7493,Cobranza!$B23,Recibos!AR$4:AR$7493) -> 0 | ... CJ23: =SUMIF(Recibos!$D$4:$D$7493,Cobranza!$B23,Recibos!AV$4:AV$7493) -> 0 | CK23: =SUM(BY23:CJ23) -> 0
B24: CL_28_ | C24: Rancho La Cuchilla No. 28 | D24: Prado de los S. | E24: 0 | F24: 0 | G24: 0 | H24: 0 | I24: 0 | J24: 0 | K24: =SUM(E24:J24) -> 0 | L24: 0 | M24: 0 | N24: 0 | O24: 0 | P24: 0 | Q24: 0 | R24: 0 | S24: 0 | T24: 0 | U24: 0 | V24: 0 | W24: 0 | X24: =SUM(L24:W24) -> 0 | Y24: 400 | Z24: 400 | AA24: 400 | AB24: 400 | AC24: 400 | AD24: 400 | AE24: 400 | AF24: 400 | AG24: 400 | AH24: 400 | AI24: 400 | AJ24: 0 | AK24: =SUM(Y24:AJ24) -> 4400 | AL24: 400 | AM24: 400 | AN24: 400 | AO24: 400 | AP24: 400 | AQ24: 400 | AR24: 400 | AS24: 400 | AT24: 400 | AU24: 400 | AV24: 400 | AW24: 0 | AX24: =SUM(AL24:AW24) -> 4400 | AY24: =SUMIF(Recibos!$D$4:$D$7493,Cobranza!$B24,Recibos!K$4:K$7493) -> 400 | AZ24: =SUMIF(Recibos!$D$4:$D$7493,Cobranza!$B24,Recibos!L$4:L$7493) -> 400 | BA24: =SUMIF(Recibos!$D$4:$D$7493,Cobranza!$B24,Recibos!M$4:M$7493) -> 400 | BB24: =SUMIF(Recibos!$D$4:$D$7493,Cobranza!$B24,Recibos!N$4:N$7493) -> 400 | BC24: =SUMIF(Recibos!$D$4:$D$7493,Cobranza!$B24,Recibos!O$4:O$7493) -> 400 | BD24: =SUMIF(Recibos!$D$4:$D$7493,Cobranza!$B24,Recibos!P$4:P$7493) -> 400 | BE24: =SUMIF(Recibos!$D$4:$D$7493,Cobranza!$B24,Recibos!Q$4:Q$7493) -> 400 | BF24: =SUMIF(Recibos!$D$4:$D$7493,Cobranza!$B24,Recibos!R$4:R$7493) -> 400 | ... BJ24: =SUMIF(Recibos!$D$4:$D$7493,Cobranza!$B24,Recibos!V$4:V$7493) -> 400 | BK24: =SUM(AY24:BJ24) -> 4800 | BL24: =SUMIF(Recibos!$D$4:$D$7493,Cobranza!$B24,Recibos!X$4:X$7493) -> 400 | BM24: =SUMIF(Recibos!$D$4:$D$7493,Cobranza!$B24,Recibos!Y$4:Y$7493) -> 400 | BN24: =SUMIF(Recibos!$D$4:$D$7493,Cobranza!$B24,Recibos!Z$4:Z$7493) -> 400 | BO24: =SUMIF(Recibos!$D$4:$D$7493,Cobranza!$B24,Recibos!AA$4:AA$7493) -> 400 | BP24: =SUMIF(Recibos!$D$4:$D$7493,Cobranza!$B24,Recibos!AB$4:AB$7493) -> 400 | BQ24: =SUMIF(Recibos!$D$4:$D$7493,Cobranza!$B24,Recibos!AC$4:AC$7493) -> 400 | BR24: =SUMIF(Recibos!$D$4:$D$7493,Cobranza!$B24,Recibos!AD$4:AD$7493) -> 400 | BS24: =SUMIF(Recibos!$D$4:$D$7493,Cobranza!$B24,Recibos!AE$4:AE$7493) -> 400 | ... BW24: =SUMIF(Recibos!$D$4:$D$7493,Cobranza!$B24,Recibos!AI$4:AI$7493) -> 0 | BX24: =SUM(BL24:BW24) -> 4400 | BY24: =SUMIF(Recibos!$D$4:$D$7493,Cobranza!$B24,Recibos!AK$4:AK$7493) -> 400 | BZ24: =SUMIF(Recibos!$D$4:$D$7493,Cobranza!$B24,Recibos!AL$4:AL$7493) -> 400 | CA24: =SUMIF(Recibos!$D$4:$D$7493,Cobranza!$B24,Recibos!AM$4:AM$7493) -> 400 | CB24: =SUMIF(Recibos!$D$4:$D$7493,Cobranza!$B24,Recibos!AN$4:AN$7493) -> 400 | CC24: =SUMIF(Recibos!$D$4:$D$7493,Cobranza!$B24,Recibos!AO$4:AO$7493) -> 400 | CD24: =SUMIF(Recibos!$D$4:$D$7493,Cobranza!$B24,Recibos!AP$4:AP$7493) -> 400 | CE24: =SUMIF(Recibos!$D$4:$D$7493,Cobranza!$B24,Recibos!AQ$4:AQ$7493) -> 400 | CF24: =SUMIF(Recibos!$D$4:$D$7493,Cobranza!$B24,Recibos!AR$4:AR$7493) -> 400 | ... CJ24: =SUMIF(Recibos!$D$4:$D$7493,Cobranza!$B24,Recibos!AV$4:AV$7493) -> 400 | CK24: =SUM(BY24:CJ24) -> 4800
B25: CL_29_ | C25: Rancho La Cuchilla No. 29 | D25: Vega Sánchez C. | E25: 0 | F25: 0 | G25: 0 | H25: 0 | I25: 0 | J25: 0 | K25: =SUM(E25:J25) -> 0 | L25: 300 | M25: 300 | N25: 300 | O25: 300 | P25: 300 | Q25: 300 | R25: 0 | S25: 300 | T25: 300 | U25: 300 | V25: 0 | W25: 300 | X25: =SUM(L25:W25) -> 3000 | Y25: 300 | Z25: 300 | AA25: 300 | AB25: 300 | AC25: 300 | AD25: 300 | AE25: 300 | AF25: 300 | AG25: 300 | AH25: 300 | AI25: 400 | AJ25: 400 | AK25: =SUM(Y25:AJ25) -> 3800 | AL25: 400 | AM25: 400 | AN25: 400 | AO25: 400 | AP25: 400 | AQ25: 400 | AR25: 400 | AS25: 400 | AT25: 400 | AU25: 400 | AV25: 400 | AW25: 400 | AX25: =SUM(AL25:AW25) -> 4800 | AY25: =SUMIF(Recibos!$D$4:$D$7493,Cobranza!$B25,Recibos!K$4:K$7493) -> 400 | AZ25: =SUMIF(Recibos!$D$4:$D$7493,Cobranza!$B25,Recibos!L$4:L$7493) -> 400 | BA25: =SUMIF(Recibos!$D$4:$D$7493,Cobranza!$B25,Recibos!M$4:M$7493) -> 400 | BB25: =SUMIF(Recibos!$D$4:$D$7493,Cobranza!$B25,Recibos!N$4:N$7493) -> 400 | BC25: =SUMIF(Recibos!$D$4:$D$7493,Cobranza!$B25,Recibos!O$4:O$7493) -> 400 | BD25: =SUMIF(Recibos!$D$4:$D$7493,Cobranza!$B25,Recibos!P$4:P$7493) -> 400 | BE25: =SUMIF(Recibos!$D$4:$D$7493,Cobranza!$B25,Recibos!Q$4:Q$7493) -> 400 | BF25: =SUMIF(Recibos!$D$4:$D$7493,Cobranza!$B25,Recibos!R$4:R$7493) -> 400 | ... BJ25: =SUMIF(Recibos!$D$4:$D$7493,Cobranza!$B25,Recibos!V$4:V$7493) -> 400 | BK25: =SUM(AY25:BJ25) -> 4800 | BL25: =SUMIF(Recibos!$D$4:$D$7493,Cobranza!$B25,Recibos!X$4:X$7493) -> 400 | BM25: =SUMIF(Recibos!$D$4:$D$7493,Cobranza!$B25,Recibos!Y$4:Y$7493) -> 400 | BN25: =SUMIF(Recibos!$D$4:$D$7493,Cobranza!$B25,Recibos!Z$4:Z$7493) -> 400 | BO25: =SUMIF(Recibos!$D$4:$D$7493,Cobranza!$B25,Recibos!AA$4:AA$7493) -> 400 | BP25: =SUMIF(Recibos!$D$4:$D$7493,Cobranza!$B25,Recibos!AB$4:AB$7493) -> 400 | BQ25: =SUMIF(Recibos!$D$4:$D$7493,Cobranza!$B25,Recibos!AC$4:AC$7493) -> 400 | BR25: =SUMIF(Recibos!$D$4:$D$7493,Cobranza!$B25,Recibos!AD$4:AD$7493) -> 400 | BS25: =SUMIF(Recibos!$D$4:$D$7493,Cobranza!$B25,Recibos!AE$4:AE$7493) -> 400 | ... BW25: =SUMIF(Recibos!$D$4:$D$7493,Cobranza!$B25,Recibos!AI$4:AI$7493) -> 400 | BX25: =SUM(BL25:BW25) -> 4800 | BY25: =SUMIF(Recibos!$D$4:$D$7493,Cobranza!$B25,Recibos!AK$4:AK$7493) -> 400 | BZ25: =SUMIF(Recibos!$D$4:$D$7493,Cobranza!$B25,Recibos!AL$4:AL$7493) -> 400 | CA25: =SUMIF(Recibos!$D$4:$D$7493,Cobranza!$B25,Recibos!AM$4:AM$7493) -> 400 | CB25: =SUMIF(Recibos!$D$4:$D$7493,Cobranza!$B25,Recibos!AN$4:AN$7493) -> 400 | CC25: =SUMIF(Recibos!$D$4:$D$7493,Cobranza!$B25,Recibos!AO$4:AO$7493) -> 400 | CD25: =SUMIF(Recibos!$D$4:$D$7493,Cobranza!$B25,Recibos!AP$4:AP$7493) -> 400 | CE25: =SUMIF(Recibos!$D$4:$D$7493,Cobranza!$B25,Recibos!AQ$4:AQ$7493) -> 400 | CF25: =SUMIF(Recibos!$D$4:$D$7493,Cobranza!$B25,Recibos!AR$4:AR$7493) -> 400 | ... CJ25: =SUMIF(Recibos!$D$4:$D$7493,Cobranza!$B25,Recibos!AV$4:AV$7493) -> 0 | CK25: =SUM(BY25:CJ25) -> 3200
B26: CL_30_ | C26: Rancho La Cuchilla No. 30 | D26: Ruiz Navarrete | E26: 0 | F26: 0 | G26: 0 | H26: 0 | I26: 0 | J26: 0 | K26: =SUM(E26:J26) -> 0 | L26: 0 | M26: 0 | N26: 0 | O26: 0 | P26: 0 | Q26: 0 | R26: 0 | S26: 0 | T26: 0 | U26: 0 | V26: 0 | W26: 0 | X26: =SUM(L26:W26) -> 0 | Y26: 0 | Z26: 0 | AA26: 0 | AB26: 0 | AC26: 0 | AD26: 0 | AE26: 0 | AF26: 0 | AG26: 0 | AH26: 0 | AI26: 0 | AJ26: 0 | AK26: =SUM(Y26:AJ26) -> 0 | AL26: 0 | AM26: 0 | AN26: 0 | AO26: 0 | AP26: 0 | AQ26: 0 | AR26: 0 | AS26: 0 | AT26: 0 | AU26: 0 | AV26: 0 | AW26: 0 | AX26: =SUM(AL26:AW26) -> 0 | AY26: =SUMIF(Recibos!$D$4:$D$7493,Cobranza!$B26,Recibos!K$4:K$7493) -> 0 | AZ26: =SUMIF(Recibos!$D$4:$D$7493,Cobranza!$B26,Recibos!L$4:L$7493) -> 0 | BA26: =SUMIF(Recibos!$D$4:$D$7493,Cobranza!$B26,Recibos!M$4:M$7493) -> 0 | BB26: =SUMIF(Recibos!$D$4:$D$7493,Cobranza!$B26,Recibos!N$4:N$7493) -> 0 | BC26: =SUMIF(Recibos!$D$4:$D$7493,Cobranza!$B26,Recibos!O$4:O$7493) -> 0 | BD26: =SUMIF(Recibos!$D$4:$D$7493,Cobranza!$B26,Recibos!P$4:P$7493) -> 0 | BE26: =SUMIF(Recibos!$D$4:$D$7493,Cobranza!$B26,Recibos!Q$4:Q$7493) -> 0 | BF26: =SUMIF(Recibos!$D$4:$D$7493,Cobranza!$B26,Recibos!R$4:R$7493) -> 0 | ... BJ26: =SUMIF(Recibos!$D$4:$D$7493,Cobranza!$B26,Recibos!V$4:V$7493) -> 0 | BK26: =SUM(AY26:BJ26) -> 0 | BL26: =SUMIF(Recibos!$D$4:$D$7493,Cobranza!$B26,Recibos!X$4:X$7493) -> 0 | BM26: =SUMIF(Recibos!$D$4:$D$7493,Cobranza!$B26,Recibos!Y$4:Y$7493) -> 0 | BN26: =SUMIF(Recibos!$D$4:$D$7493,Cobranza!$B26,Recibos!Z$4:Z$7493) -> 0 | BO26: =SUMIF(Recibos!$D$4:$D$7493,Cobranza!$B26,Recibos!AA$4:AA$7493) -> 0 | BP26: =SUMIF(Recibos!$D$4:$D$7493,Cobranza!$B26,Recibos!AB$4:AB$7493) -> 0 | BQ26: =SUMIF(Recibos!$D$4:$D$7493,Cobranza!$B26,Recibos!AC$4:AC$7493) -> 0 | BR26: =SUMIF(Recibos!$D$4:$D$7493,Cobranza!$B26,Recibos!AD$4:AD$7493) -> 0 | BS26: =SUMIF(Recibos!$D$4:$D$7493,Cobranza!$B26,Recibos!AE$4:AE$7493) -> 0 | ... BW26: =SUMIF(Recibos!$D$4:$D$7493,Cobranza!$B26,Recibos!AI$4:AI$7493) -> 0 | BX26: =SUM(BL26:BW26) -> 0 | BY26: =SUMIF(Recibos!$D$4:$D$7493,Cobranza!$B26,Recibos!AK$4:AK$7493) -> 0 | BZ26: =SUMIF(Recibos!$D$4:$D$7493,Cobranza!$B26,Recibos!AL$4:AL$7493) -> 0 | CA26: =SUMIF(Recibos!$D$4:$D$7493,Cobranza!$B26,Recibos!AM$4:AM$7493) -> 0 | CB26: =SUMIF(Recibos!$D$4:$D$7493,Cobranza!$B26,Recibos!AN$4:AN$7493) -> 0 | CC26: =SUMIF(Recibos!$D$4:$D$7493,Cobranza!$B26,Recibos!AO$4:AO$7493) -> 0 | CD26: =SUMIF(Recibos!$D$4:$D$7493,Cobranza!$B26,Recibos!AP$4:AP$7493) -> 0 | CE26: =SUMIF(Recibos!$D$4:$D$7493,Cobranza!$B26,Recibos!AQ$4:AQ$7493) -> 0 | CF26: =SUMIF(Recibos!$D$4:$D$7493,Cobranza!$B26,Recibos!AR$4:AR$7493) -> 0 | ... CJ26: =SUMIF(Recibos!$D$4:$D$7493,Cobranza!$B26,Recibos!AV$4:AV$7493) -> 0 | CK26: =SUM(BY26:CJ26) -> 0
B27: CL_31_ | C27: Rancho La Cuchilla No. 31 | D27: Lince | E27: 0 | F27: 0 | G27: 0 | H27: 0 | I27: 0 | J27: 0 | K27: =SUM(E27:J27) -> 0 | L27: 300 | M27: 300 | N27: 300 | O27: 400 | P27: 300 | Q27: 300 | R27: 300 | S27: 300 | T27: 300 | U27: 400 | V27: 400 | W27: 400 | X27: =SUM(L27:W27) -> 4000 | Y27: 300 | Z27: 0 | AA27: 0 | AB27: 0 | AC27: 400 | AD27: 300 | AE27: 300 | AF27: 300 | AG27: 0 | AH27: 0 | AI27: 0 | AJ27: 0 | AK27: =SUM(Y27:AJ27) -> 1600 | AL27: 0 | AM27: 0 | AN27: 0 | AO27: 0 | AP27: 0 | AQ27: 0 | AR27: 0 | AS27: 0 | AT27: 0 | AU27: 0 | AV27: 0 | AW27: 0 | AX27: =SUM(AL27:AW27) -> 0 | AY27: =SUMIF(Recibos!$D$4:$D$7493,Cobranza!$B27,Recibos!K$4:K$7493) -> 0 | AZ27: =SUMIF(Recibos!$D$4:$D$7493,Cobranza!$B27,Recibos!L$4:L$7493) -> 0 | BA27: =SUMIF(Recibos!$D$4:$D$7493,Cobranza!$B27,Recibos!M$4:M$7493) -> 0 | BB27: =SUMIF(Recibos!$D$4:$D$7493,Cobranza!$B27,Recibos!N$4:N$7493) -> 0 | BC27: =SUMIF(Recibos!$D$4:$D$7493,Cobranza!$B27,Recibos!O$4:O$7493) -> 0 | BD27: =SUMIF(Recibos!$D$4:$D$7493,Cobranza!$B27,Recibos!P$4:P$7493) -> 0 | BE27: =SUMIF(Recibos!$D$4:$D$7493,Cobranza!$B27,Recibos!Q$4:Q$7493) -> 0 | BF27: =SUMIF(Recibos!$D$4:$D$7493,Cobranza!$B27,Recibos!R$4:R$7493) -> 0 | ... BJ27: =SUMIF(Recibos!$D$4:$D$7493,Cobranza!$B27,Recibos!V$4:V$7493) -> 300 | BK27: =SUM(AY27:BJ27) -> 300 | BL27: =SUMIF(Recibos!$D$4:$D$7493,Cobranza!$B27,Recibos!X$4:X$7493) -> 300 | BM27: =SUMIF(Recibos!$D$4:$D$7493,Cobranza!$B27,Recibos!Y$4:Y$7493) -> 300 | BN27: =SUMIF(Recibos!$D$4:$D$7493,Cobranza!$B27,Recibos!Z$4:Z$7493) -> 300 | BO27: =SUMIF(Recibos!$D$4:$D$7493,Cobranza!$B27,Recibos!AA$4:AA$7493) -> 300 | BP27: =SUMIF(Recibos!$D$4:$D$7493,Cobranza!$B27,Recibos!AB$4:AB$7493) -> 300 | BQ27: =SUMIF(Recibos!$D$4:$D$7493,Cobranza!$B27,Recibos!AC$4:AC$7493) -> 300 | BR27: =SUMIF(Recibos!$D$4:$D$7493,Cobranza!$B27,Recibos!AD$4:AD$7493) -> 300 | BS27: =SUMIF(Recibos!$D$4:$D$7493,Cobranza!$B27,Recibos!AE$4:AE$7493) -> 300 | ... BW27: =SUMIF(Recibos!$D$4:$D$7493,Cobranza!$B27,Recibos!AI$4:AI$7493) -> 300 | BX27: =SUM(BL27:BW27) -> 3600 | BY27: =SUMIF(Recibos!$D$4:$D$7493,Cobranza!$B27,Recibos!AK$4:AK$7493) -> 300 | BZ27: =SUMIF(Recibos!$D$4:$D$7493,Cobranza!$B27,Recibos!AL$4:AL$7493) -> 300 | CA27: =SUMIF(Recibos!$D$4:$D$7493,Cobranza!$B27,Recibos!AM$4:AM$7493) -> 300 | CB27: =SUMIF(Recibos!$D$4:$D$7493,Cobranza!$B27,Recibos!AN$4:AN$7493) -> 300 | CC27: =SUMIF(Recibos!$D$4:$D$7493,Cobranza!$B27,Recibos!AO$4:AO$7493) -> 300 | CD27: =SUMIF(Recibos!$D$4:$D$7493,Cobranza!$B27,Recibos!AP$4:AP$7493) -> 0 | CE27: =SUMIF(Recibos!$D$4:$D$7493,Cobranza!$B27,Recibos!AQ$4:AQ$7493) -> 0 | CF27: =SUMIF(Recibos!$D$4:$D$7493,Cobranza!$B27,Recibos!AR$4:AR$7493) -> 0 | ... CJ27: =SUMIF(Recibos!$D$4:$D$7493,Cobranza!$B27,Recibos!AV$4:AV$7493) -> 0 | CK27: =SUM(BY27:CJ27) -> 1500
B28: CL_32_ | C28: Rancho La Cuchilla No. 32 | D28: Hernández | E28: 0 | F28: 0 | G28: 300 | H28: 300 | I28: 300 | J28: 300 | K28: =SUM(E28:J28) -> 1200 | L28: 300 | M28: 300 | N28: 300 | O28: 300 | P28: 300 | Q28: 300 | R28: 300 | S28: 300 | T28: 300 | U28: 400 | V28: 400 | W28: 400 | X28: =SUM(L28:W28) -> 3900 | Y28: 400 | Z28: 400 | AA28: 400 | AB28: 400 | AC28: 400 | AD28: 0 | AE28: 800 | AF28: 400 | AG28: 400 | AH28: 400 | AI28: 400 | AJ28: 400 | AK28: =SUM(Y28:AJ28) -> 4800 | AL28: 400 | AM28: 400 | AN28: 400 | AO28: 400 | AP28: 400 | AQ28: 400 | AR28: 400 | AS28: 400 | AT28: 400 | AU28: 400 | AV28: 400 | AW28: 400 | AX28: =SUM(AL28:AW28) -> 4800 | AY28: =SUMIF(Recibos!$D$4:$D$7493,Cobranza!$B28,Recibos!K$4:K$7493) -> 400 | AZ28: =SUMIF(Recibos!$D$4:$D$7493,Cobranza!$B28,Recibos!L$4:L$7493) -> 400 | BA28: =SUMIF(Recibos!$D$4:$D$7493,Cobranza!$B28,Recibos!M$4:M$7493) -> 400 | BB28: =SUMIF(Recibos!$D$4:$D$7493,Cobranza!$B28,Recibos!N$4:N$7493) -> 400 | BC28: =SUMIF(Recibos!$D$4:$D$7493,Cobranza!$B28,Recibos!O$4:O$7493) -> 400 | BD28: =SUMIF(Recibos!$D$4:$D$7493,Cobranza!$B28,Recibos!P$4:P$7493) -> 400 | BE28: =SUMIF(Recibos!$D$4:$D$7493,Cobranza!$B28,Recibos!Q$4:Q$7493) -> 400 | BF28: =SUMIF(Recibos!$D$4:$D$7493,Cobranza!$B28,Recibos!R$4:R$7493) -> 400 | ... BJ28: =SUMIF(Recibos!$D$4:$D$7493,Cobranza!$B28,Recibos!V$4:V$7493) -> 400 | BK28: =SUM(AY28:BJ28) -> 4800 | BL28: =SUMIF(Recibos!$D$4:$D$7493,Cobranza!$B28,Recibos!X$4:X$7493) -> 0 | BM28: =SUMIF(Recibos!$D$4:$D$7493,Cobranza!$B28,Recibos!Y$4:Y$7493) -> 400 | BN28: =SUMIF(Recibos!$D$4:$D$7493,Cobranza!$B28,Recibos!Z$4:Z$7493) -> 400 | BO28: =SUMIF(Recibos!$D$4:$D$7493,Cobranza!$B28,Recibos!AA$4:AA$7493) -> 400 | BP28: =SUMIF(Recibos!$D$4:$D$7493,Cobranza!$B28,Recibos!AB$4:AB$7493) -> 400 | BQ28: =SUMIF(Recibos!$D$4:$D$7493,Cobranza!$B28,Recibos!AC$4:AC$7493) -> 400 | BR28: =SUMIF(Recibos!$D$4:$D$7493,Cobranza!$B28,Recibos!AD$4:AD$7493) -> 400 | BS28: =SUMIF(Recibos!$D$4:$D$7493,Cobranza!$B28,Recibos!AE$4:AE$7493) -> 400 | ... BW28: =SUMIF(Recibos!$D$4:$D$7493,Cobranza!$B28,Recibos!AI$4:AI$7493) -> 400 | BX28: =SUM(BL28:BW28) -> 4400 | BY28: =SUMIF(Recibos!$D$4:$D$7493,Cobranza!$B28,Recibos!AK$4:AK$7493) -> 400 | BZ28: =SUMIF(Recibos!$D$4:$D$7493,Cobranza!$B28,Recibos!AL$4:AL$7493) -> 400 | CA28: =SUMIF(Recibos!$D$4:$D$7493,Cobranza!$B28,Recibos!AM$4:AM$7493) -> 400 | CB28: =SUMIF(Recibos!$D$4:$D$7493,Cobranza!$B28,Recibos!AN$4:AN$7493) -> 400 | CC28: =SUMIF(Recibos!$D$4:$D$7493,Cobranza!$B28,Recibos!AO$4:AO$7493) -> 400 | CD28: =SUMIF(Recibos!$D$4:$D$7493,Cobranza!$B28,Recibos!AP$4:AP$7493) -> 400 | CE28: =SUMIF(Recibos!$D$4:$D$7493,Cobranza!$B28,Recibos!AQ$4:AQ$7493) -> 400 | CF28: =SUMIF(Recibos!$D$4:$D$7493,Cobranza!$B28,Recibos!AR$4:AR$7493) -> 400 | ... CJ28: =SUMIF(Recibos!$D$4:$D$7493,Cobranza!$B28,Recibos!AV$4:AV$7493) -> 0 | CK28: =SUM(BY28:CJ28) -> 3600
... B47: CL_55_ | C47: Rancho La Cuchilla No. 55 | D47: López Velázquez | E47: 0 | F47: 0 | G47: 0 | H47: 0 | I47: 0 | J47: 300 | K47: =SUM(E47:J47) -> 300 | L47: 300 | M47: 300 | N47: 300 | O47: 300 | P47: 300 | Q47: 300 | R47: 300 | S47: 300 | T47: 300 | U47: 300 | V47: 300 | W47: 300 | X47: =SUM(L47:W47) -> 3600 | Y47: 400 | Z47: 400 | AA47: 400 | AB47: 400 | AC47: 400 | AD47: 400 | AE47: 400 | AF47: 400 | AG47: 400 | AH47: 400 | AI47: 400 | AJ47: 400 | AK47: =SUM(Y47:AJ47) -> 4800 | AL47: 400 | AM47: 400 | AN47: 400 | AO47: 400 | AP47: 400 | AQ47: 400 | AR47: 400 | AS47: 400 | AT47: 400 | AU47: 400 | AV47: 400 | AW47: 400 | AX47: =SUM(AL47:AW47) -> 4800 | AY47: =SUMIF(Recibos!$D$4:$D$7493,Cobranza!$B47,Recibos!K$4:K$7493) -> 400 | AZ47: =SUMIF(Recibos!$D$4:$D$7493,Cobranza!$B47,Recibos!L$4:L$7493) -> 400 | BA47: =SUMIF(Recibos!$D$4:$D$7493,Cobranza!$B47,Recibos!M$4:M$7493) -> 400 | BB47: =SUMIF(Recibos!$D$4:$D$7493,Cobranza!$B47,Recibos!N$4:N$7493) -> 400 | BC47: =SUMIF(Recibos!$D$4:$D$7493,Cobranza!$B47,Recibos!O$4:O$7493) -> 400 | BD47: =SUMIF(Recibos!$D$4:$D$7493,Cobranza!$B47,Recibos!P$4:P$7493) -> 400 | BE47: =SUMIF(Recibos!$D$4:$D$7493,Cobranza!$B47,Recibos!Q$4:Q$7493) -> 200 | BF47: =SUMIF(Recibos!$D$4:$D$7493,Cobranza!$B47,Recibos!R$4:R$7493) -> 400 | ... BJ47: =SUMIF(Recibos!$D$4:$D$7493,Cobranza!$B47,Recibos!V$4:V$7493) -> 400 | BK47: =SUM(AY47:BJ47) -> 4600 | BL47: =SUMIF(Recibos!$D$4:$D$7493,Cobranza!$B47,Recibos!X$4:X$7493) -> 400 | BM47: =SUMIF(Recibos!$D$4:$D$7493,Cobranza!$B47,Recibos!Y$4:Y$7493) -> 400 | BN47: =SUMIF(Recibos!$D$4:$D$7493,Cobranza!$B47,Recibos!Z$4:Z$7493) -> 400 | BO47: =SUMIF(Recibos!$D$4:$D$7493,Cobranza!$B47,Recibos!AA$4:AA$7493) -> 400 | BP47: =SUMIF(Recibos!$D$4:$D$7493,Cobranza!$B47,Recibos!AB$4:AB$7493) -> 400 | BQ47: =SUMIF(Recibos!$D$4:$D$7493,Cobranza!$B47,Recibos!AC$4:AC$7493) -> 400 | BR47: =SUMIF(Recibos!$D$4:$D$7493,Cobranza!$B47,Recibos!AD$4:AD$7493) -> 400 | BS47: =SUMIF(Recibos!$D$4:$D$7493,Cobranza!$B47,Recibos!AE$4:AE$7493) -> 400 | ... BW47: =SUMIF(Recibos!$D$4:$D$7493,Cobranza!$B47,Recibos!AI$4:AI$7493) -> 400 | BX47: =SUM(BL47:BW47) -> 4800 | BY47: =SUMIF(Recibos!$D$4:$D$7493,Cobranza!$B47,Recibos!AK$4:AK$7493) -> 400 | BZ47: =SUMIF(Recibos!$D$4:$D$7493,Cobranza!$B47,Recibos!AL$4:AL$7493) -> 400 | CA47: =SUMIF(Recibos!$D$4:$D$7493,Cobranza!$B47,Recibos!AM$4:AM$7493) -> 400 | CB47: =SUMIF(Recibos!$D$4:$D$7493,Cobranza!$B47,Recibos!AN$4:AN$7493) -> 400 | CC47: =SUMIF(Recibos!$D$4:$D$7493,Cobranza!$B47,Recibos!AO$4:AO$7493) -> 400 | CD47: =SUMIF(Recibos!$D$4:$D$7493,Cobranza!$B47,Recibos!AP$4:AP$7493) -> 400 | CE47: =SUMIF(Recibos!$D$4:$D$7493,Cobranza!$B47,Recibos!AQ$4:AQ$7493) -> 400 | CF47: =SUMIF(Recibos!$D$4:$D$7493,Cobranza!$B47,Recibos!AR$4:AR$7493) -> 400 | ... CJ47: =SUMIF(Recibos!$D$4:$D$7493,Cobranza!$B47,Recibos!AV$4:AV$7493) -> 400 | CK47: =SUM(BY47:CJ47) -> 4800
B48: CL_57_ | C48: Rancho La Cuchilla No. 57 | E48: 0 | F48: 0 | G48: 0 | H48: 0 | I48: 0 | J48: 0 | K48: =SUM(E48:J48) -> 0 | L48: 0 | M48: 0 | N48: 0 | O48: 0 | P48: 0 | Q48: 0 | R48: 0 | S48: 0 | T48: 0 | U48: 0 | V48: 0 | W48: 0 | X48: =SUM(L48:W48) -> 0 | Y48: 0 | Z48: 0 | AA48: 0 | AB48: 0 | AC48: 0 | AD48: 0 | AE48: 0 | AF48: 0 | AG48: 0 | AH48: 0 | AI48: 0 | AJ48: 0 | AK48: =SUM(Y48:AJ48) -> 0 | AL48: 0 | AM48: 0 | AN48: 0 | AO48: 0 | AP48: 0 | AQ48: 0 | AR48: 0 | AS48: 0 | AT48: 0 | AU48: 0 | AV48: 0 | AW48: 0 | AX48: =SUM(AL48:AW48) -> 0 | AY48: =SUMIF(Recibos!$D$4:$D$7493,Cobranza!$B48,Recibos!K$4:K$7493) -> 0 | AZ48: =SUMIF(Recibos!$D$4:$D$7493,Cobranza!$B48,Recibos!L$4:L$7493) -> 0 | BA48: =SUMIF(Recibos!$D$4:$D$7493,Cobranza!$B48,Recibos!M$4:M$7493) -> 0 | BB48: =SUMIF(Recibos!$D$4:$D$7493,Cobranza!$B48,Recibos!N$4:N$7493) -> 0 | BC48: =SUMIF(Recibos!$D$4:$D$7493,Cobranza!$B48,Recibos!O$4:O$7493) -> 0 | BD48: =SUMIF(Recibos!$D$4:$D$7493,Cobranza!$B48,Recibos!P$4:P$7493) -> 0 | BE48: =SUMIF(Recibos!$D$4:$D$7493,Cobranza!$B48,Recibos!Q$4:Q$7493) -> 0 | BF48: =SUMIF(Recibos!$D$4:$D$7493,Cobranza!$B48,Recibos!R$4:R$7493) -> 0 | ... BJ48: =SUMIF(Recibos!$D$4:$D$7493,Cobranza!$B48,Recibos!V$4:V$7493) -> 0 | BK48: =SUM(AY48:BJ48) -> 0 | BL48: =SUMIF(Recibos!$D$4:$D$7493,Cobranza!$B48,Recibos!X$4:X$7493) -> 0 | BM48: =SUMIF(Recibos!$D$4:$D$7493,Cobranza!$B48,Recibos!Y$4:Y$7493) -> 0 | BN48: =SUMIF(Recibos!$D$4:$D$7493,Cobranza!$B48,Recibos!Z$4:Z$7493) -> 0 | BO48: =SUMIF(Recibos!$D$4:$D$7493,Cobranza!$B48,Recibos!AA$4:AA$7493) -> 0 | BP48: =SUMIF(Recibos!$D$4:$D$7493,Cobranza!$B48,Recibos!AB$4:AB$7493) -> 0 | BQ48: =SUMIF(Recibos!$D$4:$D$7493,Cobranza!$B48,Recibos!AC$4:AC$7493) -> 0 | BR48: =SUMIF(Recibos!$D$4:$D$7493,Cobranza!$B48,Recibos!AD$4:AD$7493) -> 0 | BS48: =SUMIF(Recibos!$D$4:$D$7493,Cobranza!$B48,Recibos!AE$4:AE$7493) -> 0 | ... BW48: =SUMIF(Recibos!$D$4:$D$7493,Cobranza!$B48,Recibos!AI$4:AI$7493) -> 0 | BX48: =SUM(BL48:BW48) -> 0 | BY48: =SUMIF(Recibos!$D$4:$D$7493,Cobranza!$B48,Recibos!AK$4:AK$7493) -> 0 | BZ48: =SUMIF(Recibos!$D$4:$D$7493,Cobranza!$B48,Recibos!AL$4:AL$7493) -> 0 | CA48: =SUMIF(Recibos!$D$4:$D$7493,Cobranza!$B48,Recibos!AM$4:AM$7493) -> 0 | CB48: =SUMIF(Recibos!$D$4:$D$7493,Cobranza!$B48,Recibos!AN$4:AN$7493) -> 0 | CC48: =SUMIF(Recibos!$D$4:$D$7493,Cobranza!$B48,Recibos!AO$4:AO$7493) -> 0 | CD48: =SUMIF(Recibos!$D$4:$D$7493,Cobranza!$B48,Recibos!AP$4:AP$7493) -> 0 | CE48: =SUMIF(Recibos!$D$4:$D$7493,Cobranza!$B48,Recibos!AQ$4:AQ$7493) -> 0 | CF48: =SUMIF(Recibos!$D$4:$D$7493,Cobranza!$B48,Recibos!AR$4:AR$7493) -> 0 | ... CJ48: =SUMIF(Recibos!$D$4:$D$7493,Cobranza!$B48,Recibos!AV$4:AV$7493) -> 0 | CK48: =SUM(BY48:CJ48) -> 0
B49: CL_58_ | C49: Rancho La Cuchilla No. 58 | D49: Serdán | E49: 0 | F49: 0 | G49: 0 | H49: 0 | I49: 0 | J49: 0 | K49: =SUM(E49:J49) -> 0 | L49: 0 | M49: 0 | N49: 0 | O49: 0 | P49: 0 | Q49: 0 | R49: 0 | S49: 0 | T49: 0 | U49: 0 | V49: 0 | W49: 0 | X49: =SUM(L49:W49) -> 0 | Y49: 0 | Z49: 0 | AA49: 0 | AB49: 0 | AC49: 0 | AD49: 0 | AE49: 0 | AF49: 0 | AG49: 0 | AH49: 0 | AI49: 0 | AJ49: 0 | AK49: =SUM(Y49:AJ49) -> 0 | AL49: 0 | AM49: 0 | AN49: 0 | AO49: 0 | AP49: 0 | AQ49: 0 | AR49: 0 | AS49: 0 | AT49: 0 | AU49: 0 | AV49: 0 | AW49: 0 | AX49: =SUM(AL49:AW49) -> 0 | AY49: =SUMIF(Recibos!$D$4:$D$7493,Cobranza!$B49,Recibos!K$4:K$7493) -> 0 | AZ49: =SUMIF(Recibos!$D$4:$D$7493,Cobranza!$B49,Recibos!L$4:L$7493) -> 0 | BA49: =SUMIF(Recibos!$D$4:$D$7493,Cobranza!$B49,Recibos!M$4:M$7493) -> 0 | BB49: =SUMIF(Recibos!$D$4:$D$7493,Cobranza!$B49,Recibos!N$4:N$7493) -> 0 | BC49: =SUMIF(Recibos!$D$4:$D$7493,Cobranza!$B49,Recibos!O$4:O$7493) -> 0 | BD49: =SUMIF(Recibos!$D$4:$D$7493,Cobranza!$B49,Recibos!P$4:P$7493) -> 0 | BE49: =SUMIF(Recibos!$D$4:$D$7493,Cobranza!$B49,Recibos!Q$4:Q$7493) -> 0 | BF49: =SUMIF(Recibos!$D$4:$D$7493,Cobranza!$B49,Recibos!R$4:R$7493) -> 200 | ... BJ49: =SUMIF(Recibos!$D$4:$D$7493,Cobranza!$B49,Recibos!V$4:V$7493) -> 200 | BK49: =SUM(AY49:BJ49) -> 1000 | BL49: =SUMIF(Recibos!$D$4:$D$7493,Cobranza!$B49,Recibos!X$4:X$7493) -> 200 | BM49: =SUMIF(Recibos!$D$4:$D$7493,Cobranza!$B49,Recibos!Y$4:Y$7493) -> 200 | BN49: =SUMIF(Recibos!$D$4:$D$7493,Cobranza!$B49,Recibos!Z$4:Z$7493) -> 200 | BO49: =SUMIF(Recibos!$D$4:$D$7493,Cobranza!$B49,Recibos!AA$4:AA$7493) -> 200 | BP49: =SUMIF(Recibos!$D$4:$D$7493,Cobranza!$B49,Recibos!AB$4:AB$7493) -> 200 | BQ49: =SUMIF(Recibos!$D$4:$D$7493,Cobranza!$B49,Recibos!AC$4:AC$7493) -> 200 | BR49: =SUMIF(Recibos!$D$4:$D$7493,Cobranza!$B49,Recibos!AD$4:AD$7493) -> 200 | BS49: =SUMIF(Recibos!$D$4:$D$7493,Cobranza!$B49,Recibos!AE$4:AE$7493) -> 200 | ... BW49: =SUMIF(Recibos!$D$4:$D$7493,Cobranza!$B49,Recibos!AI$4:AI$7493) -> 0 | BX49: =SUM(BL49:BW49) -> 2200 | BY49: =SUMIF(Recibos!$D$4:$D$7493,Cobranza!$B49,Recibos!AK$4:AK$7493) -> 200 | BZ49: =SUMIF(Recibos!$D$4:$D$7493,Cobranza!$B49,Recibos!AL$4:AL$7493) -> 200 | CA49: =SUMIF(Recibos!$D$4:$D$7493,Cobranza!$B49,Recibos!AM$4:AM$7493) -> 200 | CB49: =SUMIF(Recibos!$D$4:$D$7493,Cobranza!$B49,Recibos!AN$4:AN$7493) -> 200 | CC49: =SUMIF(Recibos!$D$4:$D$7493,Cobranza!$B49,Recibos!AO$4:AO$7493) -> 200 | CD49: =SUMIF(Recibos!$D$4:$D$7493,Cobranza!$B49,Recibos!AP$4:AP$7493) -> 200 | CE49: =SUMIF(Recibos!$D$4:$D$7493,Cobranza!$B49,Recibos!AQ$4:AQ$7493) -> 200 | CF49: =SUMIF(Recibos!$D$4:$D$7493,Cobranza!$B49,Recibos!AR$4:AR$7493) -> 200 | ... CJ49: =SUMIF(Recibos!$D$4:$D$7493,Cobranza!$B49,Recibos!AV$4:AV$7493) -> 200 | CK49: =SUM(BY49:CJ49) -> 2400
B50: CL_59_ | C50: Rancho La Cuchilla No. 59 | D50: Ortega Vega | E50: 0 | F50: 0 | G50: 0 | H50: 0 | I50: 0 | J50: 300 | K50: =SUM(E50:J50) -> 300 | L50: 300 | M50: 300 | N50: 300 | O50: 300 | P50: 300 | Q50: 300 | R50: 300 | S50: 300 | T50: 300 | U50: 0 | V50: 0 | W50: 0 | X50: =SUM(L50:W50) -> 2700 | Y50: 300 | Z50: 300 | AA50: 300 | AB50: 300 | AC50: 300 | AD50: 150 | AE50: 150 | AF50: 150 | AG50: 150 | AH50: 0 | AI50: 0 | AJ50: 0 | AK50: =SUM(Y50:AJ50) -> 2100 | AL50: 150 | AM50: 150 | AN50: 150 | AO50: 150 | AP50: 150 | AQ50: 150 | AR50: 150 | AS50: 150 | AT50: 150 | AU50: 150 | AV50: 150 | AW50: 0 | AX50: =SUM(AL50:AW50) -> 1650 | AY50: =SUMIF(Recibos!$D$4:$D$7493,Cobranza!$B50,Recibos!K$4:K$7493) -> 150 | AZ50: =SUMIF(Recibos!$D$4:$D$7493,Cobranza!$B50,Recibos!L$4:L$7493) -> 150 | BA50: =SUMIF(Recibos!$D$4:$D$7493,Cobranza!$B50,Recibos!M$4:M$7493) -> 150 | BB50: =SUMIF(Recibos!$D$4:$D$7493,Cobranza!$B50,Recibos!N$4:N$7493) -> 150 | BC50: =SUMIF(Recibos!$D$4:$D$7493,Cobranza!$B50,Recibos!O$4:O$7493) -> 150 | BD50: =SUMIF(Recibos!$D$4:$D$7493,Cobranza!$B50,Recibos!P$4:P$7493) -> 150 | BE50: =SUMIF(Recibos!$D$4:$D$7493,Cobranza!$B50,Recibos!Q$4:Q$7493) -> 150 | BF50: =SUMIF(Recibos!$D$4:$D$7493,Cobranza!$B50,Recibos!R$4:R$7493) -> 150 | ... BJ50: =SUMIF(Recibos!$D$4:$D$7493,Cobranza!$B50,Recibos!V$4:V$7493) -> 150 | BK50: =SUM(AY50:BJ50) -> 1800 | BL50: =SUMIF(Recibos!$D$4:$D$7493,Cobranza!$B50,Recibos!X$4:X$7493) -> 150 | BM50: =SUMIF(Recibos!$D$4:$D$7493,Cobranza!$B50,Recibos!Y$4:Y$7493) -> 150 | BN50: =SUMIF(Recibos!$D$4:$D$7493,Cobranza!$B50,Recibos!Z$4:Z$7493) -> 150 | BO50: =SUMIF(Recibos!$D$4:$D$7493,Cobranza!$B50,Recibos!AA$4:AA$7493) -> 150 | BP50: =SUMIF(Recibos!$D$4:$D$7493,Cobranza!$B50,Recibos!AB$4:AB$7493) -> 150 | BQ50: =SUMIF(Recibos!$D$4:$D$7493,Cobranza!$B50,Recibos!AC$4:AC$7493) -> 150 | BR50: =SUMIF(Recibos!$D$4:$D$7493,Cobranza!$B50,Recibos!AD$4:AD$7493) -> 150 | BS50: =SUMIF(Recibos!$D$4:$D$7493,Cobranza!$B50,Recibos!AE$4:AE$7493) -> 150 | ... BW50: =SUMIF(Recibos!$D$4:$D$7493,Cobranza!$B50,Recibos!AI$4:AI$7493) -> 150 | BX50: =SUM(BL50:BW50) -> 1800 | BY50: =SUMIF(Recibos!$D$4:$D$7493,Cobranza!$B50,Recibos!AK$4:AK$7493) -> 150 | BZ50: =SUMIF(Recibos!$D$4:$D$7493,Cobranza!$B50,Recibos!AL$4:AL$7493) -> 150 | CA50: =SUMIF(Recibos!$D$4:$D$7493,Cobranza!$B50,Recibos!AM$4:AM$7493) -> 150 | CB50: =SUMIF(Recibos!$D$4:$D$7493,Cobranza!$B50,Recibos!AN$4:AN$7493) -> 150 | CC50: =SUMIF(Recibos!$D$4:$D$7493,Cobranza!$B50,Recibos!AO$4:AO$7493) -> 150 | CD50: =SUMIF(Recibos!$D$4:$D$7493,Cobranza!$B50,Recibos!AP$4:AP$7493) -> 150 | CE50: =SUMIF(Recibos!$D$4:$D$7493,Cobranza!$B50,Recibos!AQ$4:AQ$7493) -> 150 | CF50: =SUMIF(Recibos!$D$4:$D$7493,Cobranza!$B50,Recibos!AR$4:AR$7493) -> 150 | ... CJ50: =SUMIF(Recibos!$D$4:$D$7493,Cobranza!$B50,Recibos!AV$4:AV$7493) -> 150 | CK50: =SUM(BY50:CJ50) -> 1800
B51: CL_60_ | C51: Rancho La Cuchilla No. 60 | D51: Cedillo | E51: 0 | F51: 0 | G51: 0 | H51: 0 | I51: 0 | J51: 0 | K51: =SUM(E51:J51) -> 0 | L51: 0 | M51: 0 | N51: 0 | O51: 0 | P51: 0 | Q51: 0 | R51: 0 | S51: 0 | T51: 0 | U51: 0 | V51: 0 | W51: 0 | X51: =SUM(L51:W51) -> 0 | Y51: 0 | Z51: 0 | AA51: 0 | AB51: 0 | AC51: 0 | AD51: 0 | AE51: 0 | AF51: 0 | AG51: 0 | AH51: 0 | AI51: 0 | AJ51: 0 | AK51: =SUM(Y51:AJ51) -> 0 | AL51: 0 | AM51: 0 | AN51: 0 | AO51: 0 | AP51: 0 | AQ51: 0 | AR51: 0 | AS51: 0 | AT51: 0 | AU51: 0 | AV51: 0 | AW51: 0 | AX51: =SUM(AL51:AW51) -> 0 | AY51: =SUMIF(Recibos!$D$4:$D$7493,Cobranza!$B51,Recibos!K$4:K$7493) -> 0 | AZ51: =SUMIF(Recibos!$D$4:$D$7493,Cobranza!$B51,Recibos!L$4:L$7493) -> 0 | BA51: =SUMIF(Recibos!$D$4:$D$7493,Cobranza!$B51,Recibos!M$4:M$7493) -> 0 | BB51: =SUMIF(Recibos!$D$4:$D$7493,Cobranza!$B51,Recibos!N$4:N$7493) -> 0 | BC51: =SUMIF(Recibos!$D$4:$D$7493,Cobranza!$B51,Recibos!O$4:O$7493) -> 0 | BD51: =SUMIF(Recibos!$D$4:$D$7493,Cobranza!$B51,Recibos!P$4:P$7493) -> 0 | BE51: =SUMIF(Recibos!$D$4:$D$7493,Cobranza!$B51,Recibos!Q$4:Q$7493) -> 0 | BF51: =SUMIF(Recibos!$D$4:$D$7493,Cobranza!$B51,Recibos!R$4:R$7493) -> 0 | ... BJ51: =SUMIF(Recibos!$D$4:$D$7493,Cobranza!$B51,Recibos!V$4:V$7493) -> 0 | BK51: =SUM(AY51:BJ51) -> 0 | BL51: =SUMIF(Recibos!$D$4:$D$7493,Cobranza!$B51,Recibos!X$4:X$7493) -> 400 | BM51: =SUMIF(Recibos!$D$4:$D$7493,Cobranza!$B51,Recibos!Y$4:Y$7493) -> 400 | BN51: =SUMIF(Recibos!$D$4:$D$7493,Cobranza!$B51,Recibos!Z$4:Z$7493) -> 400 | BO51: =SUMIF(Recibos!$D$4:$D$7493,Cobranza!$B51,Recibos!AA$4:AA$7493) -> 400 | BP51: =SUMIF(Recibos!$D$4:$D$7493,Cobranza!$B51,Recibos!AB$4:AB$7493) -> 400 | BQ51: =SUMIF(Recibos!$D$4:$D$7493,Cobranza!$B51,Recibos!AC$4:AC$7493) -> 400 | BR51: =SUMIF(Recibos!$D$4:$D$7493,Cobranza!$B51,Recibos!AD$4:AD$7493) -> 400 | BS51: =SUMIF(Recibos!$D$4:$D$7493,Cobranza!$B51,Recibos!AE$4:AE$7493) -> 400 | ... BW51: =SUMIF(Recibos!$D$4:$D$7493,Cobranza!$B51,Recibos!AI$4:AI$7493) -> 400 | BX51: =SUM(BL51:BW51) -> 4800 | BY51: =SUMIF(Recibos!$D$4:$D$7493,Cobranza!$B51,Recibos!AK$4:AK$7493) -> 400 | BZ51: =SUMIF(Recibos!$D$4:$D$7493,Cobranza!$B51,Recibos!AL$4:AL$7493) -> 400 | CA51: =SUMIF(Recibos!$D$4:$D$7493,Cobranza!$B51,Recibos!AM$4:AM$7493) -> 400 | CB51: =SUMIF(Recibos!$D$4:$D$7493,Cobranza!$B51,Recibos!AN$4:AN$7493) -> 400 | CC51: =SUMIF(Recibos!$D$4:$D$7493,Cobranza!$B51,Recibos!AO$4:AO$7493) -> 400 | CD51: =SUMIF(Recibos!$D$4:$D$7493,Cobranza!$B51,Recibos!AP$4:AP$7493) -> 400 | CE51: =SUMIF(Recibos!$D$4:$D$7493,Cobranza!$B51,Recibos!AQ$4:AQ$7493) -> 400 | CF51: =SUMIF(Recibos!$D$4:$D$7493,Cobranza!$B51,Recibos!AR$4:AR$7493) -> 400 | ... CJ51: =SUMIF(Recibos!$D$4:$D$7493,Cobranza!$B51,Recibos!AV$4:AV$7493) -> 0 | CK51: =SUM(BY51:CJ51) -> 4400
B52: CL_61_ | C52: Rancho La Cuchilla No. 61 | D52: Rivera | E52: 0 | F52: 0 | G52: 0 | H52: 0 | I52: 0 | J52: 0 | K52: =SUM(E52:J52) -> 0 | L52: 300 | M52: 300 | N52: 300 | O52: 300 | P52: 300 | Q52: 300 | R52: 300 | S52: 300 | T52: 300 | U52: 400 | V52: 400 | W52: 400 | X52: =SUM(L52:W52) -> 3900 | Y52: 200 | Z52: 200 | AA52: 400 | AB52: 400 | AC52: 200 | AD52: 200 | AE52: 200 | AF52: 200 | AG52: 200 | AH52: 200 | AI52: 200 | AJ52: 200 | AK52: =SUM(Y52:AJ52) -> 2800 | AL52: 200 | AM52: 200 | AN52: 200 | AO52: 200 | AP52: 200 | AQ52: 200 | AR52: 200 | AS52: 200 | AT52: 200 | AU52: 200 | AV52: 200 | AW52: 200 | AX52: =SUM(AL52:AW52) -> 2400 | AY52: =SUMIF(Recibos!$D$4:$D$7493,Cobranza!$B52,Recibos!K$4:K$7493) -> 200 | AZ52: =SUMIF(Recibos!$D$4:$D$7493,Cobranza!$B52,Recibos!L$4:L$7493) -> 200 | BA52: =SUMIF(Recibos!$D$4:$D$7493,Cobranza!$B52,Recibos!M$4:M$7493) -> 200 | BB52: =SUMIF(Recibos!$D$4:$D$7493,Cobranza!$B52,Recibos!N$4:N$7493) -> 200 | BC52: =SUMIF(Recibos!$D$4:$D$7493,Cobranza!$B52,Recibos!O$4:O$7493) -> 200 | BD52: =SUMIF(Recibos!$D$4:$D$7493,Cobranza!$B52,Recibos!P$4:P$7493) -> 200 | BE52: =SUMIF(Recibos!$D$4:$D$7493,Cobranza!$B52,Recibos!Q$4:Q$7493) -> 200 | BF52: =SUMIF(Recibos!$D$4:$D$7493,Cobranza!$B52,Recibos!R$4:R$7493) -> 200 | ... BJ52: =SUMIF(Recibos!$D$4:$D$7493,Cobranza!$B52,Recibos!V$4:V$7493) -> 200 | BK52: =SUM(AY52:BJ52) -> 2400 | BL52: =SUMIF(Recibos!$D$4:$D$7493,Cobranza!$B52,Recibos!X$4:X$7493) -> 200 | BM52: =SUMIF(Recibos!$D$4:$D$7493,Cobranza!$B52,Recibos!Y$4:Y$7493) -> 200 | BN52: =SUMIF(Recibos!$D$4:$D$7493,Cobranza!$B52,Recibos!Z$4:Z$7493) -> 200 | BO52: =SUMIF(Recibos!$D$4:$D$7493,Cobranza!$B52,Recibos!AA$4:AA$7493) -> 200 | BP52: =SUMIF(Recibos!$D$4:$D$7493,Cobranza!$B52,Recibos!AB$4:AB$7493) -> 200 | BQ52: =SUMIF(Recibos!$D$4:$D$7493,Cobranza!$B52,Recibos!AC$4:AC$7493) -> 200 | BR52: =SUMIF(Recibos!$D$4:$D$7493,Cobranza!$B52,Recibos!AD$4:AD$7493) -> 200 | BS52: =SUMIF(Recibos!$D$4:$D$7493,Cobranza!$B52,Recibos!AE$4:AE$7493) -> 200 | ... BW52: =SUMIF(Recibos!$D$4:$D$7493,Cobranza!$B52,Recibos!AI$4:AI$7493) -> 200 | BX52: =SUM(BL52:BW52) -> 2400 | BY52: =SUMIF(Recibos!$D$4:$D$7493,Cobranza!$B52,Recibos!AK$4:AK$7493) -> 200 | BZ52: =SUMIF(Recibos!$D$4:$D$7493,Cobranza!$B52,Recibos!AL$4:AL$7493) -> 200 | CA52: =SUMIF(Recibos!$D$4:$D$7493,Cobranza!$B52,Recibos!AM$4:AM$7493) -> 200 | CB52: =SUMIF(Recibos!$D$4:$D$7493,Cobranza!$B52,Recibos!AN$4:AN$7493) -> 200 | CC52: =SUMIF(Recibos!$D$4:$D$7493,Cobranza!$B52,Recibos!AO$4:AO$7493) -> 200 | CD52: =SUMIF(Recibos!$D$4:$D$7493,Cobranza!$B52,Recibos!AP$4:AP$7493) -> 200 | CE52: =SUMIF(Recibos!$D$4:$D$7493,Cobranza!$B52,Recibos!AQ$4:AQ$7493) -> 200 | CF52: =SUMIF(Recibos!$D$4:$D$7493,Cobranza!$B52,Recibos!AR$4:AR$7493) -> 200 | ... CJ52: =SUMIF(Recibos!$D$4:$D$7493,Cobranza!$B52,Recibos!AV$4:AV$7493) -> 0 | CK52: =SUM(BY52:CJ52) -> 1600
B53: CL_62_ | C53: Rancho La Cuchilla No. 62 | D53: Frías | E53: 0 | F53: 0 | G53: 0 | H53: 0 | I53: 0 | J53: 200 | K53: =SUM(E53:J53) -> 200 | L53: 200 | M53: 200 | N53: 200 | O53: 200 | P53: 200 | Q53: 200 | R53: 200 | S53: 200 | T53: 200 | U53: 200 | V53: 0 | W53: 0 | X53: =SUM(L53:W53) -> 2000 | Y53: 0 | Z53: 0 | AA53: 0 | AB53: 0 | AC53: 0 | AD53: 0 | AE53: 0 | AF53: 0 | AG53: 0 | AH53: 0 | AI53: 0 | AJ53: 0 | AK53: =SUM(Y53:AJ53) -> 0 | AL53: 0 | AM53: 0 | AN53: 0 | AO53: 0 | AP53: 0 | AQ53: 0 | AR53: 0 | AS53: 0 | AT53: 0 | AU53: 0 | AV53: 0 | AW53: 0 | AX53: =SUM(AL53:AW53) -> 0 | AY53: =SUMIF(Recibos!$D$4:$D$7493,Cobranza!$B53,Recibos!K$4:K$7493) -> 0 | AZ53: =SUMIF(Recibos!$D$4:$D$7493,Cobranza!$B53,Recibos!L$4:L$7493) -> 0 | BA53: =SUMIF(Recibos!$D$4:$D$7493,Cobranza!$B53,Recibos!M$4:M$7493) -> 0 | BB53: =SUMIF(Recibos!$D$4:$D$7493,Cobranza!$B53,Recibos!N$4:N$7493) -> 0 | BC53: =SUMIF(Recibos!$D$4:$D$7493,Cobranza!$B53,Recibos!O$4:O$7493) -> 0 | BD53: =SUMIF(Recibos!$D$4:$D$7493,Cobranza!$B53,Recibos!P$4:P$7493) -> 0 | BE53: =SUMIF(Recibos!$D$4:$D$7493,Cobranza!$B53,Recibos!Q$4:Q$7493) -> 0 | BF53: =SUMIF(Recibos!$D$4:$D$7493,Cobranza!$B53,Recibos!R$4:R$7493) -> 0 | ... BJ53: =SUMIF(Recibos!$D$4:$D$7493,Cobranza!$B53,Recibos!V$4:V$7493) -> 0 | BK53: =SUM(AY53:BJ53) -> 0 | BL53: =SUMIF(Recibos!$D$4:$D$7493,Cobranza!$B53,Recibos!X$4:X$7493) -> 0 | BM53: =SUMIF(Recibos!$D$4:$D$7493,Cobranza!$B53,Recibos!Y$4:Y$7493) -> 0 | BN53: =SUMIF(Recibos!$D$4:$D$7493,Cobranza!$B53,Recibos!Z$4:Z$7493) -> 0 | BO53: =SUMIF(Recibos!$D$4:$D$7493,Cobranza!$B53,Recibos!AA$4:AA$7493) -> 0 | BP53: =SUMIF(Recibos!$D$4:$D$7493,Cobranza!$B53,Recibos!AB$4:AB$7493) -> 0 | BQ53: =SUMIF(Recibos!$D$4:$D$7493,Cobranza!$B53,Recibos!AC$4:AC$7493) -> 0 | BR53: =SUMIF(Recibos!$D$4:$D$7493,Cobranza!$B53,Recibos!AD$4:AD$7493) -> 0 | BS53: =SUMIF(Recibos!$D$4:$D$7493,Cobranza!$B53,Recibos!AE$4:AE$7493) -> 0 | ... BW53: =SUMIF(Recibos!$D$4:$D$7493,Cobranza!$B53,Recibos!AI$4:AI$7493) -> 0 | BX53: =SUM(BL53:BW53) -> 0 | BY53: =SUMIF(Recibos!$D$4:$D$7493,Cobranza!$B53,Recibos!AK$4:AK$7493) -> 0 | BZ53: =SUMIF(Recibos!$D$4:$D$7493,Cobranza!$B53,Recibos!AL$4:AL$7493) -> 0 | CA53: =SUMIF(Recibos!$D$4:$D$7493,Cobranza!$B53,Recibos!AM$4:AM$7493) -> 0 | CB53: =SUMIF(Recibos!$D$4:$D$7493,Cobranza!$B53,Recibos!AN$4:AN$7493) -> 0 | CC53: =SUMIF(Recibos!$D$4:$D$7493,Cobranza!$B53,Recibos!AO$4:AO$7493) -> 0 | CD53: =SUMIF(Recibos!$D$4:$D$7493,Cobranza!$B53,Recibos!AP$4:AP$7493) -> 0 | CE53: =SUMIF(Recibos!$D$4:$D$7493,Cobranza!$B53,Recibos!AQ$4:AQ$7493) -> 0 | CF53: =SUMIF(Recibos!$D$4:$D$7493,Cobranza!$B53,Recibos!AR$4:AR$7493) -> 0 | ... CJ53: =SUMIF(Recibos!$D$4:$D$7493,Cobranza!$B53,Recibos!AV$4:AV$7493) -> 0 | CK53: =SUM(BY53:CJ53) -> 0
B54: CL_63_ | C54: Rancho La Cuchilla No. 63 | D54: Díaz de la Rosa | E54: 0 | F54: 0 | G54: 0 | H54: 0 | I54: 0 | J54: 0 | K54: =SUM(E54:J54) -> 0 | L54: 0 | M54: 0 | N54: 0 | O54: 0 | P54: 0 | Q54: 0 | R54: 0 | S54: 0 | T54: 0 | U54: 0 | V54: 0 | W54: 0 | X54: =SUM(L54:W54) -> 0 | Y54: 0 | Z54: 0 | AA54: 0 | AB54: 0 | AC54: 0 | AD54: 0 | AE54: 0 | AF54: 0 | AG54: 0 | AH54: 0 | AI54: 300 | AJ54: 300 | AK54: =SUM(Y54:AJ54) -> 600 | AL54: 300 | AM54: 0 | AN54: 0 | AO54: 0 | AP54: 0 | AQ54: 0 | AR54: 0 | AS54: 0 | AT54: 0 | AU54: 0 | AV54: 0 | AW54: 0 | AX54: =SUM(AL54:AW54) -> 300 | AY54: =SUMIF(Recibos!$D$4:$D$7493,Cobranza!$B54,Recibos!K$4:K$7493) -> 0 | AZ54: =SUMIF(Recibos!$D$4:$D$7493,Cobranza!$B54,Recibos!L$4:L$7493) -> 0 | BA54: =SUMIF(Recibos!$D$4:$D$7493,Cobranza!$B54,Recibos!M$4:M$7493) -> 0 | BB54: =SUMIF(Recibos!$D$4:$D$7493,Cobranza!$B54,Recibos!N$4:N$7493) -> 0 | BC54: =SUMIF(Recibos!$D$4:$D$7493,Cobranza!$B54,Recibos!O$4:O$7493) -> 0 | BD54: =SUMIF(Recibos!$D$4:$D$7493,Cobranza!$B54,Recibos!P$4:P$7493) -> 0 | BE54: =SUMIF(Recibos!$D$4:$D$7493,Cobranza!$B54,Recibos!Q$4:Q$7493) -> 0 | BF54: =SUMIF(Recibos!$D$4:$D$7493,Cobranza!$B54,Recibos!R$4:R$7493) -> 0 | ... BJ54: =SUMIF(Recibos!$D$4:$D$7493,Cobranza!$B54,Recibos!V$4:V$7493) -> 0 | BK54: =SUM(AY54:BJ54) -> 0 | BL54: =SUMIF(Recibos!$D$4:$D$7493,Cobranza!$B54,Recibos!X$4:X$7493) -> 0 | BM54: =SUMIF(Recibos!$D$4:$D$7493,Cobranza!$B54,Recibos!Y$4:Y$7493) -> 200 | BN54: =SUMIF(Recibos!$D$4:$D$7493,Cobranza!$B54,Recibos!Z$4:Z$7493) -> 200 | BO54: =SUMIF(Recibos!$D$4:$D$7493,Cobranza!$B54,Recibos!AA$4:AA$7493) -> 200 | BP54: =SUMIF(Recibos!$D$4:$D$7493,Cobranza!$B54,Recibos!AB$4:AB$7493) -> 200 | BQ54: =SUMIF(Recibos!$D$4:$D$7493,Cobranza!$B54,Recibos!AC$4:AC$7493) -> 0 | BR54: =SUMIF(Recibos!$D$4:$D$7493,Cobranza!$B54,Recibos!AD$4:AD$7493) -> 0 | BS54: =SUMIF(Recibos!$D$4:$D$7493,Cobranza!$B54,Recibos!AE$4:AE$7493) -> 0 | ... BW54: =SUMIF(Recibos!$D$4:$D$7493,Cobranza!$B54,Recibos!AI$4:AI$7493) -> 200 | BX54: =SUM(BL54:BW54) -> 1400 | BY54: =SUMIF(Recibos!$D$4:$D$7493,Cobranza!$B54,Recibos!AK$4:AK$7493) -> 200 | BZ54: =SUMIF(Recibos!$D$4:$D$7493,Cobranza!$B54,Recibos!AL$4:AL$7493) -> 200 | CA54: =SUMIF(Recibos!$D$4:$D$7493,Cobranza!$B54,Recibos!AM$4:AM$7493) -> 200 | CB54: =SUMIF(Recibos!$D$4:$D$7493,Cobranza!$B54,Recibos!AN$4:AN$7493) -> 200 | CC54: =SUMIF(Recibos!$D$4:$D$7493,Cobranza!$B54,Recibos!AO$4:AO$7493) -> 0 | CD54: =SUMIF(Recibos!$D$4:$D$7493,Cobranza!$B54,Recibos!AP$4:AP$7493) -> 0 | CE54: =SUMIF(Recibos!$D$4:$D$7493,Cobranza!$B54,Recibos!AQ$4:AQ$7493) -> 200 | CF54: =SUMIF(Recibos!$D$4:$D$7493,Cobranza!$B54,Recibos!AR$4:AR$7493) -> 200 | ... CJ54: =SUMIF(Recibos!$D$4:$D$7493,Cobranza!$B54,Recibos!AV$4:AV$7493) -> 0 | CK54: =SUM(BY54:CJ54) -> 1400
B55: CL_65_ | C55: Rancho La Cuchilla No. 65 | D55: Garduño | E55: 0 | F55: 0 | G55: 0 | H55: 0 | I55: 0 | J55: 0 | K55: =SUM(E55:J55) -> 0 | L55: 0 | M55: 0 | N55: 0 | O55: 0 | P55: 0 | Q55: 0 | R55: 0 | S55: 0 | T55: 0 | U55: 0 | V55: 0 | W55: 0 | X55: =SUM(L55:W55) -> 0 | Y55: 0 | Z55: 0 | AA55: 0 | AB55: 0 | AC55: 0 | AD55: 0 | AE55: 0 | AF55: 0 | AG55: 0 | AH55: 0 | AI55: 0 | AJ55: 0 | AK55: =SUM(Y55:AJ55) -> 0 | AL55: 0 | AM55: 0 | AN55: 0 | AO55: 0 | AP55: 0 | AQ55: 0 | AR55: 0 | AS55: 0 | AT55: 0 | AU55: 0 | AV55: 0 | AW55: 0 | AX55: =SUM(AL55:AW55) -> 0 | AY55: =SUMIF(Recibos!$D$4:$D$7493,Cobranza!$B55,Recibos!K$4:K$7493) -> 0 | AZ55: =SUMIF(Recibos!$D$4:$D$7493,Cobranza!$B55,Recibos!L$4:L$7493) -> 0 | BA55: =SUMIF(Recibos!$D$4:$D$7493,Cobranza!$B55,Recibos!M$4:M$7493) -> 0 | BB55: =SUMIF(Recibos!$D$4:$D$7493,Cobranza!$B55,Recibos!N$4:N$7493) -> 0 | BC55: =SUMIF(Recibos!$D$4:$D$7493,Cobranza!$B55,Recibos!O$4:O$7493) -> 0 | BD55: =SUMIF(Recibos!$D$4:$D$7493,Cobranza!$B55,Recibos!P$4:P$7493) -> 0 | BE55: =SUMIF(Recibos!$D$4:$D$7493,Cobranza!$B55,Recibos!Q$4:Q$7493) -> 0 | BF55: =SUMIF(Recibos!$D$4:$D$7493,Cobranza!$B55,Recibos!R$4:R$7493) -> 0 | ... BJ55: =SUMIF(Recibos!$D$4:$D$7493,Cobranza!$B55,Recibos!V$4:V$7493) -> 0 | BK55: =SUM(AY55:BJ55) -> 0 | BL55: =SUMIF(Recibos!$D$4:$D$7493,Cobranza!$B55,Recibos!X$4:X$7493) -> 0 | BM55: =SUMIF(Recibos!$D$4:$D$7493,Cobranza!$B55,Recibos!Y$4:Y$7493) -> 0 | BN55: =SUMIF(Recibos!$D$4:$D$7493,Cobranza!$B55,Recibos!Z$4:Z$7493) -> 0 | BO55: =SUMIF(Recibos!$D$4:$D$7493,Cobranza!$B55,Recibos!AA$4:AA$7493) -> 0 | BP55: =SUMIF(Recibos!$D$4:$D$7493,Cobranza!$B55,Recibos!AB$4:AB$7493) -> 0 | BQ55: =SUMIF(Recibos!$D$4:$D$7493,Cobranza!$B55,Recibos!AC$4:AC$7493) -> 0 | BR55: =SUMIF(Recibos!$D$4:$D$7493,Cobranza!$B55,Recibos!AD$4:AD$7493) -> 0 | BS55: =SUMIF(Recibos!$D$4:$D$7493,Cobranza!$B55,Recibos!AE$4:AE$7493) -> 0 | ... BW55: =SUMIF(Recibos!$D$4:$D$7493,Cobranza!$B55,Recibos!AI$4:AI$7493) -> 0 | BX55: =SUM(BL55:BW55) -> 0 | BY55: =SUMIF(Recibos!$D$4:$D$7493,Cobranza!$B55,Recibos!AK$4:AK$7493) -> 0 | BZ55: =SUMIF(Recibos!$D$4:$D$7493,Cobranza!$B55,Recibos!AL$4:AL$7493) -> 0 | CA55: =SUMIF(Recibos!$D$4:$D$7493,Cobranza!$B55,Recibos!AM$4:AM$7493) -> 0 | CB55: =SUMIF(Recibos!$D$4:$D$7493,Cobranza!$B55,Recibos!AN$4:AN$7493) -> 0 | CC55: =SUMIF(Recibos!$D$4:$D$7493,Cobranza!$B55,Recibos!AO$4:AO$7493) -> 0 | CD55: =SUMIF(Recibos!$D$4:$D$7493,Cobranza!$B55,Recibos!AP$4:AP$7493) -> 0 | CE55: =SUMIF(Recibos!$D$4:$D$7493,Cobranza!$B55,Recibos!AQ$4:AQ$7493) -> 0 | CF55: =SUMIF(Recibos!$D$4:$D$7493,Cobranza!$B55,Recibos!AR$4:AR$7493) -> 0 | ... CJ55: =SUMIF(Recibos!$D$4:$D$7493,Cobranza!$B55,Recibos!AV$4:AV$7493) -> 0 | CK55: =SUM(BY55:CJ55) -> 0
B56: CL_66_ | C56: Rancho La Cuchilla No. 66 | D56: Prieto | E56: 0 | F56: 0 | G56: 0 | H56: 300 | I56: 300 | J56: 300 | K56: =SUM(E56:J56) -> 900 | L56: 300 | M56: 300 | N56: 300 | O56: 300 | P56: 300 | Q56: 300 | R56: 300 | S56: 300 | T56: 300 | U56: 300 | V56: 400 | W56: 400 | X56: =SUM(L56:W56) -> 3800 | Y56: 400 | Z56: 400 | AA56: 400 | AB56: 400 | AC56: 400 | AD56: 400 | AE56: 400 | AF56: 400 | AG56: 400 | AH56: 400 | AI56: 400 | AJ56: 400 | AK56: =SUM(Y56:AJ56) -> 4800 | AL56: 400 | AM56: 400 | AN56: 400 | AO56: 400 | AP56: 400 | AQ56: 400 | AR56: 400 | AS56: 400 | AT56: 400 | AU56: 400 | AV56: 400 | AW56: 400 | AX56: =SUM(AL56:AW56) -> 4800 | AY56: =SUMIF(Recibos!$D$4:$D$7493,Cobranza!$B56,Recibos!K$4:K$7493) -> 400 | AZ56: =SUMIF(Recibos!$D$4:$D$7493,Cobranza!$B56,Recibos!L$4:L$7493) -> 400 | BA56: =SUMIF(Recibos!$D$4:$D$7493,Cobranza!$B56,Recibos!M$4:M$7493) -> 400 | BB56: =SUMIF(Recibos!$D$4:$D$7493,Cobranza!$B56,Recibos!N$4:N$7493) -> 400 | BC56: =SUMIF(Recibos!$D$4:$D$7493,Cobranza!$B56,Recibos!O$4:O$7493) -> 400 | BD56: =SUMIF(Recibos!$D$4:$D$7493,Cobranza!$B56,Recibos!P$4:P$7493) -> 400 | BE56: =SUMIF(Recibos!$D$4:$D$7493,Cobranza!$B56,Recibos!Q$4:Q$7493) -> 400 | BF56: =SUMIF(Recibos!$D$4:$D$7493,Cobranza!$B56,Recibos!R$4:R$7493) -> 400 | ... BJ56: =SUMIF(Recibos!$D$4:$D$7493,Cobranza!$B56,Recibos!V$4:V$7493) -> 400 | BK56: =SUM(AY56:BJ56) -> 4800 | BL56: =SUMIF(Recibos!$D$4:$D$7493,Cobranza!$B56,Recibos!X$4:X$7493) -> 400 | BM56: =SUMIF(Recibos!$D$4:$D$7493,Cobranza!$B56,Recibos!Y$4:Y$7493) -> 400 | BN56: =SUMIF(Recibos!$D$4:$D$7493,Cobranza!$B56,Recibos!Z$4:Z$7493) -> 400 | BO56: =SUMIF(Recibos!$D$4:$D$7493,Cobranza!$B56,Recibos!AA$4:AA$7493) -> 400 | BP56: =SUMIF(Recibos!$D$4:$D$7493,Cobranza!$B56,Recibos!AB$4:AB$7493) -> 400 | BQ56: =SUMIF(Recibos!$D$4:$D$7493,Cobranza!$B56,Recibos!AC$4:AC$7493) -> 400 | BR56: =SUMIF(Recibos!$D$4:$D$7493,Cobranza!$B56,Recibos!AD$4:AD$7493) -> 400 | BS56: =SUMIF(Recibos!$D$4:$D$7493,Cobranza!$B56,Recibos!AE$4:AE$7493) -> 400 | ... BW56: =SUMIF(Recibos!$D$4:$D$7493,Cobranza!$B56,Recibos!AI$4:AI$7493) -> 400 | BX56: =SUM(BL56:BW56) -> 4800 | BY56: =SUMIF(Recibos!$D$4:$D$7493,Cobranza!$B56,Recibos!AK$4:AK$7493) -> 400 | BZ56: =SUMIF(Recibos!$D$4:$D$7493,Cobranza!$B56,Recibos!AL$4:AL$7493) -> 400 | CA56: =SUMIF(Recibos!$D$4:$D$7493,Cobranza!$B56,Recibos!AM$4:AM$7493) -> 400 | CB56: =SUMIF(Recibos!$D$4:$D$7493,Cobranza!$B56,Recibos!AN$4:AN$7493) -> 400 | CC56: =SUMIF(Recibos!$D$4:$D$7493,Cobranza!$B56,Recibos!AO$4:AO$7493) -> 400 | CD56: =SUMIF(Recibos!$D$4:$D$7493,Cobranza!$B56,Recibos!AP$4:AP$7493) -> 400 | CE56: =SUMIF(Recibos!$D$4:$D$7493,Cobranza!$B56,Recibos!AQ$4:AQ$7493) -> 400 | CF56: =SUMIF(Recibos!$D$4:$D$7493,Cobranza!$B56,Recibos!AR$4:AR$7493) -> 400 | ... CJ56: =SUMIF(Recibos!$D$4:$D$7493,Cobranza!$B56,Recibos!AV$4:AV$7493) -> 0 | CK56: =SUM(BY56:CJ56) -> 3600
B57: CL_67_ | C57: Rancho La Cuchilla No. 67 | D57: Quezada Viruega | E57: 0 | F57: 0 | G57: 0 | H57: 0 | I57: 0 | J57: 0 | K57: =SUM(E57:J57) -> 0 | L57: 300 | M57: 300 | N57: 0 | O57: 0 | P57: 0 | Q57: 0 | R57: 0 | S57: 0 | T57: 0 | U57: 400 | V57: 400 | W57: 0 | X57: =SUM(L57:W57) -> 1400 | Y57: 400 | Z57: 400 | AA57: 400 | AB57: 0 | AC57: 0 | AD57: 0 | AE57: 0 | AF57: 0 | AG57: 0 | AH57: 0 | AI57: 0 | AJ57: 0 | AK57: =SUM(Y57:AJ57) -> 1200 | AL57: 0 | AM57: 0 | AN57: 0 | AO57: 0 | AP57: 0 | AQ57: 0 | AR57: 0 | AS57: 0 | AT57: 0 | AU57: 0 | AV57: 0 | AW57: 0 | AX57: =SUM(AL57:AW57) -> 0 | AY57: =SUMIF(Recibos!$D$4:$D$7493,Cobranza!$B57,Recibos!K$4:K$7493) -> 0 | AZ57: =SUMIF(Recibos!$D$4:$D$7493,Cobranza!$B57,Recibos!L$4:L$7493) -> 0 | BA57: =SUMIF(Recibos!$D$4:$D$7493,Cobranza!$B57,Recibos!M$4:M$7493) -> 0 | BB57: =SUMIF(Recibos!$D$4:$D$7493,Cobranza!$B57,Recibos!N$4:N$7493) -> 0 | BC57: =SUMIF(Recibos!$D$4:$D$7493,Cobranza!$B57,Recibos!O$4:O$7493) -> 0 | BD57: =SUMIF(Recibos!$D$4:$D$7493,Cobranza!$B57,Recibos!P$4:P$7493) -> 0 | BE57: =SUMIF(Recibos!$D$4:$D$7493,Cobranza!$B57,Recibos!Q$4:Q$7493) -> 400 | BF57: =SUMIF(Recibos!$D$4:$D$7493,Cobranza!$B57,Recibos!R$4:R$7493) -> 0 | ... BJ57: =SUMIF(Recibos!$D$4:$D$7493,Cobranza!$B57,Recibos!V$4:V$7493) -> 0 | BK57: =SUM(AY57:BJ57) -> 400 | BL57: =SUMIF(Recibos!$D$4:$D$7493,Cobranza!$B57,Recibos!X$4:X$7493) -> 0 | BM57: =SUMIF(Recibos!$D$4:$D$7493,Cobranza!$B57,Recibos!Y$4:Y$7493) -> 0 | BN57: =SUMIF(Recibos!$D$4:$D$7493,Cobranza!$B57,Recibos!Z$4:Z$7493) -> 0 | BO57: =SUMIF(Recibos!$D$4:$D$7493,Cobranza!$B57,Recibos!AA$4:AA$7493) -> 0 | BP57: =SUMIF(Recibos!$D$4:$D$7493,Cobranza!$B57,Recibos!AB$4:AB$7493) -> 0 | BQ57: =SUMIF(Recibos!$D$4:$D$7493,Cobranza!$B57,Recibos!AC$4:AC$7493) -> 0 | BR57: =SUMIF(Recibos!$D$4:$D$7493,Cobranza!$B57,Recibos!AD$4:AD$7493) -> 0 | BS57: =SUMIF(Recibos!$D$4:$D$7493,Cobranza!$B57,Recibos!AE$4:AE$7493) -> 0 | ... BW57: =SUMIF(Recibos!$D$4:$D$7493,Cobranza!$B57,Recibos!AI$4:AI$7493) -> 0 | BX57: =SUM(BL57:BW57) -> 0 | BY57: =SUMIF(Recibos!$D$4:$D$7493,Cobranza!$B57,Recibos!AK$4:AK$7493) -> 0 | BZ57: =SUMIF(Recibos!$D$4:$D$7493,Cobranza!$B57,Recibos!AL$4:AL$7493) -> 0 | CA57: =SUMIF(Recibos!$D$4:$D$7493,Cobranza!$B57,Recibos!AM$4:AM$7493) -> 0 | CB57: =SUMIF(Recibos!$D$4:$D$7493,Cobranza!$B57,Recibos!AN$4:AN$7493) -> 0 | CC57: =SUMIF(Recibos!$D$4:$D$7493,Cobranza!$B57,Recibos!AO$4:AO$7493) -> 400 | CD57: =SUMIF(Recibos!$D$4:$D$7493,Cobranza!$B57,Recibos!AP$4:AP$7493) -> 400 | CE57: =SUMIF(Recibos!$D$4:$D$7493,Cobranza!$B57,Recibos!AQ$4:AQ$7493) -> 400 | CF57: =SUMIF(Recibos!$D$4:$D$7493,Cobranza!$B57,Recibos!AR$4:AR$7493) -> 400 | ... CJ57: =SUMIF(Recibos!$D$4:$D$7493,Cobranza!$B57,Recibos!AV$4:AV$7493) -> 0 | CK57: =SUM(BY57:CJ57) -> 1600
B58: CL_68_ | C58: Rancho La Cuchilla No. 68 | D58: Montesinos | E58: 0 | F58: 0 | G58: 0 | H58: 0 | I58: 300 | J58: 300 | K58: =SUM(E58:J58) -> 600 | L58: 300 | M58: 300 | N58: 0 | O58: 0 | P58: 0 | Q58: 0 | R58: 0 | S58: 0 | T58: 0 | U58: 0 | V58: 0 | W58: 0 | X58: =SUM(L58:W58) -> 600 | Y58: 0 | Z58: 0 | AA58: 0 | AB58: 200 | AC58: 200 | AD58: 200 | AE58: 200 | AF58: 200 | AG58: 200 | AH58: 200 | AI58: 200 | AJ58: 200 | AK58: =SUM(Y58:AJ58) -> 1800 | AL58: 200 | AM58: 200 | AN58: 200 | AO58: 200 | AP58: 200 | AQ58: 200 | AR58: 200 | AS58: 200 | AT58: 200 | AU58: 200 | AV58: 200 | AW58: 200 | AX58: =SUM(AL58:AW58) -> 2400 | AY58: =SUMIF(Recibos!$D$4:$D$7493,Cobranza!$B58,Recibos!K$4:K$7493) -> 200 | AZ58: =SUMIF(Recibos!$D$4:$D$7493,Cobranza!$B58,Recibos!L$4:L$7493) -> 200 | BA58: =SUMIF(Recibos!$D$4:$D$7493,Cobranza!$B58,Recibos!M$4:M$7493) -> 200 | BB58: =SUMIF(Recibos!$D$4:$D$7493,Cobranza!$B58,Recibos!N$4:N$7493) -> 200 | BC58: =SUMIF(Recibos!$D$4:$D$7493,Cobranza!$B58,Recibos!O$4:O$7493) -> 200 | BD58: =SUMIF(Recibos!$D$4:$D$7493,Cobranza!$B58,Recibos!P$4:P$7493) -> 200 | BE58: =SUMIF(Recibos!$D$4:$D$7493,Cobranza!$B58,Recibos!Q$4:Q$7493) -> 200 | BF58: =SUMIF(Recibos!$D$4:$D$7493,Cobranza!$B58,Recibos!R$4:R$7493) -> 200 | ... BJ58: =SUMIF(Recibos!$D$4:$D$7493,Cobranza!$B58,Recibos!V$4:V$7493) -> 200 | BK58: =SUM(AY58:BJ58) -> 2400 | BL58: =SUMIF(Recibos!$D$4:$D$7493,Cobranza!$B58,Recibos!X$4:X$7493) -> 200 | BM58: =SUMIF(Recibos!$D$4:$D$7493,Cobranza!$B58,Recibos!Y$4:Y$7493) -> 200 | BN58: =SUMIF(Recibos!$D$4:$D$7493,Cobranza!$B58,Recibos!Z$4:Z$7493) -> 200 | BO58: =SUMIF(Recibos!$D$4:$D$7493,Cobranza!$B58,Recibos!AA$4:AA$7493) -> 200 | BP58: =SUMIF(Recibos!$D$4:$D$7493,Cobranza!$B58,Recibos!AB$4:AB$7493) -> 200 | BQ58: =SUMIF(Recibos!$D$4:$D$7493,Cobranza!$B58,Recibos!AC$4:AC$7493) -> 200 | BR58: =SUMIF(Recibos!$D$4:$D$7493,Cobranza!$B58,Recibos!AD$4:AD$7493) -> 200 | BS58: =SUMIF(Recibos!$D$4:$D$7493,Cobranza!$B58,Recibos!AE$4:AE$7493) -> 200 | ... BW58: =SUMIF(Recibos!$D$4:$D$7493,Cobranza!$B58,Recibos!AI$4:AI$7493) -> 200 | BX58: =SUM(BL58:BW58) -> 2400 | BY58: =SUMIF(Recibos!$D$4:$D$7493,Cobranza!$B58,Recibos!AK$4:AK$7493) -> 200 | BZ58: =SUMIF(Recibos!$D$4:$D$7493,Cobranza!$B58,Recibos!AL$4:AL$7493) -> 200 | CA58: =SUMIF(Recibos!$D$4:$D$7493,Cobranza!$B58,Recibos!AM$4:AM$7493) -> 200 | CB58: =SUMIF(Recibos!$D$4:$D$7493,Cobranza!$B58,Recibos!AN$4:AN$7493) -> 200 | CC58: =SUMIF(Recibos!$D$4:$D$7493,Cobranza!$B58,Recibos!AO$4:AO$7493) -> 200 | CD58: =SUMIF(Recibos!$D$4:$D$7493,Cobranza!$B58,Recibos!AP$4:AP$7493) -> 200 | CE58: =SUMIF(Recibos!$D$4:$D$7493,Cobranza!$B58,Recibos!AQ$4:AQ$7493) -> 200 | CF58: =SUMIF(Recibos!$D$4:$D$7493,Cobranza!$B58,Recibos!AR$4:AR$7493) -> 200 | ... CJ58: =SUMIF(Recibos!$D$4:$D$7493,Cobranza!$B58,Recibos!AV$4:AV$7493) -> 0 | CK58: =SUM(BY58:CJ58) -> 2000
B59: CL_69_ | C59: Rancho La Cuchilla No. 69 | D59: Romero | E59: 0 | F59: 0 | G59: 0 | H59: 0 | I59: 0 | J59: 0 | K59: =SUM(E59:J59) -> 0 | L59: 0 | M59: 0 | N59: 0 | O59: 0 | P59: 0 | Q59: 0 | R59: 0 | S59: 0 | T59: 0 | U59: 0 | V59: 0 | W59: 0 | X59: =SUM(L59:W59) -> 0 | Y59: 0 | Z59: 0 | AA59: 0 | AB59: 0 | AC59: 0 | AD59: 0 | AE59: 0 | AF59: 0 | AG59: 0 | AH59: 0 | AI59: 400 | AJ59: 0 | AK59: =SUM(Y59:AJ59) -> 400 | AL59: 0 | AM59: 0 | AN59: 0 | AO59: 0 | AP59: 0 | AQ59: 0 | AR59: 0 | AS59: 0 | AT59: 0 | AU59: 0 | AV59: 0 | AW59: 0 | AX59: =SUM(AL59:AW59) -> 0 | AY59: =SUMIF(Recibos!$D$4:$D$7493,Cobranza!$B59,Recibos!K$4:K$7493) -> 0 | AZ59: =SUMIF(Recibos!$D$4:$D$7493,Cobranza!$B59,Recibos!L$4:L$7493) -> 0 | BA59: =SUMIF(Recibos!$D$4:$D$7493,Cobranza!$B59,Recibos!M$4:M$7493) -> 400 | BB59: =SUMIF(Recibos!$D$4:$D$7493,Cobranza!$B59,Recibos!N$4:N$7493) -> 400 | BC59: =SUMIF(Recibos!$D$4:$D$7493,Cobranza!$B59,Recibos!O$4:O$7493) -> 0 | BD59: =SUMIF(Recibos!$D$4:$D$7493,Cobranza!$B59,Recibos!P$4:P$7493) -> 0 | BE59: =SUMIF(Recibos!$D$4:$D$7493,Cobranza!$B59,Recibos!Q$4:Q$7493) -> 0 | BF59: =SUMIF(Recibos!$D$4:$D$7493,Cobranza!$B59,Recibos!R$4:R$7493) -> 0 | ... BJ59: =SUMIF(Recibos!$D$4:$D$7493,Cobranza!$B59,Recibos!V$4:V$7493) -> 0 | BK59: =SUM(AY59:BJ59) -> 800 | BL59: =SUMIF(Recibos!$D$4:$D$7493,Cobranza!$B59,Recibos!X$4:X$7493) -> 0 | BM59: =SUMIF(Recibos!$D$4:$D$7493,Cobranza!$B59,Recibos!Y$4:Y$7493) -> 0 | BN59: =SUMIF(Recibos!$D$4:$D$7493,Cobranza!$B59,Recibos!Z$4:Z$7493) -> 0 | BO59: =SUMIF(Recibos!$D$4:$D$7493,Cobranza!$B59,Recibos!AA$4:AA$7493) -> 0 | BP59: =SUMIF(Recibos!$D$4:$D$7493,Cobranza!$B59,Recibos!AB$4:AB$7493) -> 0 | BQ59: =SUMIF(Recibos!$D$4:$D$7493,Cobranza!$B59,Recibos!AC$4:AC$7493) -> 0 | BR59: =SUMIF(Recibos!$D$4:$D$7493,Cobranza!$B59,Recibos!AD$4:AD$7493) -> 0 | BS59: =SUMIF(Recibos!$D$4:$D$7493,Cobranza!$B59,Recibos!AE$4:AE$7493) -> 0 | ... BW59: =SUMIF(Recibos!$D$4:$D$7493,Cobranza!$B59,Recibos!AI$4:AI$7493) -> 0 | BX59: =SUM(BL59:BW59) -> 0 | BY59: =SUMIF(Recibos!$D$4:$D$7493,Cobranza!$B59,Recibos!AK$4:AK$7493) -> 0 | BZ59: =SUMIF(Recibos!$D$4:$D$7493,Cobranza!$B59,Recibos!AL$4:AL$7493) -> 0 | CA59: =SUMIF(Recibos!$D$4:$D$7493,Cobranza!$B59,Recibos!AM$4:AM$7493) -> 0 | CB59: =SUMIF(Recibos!$D$4:$D$7493,Cobranza!$B59,Recibos!AN$4:AN$7493) -> 0 | CC59: =SUMIF(Recibos!$D$4:$D$7493,Cobranza!$B59,Recibos!AO$4:AO$7493) -> 0 | CD59: =SUMIF(Recibos!$D$4:$D$7493,Cobranza!$B59,Recibos!AP$4:AP$7493) -> 0 | CE59: =SUMIF(Recibos!$D$4:$D$7493,Cobranza!$B59,Recibos!AQ$4:AQ$7493) -> 0 | CF59: =SUMIF(Recibos!$D$4:$D$7493,Cobranza!$B59,Recibos!AR$4:AR$7493) -> 0 | ... CJ59: =SUMIF(Recibos!$D$4:$D$7493,Cobranza!$B59,Recibos!AV$4:AV$7493) -> 0 | CK59: =SUM(BY59:CJ59) -> 0
B60: CL_70_ | C60: Rancho La Cuchilla No. 70 | E60: 0 | F60: 0 | G60: 0 | H60: 0 | I60: 0 | J60: 0 | K60: =SUM(E60:J60) -> 0 | L60: 0 | M60: 0 | N60: 0 | O60: 0 | P60: 0 | Q60: 0 | R60: 0 | S60: 0 | T60: 0 | U60: 0 | V60: 0 | W60: 0 | X60: =SUM(L60:W60) -> 0 | Y60: 0 | Z60: 0 | AA60: 0 | AB60: 0 | AC60: 0 | AD60: 0 | AE60: 0 | AF60: 0 | AG60: 0 | AH60: 200 | AI60: 0 | AJ60: 0 | AK60: =SUM(Y60:AJ60) -> 200 | AL60: 0 | AM60: 0 | AN60: 0 | AO60: 0 | AP60: 0 | AQ60: 0 | AR60: 0 | AS60: 0 | AT60: 0 | AU60: 0 | AV60: 0 | AW60: 0 | AX60: =SUM(AL60:AW60) -> 0 | AY60: =SUMIF(Recibos!$D$4:$D$7493,Cobranza!$B60,Recibos!K$4:K$7493) -> 0 | AZ60: =SUMIF(Recibos!$D$4:$D$7493,Cobranza!$B60,Recibos!L$4:L$7493) -> 0 | BA60: =SUMIF(Recibos!$D$4:$D$7493,Cobranza!$B60,Recibos!M$4:M$7493) -> 0 | BB60: =SUMIF(Recibos!$D$4:$D$7493,Cobranza!$B60,Recibos!N$4:N$7493) -> 0 | BC60: =SUMIF(Recibos!$D$4:$D$7493,Cobranza!$B60,Recibos!O$4:O$7493) -> 0 | BD60: =SUMIF(Recibos!$D$4:$D$7493,Cobranza!$B60,Recibos!P$4:P$7493) -> 0 | BE60: =SUMIF(Recibos!$D$4:$D$7493,Cobranza!$B60,Recibos!Q$4:Q$7493) -> 0 | BF60: =SUMIF(Recibos!$D$4:$D$7493,Cobranza!$B60,Recibos!R$4:R$7493) -> 0 | ... BJ60: =SUMIF(Recibos!$D$4:$D$7493,Cobranza!$B60,Recibos!V$4:V$7493) -> 0 | BK60: =SUM(AY60:BJ60) -> 0 | BL60: =SUMIF(Recibos!$D$4:$D$7493,Cobranza!$B60,Recibos!X$4:X$7493) -> 0 | BM60: =SUMIF(Recibos!$D$4:$D$7493,Cobranza!$B60,Recibos!Y$4:Y$7493) -> 0 | BN60: =SUMIF(Recibos!$D$4:$D$7493,Cobranza!$B60,Recibos!Z$4:Z$7493) -> 0 | BO60: =SUMIF(Recibos!$D$4:$D$7493,Cobranza!$B60,Recibos!AA$4:AA$7493) -> 0 | BP60: =SUMIF(Recibos!$D$4:$D$7493,Cobranza!$B60,Recibos!AB$4:AB$7493) -> 0 | BQ60: =SUMIF(Recibos!$D$4:$D$7493,Cobranza!$B60,Recibos!AC$4:AC$7493) -> 0 | BR60: =SUMIF(Recibos!$D$4:$D$7493,Cobranza!$B60,Recibos!AD$4:AD$7493) -> 0 | BS60: =SUMIF(Recibos!$D$4:$D$7493,Cobranza!$B60,Recibos!AE$4:AE$7493) -> 0 | ... BW60: =SUMIF(Recibos!$D$4:$D$7493,Cobranza!$B60,Recibos!AI$4:AI$7493) -> 0 | BX60: =SUM(BL60:BW60) -> 0 | BY60: =SUMIF(Recibos!$D$4:$D$7493,Cobranza!$B60,Recibos!AK$4:AK$7493) -> 0 | BZ60: =SUMIF(Recibos!$D$4:$D$7493,Cobranza!$B60,Recibos!AL$4:AL$7493) -> 0 | CA60: =SUMIF(Recibos!$D$4:$D$7493,Cobranza!$B60,Recibos!AM$4:AM$7493) -> 0 | CB60: =SUMIF(Recibos!$D$4:$D$7493,Cobranza!$B60,Recibos!AN$4:AN$7493) -> 0 | CC60: =SUMIF(Recibos!$D$4:$D$7493,Cobranza!$B60,Recibos!AO$4:AO$7493) -> 0 | CD60: =SUMIF(Recibos!$D$4:$D$7493,Cobranza!$B60,Recibos!AP$4:AP$7493) -> 0 | CE60: =SUMIF(Recibos!$D$4:$D$7493,Cobranza!$B60,Recibos!AQ$4:AQ$7493) -> 0 | CF60: =SUMIF(Recibos!$D$4:$D$7493,Cobranza!$B60,Recibos!AR$4:AR$7493) -> 0 | ... CJ60: =SUMIF(Recibos!$D$4:$D$7493,Cobranza!$B60,Recibos!AV$4:AV$7493) -> 0 | CK60: =SUM(BY60:CJ60) -> 0
B61: CL_71_ | C61: Rancho La Cuchilla No. 71 | D61: Flores | E61: 0 | F61: 0 | G61: 0 | H61: 0 | I61: 0 | J61: 300 | K61: =SUM(E61:J61) -> 300 | L61: 300 | M61: 300 | N61: 300 | O61: 300 | P61: 300 | Q61: 300 | R61: 300 | S61: 300 | T61: 300 | U61: 300 | V61: 300 | W61: 300 | X61: =SUM(L61:W61) -> 3600 | Y61: 350 | Z61: 350 | AA61: 350 | AB61: 350 | AC61: 350 | AD61: 350 | AE61: 350 | AF61: 0 | AG61: 350 | AH61: 700 | AI61: 350 | AJ61: 350 | AK61: =SUM(Y61:AJ61) -> 4200 | AL61: 350 | AM61: 350 | AN61: 350 | AO61: 350 | AP61: 350 | AQ61: 350 | AR61: 350 | AS61: 350 | AT61: 350 | AU61: 350 | AV61: 350 | AW61: 350 | AX61: =SUM(AL61:AW61) -> 4200 | AY61: =SUMIF(Recibos!$D$4:$D$7493,Cobranza!$B61,Recibos!K$4:K$7493) -> 350 | AZ61: =SUMIF(Recibos!$D$4:$D$7493,Cobranza!$B61,Recibos!L$4:L$7493) -> 350 | BA61: =SUMIF(Recibos!$D$4:$D$7493,Cobranza!$B61,Recibos!M$4:M$7493) -> 350 | BB61: =SUMIF(Recibos!$D$4:$D$7493,Cobranza!$B61,Recibos!N$4:N$7493) -> 350 | BC61: =SUMIF(Recibos!$D$4:$D$7493,Cobranza!$B61,Recibos!O$4:O$7493) -> 400 | BD61: =SUMIF(Recibos!$D$4:$D$7493,Cobranza!$B61,Recibos!P$4:P$7493) -> 400 | BE61: =SUMIF(Recibos!$D$4:$D$7493,Cobranza!$B61,Recibos!Q$4:Q$7493) -> 400 | BF61: =SUMIF(Recibos!$D$4:$D$7493,Cobranza!$B61,Recibos!R$4:R$7493) -> 400 | ... BJ61: =SUMIF(Recibos!$D$4:$D$7493,Cobranza!$B61,Recibos!V$4:V$7493) -> 400 | BK61: =SUM(AY61:BJ61) -> 4600 | BL61: =SUMIF(Recibos!$D$4:$D$7493,Cobranza!$B61,Recibos!X$4:X$7493) -> 0 | BM61: =SUMIF(Recibos!$D$4:$D$7493,Cobranza!$B61,Recibos!Y$4:Y$7493) -> 0 | BN61: =SUMIF(Recibos!$D$4:$D$7493,Cobranza!$B61,Recibos!Z$4:Z$7493) -> 0 | BO61: =SUMIF(Recibos!$D$4:$D$7493,Cobranza!$B61,Recibos!AA$4:AA$7493) -> 0 | BP61: =SUMIF(Recibos!$D$4:$D$7493,Cobranza!$B61,Recibos!AB$4:AB$7493) -> 0 | BQ61: =SUMIF(Recibos!$D$4:$D$7493,Cobranza!$B61,Recibos!AC$4:AC$7493) -> 0 | BR61: =SUMIF(Recibos!$D$4:$D$7493,Cobranza!$B61,Recibos!AD$4:AD$7493) -> 0 | BS61: =SUMIF(Recibos!$D$4:$D$7493,Cobranza!$B61,Recibos!AE$4:AE$7493) -> 0 | ... BW61: =SUMIF(Recibos!$D$4:$D$7493,Cobranza!$B61,Recibos!AI$4:AI$7493) -> 0 | BX61: =SUM(BL61:BW61) -> 0 | BY61: =SUMIF(Recibos!$D$4:$D$7493,Cobranza!$B61,Recibos!AK$4:AK$7493) -> 0 | BZ61: =SUMIF(Recibos!$D$4:$D$7493,Cobranza!$B61,Recibos!AL$4:AL$7493) -> 0 | CA61: =SUMIF(Recibos!$D$4:$D$7493,Cobranza!$B61,Recibos!AM$4:AM$7493) -> 0 | CB61: =SUMIF(Recibos!$D$4:$D$7493,Cobranza!$B61,Recibos!AN$4:AN$7493) -> 0 | CC61: =SUMIF(Recibos!$D$4:$D$7493,Cobranza!$B61,Recibos!AO$4:AO$7493) -> 0 | CD61: =SUMIF(Recibos!$D$4:$D$7493,Cobranza!$B61,Recibos!AP$4:AP$7493) -> 0 | CE61: =SUMIF(Recibos!$D$4:$D$7493,Cobranza!$B61,Recibos!AQ$4:AQ$7493) -> 0 | CF61: =SUMIF(Recibos!$D$4:$D$7493,Cobranza!$B61,Recibos!AR$4:AR$7493) -> 0 | ... CJ61: =SUMIF(Recibos!$D$4:$D$7493,Cobranza!$B61,Recibos!AV$4:AV$7493) -> 0 | CK61: =SUM(BY61:CJ61) -> 0
B62: CL_72_ | C62: Rancho La Cuchilla No. 72 | D62: Ortiz González | E62: 0 | F62: 0 | G62: 0 | H62: 0 | I62: 0 | J62: 300 | K62: =SUM(E62:J62) -> 300 | L62: 300 | M62: 300 | N62: 300 | O62: 300 | P62: 300 | Q62: 0 | R62: 300 | S62: 300 | T62: 300 | U62: 400 | V62: 400 | W62: 400 | X62: =SUM(L62:W62) -> 3600 | Y62: 400 | Z62: 400 | AA62: 400 | AB62: 400 | AC62: 400 | AD62: 400 | AE62: 400 | AF62: 400 | AG62: 400 | AH62: 400 | AI62: 400 | AJ62: 400 | AK62: =SUM(Y62:AJ62) -> 4800 | AL62: 400 | AM62: 400 | AN62: 400 | AO62: 400 | AP62: 400 | AQ62: 400 | AR62: 400 | AS62: 400 | AT62: 400 | AU62: 400 | AV62: 400 | AW62: 400 | AX62: =SUM(AL62:AW62) -> 4800 | AY62: =SUMIF(Recibos!$D$4:$D$7493,Cobranza!$B62,Recibos!K$4:K$7493) -> 400 | AZ62: =SUMIF(Recibos!$D$4:$D$7493,Cobranza!$B62,Recibos!L$4:L$7493) -> 400 | BA62: =SUMIF(Recibos!$D$4:$D$7493,Cobranza!$B62,Recibos!M$4:M$7493) -> 400 | BB62: =SUMIF(Recibos!$D$4:$D$7493,Cobranza!$B62,Recibos!N$4:N$7493) -> 400 | BC62: =SUMIF(Recibos!$D$4:$D$7493,Cobranza!$B62,Recibos!O$4:O$7493) -> 400 | BD62: =SUMIF(Recibos!$D$4:$D$7493,Cobranza!$B62,Recibos!P$4:P$7493) -> 400 | BE62: =SUMIF(Recibos!$D$4:$D$7493,Cobranza!$B62,Recibos!Q$4:Q$7493) -> 400 | BF62: =SUMIF(Recibos!$D$4:$D$7493,Cobranza!$B62,Recibos!R$4:R$7493) -> 400 | ... BJ62: =SUMIF(Recibos!$D$4:$D$7493,Cobranza!$B62,Recibos!V$4:V$7493) -> 400 | BK62: =SUM(AY62:BJ62) -> 4800 | BL62: =SUMIF(Recibos!$D$4:$D$7493,Cobranza!$B62,Recibos!X$4:X$7493) -> 400 | BM62: =SUMIF(Recibos!$D$4:$D$7493,Cobranza!$B62,Recibos!Y$4:Y$7493) -> 400 | BN62: =SUMIF(Recibos!$D$4:$D$7493,Cobranza!$B62,Recibos!Z$4:Z$7493) -> 400 | BO62: =SUMIF(Recibos!$D$4:$D$7493,Cobranza!$B62,Recibos!AA$4:AA$7493) -> 400 | BP62: =SUMIF(Recibos!$D$4:$D$7493,Cobranza!$B62,Recibos!AB$4:AB$7493) -> 400 | BQ62: =SUMIF(Recibos!$D$4:$D$7493,Cobranza!$B62,Recibos!AC$4:AC$7493) -> 400 | BR62: =SUMIF(Recibos!$D$4:$D$7493,Cobranza!$B62,Recibos!AD$4:AD$7493) -> 400 | BS62: =SUMIF(Recibos!$D$4:$D$7493,Cobranza!$B62,Recibos!AE$4:AE$7493) -> 400 | ... BW62: =SUMIF(Recibos!$D$4:$D$7493,Cobranza!$B62,Recibos!AI$4:AI$7493) -> 400 | BX62: =SUM(BL62:BW62) -> 4800 | BY62: =SUMIF(Recibos!$D$4:$D$7493,Cobranza!$B62,Recibos!AK$4:AK$7493) -> 400 | BZ62: =SUMIF(Recibos!$D$4:$D$7493,Cobranza!$B62,Recibos!AL$4:AL$7493) -> 400 | CA62: =SUMIF(Recibos!$D$4:$D$7493,Cobranza!$B62,Recibos!AM$4:AM$7493) -> 400 | CB62: =SUMIF(Recibos!$D$4:$D$7493,Cobranza!$B62,Recibos!AN$4:AN$7493) -> 400 | CC62: =SUMIF(Recibos!$D$4:$D$7493,Cobranza!$B62,Recibos!AO$4:AO$7493) -> 400 | CD62: =SUMIF(Recibos!$D$4:$D$7493,Cobranza!$B62,Recibos!AP$4:AP$7493) -> 400 | CE62: =SUMIF(Recibos!$D$4:$D$7493,Cobranza!$B62,Recibos!AQ$4:AQ$7493) -> 400 | CF62: =SUMIF(Recibos!$D$4:$D$7493,Cobranza!$B62,Recibos!AR$4:AR$7493) -> 400 | ... CJ62: =SUMIF(Recibos!$D$4:$D$7493,Cobranza!$B62,Recibos!AV$4:AV$7493) -> 0 | CK62: =SUM(BY62:CJ62) -> 4000
B63: CL_73_ | C63: Rancho La Cuchilla No. 73 | D63: Cooper | E63: 0 | F63: 0 | G63: 0 | H63: 0 | I63: 0 | J63: 0 | K63: =SUM(E63:J63) -> 0 | L63: 300 | M63: 300 | N63: 0 | O63: 300 | P63: 300 | Q63: 300 | R63: 300 | S63: 300 | T63: 300 | U63: 300 | V63: 300 | W63: 300 | X63: =SUM(L63:W63) -> 3300 | Y63: 400 | Z63: 400 | AA63: 400 | AB63: 400 | AC63: 400 | AD63: 400 | AE63: 400 | AF63: 400 | AG63: 400 | AH63: 0 | AI63: 0 | AJ63: 0 | AK63: =SUM(Y63:AJ63) -> 3600 | AL63: 400 | AM63: 400 | AN63: 400 | AO63: 400 | AP63: 400 | AQ63: 400 | AR63: 400 | AS63: 400 | AT63: 400 | AU63: 400 | AV63: 400 | AW63: 0 | AX63: =SUM(AL63:AW63) -> 4400 | AY63: =SUMIF(Recibos!$D$4:$D$7493,Cobranza!$B63,Recibos!K$4:K$7493) -> 400 | AZ63: =SUMIF(Recibos!$D$4:$D$7493,Cobranza!$B63,Recibos!L$4:L$7493) -> 400 | BA63: =SUMIF(Recibos!$D$4:$D$7493,Cobranza!$B63,Recibos!M$4:M$7493) -> 400 | BB63: =SUMIF(Recibos!$D$4:$D$7493,Cobranza!$B63,Recibos!N$4:N$7493) -> 400 | BC63: =SUMIF(Recibos!$D$4:$D$7493,Cobranza!$B63,Recibos!O$4:O$7493) -> 400 | BD63: =SUMIF(Recibos!$D$4:$D$7493,Cobranza!$B63,Recibos!P$4:P$7493) -> 400 | BE63: =SUMIF(Recibos!$D$4:$D$7493,Cobranza!$B63,Recibos!Q$4:Q$7493) -> 400 | BF63: =SUMIF(Recibos!$D$4:$D$7493,Cobranza!$B63,Recibos!R$4:R$7493) -> 400 | ... BJ63: =SUMIF(Recibos!$D$4:$D$7493,Cobranza!$B63,Recibos!V$4:V$7493) -> 0 | BK63: =SUM(AY63:BJ63) -> 4400 | BL63: =SUMIF(Recibos!$D$4:$D$7493,Cobranza!$B63,Recibos!X$4:X$7493) -> 400 | BM63: =SUMIF(Recibos!$D$4:$D$7493,Cobranza!$B63,Recibos!Y$4:Y$7493) -> 400 | BN63: =SUMIF(Recibos!$D$4:$D$7493,Cobranza!$B63,Recibos!Z$4:Z$7493) -> 400 | BO63: =SUMIF(Recibos!$D$4:$D$7493,Cobranza!$B63,Recibos!AA$4:AA$7493) -> 400 | BP63: =SUMIF(Recibos!$D$4:$D$7493,Cobranza!$B63,Recibos!AB$4:AB$7493) -> 400 | BQ63: =SUMIF(Recibos!$D$4:$D$7493,Cobranza!$B63,Recibos!AC$4:AC$7493) -> 400 | BR63: =SUMIF(Recibos!$D$4:$D$7493,Cobranza!$B63,Recibos!AD$4:AD$7493) -> 400 | BS63: =SUMIF(Recibos!$D$4:$D$7493,Cobranza!$B63,Recibos!AE$4:AE$7493) -> 400 | ... BW63: =SUMIF(Recibos!$D$4:$D$7493,Cobranza!$B63,Recibos!AI$4:AI$7493) -> 400 | BX63: =SUM(BL63:BW63) -> 4800 | BY63: =SUMIF(Recibos!$D$4:$D$7493,Cobranza!$B63,Recibos!AK$4:AK$7493) -> 400 | BZ63: =SUMIF(Recibos!$D$4:$D$7493,Cobranza!$B63,Recibos!AL$4:AL$7493) -> 400 | CA63: =SUMIF(Recibos!$D$4:$D$7493,Cobranza!$B63,Recibos!AM$4:AM$7493) -> 400 | CB63: =SUMIF(Recibos!$D$4:$D$7493,Cobranza!$B63,Recibos!AN$4:AN$7493) -> 400 | CC63: =SUMIF(Recibos!$D$4:$D$7493,Cobranza!$B63,Recibos!AO$4:AO$7493) -> 400 | CD63: =SUMIF(Recibos!$D$4:$D$7493,Cobranza!$B63,Recibos!AP$4:AP$7493) -> 400 | CE63: =SUMIF(Recibos!$D$4:$D$7493,Cobranza!$B63,Recibos!AQ$4:AQ$7493) -> 0 | CF63: =SUMIF(Recibos!$D$4:$D$7493,Cobranza!$B63,Recibos!AR$4:AR$7493) -> 0 | ... CJ63: =SUMIF(Recibos!$D$4:$D$7493,Cobranza!$B63,Recibos!AV$4:AV$7493) -> 0 | CK63: =SUM(BY63:CJ63) -> 2400
B64: CL_74_ | C64: Rancho La Cuchilla No. 74 | D64: Gil | E64: 0 | F64: 0 | G64: 0 | H64: 0 | I64: 0 | J64: 0 | K64: =SUM(E64:J64) -> 0 | L64: 600 | M64: 300 | N64: 300 | O64: 300 | P64: 300 | Q64: 300 | R64: 300 | S64: 300 | T64: 300 | U64: 0 | V64: 0 | W64: 0 | X64: =SUM(L64:W64) -> 3000 | Y64: 0 | Z64: 0 | AA64: 0 | AB64: 0 | AC64: 0 | AD64: 0 | AE64: 0 | AF64: 0 | AG64: 0 | AH64: 0 | AI64: 0 | AJ64: 0 | AK64: =SUM(Y64:AJ64) -> 0 | AL64: 400 | AM64: 400 | AN64: 400 | AO64: 400 | AP64: 0 | AQ64: 0 | AR64: 0 | AS64: 0 | AT64: 0 | AU64: 0 | AV64: 0 | AW64: 0 | AX64: =SUM(AL64:AW64) -> 1600 | AY64: =SUMIF(Recibos!$D$4:$D$7493,Cobranza!$B64,Recibos!K$4:K$7493) -> 400 | AZ64: =SUMIF(Recibos!$D$4:$D$7493,Cobranza!$B64,Recibos!L$4:L$7493) -> 400 | BA64: =SUMIF(Recibos!$D$4:$D$7493,Cobranza!$B64,Recibos!M$4:M$7493) -> 400 | BB64: =SUMIF(Recibos!$D$4:$D$7493,Cobranza!$B64,Recibos!N$4:N$7493) -> 400 | BC64: =SUMIF(Recibos!$D$4:$D$7493,Cobranza!$B64,Recibos!O$4:O$7493) -> 400 | BD64: =SUMIF(Recibos!$D$4:$D$7493,Cobranza!$B64,Recibos!P$4:P$7493) -> 0 | BE64: =SUMIF(Recibos!$D$4:$D$7493,Cobranza!$B64,Recibos!Q$4:Q$7493) -> 0 | BF64: =SUMIF(Recibos!$D$4:$D$7493,Cobranza!$B64,Recibos!R$4:R$7493) -> 0 | ... BJ64: =SUMIF(Recibos!$D$4:$D$7493,Cobranza!$B64,Recibos!V$4:V$7493) -> 0 | BK64: =SUM(AY64:BJ64) -> 2000 | BL64: =SUMIF(Recibos!$D$4:$D$7493,Cobranza!$B64,Recibos!X$4:X$7493) -> 400 | BM64: =SUMIF(Recibos!$D$4:$D$7493,Cobranza!$B64,Recibos!Y$4:Y$7493) -> 400 | BN64: =SUMIF(Recibos!$D$4:$D$7493,Cobranza!$B64,Recibos!Z$4:Z$7493) -> 400 | BO64: =SUMIF(Recibos!$D$4:$D$7493,Cobranza!$B64,Recibos!AA$4:AA$7493) -> 400 | BP64: =SUMIF(Recibos!$D$4:$D$7493,Cobranza!$B64,Recibos!AB$4:AB$7493) -> 400 | BQ64: =SUMIF(Recibos!$D$4:$D$7493,Cobranza!$B64,Recibos!AC$4:AC$7493) -> 400 | BR64: =SUMIF(Recibos!$D$4:$D$7493,Cobranza!$B64,Recibos!AD$4:AD$7493) -> 0 | BS64: =SUMIF(Recibos!$D$4:$D$7493,Cobranza!$B64,Recibos!AE$4:AE$7493) -> 0 | ... BW64: =SUMIF(Recibos!$D$4:$D$7493,Cobranza!$B64,Recibos!AI$4:AI$7493) -> 0 | BX64: =SUM(BL64:BW64) -> 2400 | BY64: =SUMIF(Recibos!$D$4:$D$7493,Cobranza!$B64,Recibos!AK$4:AK$7493) -> 0 | BZ64: =SUMIF(Recibos!$D$4:$D$7493,Cobranza!$B64,Recibos!AL$4:AL$7493) -> 0 | CA64: =SUMIF(Recibos!$D$4:$D$7493,Cobranza!$B64,Recibos!AM$4:AM$7493) -> 0 | CB64: =SUMIF(Recibos!$D$4:$D$7493,Cobranza!$B64,Recibos!AN$4:AN$7493) -> 0 | CC64: =SUMIF(Recibos!$D$4:$D$7493,Cobranza!$B64,Recibos!AO$4:AO$7493) -> 0 | CD64: =SUMIF(Recibos!$D$4:$D$7493,Cobranza!$B64,Recibos!AP$4:AP$7493) -> 0 | CE64: =SUMIF(Recibos!$D$4:$D$7493,Cobranza!$B64,Recibos!AQ$4:AQ$7493) -> 0 | CF64: =SUMIF(Recibos!$D$4:$D$7493,Cobranza!$B64,Recibos!AR$4:AR$7493) -> 0 | ... CJ64: =SUMIF(Recibos!$D$4:$D$7493,Cobranza!$B64,Recibos!AV$4:AV$7493) -> 0 | CK64: =SUM(BY64:CJ64) -> 400
B65: CL_75_ | C65: Rancho La Cuchilla No. 75 | D65: Sosa Lucio | E65: 0 | F65: 0 | G65: 0 | H65: 0 | I65: 300 | J65: 300 | K65: =SUM(E65:J65) -> 600 | L65: 300 | M65: 300 | N65: 300 | O65: 300 | P65: 300 | Q65: 300 | R65: 300 | S65: 300 | T65: 300 | U65: 400 | V65: 400 | W65: 400 | X65: =SUM(L65:W65) -> 3900 | Y65: 400 | Z65: 400 | AA65: 400 | AB65: 400 | AC65: 400 | AD65: 400 | AE65: 400 | AF65: 400 | AG65: 400 | AH65: 400 | AI65: 400 | AJ65: 300 | AK65: =SUM(Y65:AJ65) -> 4700 | AL65: 300 | AM65: 300 | AN65: 300 | AO65: 300 | AP65: 300 | AQ65: 300 | AR65: 300 | AS65: 300 | AT65: 300 | AU65: 300 | AV65: 300 | AW65: 300 | AX65: =SUM(AL65:AW65) -> 3600 | AY65: =SUMIF(Recibos!$D$4:$D$7493,Cobranza!$B65,Recibos!K$4:K$7493) -> 300 | AZ65: =SUMIF(Recibos!$D$4:$D$7493,Cobranza!$B65,Recibos!L$4:L$7493) -> 300 | BA65: =SUMIF(Recibos!$D$4:$D$7493,Cobranza!$B65,Recibos!M$4:M$7493) -> 300 | BB65: =SUMIF(Recibos!$D$4:$D$7493,Cobranza!$B65,Recibos!N$4:N$7493) -> 300 | BC65: =SUMIF(Recibos!$D$4:$D$7493,Cobranza!$B65,Recibos!O$4:O$7493) -> 300 | BD65: =SUMIF(Recibos!$D$4:$D$7493,Cobranza!$B65,Recibos!P$4:P$7493) -> 300 | BE65: =SUMIF(Recibos!$D$4:$D$7493,Cobranza!$B65,Recibos!Q$4:Q$7493) -> 300 | BF65: =SUMIF(Recibos!$D$4:$D$7493,Cobranza!$B65,Recibos!R$4:R$7493) -> 300 | ... BJ65: =SUMIF(Recibos!$D$4:$D$7493,Cobranza!$B65,Recibos!V$4:V$7493) -> 300 | BK65: =SUM(AY65:BJ65) -> 3600 | BL65: =SUMIF(Recibos!$D$4:$D$7493,Cobranza!$B65,Recibos!X$4:X$7493) -> 300 | BM65: =SUMIF(Recibos!$D$4:$D$7493,Cobranza!$B65,Recibos!Y$4:Y$7493) -> 300 | BN65: =SUMIF(Recibos!$D$4:$D$7493,Cobranza!$B65,Recibos!Z$4:Z$7493) -> 300 | BO65: =SUMIF(Recibos!$D$4:$D$7493,Cobranza!$B65,Recibos!AA$4:AA$7493) -> 300 | BP65: =SUMIF(Recibos!$D$4:$D$7493,Cobranza!$B65,Recibos!AB$4:AB$7493) -> 300 | BQ65: =SUMIF(Recibos!$D$4:$D$7493,Cobranza!$B65,Recibos!AC$4:AC$7493) -> 300 | BR65: =SUMIF(Recibos!$D$4:$D$7493,Cobranza!$B65,Recibos!AD$4:AD$7493) -> 300 | BS65: =SUMIF(Recibos!$D$4:$D$7493,Cobranza!$B65,Recibos!AE$4:AE$7493) -> 300 | ... BW65: =SUMIF(Recibos!$D$4:$D$7493,Cobranza!$B65,Recibos!AI$4:AI$7493) -> 300 | BX65: =SUM(BL65:BW65) -> 3600 | BY65: =SUMIF(Recibos!$D$4:$D$7493,Cobranza!$B65,Recibos!AK$4:AK$7493) -> 300 | BZ65: =SUMIF(Recibos!$D$4:$D$7493,Cobranza!$B65,Recibos!AL$4:AL$7493) -> 300 | CA65: =SUMIF(Recibos!$D$4:$D$7493,Cobranza!$B65,Recibos!AM$4:AM$7493) -> 300 | CB65: =SUMIF(Recibos!$D$4:$D$7493,Cobranza!$B65,Recibos!AN$4:AN$7493) -> 300 | CC65: =SUMIF(Recibos!$D$4:$D$7493,Cobranza!$B65,Recibos!AO$4:AO$7493) -> 300 | CD65: =SUMIF(Recibos!$D$4:$D$7493,Cobranza!$B65,Recibos!AP$4:AP$7493) -> 300 | CE65: =SUMIF(Recibos!$D$4:$D$7493,Cobranza!$B65,Recibos!AQ$4:AQ$7493) -> 300 | CF65: =SUMIF(Recibos!$D$4:$D$7493,Cobranza!$B65,Recibos!AR$4:AR$7493) -> 300 | ... CJ65: =SUMIF(Recibos!$D$4:$D$7493,Cobranza!$B65,Recibos!AV$4:AV$7493) -> 0 | CK65: =SUM(BY65:CJ65) -> 2700
B66: CL_76_ | C66: Rancho La Cuchilla No. 76 | E66: 0 | F66: 0 | G66: 0 | H66: 0 | I66: 0 | J66: 0 | K66: =SUM(E66:J66) -> 0 | L66: 0 | M66: 0 | N66: 0 | O66: 0 | P66: 0 | Q66: 0 | R66: 0 | S66: 0 | T66: 0 | U66: 0 | V66: 0 | W66: 0 | X66: =SUM(L66:W66) -> 0 | Y66: 0 | Z66: 0 | AA66: 0 | AB66: 0 | AC66: 0 | AD66: 0 | AE66: 0 | AF66: 0 | AG66: 0 | AH66: 0 | AI66: 0 | AJ66: 0 | AK66: =SUM(Y66:AJ66) -> 0 | AL66: 0 | AM66: 0 | AN66: 0 | AO66: 0 | AP66: 0 | AQ66: 0 | AR66: 0 | AS66: 0 | AT66: 0 | AU66: 0 | AV66: 0 | AW66: 0 | AX66: =SUM(AL66:AW66) -> 0 | AY66: =SUMIF(Recibos!$D$4:$D$7493,Cobranza!$B66,Recibos!K$4:K$7493) -> 0 | AZ66: =SUMIF(Recibos!$D$4:$D$7493,Cobranza!$B66,Recibos!L$4:L$7493) -> 0 | BA66: =SUMIF(Recibos!$D$4:$D$7493,Cobranza!$B66,Recibos!M$4:M$7493) -> 0 | BB66: =SUMIF(Recibos!$D$4:$D$7493,Cobranza!$B66,Recibos!N$4:N$7493) -> 0 | BC66: =SUMIF(Recibos!$D$4:$D$7493,Cobranza!$B66,Recibos!O$4:O$7493) -> 0 | BD66: =SUMIF(Recibos!$D$4:$D$7493,Cobranza!$B66,Recibos!P$4:P$7493) -> 0 | BE66: =SUMIF(Recibos!$D$4:$D$7493,Cobranza!$B66,Recibos!Q$4:Q$7493) -> 0 | BF66: =SUMIF(Recibos!$D$4:$D$7493,Cobranza!$B66,Recibos!R$4:R$7493) -> 0 | ... BJ66: =SUMIF(Recibos!$D$4:$D$7493,Cobranza!$B66,Recibos!V$4:V$7493) -> 0 | BK66: =SUM(AY66:BJ66) -> 0 | BL66: =SUMIF(Recibos!$D$4:$D$7493,Cobranza!$B66,Recibos!X$4:X$7493) -> 0 | BM66: =SUMIF(Recibos!$D$4:$D$7493,Cobranza!$B66,Recibos!Y$4:Y$7493) -> 0 | BN66: =SUMIF(Recibos!$D$4:$D$7493,Cobranza!$B66,Recibos!Z$4:Z$7493) -> 0 | BO66: =SUMIF(Recibos!$D$4:$D$7493,Cobranza!$B66,Recibos!AA$4:AA$7493) -> 0 | BP66: =SUMIF(Recibos!$D$4:$D$7493,Cobranza!$B66,Recibos!AB$4:AB$7493) -> 0 | BQ66: =SUMIF(Recibos!$D$4:$D$7493,Cobranza!$B66,Recibos!AC$4:AC$7493) -> 0 | BR66: =SUMIF(Recibos!$D$4:$D$7493,Cobranza!$B66,Recibos!AD$4:AD$7493) -> 0 | BS66: =SUMIF(Recibos!$D$4:$D$7493,Cobranza!$B66,Recibos!AE$4:AE$7493) -> 0 | ... BW66: =SUMIF(Recibos!$D$4:$D$7493,Cobranza!$B66,Recibos!AI$4:AI$7493) -> 0 | BX66: =SUM(BL66:BW66) -> 0 | BY66: =SUMIF(Recibos!$D$4:$D$7493,Cobranza!$B66,Recibos!AK$4:AK$7493) -> 0 | BZ66: =SUMIF(Recibos!$D$4:$D$7493,Cobranza!$B66,Recibos!AL$4:AL$7493) -> 0 | CA66: =SUMIF(Recibos!$D$4:$D$7493,Cobranza!$B66,Recibos!AM$4:AM$7493) -> 0 | CB66: =SUMIF(Recibos!$D$4:$D$7493,Cobranza!$B66,Recibos!AN$4:AN$7493) -> 0 | CC66: =SUMIF(Recibos!$D$4:$D$7493,Cobranza!$B66,Recibos!AO$4:AO$7493) -> 0 | CD66: =SUMIF(Recibos!$D$4:$D$7493,Cobranza!$B66,Recibos!AP$4:AP$7493) -> 0 | CE66: =SUMIF(Recibos!$D$4:$D$7493,Cobranza!$B66,Recibos!AQ$4:AQ$7493) -> 0 | CF66: =SUMIF(Recibos!$D$4:$D$7493,Cobranza!$B66,Recibos!AR$4:AR$7493) -> 0 | ... CJ66: =SUMIF(Recibos!$D$4:$D$7493,Cobranza!$B66,Recibos!AV$4:AV$7493) -> 0 | CK66: =SUM(BY66:CJ66) -> 0
B67: CL_77_ | C67: Rancho La Cuchilla No. 77 | D67: Loperena | E67: 0 | F67: 0 | G67: 0 | H67: 300 | I67: 300 | J67: 0 | K67: =SUM(E67:J67) -> 600 | L67: 300 | M67: 300 | N67: 300 | O67: 300 | P67: 300 | Q67: 300 | R67: 300 | S67: 300 | T67: 0 | U67: 0 | V67: 0 | W67: 0 | X67: =SUM(L67:W67) -> 2400 | Y67: 300 | Z67: 300 | AA67: 300 | AB67: 300 | AC67: 300 | AD67: 0 | AE67: 300 | AF67: 300 | AG67: 300 | AH67: 0 | AI67: 0 | AJ67: 0 | AK67: =SUM(Y67:AJ67) -> 2400 | AL67: 300 | AM67: 300 | AN67: 300 | AO67: 300 | AP67: 300 | AQ67: 300 | AR67: 300 | AS67: 300 | AT67: 300 | AU67: 300 | AV67: 300 | AW67: 300 | AX67: =SUM(AL67:AW67) -> 3600 | AY67: =SUMIF(Recibos!$D$4:$D$7493,Cobranza!$B67,Recibos!K$4:K$7493) -> 300 | AZ67: =SUMIF(Recibos!$D$4:$D$7493,Cobranza!$B67,Recibos!L$4:L$7493) -> 300 | BA67: =SUMIF(Recibos!$D$4:$D$7493,Cobranza!$B67,Recibos!M$4:M$7493) -> 300 | BB67: =SUMIF(Recibos!$D$4:$D$7493,Cobranza!$B67,Recibos!N$4:N$7493) -> 300 | BC67: =SUMIF(Recibos!$D$4:$D$7493,Cobranza!$B67,Recibos!O$4:O$7493) -> 300 | BD67: =SUMIF(Recibos!$D$4:$D$7493,Cobranza!$B67,Recibos!P$4:P$7493) -> 300 | BE67: =SUMIF(Recibos!$D$4:$D$7493,Cobranza!$B67,Recibos!Q$4:Q$7493) -> 300 | BF67: =SUMIF(Recibos!$D$4:$D$7493,Cobranza!$B67,Recibos!R$4:R$7493) -> 300 | ... BJ67: =SUMIF(Recibos!$D$4:$D$7493,Cobranza!$B67,Recibos!V$4:V$7493) -> 300 | BK67: =SUM(AY67:BJ67) -> 3600 | BL67: =SUMIF(Recibos!$D$4:$D$7493,Cobranza!$B67,Recibos!X$4:X$7493) -> 300 | BM67: =SUMIF(Recibos!$D$4:$D$7493,Cobranza!$B67,Recibos!Y$4:Y$7493) -> 300 | BN67: =SUMIF(Recibos!$D$4:$D$7493,Cobranza!$B67,Recibos!Z$4:Z$7493) -> 300 | BO67: =SUMIF(Recibos!$D$4:$D$7493,Cobranza!$B67,Recibos!AA$4:AA$7493) -> 300 | BP67: =SUMIF(Recibos!$D$4:$D$7493,Cobranza!$B67,Recibos!AB$4:AB$7493) -> 0 | BQ67: =SUMIF(Recibos!$D$4:$D$7493,Cobranza!$B67,Recibos!AC$4:AC$7493) -> 0 | BR67: =SUMIF(Recibos!$D$4:$D$7493,Cobranza!$B67,Recibos!AD$4:AD$7493) -> 0 | BS67: =SUMIF(Recibos!$D$4:$D$7493,Cobranza!$B67,Recibos!AE$4:AE$7493) -> 300 | ... BW67: =SUMIF(Recibos!$D$4:$D$7493,Cobranza!$B67,Recibos!AI$4:AI$7493) -> 300 | BX67: =SUM(BL67:BW67) -> 2700 | BY67: =SUMIF(Recibos!$D$4:$D$7493,Cobranza!$B67,Recibos!AK$4:AK$7493) -> 300 | BZ67: =SUMIF(Recibos!$D$4:$D$7493,Cobranza!$B67,Recibos!AL$4:AL$7493) -> 300 | CA67: =SUMIF(Recibos!$D$4:$D$7493,Cobranza!$B67,Recibos!AM$4:AM$7493) -> 300 | CB67: =SUMIF(Recibos!$D$4:$D$7493,Cobranza!$B67,Recibos!AN$4:AN$7493) -> 300 | CC67: =SUMIF(Recibos!$D$4:$D$7493,Cobranza!$B67,Recibos!AO$4:AO$7493) -> 300 | CD67: =SUMIF(Recibos!$D$4:$D$7493,Cobranza!$B67,Recibos!AP$4:AP$7493) -> 300 | CE67: =SUMIF(Recibos!$D$4:$D$7493,Cobranza!$B67,Recibos!AQ$4:AQ$7493) -> 300 | CF67: =SUMIF(Recibos!$D$4:$D$7493,Cobranza!$B67,Recibos!AR$4:AR$7493) -> 300 | ... CJ67: =SUMIF(Recibos!$D$4:$D$7493,Cobranza!$B67,Recibos!AV$4:AV$7493) -> 0 | CK67: =SUM(BY67:CJ67) -> 2400
B68: CL_78_ | C68: Rancho La Cuchilla No. 78 | D68: García | E68: 0 | F68: 0 | G68: 0 | H68: 0 | I68: 0 | J68: 0 | K68: =SUM(E68:J68) -> 0 | L68: 0 | M68: 0 | N68: 0 | O68: 0 | P68: 0 | Q68: 0 | R68: 0 | S68: 0 | T68: 0 | U68: 0 | V68: 0 | W68: 0 | X68: =SUM(L68:W68) -> 0 | Y68: 0 | Z68: 0 | AA68: 0 | AB68: 0 | AC68: 0 | AD68: 0 | AE68: 0 | AF68: 0 | AG68: 0 | AH68: 0 | AI68: 0 | AJ68: 400 | AK68: =SUM(Y68:AJ68) -> 400 | AL68: 400 | AM68: 400 | AN68: 400 | AO68: 400 | AP68: 400 | AQ68: 400 | AR68: 400 | AS68: 400 | AT68: 400 | AU68: 400 | AV68: 400 | AW68: 400 | AX68: =SUM(AL68:AW68) -> 4800 | AY68: =SUMIF(Recibos!$D$4:$D$7493,Cobranza!$B68,Recibos!K$4:K$7493) -> 400 | AZ68: =SUMIF(Recibos!$D$4:$D$7493,Cobranza!$B68,Recibos!L$4:L$7493) -> 400 | BA68: =SUMIF(Recibos!$D$4:$D$7493,Cobranza!$B68,Recibos!M$4:M$7493) -> 400 | BB68: =SUMIF(Recibos!$D$4:$D$7493,Cobranza!$B68,Recibos!N$4:N$7493) -> 400 | BC68: =SUMIF(Recibos!$D$4:$D$7493,Cobranza!$B68,Recibos!O$4:O$7493) -> 400 | BD68: =SUMIF(Recibos!$D$4:$D$7493,Cobranza!$B68,Recibos!P$4:P$7493) -> 400 | BE68: =SUMIF(Recibos!$D$4:$D$7493,Cobranza!$B68,Recibos!Q$4:Q$7493) -> 400 | BF68: =SUMIF(Recibos!$D$4:$D$7493,Cobranza!$B68,Recibos!R$4:R$7493) -> 400 | ... BJ68: =SUMIF(Recibos!$D$4:$D$7493,Cobranza!$B68,Recibos!V$4:V$7493) -> 400 | BK68: =SUM(AY68:BJ68) -> 4800 | BL68: =SUMIF(Recibos!$D$4:$D$7493,Cobranza!$B68,Recibos!X$4:X$7493) -> 400 | BM68: =SUMIF(Recibos!$D$4:$D$7493,Cobranza!$B68,Recibos!Y$4:Y$7493) -> 400 | BN68: =SUMIF(Recibos!$D$4:$D$7493,Cobranza!$B68,Recibos!Z$4:Z$7493) -> 400 | BO68: =SUMIF(Recibos!$D$4:$D$7493,Cobranza!$B68,Recibos!AA$4:AA$7493) -> 400 | BP68: =SUMIF(Recibos!$D$4:$D$7493,Cobranza!$B68,Recibos!AB$4:AB$7493) -> 400 | BQ68: =SUMIF(Recibos!$D$4:$D$7493,Cobranza!$B68,Recibos!AC$4:AC$7493) -> 400 | BR68: =SUMIF(Recibos!$D$4:$D$7493,Cobranza!$B68,Recibos!AD$4:AD$7493) -> 300 | BS68: =SUMIF(Recibos!$D$4:$D$7493,Cobranza!$B68,Recibos!AE$4:AE$7493) -> 400 | ... BW68: =SUMIF(Recibos!$D$4:$D$7493,Cobranza!$B68,Recibos!AI$4:AI$7493) -> 400 | BX68: =SUM(BL68:BW68) -> 4700 | BY68: =SUMIF(Recibos!$D$4:$D$7493,Cobranza!$B68,Recibos!AK$4:AK$7493) -> 400 | BZ68: =SUMIF(Recibos!$D$4:$D$7493,Cobranza!$B68,Recibos!AL$4:AL$7493) -> 400 | CA68: =SUMIF(Recibos!$D$4:$D$7493,Cobranza!$B68,Recibos!AM$4:AM$7493) -> 400 | CB68: =SUMIF(Recibos!$D$4:$D$7493,Cobranza!$B68,Recibos!AN$4:AN$7493) -> 400 | CC68: =SUMIF(Recibos!$D$4:$D$7493,Cobranza!$B68,Recibos!AO$4:AO$7493) -> 400 | CD68: =SUMIF(Recibos!$D$4:$D$7493,Cobranza!$B68,Recibos!AP$4:AP$7493) -> 400 | CE68: =SUMIF(Recibos!$D$4:$D$7493,Cobranza!$B68,Recibos!AQ$4:AQ$7493) -> 400 | CF68: =SUMIF(Recibos!$D$4:$D$7493,Cobranza!$B68,Recibos!AR$4:AR$7493) -> 400 | ... CJ68: =SUMIF(Recibos!$D$4:$D$7493,Cobranza!$B68,Recibos!AV$4:AV$7493) -> 0 | CK68: =SUM(BY68:CJ68) -> 4000
B69: CL_79_ | C69: Rancho La Cuchilla No. 79 | D69: De La Rosa | E69: 0 | F69: 0 | G69: 0 | H69: 0 | I69: 0 | J69: 0 | K69: =SUM(E69:J69) -> 0 | L69: 0 | M69: 0 | N69: 0 | O69: 0 | P69: 0 | Q69: 0 | R69: 0 | S69: 0 | T69: 0 | U69: 0 | V69: 0 | W69: 0 | X69: =SUM(L69:W69) -> 0 | Y69: 0 | Z69: 0 | AA69: 0 | AB69: 0 | AC69: 0 | AD69: 0 | AE69: 0 | AF69: 0 | AG69: 0 | AH69: 0 | AI69: 0 | AJ69: 0 | AK69: =SUM(Y69:AJ69) -> 0 | AL69: 0 | AM69: 200 | AN69: 200 | AO69: 200 | AP69: 200 | AQ69: 200 | AR69: 200 | AS69: 200 | AT69: 200 | AU69: 200 | AV69: 200 | AW69: 0 | AX69: =SUM(AL69:AW69) -> 2000 | AY69: =SUMIF(Recibos!$D$4:$D$7493,Cobranza!$B69,Recibos!K$4:K$7493) -> 200 | AZ69: =SUMIF(Recibos!$D$4:$D$7493,Cobranza!$B69,Recibos!L$4:L$7493) -> 200 | BA69: =SUMIF(Recibos!$D$4:$D$7493,Cobranza!$B69,Recibos!M$4:M$7493) -> 200 | BB69: =SUMIF(Recibos!$D$4:$D$7493,Cobranza!$B69,Recibos!N$4:N$7493) -> 200 | BC69: =SUMIF(Recibos!$D$4:$D$7493,Cobranza!$B69,Recibos!O$4:O$7493) -> 200 | BD69: =SUMIF(Recibos!$D$4:$D$7493,Cobranza!$B69,Recibos!P$4:P$7493) -> 200 | BE69: =SUMIF(Recibos!$D$4:$D$7493,Cobranza!$B69,Recibos!Q$4:Q$7493) -> 0 | BF69: =SUMIF(Recibos!$D$4:$D$7493,Cobranza!$B69,Recibos!R$4:R$7493) -> 0 | ... BJ69: =SUMIF(Recibos!$D$4:$D$7493,Cobranza!$B69,Recibos!V$4:V$7493) -> 0 | BK69: =SUM(AY69:BJ69) -> 1200 | BL69: =SUMIF(Recibos!$D$4:$D$7493,Cobranza!$B69,Recibos!X$4:X$7493) -> 200 | BM69: =SUMIF(Recibos!$D$4:$D$7493,Cobranza!$B69,Recibos!Y$4:Y$7493) -> 200 | BN69: =SUMIF(Recibos!$D$4:$D$7493,Cobranza!$B69,Recibos!Z$4:Z$7493) -> 200 | BO69: =SUMIF(Recibos!$D$4:$D$7493,Cobranza!$B69,Recibos!AA$4:AA$7493) -> 0 | BP69: =SUMIF(Recibos!$D$4:$D$7493,Cobranza!$B69,Recibos!AB$4:AB$7493) -> 200 | BQ69: =SUMIF(Recibos!$D$4:$D$7493,Cobranza!$B69,Recibos!AC$4:AC$7493) -> 200 | BR69: =SUMIF(Recibos!$D$4:$D$7493,Cobranza!$B69,Recibos!AD$4:AD$7493) -> 200 | BS69: =SUMIF(Recibos!$D$4:$D$7493,Cobranza!$B69,Recibos!AE$4:AE$7493) -> 200 | ... BW69: =SUMIF(Recibos!$D$4:$D$7493,Cobranza!$B69,Recibos!AI$4:AI$7493) -> 0 | BX69: =SUM(BL69:BW69) -> 1800 | BY69: =SUMIF(Recibos!$D$4:$D$7493,Cobranza!$B69,Recibos!AK$4:AK$7493) -> 200 | BZ69: =SUMIF(Recibos!$D$4:$D$7493,Cobranza!$B69,Recibos!AL$4:AL$7493) -> 200 | CA69: =SUMIF(Recibos!$D$4:$D$7493,Cobranza!$B69,Recibos!AM$4:AM$7493) -> 200 | CB69: =SUMIF(Recibos!$D$4:$D$7493,Cobranza!$B69,Recibos!AN$4:AN$7493) -> 200 | CC69: =SUMIF(Recibos!$D$4:$D$7493,Cobranza!$B69,Recibos!AO$4:AO$7493) -> 0 | CD69: =SUMIF(Recibos!$D$4:$D$7493,Cobranza!$B69,Recibos!AP$4:AP$7493) -> 0 | CE69: =SUMIF(Recibos!$D$4:$D$7493,Cobranza!$B69,Recibos!AQ$4:AQ$7493) -> 200 | CF69: =SUMIF(Recibos!$D$4:$D$7493,Cobranza!$B69,Recibos!AR$4:AR$7493) -> 200 | ... CJ69: =SUMIF(Recibos!$D$4:$D$7493,Cobranza!$B69,Recibos!AV$4:AV$7493) -> 0 | CK69: =SUM(BY69:CJ69) -> 1400
B70: CL_80_ | C70: Rancho La Cuchilla No. 80 | D70: Aparicio | E70: 0 | F70: 0 | G70: 0 | H70: 0 | I70: 0 | J70: 0 | K70: =SUM(E70:J70) -> 0 | L70: 300 | M70: 300 | N70: 300 | O70: 300 | P70: 300 | Q70: 300 | R70: 300 | S70: 300 | T70: 300 | U70: 300 | V70: 300 | W70: 0 | X70: =SUM(L70:W70) -> 3300 | Y70: 400 | Z70: 400 | AA70: 400 | AB70: 400 | AC70: 400 | AD70: 400 | AE70: 400 | AF70: 400 | AG70: 400 | AH70: 400 | AI70: 400 | AJ70: 0 | AK70: =SUM(Y70:AJ70) -> 4400 | AL70: 400 | AM70: 400 | AN70: 400 | AO70: 400 | AP70: 400 | AQ70: 400 | AR70: 400 | AS70: 400 | AT70: 400 | AU70: 400 | AV70: 400 | AW70: 0 | AX70: =SUM(AL70:AW70) -> 4400 | AY70: =SUMIF(Recibos!$D$4:$D$7493,Cobranza!$B70,Recibos!K$4:K$7493) -> 400 | AZ70: =SUMIF(Recibos!$D$4:$D$7493,Cobranza!$B70,Recibos!L$4:L$7493) -> 400 | BA70: =SUMIF(Recibos!$D$4:$D$7493,Cobranza!$B70,Recibos!M$4:M$7493) -> 400 | BB70: =SUMIF(Recibos!$D$4:$D$7493,Cobranza!$B70,Recibos!N$4:N$7493) -> 400 | BC70: =SUMIF(Recibos!$D$4:$D$7493,Cobranza!$B70,Recibos!O$4:O$7493) -> 400 | BD70: =SUMIF(Recibos!$D$4:$D$7493,Cobranza!$B70,Recibos!P$4:P$7493) -> 400 | BE70: =SUMIF(Recibos!$D$4:$D$7493,Cobranza!$B70,Recibos!Q$4:Q$7493) -> 400 | BF70: =SUMIF(Recibos!$D$4:$D$7493,Cobranza!$B70,Recibos!R$4:R$7493) -> 400 | ... BJ70: =SUMIF(Recibos!$D$4:$D$7493,Cobranza!$B70,Recibos!V$4:V$7493) -> 0 | BK70: =SUM(AY70:BJ70) -> 4400 | BL70: =SUMIF(Recibos!$D$4:$D$7493,Cobranza!$B70,Recibos!X$4:X$7493) -> 400 | BM70: =SUMIF(Recibos!$D$4:$D$7493,Cobranza!$B70,Recibos!Y$4:Y$7493) -> 400 | BN70: =SUMIF(Recibos!$D$4:$D$7493,Cobranza!$B70,Recibos!Z$4:Z$7493) -> 400 | BO70: =SUMIF(Recibos!$D$4:$D$7493,Cobranza!$B70,Recibos!AA$4:AA$7493) -> 400 | BP70: =SUMIF(Recibos!$D$4:$D$7493,Cobranza!$B70,Recibos!AB$4:AB$7493) -> 400 | BQ70: =SUMIF(Recibos!$D$4:$D$7493,Cobranza!$B70,Recibos!AC$4:AC$7493) -> 400 | BR70: =SUMIF(Recibos!$D$4:$D$7493,Cobranza!$B70,Recibos!AD$4:AD$7493) -> 400 | BS70: =SUMIF(Recibos!$D$4:$D$7493,Cobranza!$B70,Recibos!AE$4:AE$7493) -> 400 | ... BW70: =SUMIF(Recibos!$D$4:$D$7493,Cobranza!$B70,Recibos!AI$4:AI$7493) -> 0 | BX70: =SUM(BL70:BW70) -> 4400 | BY70: =SUMIF(Recibos!$D$4:$D$7493,Cobranza!$B70,Recibos!AK$4:AK$7493) -> 400 | BZ70: =SUMIF(Recibos!$D$4:$D$7493,Cobranza!$B70,Recibos!AL$4:AL$7493) -> 400 | CA70: =SUMIF(Recibos!$D$4:$D$7493,Cobranza!$B70,Recibos!AM$4:AM$7493) -> 400 | CB70: =SUMIF(Recibos!$D$4:$D$7493,Cobranza!$B70,Recibos!AN$4:AN$7493) -> 400 | CC70: =SUMIF(Recibos!$D$4:$D$7493,Cobranza!$B70,Recibos!AO$4:AO$7493) -> 400 | CD70: =SUMIF(Recibos!$D$4:$D$7493,Cobranza!$B70,Recibos!AP$4:AP$7493) -> 400 | CE70: =SUMIF(Recibos!$D$4:$D$7493,Cobranza!$B70,Recibos!AQ$4:AQ$7493) -> 400 | CF70: =SUMIF(Recibos!$D$4:$D$7493,Cobranza!$B70,Recibos!AR$4:AR$7493) -> 400 | ... CJ70: =SUMIF(Recibos!$D$4:$D$7493,Cobranza!$B70,Recibos!AV$4:AV$7493) -> 0 | CK70: =SUM(BY70:CJ70) -> 4400
B71: CL_81_ | C71: Rancho La Cuchilla No. 81 | D71: Suárez | E71: 0 | F71: 0 | G71: 0 | H71: 0 | I71: 0 | J71: 0 | K71: =SUM(E71:J71) -> 0 | L71: 0 | M71: 0 | N71: 0 | O71: 0 | P71: 0 | Q71: 0 | R71: 0 | S71: 0 | T71: 0 | U71: 0 | V71: 0 | W71: 0 | X71: =SUM(L71:W71) -> 0 | Y71: 0 | Z71: 0 | AA71: 0 | AB71: 0 | AC71: 0 | AD71: 0 | AE71: 0 | AF71: 0 | AG71: 0 | AH71: 0 | AI71: 0 | AJ71: 0 | AK71: =SUM(Y71:AJ71) -> 0 | AL71: 400 | AM71: 400 | AN71: 400 | AO71: 400 | AP71: 400 | AQ71: 400 | AR71: 400 | AS71: 400 | AT71: 400 | AU71: 400 | AV71: 400 | AW71: 400 | AX71: =SUM(AL71:AW71) -> 4800 | AY71: =SUMIF(Recibos!$D$4:$D$7493,Cobranza!$B71,Recibos!K$4:K$7493) -> 400 | AZ71: =SUMIF(Recibos!$D$4:$D$7493,Cobranza!$B71,Recibos!L$4:L$7493) -> 400 | BA71: =SUMIF(Recibos!$D$4:$D$7493,Cobranza!$B71,Recibos!M$4:M$7493) -> 400 | BB71: =SUMIF(Recibos!$D$4:$D$7493,Cobranza!$B71,Recibos!N$4:N$7493) -> 400 | BC71: =SUMIF(Recibos!$D$4:$D$7493,Cobranza!$B71,Recibos!O$4:O$7493) -> 400 | BD71: =SUMIF(Recibos!$D$4:$D$7493,Cobranza!$B71,Recibos!P$4:P$7493) -> 400 | BE71: =SUMIF(Recibos!$D$4:$D$7493,Cobranza!$B71,Recibos!Q$4:Q$7493) -> 400 | BF71: =SUMIF(Recibos!$D$4:$D$7493,Cobranza!$B71,Recibos!R$4:R$7493) -> 400 | ... BJ71: =SUMIF(Recibos!$D$4:$D$7493,Cobranza!$B71,Recibos!V$4:V$7493) -> 0 | BK71: =SUM(AY71:BJ71) -> 4400 | BL71: =SUMIF(Recibos!$D$4:$D$7493,Cobranza!$B71,Recibos!X$4:X$7493) -> 400 | BM71: =SUMIF(Recibos!$D$4:$D$7493,Cobranza!$B71,Recibos!Y$4:Y$7493) -> 400 | BN71: =SUMIF(Recibos!$D$4:$D$7493,Cobranza!$B71,Recibos!Z$4:Z$7493) -> 400 | BO71: =SUMIF(Recibos!$D$4:$D$7493,Cobranza!$B71,Recibos!AA$4:AA$7493) -> 400 | BP71: =SUMIF(Recibos!$D$4:$D$7493,Cobranza!$B71,Recibos!AB$4:AB$7493) -> 400 | BQ71: =SUMIF(Recibos!$D$4:$D$7493,Cobranza!$B71,Recibos!AC$4:AC$7493) -> 400 | BR71: =SUMIF(Recibos!$D$4:$D$7493,Cobranza!$B71,Recibos!AD$4:AD$7493) -> 400 | BS71: =SUMIF(Recibos!$D$4:$D$7493,Cobranza!$B71,Recibos!AE$4:AE$7493) -> 400 | ... BW71: =SUMIF(Recibos!$D$4:$D$7493,Cobranza!$B71,Recibos!AI$4:AI$7493) -> 0 | BX71: =SUM(BL71:BW71) -> 4400 | BY71: =SUMIF(Recibos!$D$4:$D$7493,Cobranza!$B71,Recibos!AK$4:AK$7493) -> 400 | BZ71: =SUMIF(Recibos!$D$4:$D$7493,Cobranza!$B71,Recibos!AL$4:AL$7493) -> 400 | CA71: =SUMIF(Recibos!$D$4:$D$7493,Cobranza!$B71,Recibos!AM$4:AM$7493) -> 400 | CB71: =SUMIF(Recibos!$D$4:$D$7493,Cobranza!$B71,Recibos!AN$4:AN$7493) -> 400 | CC71: =SUMIF(Recibos!$D$4:$D$7493,Cobranza!$B71,Recibos!AO$4:AO$7493) -> 400 | CD71: =SUMIF(Recibos!$D$4:$D$7493,Cobranza!$B71,Recibos!AP$4:AP$7493) -> 400 | CE71: =SUMIF(Recibos!$D$4:$D$7493,Cobranza!$B71,Recibos!AQ$4:AQ$7493) -> 400 | CF71: =SUMIF(Recibos!$D$4:$D$7493,Cobranza!$B71,Recibos!AR$4:AR$7493) -> 400 | ... CJ71: =SUMIF(Recibos!$D$4:$D$7493,Cobranza!$B71,Recibos!AV$4:AV$7493) -> 0 | CK71: =SUM(BY71:CJ71) -> 4400
B72: CL_81_A | C72: Rancho La Cuchilla No. 81, A | D72: Barrientos López | E72: 0 | F72: 0 | G72: 0 | H72: 0 | I72: 0 | J72: 300 | K72: =SUM(E72:J72) -> 300 | L72: 300 | M72: 300 | N72: 300 | O72: 300 | P72: 300 | Q72: 300 | R72: 300 | S72: 300 | T72: 300 | U72: 500 | V72: 500 | W72: 500 | X72: =SUM(L72:W72) -> 4200 | Y72: 400 | Z72: 400 | AA72: 400 | AB72: 400 | AC72: 400 | AD72: 400 | AE72: 400 | AF72: 400 | AG72: 800 | AH72: 400 | AI72: 400 | AJ72: 400 | AK72: =SUM(Y72:AJ72) -> 5200 | AL72: 400 | AM72: 400 | AN72: 400 | AO72: 400 | AP72: 400 | AQ72: 400 | AR72: 400 | AS72: 400 | AT72: 400 | AU72: 400 | AV72: 400 | AW72: 400 | AX72: =SUM(AL72:AW72) -> 4800 | AY72: =SUMIF(Recibos!$D$4:$D$7493,Cobranza!$B72,Recibos!K$4:K$7493) -> 400 | AZ72: =SUMIF(Recibos!$D$4:$D$7493,Cobranza!$B72,Recibos!L$4:L$7493) -> 400 | BA72: =SUMIF(Recibos!$D$4:$D$7493,Cobranza!$B72,Recibos!M$4:M$7493) -> 400 | BB72: =SUMIF(Recibos!$D$4:$D$7493,Cobranza!$B72,Recibos!N$4:N$7493) -> 400 | BC72: =SUMIF(Recibos!$D$4:$D$7493,Cobranza!$B72,Recibos!O$4:O$7493) -> 400 | BD72: =SUMIF(Recibos!$D$4:$D$7493,Cobranza!$B72,Recibos!P$4:P$7493) -> 400 | BE72: =SUMIF(Recibos!$D$4:$D$7493,Cobranza!$B72,Recibos!Q$4:Q$7493) -> 400 | BF72: =SUMIF(Recibos!$D$4:$D$7493,Cobranza!$B72,Recibos!R$4:R$7493) -> 400 | ... BJ72: =SUMIF(Recibos!$D$4:$D$7493,Cobranza!$B72,Recibos!V$4:V$7493) -> 400 | BK72: =SUM(AY72:BJ72) -> 4800 | BL72: =SUMIF(Recibos!$D$4:$D$7493,Cobranza!$B72,Recibos!X$4:X$7493) -> 400 | BM72: =SUMIF(Recibos!$D$4:$D$7493,Cobranza!$B72,Recibos!Y$4:Y$7493) -> 400 | BN72: =SUMIF(Recibos!$D$4:$D$7493,Cobranza!$B72,Recibos!Z$4:Z$7493) -> 400 | BO72: =SUMIF(Recibos!$D$4:$D$7493,Cobranza!$B72,Recibos!AA$4:AA$7493) -> 400 | BP72: =SUMIF(Recibos!$D$4:$D$7493,Cobranza!$B72,Recibos!AB$4:AB$7493) -> 400 | BQ72: =SUMIF(Recibos!$D$4:$D$7493,Cobranza!$B72,Recibos!AC$4:AC$7493) -> 400 | BR72: =SUMIF(Recibos!$D$4:$D$7493,Cobranza!$B72,Recibos!AD$4:AD$7493) -> 400 | BS72: =SUMIF(Recibos!$D$4:$D$7493,Cobranza!$B72,Recibos!AE$4:AE$7493) -> 400 | ... BW72: =SUMIF(Recibos!$D$4:$D$7493,Cobranza!$B72,Recibos!AI$4:AI$7493) -> 400 | BX72: =SUM(BL72:BW72) -> 4800 | BY72: =SUMIF(Recibos!$D$4:$D$7493,Cobranza!$B72,Recibos!AK$4:AK$7493) -> 400 | BZ72: =SUMIF(Recibos!$D$4:$D$7493,Cobranza!$B72,Recibos!AL$4:AL$7493) -> 400 | CA72: =SUMIF(Recibos!$D$4:$D$7493,Cobranza!$B72,Recibos!AM$4:AM$7493) -> 400 | CB72: =SUMIF(Recibos!$D$4:$D$7493,Cobranza!$B72,Recibos!AN$4:AN$7493) -> 400 | CC72: =SUMIF(Recibos!$D$4:$D$7493,Cobranza!$B72,Recibos!AO$4:AO$7493) -> 400 | CD72: =SUMIF(Recibos!$D$4:$D$7493,Cobranza!$B72,Recibos!AP$4:AP$7493) -> 400 | CE72: =SUMIF(Recibos!$D$4:$D$7493,Cobranza!$B72,Recibos!AQ$4:AQ$7493) -> 400 | CF72: =SUMIF(Recibos!$D$4:$D$7493,Cobranza!$B72,Recibos!AR$4:AR$7493) -> 400 | ... CJ72: =SUMIF(Recibos!$D$4:$D$7493,Cobranza!$B72,Recibos!AV$4:AV$7493) -> 0 | CK72: =SUM(BY72:CJ72) -> 4000
B73: CL_81_B | C73: Rancho La Cuchilla No. 81, B | D73: Suarez | E73: 0 | F73: 0 | G73: 0 | H73: 0 | I73: 0 | J73: 0 | K73: =SUM(E73:J73) -> 0 | L73: 300 | M73: 300 | N73: 300 | O73: 300 | P73: 300 | Q73: 300 | R73: 300 | S73: 300 | T73: 300 | U73: 300 | V73: 300 | W73: 0 | X73: =SUM(L73:W73) -> 3300 | Y73: 300 | Z73: 400 | AA73: 0 | AB73: 400 | AC73: 400 | AD73: 400 | AE73: 400 | AF73: 400 | AG73: 0 | AH73: 400 | AI73: 400 | AJ73: 400 | AK73: =SUM(Y73:AJ73) -> 3900 | AL73: 0 | AM73: 0 | AN73: 0 | AO73: 0 | AP73: 0 | AQ73: 0 | AR73: 0 | AS73: 0 | AT73: 0 | AU73: 0 | AV73: 0 | AW73: 0 | AX73: =SUM(AL73:AW73) -> 0 | AY73: =SUMIF(Recibos!$D$4:$D$7493,Cobranza!$B73,Recibos!K$4:K$7493) -> 0 | AZ73: =SUMIF(Recibos!$D$4:$D$7493,Cobranza!$B73,Recibos!L$4:L$7493) -> 0 | BA73: =SUMIF(Recibos!$D$4:$D$7493,Cobranza!$B73,Recibos!M$4:M$7493) -> 0 | BB73: =SUMIF(Recibos!$D$4:$D$7493,Cobranza!$B73,Recibos!N$4:N$7493) -> 0 | BC73: =SUMIF(Recibos!$D$4:$D$7493,Cobranza!$B73,Recibos!O$4:O$7493) -> 0 | BD73: =SUMIF(Recibos!$D$4:$D$7493,Cobranza!$B73,Recibos!P$4:P$7493) -> 0 | BE73: =SUMIF(Recibos!$D$4:$D$7493,Cobranza!$B73,Recibos!Q$4:Q$7493) -> 0 | BF73: =SUMIF(Recibos!$D$4:$D$7493,Cobranza!$B73,Recibos!R$4:R$7493) -> 0 | ... BJ73: =SUMIF(Recibos!$D$4:$D$7493,Cobranza!$B73,Recibos!V$4:V$7493) -> 0 | BK73: =SUM(AY73:BJ73) -> 0 | BL73: =SUMIF(Recibos!$D$4:$D$7493,Cobranza!$B73,Recibos!X$4:X$7493) -> 0 | BM73: =SUMIF(Recibos!$D$4:$D$7493,Cobranza!$B73,Recibos!Y$4:Y$7493) -> 0 | BN73: =SUMIF(Recibos!$D$4:$D$7493,Cobranza!$B73,Recibos!Z$4:Z$7493) -> 0 | BO73: =SUMIF(Recibos!$D$4:$D$7493,Cobranza!$B73,Recibos!AA$4:AA$7493) -> 0 | BP73: =SUMIF(Recibos!$D$4:$D$7493,Cobranza!$B73,Recibos!AB$4:AB$7493) -> 0 | BQ73: =SUMIF(Recibos!$D$4:$D$7493,Cobranza!$B73,Recibos!AC$4:AC$7493) -> 0 | BR73: =SUMIF(Recibos!$D$4:$D$7493,Cobranza!$B73,Recibos!AD$4:AD$7493) -> 0 | BS73: =SUMIF(Recibos!$D$4:$D$7493,Cobranza!$B73,Recibos!AE$4:AE$7493) -> 0 | ... BW73: =SUMIF(Recibos!$D$4:$D$7493,Cobranza!$B73,Recibos!AI$4:AI$7493) -> 0 | BX73: =SUM(BL73:BW73) -> 0 | BY73: =SUMIF(Recibos!$D$4:$D$7493,Cobranza!$B73,Recibos!AK$4:AK$7493) -> 0 | BZ73: =SUMIF(Recibos!$D$4:$D$7493,Cobranza!$B73,Recibos!AL$4:AL$7493) -> 0 | CA73: =SUMIF(Recibos!$D$4:$D$7493,Cobranza!$B73,Recibos!AM$4:AM$7493) -> 0 | CB73: =SUMIF(Recibos!$D$4:$D$7493,Cobranza!$B73,Recibos!AN$4:AN$7493) -> 0 | CC73: =SUMIF(Recibos!$D$4:$D$7493,Cobranza!$B73,Recibos!AO$4:AO$7493) -> 0 | CD73: =SUMIF(Recibos!$D$4:$D$7493,Cobranza!$B73,Recibos!AP$4:AP$7493) -> 0 | CE73: =SUMIF(Recibos!$D$4:$D$7493,Cobranza!$B73,Recibos!AQ$4:AQ$7493) -> 0 | CF73: =SUMIF(Recibos!$D$4:$D$7493,Cobranza!$B73,Recibos!AR$4:AR$7493) -> 0 | ... CJ73: =SUMIF(Recibos!$D$4:$D$7493,Cobranza!$B73,Recibos!AV$4:AV$7493) -> 0 | CK73: =SUM(BY73:CJ73) -> 0
B74: CL_82_ | C74: Rancho La Cuchilla No. 82 | D74: Cruz | E74: 0 | F74: 0 | G74: 0 | H74: 0 | I74: 300 | J74: 300 | K74: =SUM(E74:J74) -> 600 | L74: 300 | M74: 300 | N74: 300 | O74: 300 | P74: 300 | Q74: 300 | R74: 300 | S74: 300 | T74: 300 | U74: 400 | V74: 400 | W74: 400 | X74: =SUM(L74:W74) -> 3900 | Y74: 400 | Z74: 400 | AA74: 400 | AB74: 400 | AC74: 400 | AD74: 400 | AE74: 400 | AF74: 400 | AG74: 400 | AH74: 400 | AI74: 400 | AJ74: 400 | AK74: =SUM(Y74:AJ74) -> 4800 | AL74: 400 | AM74: 400 | AN74: 400 | AO74: 400 | AP74: 400 | AQ74: 400 | AR74: 400 | AS74: 400 | AT74: 400 | AU74: 400 | AV74: 400 | AW74: 400 | AX74: =SUM(AL74:AW74) -> 4800 | AY74: =SUMIF(Recibos!$D$4:$D$7493,Cobranza!$B74,Recibos!K$4:K$7493) -> 400 | AZ74: =SUMIF(Recibos!$D$4:$D$7493,Cobranza!$B74,Recibos!L$4:L$7493) -> 400 | BA74: =SUMIF(Recibos!$D$4:$D$7493,Cobranza!$B74,Recibos!M$4:M$7493) -> 400 | BB74: =SUMIF(Recibos!$D$4:$D$7493,Cobranza!$B74,Recibos!N$4:N$7493) -> 400 | BC74: =SUMIF(Recibos!$D$4:$D$7493,Cobranza!$B74,Recibos!O$4:O$7493) -> 400 | BD74: =SUMIF(Recibos!$D$4:$D$7493,Cobranza!$B74,Recibos!P$4:P$7493) -> 400 | BE74: =SUMIF(Recibos!$D$4:$D$7493,Cobranza!$B74,Recibos!Q$4:Q$7493) -> 400 | BF74: =SUMIF(Recibos!$D$4:$D$7493,Cobranza!$B74,Recibos!R$4:R$7493) -> 400 | ... BJ74: =SUMIF(Recibos!$D$4:$D$7493,Cobranza!$B74,Recibos!V$4:V$7493) -> 0 | BK74: =SUM(AY74:BJ74) -> 4400 | BL74: =SUMIF(Recibos!$D$4:$D$7493,Cobranza!$B74,Recibos!X$4:X$7493) -> 400 | BM74: =SUMIF(Recibos!$D$4:$D$7493,Cobranza!$B74,Recibos!Y$4:Y$7493) -> 400 | BN74: =SUMIF(Recibos!$D$4:$D$7493,Cobranza!$B74,Recibos!Z$4:Z$7493) -> 400 | BO74: =SUMIF(Recibos!$D$4:$D$7493,Cobranza!$B74,Recibos!AA$4:AA$7493) -> 400 | BP74: =SUMIF(Recibos!$D$4:$D$7493,Cobranza!$B74,Recibos!AB$4:AB$7493) -> 400 | BQ74: =SUMIF(Recibos!$D$4:$D$7493,Cobranza!$B74,Recibos!AC$4:AC$7493) -> 400 | BR74: =SUMIF(Recibos!$D$4:$D$7493,Cobranza!$B74,Recibos!AD$4:AD$7493) -> 400 | BS74: =SUMIF(Recibos!$D$4:$D$7493,Cobranza!$B74,Recibos!AE$4:AE$7493) -> 400 | ... BW74: =SUMIF(Recibos!$D$4:$D$7493,Cobranza!$B74,Recibos!AI$4:AI$7493) -> 400 | BX74: =SUM(BL74:BW74) -> 4800 | BY74: =SUMIF(Recibos!$D$4:$D$7493,Cobranza!$B74,Recibos!AK$4:AK$7493) -> 400 | BZ74: =SUMIF(Recibos!$D$4:$D$7493,Cobranza!$B74,Recibos!AL$4:AL$7493) -> 400 | CA74: =SUMIF(Recibos!$D$4:$D$7493,Cobranza!$B74,Recibos!AM$4:AM$7493) -> 400 | CB74: =SUMIF(Recibos!$D$4:$D$7493,Cobranza!$B74,Recibos!AN$4:AN$7493) -> 400 | CC74: =SUMIF(Recibos!$D$4:$D$7493,Cobranza!$B74,Recibos!AO$4:AO$7493) -> 400 | CD74: =SUMIF(Recibos!$D$4:$D$7493,Cobranza!$B74,Recibos!AP$4:AP$7493) -> 400 | CE74: =SUMIF(Recibos!$D$4:$D$7493,Cobranza!$B74,Recibos!AQ$4:AQ$7493) -> 400 | CF74: =SUMIF(Recibos!$D$4:$D$7493,Cobranza!$B74,Recibos!AR$4:AR$7493) -> 400 | ... CJ74: =SUMIF(Recibos!$D$4:$D$7493,Cobranza!$B74,Recibos!AV$4:AV$7493) -> 0 | CK74: =SUM(BY74:CJ74) -> 3400
B75: CL_83_ | C75: Rancho La Cuchilla No. 83 | D75: Barradas | E75: 0 | F75: 0 | G75: 0 | H75: 0 | I75: 0 | J75: 0 | K75: =SUM(E75:J75) -> 0 | L75: 0 | M75: 0 | N75: 0 | O75: 0 | P75: 0 | Q75: 0 | R75: 0 | S75: 0 | T75: 0 | U75: 0 | V75: 0 | W75: 0 | X75: =SUM(L75:W75) -> 0 | Y75: 0 | Z75: 0 | AA75: 0 | AB75: 0 | AC75: 0 | AD75: 0 | AE75: 0 | AF75: 0 | AG75: 0 | AH75: 0 | AI75: 0 | AJ75: 0 | AK75: =SUM(Y75:AJ75) -> 0 | AL75: 0 | AM75: 0 | AN75: 0 | AO75: 0 | AP75: 0 | AQ75: 0 | AR75: 0 | AS75: 0 | AT75: 0 | AU75: 0 | AV75: 0 | AW75: 0 | AX75: =SUM(AL75:AW75) -> 0 | AY75: =SUMIF(Recibos!$D$4:$D$7493,Cobranza!$B75,Recibos!K$4:K$7493) -> 0 | AZ75: =SUMIF(Recibos!$D$4:$D$7493,Cobranza!$B75,Recibos!L$4:L$7493) -> 0 | BA75: =SUMIF(Recibos!$D$4:$D$7493,Cobranza!$B75,Recibos!M$4:M$7493) -> 0 | BB75: =SUMIF(Recibos!$D$4:$D$7493,Cobranza!$B75,Recibos!N$4:N$7493) -> 0 | BC75: =SUMIF(Recibos!$D$4:$D$7493,Cobranza!$B75,Recibos!O$4:O$7493) -> 0 | BD75: =SUMIF(Recibos!$D$4:$D$7493,Cobranza!$B75,Recibos!P$4:P$7493) -> 0 | BE75: =SUMIF(Recibos!$D$4:$D$7493,Cobranza!$B75,Recibos!Q$4:Q$7493) -> 0 | BF75: =SUMIF(Recibos!$D$4:$D$7493,Cobranza!$B75,Recibos!R$4:R$7493) -> 0 | ... BJ75: =SUMIF(Recibos!$D$4:$D$7493,Cobranza!$B75,Recibos!V$4:V$7493) -> 0 | BK75: =SUM(AY75:BJ75) -> 0 | BL75: =SUMIF(Recibos!$D$4:$D$7493,Cobranza!$B75,Recibos!X$4:X$7493) -> 0 | BM75: =SUMIF(Recibos!$D$4:$D$7493,Cobranza!$B75,Recibos!Y$4:Y$7493) -> 0 | BN75: =SUMIF(Recibos!$D$4:$D$7493,Cobranza!$B75,Recibos!Z$4:Z$7493) -> 0 | BO75: =SUMIF(Recibos!$D$4:$D$7493,Cobranza!$B75,Recibos!AA$4:AA$7493) -> 0 | BP75: =SUMIF(Recibos!$D$4:$D$7493,Cobranza!$B75,Recibos!AB$4:AB$7493) -> 0 | BQ75: =SUMIF(Recibos!$D$4:$D$7493,Cobranza!$B75,Recibos!AC$4:AC$7493) -> 0 | BR75: =SUMIF(Recibos!$D$4:$D$7493,Cobranza!$B75,Recibos!AD$4:AD$7493) -> 0 | BS75: =SUMIF(Recibos!$D$4:$D$7493,Cobranza!$B75,Recibos!AE$4:AE$7493) -> 0 | ... BW75: =SUMIF(Recibos!$D$4:$D$7493,Cobranza!$B75,Recibos!AI$4:AI$7493) -> 0 | BX75: =SUM(BL75:BW75) -> 0 | BY75: =SUMIF(Recibos!$D$4:$D$7493,Cobranza!$B75,Recibos!AK$4:AK$7493) -> 0 | BZ75: =SUMIF(Recibos!$D$4:$D$7493,Cobranza!$B75,Recibos!AL$4:AL$7493) -> 0 | CA75: =SUMIF(Recibos!$D$4:$D$7493,Cobranza!$B75,Recibos!AM$4:AM$7493) -> 0 | CB75: =SUMIF(Recibos!$D$4:$D$7493,Cobranza!$B75,Recibos!AN$4:AN$7493) -> 0 | CC75: =SUMIF(Recibos!$D$4:$D$7493,Cobranza!$B75,Recibos!AO$4:AO$7493) -> 0 | CD75: =SUMIF(Recibos!$D$4:$D$7493,Cobranza!$B75,Recibos!AP$4:AP$7493) -> 0 | CE75: =SUMIF(Recibos!$D$4:$D$7493,Cobranza!$B75,Recibos!AQ$4:AQ$7493) -> 0 | CF75: =SUMIF(Recibos!$D$4:$D$7493,Cobranza!$B75,Recibos!AR$4:AR$7493) -> 0 | ... CJ75: =SUMIF(Recibos!$D$4:$D$7493,Cobranza!$B75,Recibos!AV$4:AV$7493) -> 0 | CK75: =SUM(BY75:CJ75) -> 0
B76: CL_86_ | C76: Rancho La Cuchilla No. 86 | D76: Del Villar | E76: 0 | F76: 0 | G76: 0 | H76: 0 | I76: 0 | J76: 0 | K76: =SUM(E76:J76) -> 0 | L76: 300 | M76: 300 | N76: 300 | O76: 300 | P76: 300 | Q76: 300 | R76: 300 | S76: 300 | T76: 300 | U76: 400 | V76: 400 | W76: 400 | X76: =SUM(L76:W76) -> 3900 | Y76: 400 | Z76: 0 | AA76: 400 | AB76: 400 | AC76: 400 | AD76: 400 | AE76: 400 | AF76: 400 | AG76: 400 | AH76: 400 | AI76: 400 | AJ76: 400 | AK76: =SUM(Y76:AJ76) -> 4400 | AL76: 400 | AM76: 400 | AN76: 400 | AO76: 400 | AP76: 300 | AQ76: 300 | AR76: 300 | AS76: 300 | AT76: 300 | AU76: 300 | AV76: 300 | AW76: 300 | AX76: =SUM(AL76:AW76) -> 4000 | AY76: =SUMIF(Recibos!$D$4:$D$7493,Cobranza!$B76,Recibos!K$4:K$7493) -> 300 | AZ76: =SUMIF(Recibos!$D$4:$D$7493,Cobranza!$B76,Recibos!L$4:L$7493) -> 300 | BA76: =SUMIF(Recibos!$D$4:$D$7493,Cobranza!$B76,Recibos!M$4:M$7493) -> 300 | BB76: =SUMIF(Recibos!$D$4:$D$7493,Cobranza!$B76,Recibos!N$4:N$7493) -> 300 | BC76: =SUMIF(Recibos!$D$4:$D$7493,Cobranza!$B76,Recibos!O$4:O$7493) -> 300 | BD76: =SUMIF(Recibos!$D$4:$D$7493,Cobranza!$B76,Recibos!P$4:P$7493) -> 300 | BE76: =SUMIF(Recibos!$D$4:$D$7493,Cobranza!$B76,Recibos!Q$4:Q$7493) -> 300 | BF76: =SUMIF(Recibos!$D$4:$D$7493,Cobranza!$B76,Recibos!R$4:R$7493) -> 300 | ... BJ76: =SUMIF(Recibos!$D$4:$D$7493,Cobranza!$B76,Recibos!V$4:V$7493) -> 300 | BK76: =SUM(AY76:BJ76) -> 3600 | BL76: =SUMIF(Recibos!$D$4:$D$7493,Cobranza!$B76,Recibos!X$4:X$7493) -> 400 | BM76: =SUMIF(Recibos!$D$4:$D$7493,Cobranza!$B76,Recibos!Y$4:Y$7493) -> 400 | BN76: =SUMIF(Recibos!$D$4:$D$7493,Cobranza!$B76,Recibos!Z$4:Z$7493) -> 400 | BO76: =SUMIF(Recibos!$D$4:$D$7493,Cobranza!$B76,Recibos!AA$4:AA$7493) -> 400 | BP76: =SUMIF(Recibos!$D$4:$D$7493,Cobranza!$B76,Recibos!AB$4:AB$7493) -> 400 | BQ76: =SUMIF(Recibos!$D$4:$D$7493,Cobranza!$B76,Recibos!AC$4:AC$7493) -> 400 | BR76: =SUMIF(Recibos!$D$4:$D$7493,Cobranza!$B76,Recibos!AD$4:AD$7493) -> 400 | BS76: =SUMIF(Recibos!$D$4:$D$7493,Cobranza!$B76,Recibos!AE$4:AE$7493) -> 400 | ... BW76: =SUMIF(Recibos!$D$4:$D$7493,Cobranza!$B76,Recibos!AI$4:AI$7493) -> 0 | BX76: =SUM(BL76:BW76) -> 4400 | BY76: =SUMIF(Recibos!$D$4:$D$7493,Cobranza!$B76,Recibos!AK$4:AK$7493) -> 400 | BZ76: =SUMIF(Recibos!$D$4:$D$7493,Cobranza!$B76,Recibos!AL$4:AL$7493) -> 400 | CA76: =SUMIF(Recibos!$D$4:$D$7493,Cobranza!$B76,Recibos!AM$4:AM$7493) -> 400 | CB76: =SUMIF(Recibos!$D$4:$D$7493,Cobranza!$B76,Recibos!AN$4:AN$7493) -> 400 | CC76: =SUMIF(Recibos!$D$4:$D$7493,Cobranza!$B76,Recibos!AO$4:AO$7493) -> 400 | CD76: =SUMIF(Recibos!$D$4:$D$7493,Cobranza!$B76,Recibos!AP$4:AP$7493) -> 800 | CE76: =SUMIF(Recibos!$D$4:$D$7493,Cobranza!$B76,Recibos!AQ$4:AQ$7493) -> 400 | CF76: =SUMIF(Recibos!$D$4:$D$7493,Cobranza!$B76,Recibos!AR$4:AR$7493) -> 400 | ... CJ76: =SUMIF(Recibos!$D$4:$D$7493,Cobranza!$B76,Recibos!AV$4:AV$7493) -> 0 | CK76: =SUM(BY76:CJ76) -> 4800
B77: CL_87_ | C77: Rancho La Cuchilla No. 87 | D77: Villanueva S. | E77: 0 | F77: 0 | G77: 0 | H77: 0 | I77: 300 | J77: 300 | K77: =SUM(E77:J77) -> 600 | L77: 300 | M77: 300 | N77: 300 | O77: 300 | P77: 300 | Q77: 300 | R77: 300 | S77: 300 | T77: 300 | U77: 400 | V77: 400 | W77: 400 | X77: =SUM(L77:W77) -> 3900 | Y77: 400 | Z77: 400 | AA77: 400 | AB77: 400 | AC77: 400 | AD77: 400 | AE77: 400 | AF77: 400 | AG77: 400 | AH77: 400 | AI77: 400 | AJ77: 400 | AK77: =SUM(Y77:AJ77) -> 4800 | AL77: 400 | AM77: 400 | AN77: 400 | AO77: 400 | AP77: 400 | AQ77: 400 | AR77: 400 | AS77: 400 | AT77: 400 | AU77: 400 | AV77: 400 | AW77: 400 | AX77: =SUM(AL77:AW77) -> 4800 | AY77: =SUMIF(Recibos!$D$4:$D$7493,Cobranza!$B77,Recibos!K$4:K$7493) -> 400 | AZ77: =SUMIF(Recibos!$D$4:$D$7493,Cobranza!$B77,Recibos!L$4:L$7493) -> 400 | BA77: =SUMIF(Recibos!$D$4:$D$7493,Cobranza!$B77,Recibos!M$4:M$7493) -> 400 | BB77: =SUMIF(Recibos!$D$4:$D$7493,Cobranza!$B77,Recibos!N$4:N$7493) -> 400 | BC77: =SUMIF(Recibos!$D$4:$D$7493,Cobranza!$B77,Recibos!O$4:O$7493) -> 400 | BD77: =SUMIF(Recibos!$D$4:$D$7493,Cobranza!$B77,Recibos!P$4:P$7493) -> 400 | BE77: =SUMIF(Recibos!$D$4:$D$7493,Cobranza!$B77,Recibos!Q$4:Q$7493) -> 400 | BF77: =SUMIF(Recibos!$D$4:$D$7493,Cobranza!$B77,Recibos!R$4:R$7493) -> 400 | ... BJ77: =SUMIF(Recibos!$D$4:$D$7493,Cobranza!$B77,Recibos!V$4:V$7493) -> 400 | BK77: =SUM(AY77:BJ77) -> 4800 | BL77: =SUMIF(Recibos!$D$4:$D$7493,Cobranza!$B77,Recibos!X$4:X$7493) -> 400 | BM77: =SUMIF(Recibos!$D$4:$D$7493,Cobranza!$B77,Recibos!Y$4:Y$7493) -> 400 | BN77: =SUMIF(Recibos!$D$4:$D$7493,Cobranza!$B77,Recibos!Z$4:Z$7493) -> 400 | BO77: =SUMIF(Recibos!$D$4:$D$7493,Cobranza!$B77,Recibos!AA$4:AA$7493) -> 400 | BP77: =SUMIF(Recibos!$D$4:$D$7493,Cobranza!$B77,Recibos!AB$4:AB$7493) -> 400 | BQ77: =SUMIF(Recibos!$D$4:$D$7493,Cobranza!$B77,Recibos!AC$4:AC$7493) -> 400 | BR77: =SUMIF(Recibos!$D$4:$D$7493,Cobranza!$B77,Recibos!AD$4:AD$7493) -> 400 | BS77: =SUMIF(Recibos!$D$4:$D$7493,Cobranza!$B77,Recibos!AE$4:AE$7493) -> 400 | ... BW77: =SUMIF(Recibos!$D$4:$D$7493,Cobranza!$B77,Recibos!AI$4:AI$7493) -> 400 | BX77: =SUM(BL77:BW77) -> 4800 | BY77: =SUMIF(Recibos!$D$4:$D$7493,Cobranza!$B77,Recibos!AK$4:AK$7493) -> 400 | BZ77: =SUMIF(Recibos!$D$4:$D$7493,Cobranza!$B77,Recibos!AL$4:AL$7493) -> 400 | CA77: =SUMIF(Recibos!$D$4:$D$7493,Cobranza!$B77,Recibos!AM$4:AM$7493) -> 400 | CB77: =SUMIF(Recibos!$D$4:$D$7493,Cobranza!$B77,Recibos!AN$4:AN$7493) -> 400 | CC77: =SUMIF(Recibos!$D$4:$D$7493,Cobranza!$B77,Recibos!AO$4:AO$7493) -> 800 | CD77: =SUMIF(Recibos!$D$4:$D$7493,Cobranza!$B77,Recibos!AP$4:AP$7493) -> 400 | CE77: =SUMIF(Recibos!$D$4:$D$7493,Cobranza!$B77,Recibos!AQ$4:AQ$7493) -> 400 | CF77: =SUMIF(Recibos!$D$4:$D$7493,Cobranza!$B77,Recibos!AR$4:AR$7493) -> 400 | ... CJ77: =SUMIF(Recibos!$D$4:$D$7493,Cobranza!$B77,Recibos!AV$4:AV$7493) -> 0 | CK77: =SUM(BY77:CJ77) -> 4400
B78: CL_88_ | C78: Rancho La Cuchilla No. 88 | E78: 0 | F78: 0 | G78: 0 | H78: 0 | I78: 0 | J78: 0 | K78: =SUM(E78:J78) -> 0 | L78: 0 | M78: 0 | N78: 0 | O78: 0 | P78: 0 | Q78: 0 | R78: 0 | S78: 0 | T78: 0 | U78: 0 | V78: 0 | W78: 0 | X78: =SUM(L78:W78) -> 0 | Y78: 0 | Z78: 0 | AA78: 0 | AB78: 0 | AC78: 0 | AD78: 0 | AE78: 0 | AF78: 0 | AG78: 0 | AH78: 0 | AI78: 0 | AJ78: 0 | AK78: =SUM(Y78:AJ78) -> 0 | AL78: 0 | AM78: 0 | AN78: 0 | AO78: 0 | AP78: 0 | AQ78: 0 | AR78: 0 | AS78: 0 | AT78: 0 | AU78: 0 | AV78: 0 | AW78: 0 | AX78: =SUM(AL78:AW78) -> 0 | AY78: =SUMIF(Recibos!$D$4:$D$7493,Cobranza!$B78,Recibos!K$4:K$7493) -> 0 | AZ78: =SUMIF(Recibos!$D$4:$D$7493,Cobranza!$B78,Recibos!L$4:L$7493) -> 0 | BA78: =SUMIF(Recibos!$D$4:$D$7493,Cobranza!$B78,Recibos!M$4:M$7493) -> 0 | BB78: =SUMIF(Recibos!$D$4:$D$7493,Cobranza!$B78,Recibos!N$4:N$7493) -> 0 | BC78: =SUMIF(Recibos!$D$4:$D$7493,Cobranza!$B78,Recibos!O$4:O$7493) -> 0 | BD78: =SUMIF(Recibos!$D$4:$D$7493,Cobranza!$B78,Recibos!P$4:P$7493) -> 0 | BE78: =SUMIF(Recibos!$D$4:$D$7493,Cobranza!$B78,Recibos!Q$4:Q$7493) -> 0 | BF78: =SUMIF(Recibos!$D$4:$D$7493,Cobranza!$B78,Recibos!R$4:R$7493) -> 0 | ... BJ78: =SUMIF(Recibos!$D$4:$D$7493,Cobranza!$B78,Recibos!V$4:V$7493) -> 0 | BK78: =SUM(AY78:BJ78) -> 0 | BL78: =SUMIF(Recibos!$D$4:$D$7493,Cobranza!$B78,Recibos!X$4:X$7493) -> 0 | BM78: =SUMIF(Recibos!$D$4:$D$7493,Cobranza!$B78,Recibos!Y$4:Y$7493) -> 0 | BN78: =SUMIF(Recibos!$D$4:$D$7493,Cobranza!$B78,Recibos!Z$4:Z$7493) -> 0 | BO78: =SUMIF(Recibos!$D$4:$D$7493,Cobranza!$B78,Recibos!AA$4:AA$7493) -> 0 | BP78: =SUMIF(Recibos!$D$4:$D$7493,Cobranza!$B78,Recibos!AB$4:AB$7493) -> 0 | BQ78: =SUMIF(Recibos!$D$4:$D$7493,Cobranza!$B78,Recibos!AC$4:AC$7493) -> 0 | BR78: =SUMIF(Recibos!$D$4:$D$7493,Cobranza!$B78,Recibos!AD$4:AD$7493) -> 0 | BS78: =SUMIF(Recibos!$D$4:$D$7493,Cobranza!$B78,Recibos!AE$4:AE$7493) -> 0 | ... BW78: =SUMIF(Recibos!$D$4:$D$7493,Cobranza!$B78,Recibos!AI$4:AI$7493) -> 0 | BX78: =SUM(BL78:BW78) -> 0 | BY78: =SUMIF(Recibos!$D$4:$D$7493,Cobranza!$B78,Recibos!AK$4:AK$7493) -> 0 | BZ78: =SUMIF(Recibos!$D$4:$D$7493,Cobranza!$B78,Recibos!AL$4:AL$7493) -> 0 | CA78: =SUMIF(Recibos!$D$4:$D$7493,Cobranza!$B78,Recibos!AM$4:AM$7493) -> 0 | CB78: =SUMIF(Recibos!$D$4:$D$7493,Cobranza!$B78,Recibos!AN$4:AN$7493) -> 0 | CC78: =SUMIF(Recibos!$D$4:$D$7493,Cobranza!$B78,Recibos!AO$4:AO$7493) -> 0 | CD78: =SUMIF(Recibos!$D$4:$D$7493,Cobranza!$B78,Recibos!AP$4:AP$7493) -> 0 | CE78: =SUMIF(Recibos!$D$4:$D$7493,Cobranza!$B78,Recibos!AQ$4:AQ$7493) -> 0 | CF78: =SUMIF(Recibos!$D$4:$D$7493,Cobranza!$B78,Recibos!AR$4:AR$7493) -> 0 | ... CJ78: =SUMIF(Recibos!$D$4:$D$7493,Cobranza!$B78,Recibos!AV$4:AV$7493) -> 0 | CK78: =SUM(BY78:CJ78) -> 0
B79: CL_89_ | C79: Rancho La Cuchilla No. 89 | D79: Gálvez | E79: 0 | F79: 0 | G79: 0 | H79: 0 | I79: 0 | J79: 300 | K79: =SUM(E79:J79) -> 300 | L79: 300 | M79: 300 | N79: 300 | O79: 300 | P79: 300 | Q79: 300 | R79: 300 | S79: 300 | T79: 300 | U79: 400 | V79: 400 | W79: 400 | X79: =SUM(L79:W79) -> 3900 | Y79: 400 | Z79: 400 | AA79: 400 | AB79: 400 | AC79: 400 | AD79: 400 | AE79: 400 | AF79: 400 | AG79: 400 | AH79: 400 | AI79: 400 | AJ79: 400 | AK79: =SUM(Y79:AJ79) -> 4800 | AL79: 400 | AM79: 400 | AN79: 400 | AO79: 400 | AP79: 400 | AQ79: 400 | AR79: 400 | AS79: 400 | AT79: 400 | AU79: 400 | AV79: 400 | AW79: 400 | AX79: =SUM(AL79:AW79) -> 4800 | AY79: =SUMIF(Recibos!$D$4:$D$7493,Cobranza!$B79,Recibos!K$4:K$7493) -> 400 | AZ79: =SUMIF(Recibos!$D$4:$D$7493,Cobranza!$B79,Recibos!L$4:L$7493) -> 400 | BA79: =SUMIF(Recibos!$D$4:$D$7493,Cobranza!$B79,Recibos!M$4:M$7493) -> 400 | BB79: =SUMIF(Recibos!$D$4:$D$7493,Cobranza!$B79,Recibos!N$4:N$7493) -> 400 | BC79: =SUMIF(Recibos!$D$4:$D$7493,Cobranza!$B79,Recibos!O$4:O$7493) -> 400 | BD79: =SUMIF(Recibos!$D$4:$D$7493,Cobranza!$B79,Recibos!P$4:P$7493) -> 400 | BE79: =SUMIF(Recibos!$D$4:$D$7493,Cobranza!$B79,Recibos!Q$4:Q$7493) -> 400 | BF79: =SUMIF(Recibos!$D$4:$D$7493,Cobranza!$B79,Recibos!R$4:R$7493) -> 400 | ... BJ79: =SUMIF(Recibos!$D$4:$D$7493,Cobranza!$B79,Recibos!V$4:V$7493) -> 400 | BK79: =SUM(AY79:BJ79) -> 4800 | BL79: =SUMIF(Recibos!$D$4:$D$7493,Cobranza!$B79,Recibos!X$4:X$7493) -> 400 | BM79: =SUMIF(Recibos!$D$4:$D$7493,Cobranza!$B79,Recibos!Y$4:Y$7493) -> 400 | BN79: =SUMIF(Recibos!$D$4:$D$7493,Cobranza!$B79,Recibos!Z$4:Z$7493) -> 400 | BO79: =SUMIF(Recibos!$D$4:$D$7493,Cobranza!$B79,Recibos!AA$4:AA$7493) -> 400 | BP79: =SUMIF(Recibos!$D$4:$D$7493,Cobranza!$B79,Recibos!AB$4:AB$7493) -> 400 | BQ79: =SUMIF(Recibos!$D$4:$D$7493,Cobranza!$B79,Recibos!AC$4:AC$7493) -> 400 | BR79: =SUMIF(Recibos!$D$4:$D$7493,Cobranza!$B79,Recibos!AD$4:AD$7493) -> 400 | BS79: =SUMIF(Recibos!$D$4:$D$7493,Cobranza!$B79,Recibos!AE$4:AE$7493) -> 400 | ... BW79: =SUMIF(Recibos!$D$4:$D$7493,Cobranza!$B79,Recibos!AI$4:AI$7493) -> 400 | BX79: =SUM(BL79:BW79) -> 4800 | BY79: =SUMIF(Recibos!$D$4:$D$7493,Cobranza!$B79,Recibos!AK$4:AK$7493) -> 400 | BZ79: =SUMIF(Recibos!$D$4:$D$7493,Cobranza!$B79,Recibos!AL$4:AL$7493) -> 400 | CA79: =SUMIF(Recibos!$D$4:$D$7493,Cobranza!$B79,Recibos!AM$4:AM$7493) -> 400 | CB79: =SUMIF(Recibos!$D$4:$D$7493,Cobranza!$B79,Recibos!AN$4:AN$7493) -> 400 | CC79: =SUMIF(Recibos!$D$4:$D$7493,Cobranza!$B79,Recibos!AO$4:AO$7493) -> 400 | CD79: =SUMIF(Recibos!$D$4:$D$7493,Cobranza!$B79,Recibos!AP$4:AP$7493) -> 400 | CE79: =SUMIF(Recibos!$D$4:$D$7493,Cobranza!$B79,Recibos!AQ$4:AQ$7493) -> 400 | CF79: =SUMIF(Recibos!$D$4:$D$7493,Cobranza!$B79,Recibos!AR$4:AR$7493) -> 400 | ... CJ79: =SUMIF(Recibos!$D$4:$D$7493,Cobranza!$B79,Recibos!AV$4:AV$7493) -> 0 | CK79: =SUM(BY79:CJ79) -> 4000
B80: CL_90_ | C80: Rancho La Cuchilla No. 90 | D80: Porras Fuentes | E80: 0 | F80: 0 | G80: 0 | H80: 0 | I80: 150 | J80: 150 | K80: =SUM(E80:J80) -> 300 | L80: 150 | M80: 150 | N80: 150 | O80: 150 | P80: 150 | Q80: 150 | R80: 150 | S80: 150 | T80: 150 | U80: 200 | V80: 200 | W80: 200 | X80: =SUM(L80:W80) -> 1950 | Y80: 200 | Z80: 200 | AA80: 200 | AB80: 200 | AC80: 200 | AD80: 200 | AE80: 200 | AF80: 200 | AG80: 0 | AH80: 0 | AI80: 200 | AJ80: 200 | AK80: =SUM(Y80:AJ80) -> 2000 | AL80: 200 | AM80: 200 | AN80: 200 | AO80: 200 | AP80: 200 | AQ80: 200 | AR80: 200 | AS80: 200 | AT80: 200 | AU80: 200 | AV80: 200 | AW80: 200 | AX80: =SUM(AL80:AW80) -> 2400 | AY80: =SUMIF(Recibos!$D$4:$D$7493,Cobranza!$B80,Recibos!K$4:K$7493) -> 200 | AZ80: =SUMIF(Recibos!$D$4:$D$7493,Cobranza!$B80,Recibos!L$4:L$7493) -> 200 | BA80: =SUMIF(Recibos!$D$4:$D$7493,Cobranza!$B80,Recibos!M$4:M$7493) -> 200 | BB80: =SUMIF(Recibos!$D$4:$D$7493,Cobranza!$B80,Recibos!N$4:N$7493) -> 200 | BC80: =SUMIF(Recibos!$D$4:$D$7493,Cobranza!$B80,Recibos!O$4:O$7493) -> 200 | BD80: =SUMIF(Recibos!$D$4:$D$7493,Cobranza!$B80,Recibos!P$4:P$7493) -> 200 | BE80: =SUMIF(Recibos!$D$4:$D$7493,Cobranza!$B80,Recibos!Q$4:Q$7493) -> 200 | BF80: =SUMIF(Recibos!$D$4:$D$7493,Cobranza!$B80,Recibos!R$4:R$7493) -> 200 | ... BJ80: =SUMIF(Recibos!$D$4:$D$7493,Cobranza!$B80,Recibos!V$4:V$7493) -> 200 | BK80: =SUM(AY80:BJ80) -> 2400 | BL80: =SUMIF(Recibos!$D$4:$D$7493,Cobranza!$B80,Recibos!X$4:X$7493) -> 200 | BM80: =SUMIF(Recibos!$D$4:$D$7493,Cobranza!$B80,Recibos!Y$4:Y$7493) -> 200 | BN80: =SUMIF(Recibos!$D$4:$D$7493,Cobranza!$B80,Recibos!Z$4:Z$7493) -> 200 | BO80: =SUMIF(Recibos!$D$4:$D$7493,Cobranza!$B80,Recibos!AA$4:AA$7493) -> 200 | BP80: =SUMIF(Recibos!$D$4:$D$7493,Cobranza!$B80,Recibos!AB$4:AB$7493) -> 200 | BQ80: =SUMIF(Recibos!$D$4:$D$7493,Cobranza!$B80,Recibos!AC$4:AC$7493) -> 200 | BR80: =SUMIF(Recibos!$D$4:$D$7493,Cobranza!$B80,Recibos!AD$4:AD$7493) -> 200 | BS80: =SUMIF(Recibos!$D$4:$D$7493,Cobranza!$B80,Recibos!AE$4:AE$7493) -> 200 | ... BW80: =SUMIF(Recibos!$D$4:$D$7493,Cobranza!$B80,Recibos!AI$4:AI$7493) -> 200 | BX80: =SUM(BL80:BW80) -> 2400 | BY80: =SUMIF(Recibos!$D$4:$D$7493,Cobranza!$B80,Recibos!AK$4:AK$7493) -> 200 | BZ80: =SUMIF(Recibos!$D$4:$D$7493,Cobranza!$B80,Recibos!AL$4:AL$7493) -> 200 | CA80: =SUMIF(Recibos!$D$4:$D$7493,Cobranza!$B80,Recibos!AM$4:AM$7493) -> 200 | CB80: =SUMIF(Recibos!$D$4:$D$7493,Cobranza!$B80,Recibos!AN$4:AN$7493) -> 200 | CC80: =SUMIF(Recibos!$D$4:$D$7493,Cobranza!$B80,Recibos!AO$4:AO$7493) -> 200 | CD80: =SUMIF(Recibos!$D$4:$D$7493,Cobranza!$B80,Recibos!AP$4:AP$7493) -> 200 | CE80: =SUMIF(Recibos!$D$4:$D$7493,Cobranza!$B80,Recibos!AQ$4:AQ$7493) -> 200 | CF80: =SUMIF(Recibos!$D$4:$D$7493,Cobranza!$B80,Recibos!AR$4:AR$7493) -> 200 | ... CJ80: =SUMIF(Recibos!$D$4:$D$7493,Cobranza!$B80,Recibos!AV$4:AV$7493) -> 0 | CK80: =SUM(BY80:CJ80) -> 2000
B81: CL_91_ | C81: Rancho La Cuchilla No. 91 | D81: Roldán Flores | E81: 0 | F81: 0 | G81: 0 | H81: 0 | I81: 0 | J81: 0 | K81: =SUM(E81:J81) -> 0 | L81: 300 | M81: 300 | N81: 300 | O81: 300 | P81: 300 | Q81: 300 | R81: 300 | S81: 300 | T81: 300 | U81: 300 | V81: 300 | W81: 0 | X81: =SUM(L81:W81) -> 3300 | Y81: 400 | Z81: 400 | AA81: 400 | AB81: 400 | AC81: 400 | AD81: 400 | AE81: 400 | AF81: 400 | AG81: 400 | AH81: 400 | AI81: 400 | AJ81: 0 | AK81: =SUM(Y81:AJ81) -> 4400 | AL81: 400 | AM81: 400 | AN81: 400 | AO81: 400 | AP81: 400 | AQ81: 400 | AR81: 400 | AS81: 400 | AT81: 400 | AU81: 400 | AV81: 400 | AW81: 0 | AX81: =SUM(AL81:AW81) -> 4400 | AY81: =SUMIF(Recibos!$D$4:$D$7493,Cobranza!$B81,Recibos!K$4:K$7493) -> 400 | AZ81: =SUMIF(Recibos!$D$4:$D$7493,Cobranza!$B81,Recibos!L$4:L$7493) -> 400 | BA81: =SUMIF(Recibos!$D$4:$D$7493,Cobranza!$B81,Recibos!M$4:M$7493) -> 400 | BB81: =SUMIF(Recibos!$D$4:$D$7493,Cobranza!$B81,Recibos!N$4:N$7493) -> 400 | BC81: =SUMIF(Recibos!$D$4:$D$7493,Cobranza!$B81,Recibos!O$4:O$7493) -> 400 | BD81: =SUMIF(Recibos!$D$4:$D$7493,Cobranza!$B81,Recibos!P$4:P$7493) -> 400 | BE81: =SUMIF(Recibos!$D$4:$D$7493,Cobranza!$B81,Recibos!Q$4:Q$7493) -> 400 | BF81: =SUMIF(Recibos!$D$4:$D$7493,Cobranza!$B81,Recibos!R$4:R$7493) -> 400 | ... BJ81: =SUMIF(Recibos!$D$4:$D$7493,Cobranza!$B81,Recibos!V$4:V$7493) -> 0 | BK81: =SUM(AY81:BJ81) -> 4400 | BL81: =SUMIF(Recibos!$D$4:$D$7493,Cobranza!$B81,Recibos!X$4:X$7493) -> 400 | BM81: =SUMIF(Recibos!$D$4:$D$7493,Cobranza!$B81,Recibos!Y$4:Y$7493) -> 400 | BN81: =SUMIF(Recibos!$D$4:$D$7493,Cobranza!$B81,Recibos!Z$4:Z$7493) -> 400 | BO81: =SUMIF(Recibos!$D$4:$D$7493,Cobranza!$B81,Recibos!AA$4:AA$7493) -> 400 | BP81: =SUMIF(Recibos!$D$4:$D$7493,Cobranza!$B81,Recibos!AB$4:AB$7493) -> 400 | BQ81: =SUMIF(Recibos!$D$4:$D$7493,Cobranza!$B81,Recibos!AC$4:AC$7493) -> 400 | BR81: =SUMIF(Recibos!$D$4:$D$7493,Cobranza!$B81,Recibos!AD$4:AD$7493) -> 400 | BS81: =SUMIF(Recibos!$D$4:$D$7493,Cobranza!$B81,Recibos!AE$4:AE$7493) -> 400 | ... BW81: =SUMIF(Recibos!$D$4:$D$7493,Cobranza!$B81,Recibos!AI$4:AI$7493) -> 0 | BX81: =SUM(BL81:BW81) -> 4400 | BY81: =SUMIF(Recibos!$D$4:$D$7493,Cobranza!$B81,Recibos!AK$4:AK$7493) -> 400 | BZ81: =SUMIF(Recibos!$D$4:$D$7493,Cobranza!$B81,Recibos!AL$4:AL$7493) -> 400 | CA81: =SUMIF(Recibos!$D$4:$D$7493,Cobranza!$B81,Recibos!AM$4:AM$7493) -> 400 | CB81: =SUMIF(Recibos!$D$4:$D$7493,Cobranza!$B81,Recibos!AN$4:AN$7493) -> 400 | CC81: =SUMIF(Recibos!$D$4:$D$7493,Cobranza!$B81,Recibos!AO$4:AO$7493) -> 400 | CD81: =SUMIF(Recibos!$D$4:$D$7493,Cobranza!$B81,Recibos!AP$4:AP$7493) -> 400 | CE81: =SUMIF(Recibos!$D$4:$D$7493,Cobranza!$B81,Recibos!AQ$4:AQ$7493) -> 400 | CF81: =SUMIF(Recibos!$D$4:$D$7493,Cobranza!$B81,Recibos!AR$4:AR$7493) -> 400 | ... CJ81: =SUMIF(Recibos!$D$4:$D$7493,Cobranza!$B81,Recibos!AV$4:AV$7493) -> 0 | CK81: =SUM(BY81:CJ81) -> 4400
B82: CL_92_ | C82: Rancho La Cuchilla No. 92 | D82: Cabrera | E82: 0 | F82: 0 | G82: 0 | H82: 0 | I82: 0 | J82: 0 | K82: =SUM(E82:J82) -> 0 | L82: 300 | M82: 300 | N82: 300 | O82: 300 | P82: 300 | Q82: 300 | R82: 300 | S82: 300 | T82: 300 | U82: 400 | V82: 400 | W82: 400 | X82: =SUM(L82:W82) -> 3900 | Y82: 400 | Z82: 400 | AA82: 400 | AB82: 400 | AC82: 400 | AD82: 400 | AE82: 400 | AF82: 400 | AG82: 400 | AH82: 400 | AI82: 400 | AJ82: 400 | AK82: =SUM(Y82:AJ82) -> 4800 | AL82: 400 | AM82: 400 | AN82: 400 | AO82: 400 | AP82: 400 | AQ82: 400 | AR82: 400 | AS82: 400 | AT82: 400 | AU82: 400 | AV82: 400 | AW82: 0 | AX82: =SUM(AL82:AW82) -> 4400 | AY82: =SUMIF(Recibos!$D$4:$D$7493,Cobranza!$B82,Recibos!K$4:K$7493) -> 400 | AZ82: =SUMIF(Recibos!$D$4:$D$7493,Cobranza!$B82,Recibos!L$4:L$7493) -> 400 | BA82: =SUMIF(Recibos!$D$4:$D$7493,Cobranza!$B82,Recibos!M$4:M$7493) -> 400 | BB82: =SUMIF(Recibos!$D$4:$D$7493,Cobranza!$B82,Recibos!N$4:N$7493) -> 400 | BC82: =SUMIF(Recibos!$D$4:$D$7493,Cobranza!$B82,Recibos!O$4:O$7493) -> 400 | BD82: =SUMIF(Recibos!$D$4:$D$7493,Cobranza!$B82,Recibos!P$4:P$7493) -> 400 | BE82: =SUMIF(Recibos!$D$4:$D$7493,Cobranza!$B82,Recibos!Q$4:Q$7493) -> 400 | BF82: =SUMIF(Recibos!$D$4:$D$7493,Cobranza!$B82,Recibos!R$4:R$7493) -> 400 | ... BJ82: =SUMIF(Recibos!$D$4:$D$7493,Cobranza!$B82,Recibos!V$4:V$7493) -> 400 | BK82: =SUM(AY82:BJ82) -> 4800 | BL82: =SUMIF(Recibos!$D$4:$D$7493,Cobranza!$B82,Recibos!X$4:X$7493) -> 400 | BM82: =SUMIF(Recibos!$D$4:$D$7493,Cobranza!$B82,Recibos!Y$4:Y$7493) -> 400 | BN82: =SUMIF(Recibos!$D$4:$D$7493,Cobranza!$B82,Recibos!Z$4:Z$7493) -> 400 | BO82: =SUMIF(Recibos!$D$4:$D$7493,Cobranza!$B82,Recibos!AA$4:AA$7493) -> 400 | BP82: =SUMIF(Recibos!$D$4:$D$7493,Cobranza!$B82,Recibos!AB$4:AB$7493) -> 400 | BQ82: =SUMIF(Recibos!$D$4:$D$7493,Cobranza!$B82,Recibos!AC$4:AC$7493) -> 0 | BR82: =SUMIF(Recibos!$D$4:$D$7493,Cobranza!$B82,Recibos!AD$4:AD$7493) -> 0 | BS82: =SUMIF(Recibos!$D$4:$D$7493,Cobranza!$B82,Recibos!AE$4:AE$7493) -> 0 | ... BW82: =SUMIF(Recibos!$D$4:$D$7493,Cobranza!$B82,Recibos!AI$4:AI$7493) -> 0 | BX82: =SUM(BL82:BW82) -> 2000 | BY82: =SUMIF(Recibos!$D$4:$D$7493,Cobranza!$B82,Recibos!AK$4:AK$7493) -> 0 | BZ82: =SUMIF(Recibos!$D$4:$D$7493,Cobranza!$B82,Recibos!AL$4:AL$7493) -> 0 | CA82: =SUMIF(Recibos!$D$4:$D$7493,Cobranza!$B82,Recibos!AM$4:AM$7493) -> 0 | CB82: =SUMIF(Recibos!$D$4:$D$7493,Cobranza!$B82,Recibos!AN$4:AN$7493) -> 0 | CC82: =SUMIF(Recibos!$D$4:$D$7493,Cobranza!$B82,Recibos!AO$4:AO$7493) -> 0 | CD82: =SUMIF(Recibos!$D$4:$D$7493,Cobranza!$B82,Recibos!AP$4:AP$7493) -> 0 | CE82: =SUMIF(Recibos!$D$4:$D$7493,Cobranza!$B82,Recibos!AQ$4:AQ$7493) -> 0 | CF82: =SUMIF(Recibos!$D$4:$D$7493,Cobranza!$B82,Recibos!AR$4:AR$7493) -> 0 | ... CJ82: =SUMIF(Recibos!$D$4:$D$7493,Cobranza!$B82,Recibos!AV$4:AV$7493) -> 0 | CK82: =SUM(BY82:CJ82) -> 0
B83: CL_93_ | C83: Rancho La Cuchilla No. 93 | D83: Alcántara Silva | E83: 0 | F83: 0 | G83: 0 | H83: 0 | I83: 0 | J83: 300 | K83: =SUM(E83:J83) -> 300 | L83: 300 | M83: 300 | N83: 300 | O83: 150 | P83: 170 | Q83: 300 | R83: 300 | S83: 300 | T83: 300 | U83: 400 | V83: 400 | W83: 400 | X83: =SUM(L83:W83) -> 3620 | Y83: 400 | Z83: 400 | AA83: 800 | AB83: 400 | AC83: 400 | AD83: 400 | AE83: 400 | AF83: 400 | AG83: 400 | AH83: 400 | AI83: 400 | AJ83: 400 | AK83: =SUM(Y83:AJ83) -> 5200 | AL83: 400 | AM83: 400 | AN83: 400 | AO83: 400 | AP83: 400 | AQ83: 400 | AR83: 400 | AS83: 400 | AT83: 400 | AU83: 400 | AV83: 400 | AW83: 400 | AX83: =SUM(AL83:AW83) -> 4800 | AY83: =SUMIF(Recibos!$D$4:$D$7493,Cobranza!$B83,Recibos!K$4:K$7493) -> 400 | AZ83: =SUMIF(Recibos!$D$4:$D$7493,Cobranza!$B83,Recibos!L$4:L$7493) -> 400 | BA83: =SUMIF(Recibos!$D$4:$D$7493,Cobranza!$B83,Recibos!M$4:M$7493) -> 400 | BB83: =SUMIF(Recibos!$D$4:$D$7493,Cobranza!$B83,Recibos!N$4:N$7493) -> 400 | BC83: =SUMIF(Recibos!$D$4:$D$7493,Cobranza!$B83,Recibos!O$4:O$7493) -> 400 | BD83: =SUMIF(Recibos!$D$4:$D$7493,Cobranza!$B83,Recibos!P$4:P$7493) -> 400 | BE83: =SUMIF(Recibos!$D$4:$D$7493,Cobranza!$B83,Recibos!Q$4:Q$7493) -> 400 | BF83: =SUMIF(Recibos!$D$4:$D$7493,Cobranza!$B83,Recibos!R$4:R$7493) -> 400 | ... BJ83: =SUMIF(Recibos!$D$4:$D$7493,Cobranza!$B83,Recibos!V$4:V$7493) -> 400 | BK83: =SUM(AY83:BJ83) -> 4800 | BL83: =SUMIF(Recibos!$D$4:$D$7493,Cobranza!$B83,Recibos!X$4:X$7493) -> 400 | BM83: =SUMIF(Recibos!$D$4:$D$7493,Cobranza!$B83,Recibos!Y$4:Y$7493) -> 400 | BN83: =SUMIF(Recibos!$D$4:$D$7493,Cobranza!$B83,Recibos!Z$4:Z$7493) -> 400 | BO83: =SUMIF(Recibos!$D$4:$D$7493,Cobranza!$B83,Recibos!AA$4:AA$7493) -> 400 | BP83: =SUMIF(Recibos!$D$4:$D$7493,Cobranza!$B83,Recibos!AB$4:AB$7493) -> 400 | BQ83: =SUMIF(Recibos!$D$4:$D$7493,Cobranza!$B83,Recibos!AC$4:AC$7493) -> 400 | BR83: =SUMIF(Recibos!$D$4:$D$7493,Cobranza!$B83,Recibos!AD$4:AD$7493) -> 400 | BS83: =SUMIF(Recibos!$D$4:$D$7493,Cobranza!$B83,Recibos!AE$4:AE$7493) -> 400 | ... BW83: =SUMIF(Recibos!$D$4:$D$7493,Cobranza!$B83,Recibos!AI$4:AI$7493) -> 400 | BX83: =SUM(BL83:BW83) -> 4800 | BY83: =SUMIF(Recibos!$D$4:$D$7493,Cobranza!$B83,Recibos!AK$4:AK$7493) -> 400 | BZ83: =SUMIF(Recibos!$D$4:$D$7493,Cobranza!$B83,Recibos!AL$4:AL$7493) -> 400 | CA83: =SUMIF(Recibos!$D$4:$D$7493,Cobranza!$B83,Recibos!AM$4:AM$7493) -> 400 | CB83: =SUMIF(Recibos!$D$4:$D$7493,Cobranza!$B83,Recibos!AN$4:AN$7493) -> 400 | CC83: =SUMIF(Recibos!$D$4:$D$7493,Cobranza!$B83,Recibos!AO$4:AO$7493) -> 400 | CD83: =SUMIF(Recibos!$D$4:$D$7493,Cobranza!$B83,Recibos!AP$4:AP$7493) -> 400 | CE83: =SUMIF(Recibos!$D$4:$D$7493,Cobranza!$B83,Recibos!AQ$4:AQ$7493) -> 400 | CF83: =SUMIF(Recibos!$D$4:$D$7493,Cobranza!$B83,Recibos!AR$4:AR$7493) -> 400 | ... CJ83: =SUMIF(Recibos!$D$4:$D$7493,Cobranza!$B83,Recibos!AV$4:AV$7493) -> 0 | CK83: =SUM(BY83:CJ83) -> 3600
B84: CL_94_ | C84: Rancho La Cuchilla No. 94 | D84: Sánchez Márquez | E84: 0 | F84: 0 | G84: 0 | H84: 0 | I84: 0 | J84: 300 | K84: =SUM(E84:J84) -> 300 | L84: 300 | M84: 300 | N84: 0 | O84: 300 | P84: 300 | Q84: 300 | R84: 300 | S84: 300 | T84: 300 | U84: 400 | V84: 400 | W84: 400 | X84: =SUM(L84:W84) -> 3600 | Y84: 400 | Z84: 400 | AA84: 400 | AB84: 0 | AC84: 400 | AD84: 400 | AE84: 400 | AF84: 400 | AG84: 400 | AH84: 400 | AI84: 400 | AJ84: 0 | AK84: =SUM(Y84:AJ84) -> 4000 | AL84: 400 | AM84: 400 | AN84: 400 | AO84: 400 | AP84: 400 | AQ84: 400 | AR84: 400 | AS84: 400 | AT84: 400 | AU84: 400 | AV84: 400 | AW84: 400 | AX84: =SUM(AL84:AW84) -> 4800 | AY84: =SUMIF(Recibos!$D$4:$D$7493,Cobranza!$B84,Recibos!K$4:K$7493) -> 400 | AZ84: =SUMIF(Recibos!$D$4:$D$7493,Cobranza!$B84,Recibos!L$4:L$7493) -> 400 | BA84: =SUMIF(Recibos!$D$4:$D$7493,Cobranza!$B84,Recibos!M$4:M$7493) -> 400 | BB84: =SUMIF(Recibos!$D$4:$D$7493,Cobranza!$B84,Recibos!N$4:N$7493) -> 400 | BC84: =SUMIF(Recibos!$D$4:$D$7493,Cobranza!$B84,Recibos!O$4:O$7493) -> 400 | BD84: =SUMIF(Recibos!$D$4:$D$7493,Cobranza!$B84,Recibos!P$4:P$7493) -> 400 | BE84: =SUMIF(Recibos!$D$4:$D$7493,Cobranza!$B84,Recibos!Q$4:Q$7493) -> 400 | BF84: =SUMIF(Recibos!$D$4:$D$7493,Cobranza!$B84,Recibos!R$4:R$7493) -> 400 | ... BJ84: =SUMIF(Recibos!$D$4:$D$7493,Cobranza!$B84,Recibos!V$4:V$7493) -> 400 | BK84: =SUM(AY84:BJ84) -> 4800 | BL84: =SUMIF(Recibos!$D$4:$D$7493,Cobranza!$B84,Recibos!X$4:X$7493) -> 400 | BM84: =SUMIF(Recibos!$D$4:$D$7493,Cobranza!$B84,Recibos!Y$4:Y$7493) -> 400 | BN84: =SUMIF(Recibos!$D$4:$D$7493,Cobranza!$B84,Recibos!Z$4:Z$7493) -> 400 | BO84: =SUMIF(Recibos!$D$4:$D$7493,Cobranza!$B84,Recibos!AA$4:AA$7493) -> 400 | BP84: =SUMIF(Recibos!$D$4:$D$7493,Cobranza!$B84,Recibos!AB$4:AB$7493) -> 400 | BQ84: =SUMIF(Recibos!$D$4:$D$7493,Cobranza!$B84,Recibos!AC$4:AC$7493) -> 400 | BR84: =SUMIF(Recibos!$D$4:$D$7493,Cobranza!$B84,Recibos!AD$4:AD$7493) -> 400 | BS84: =SUMIF(Recibos!$D$4:$D$7493,Cobranza!$B84,Recibos!AE$4:AE$7493) -> 400 | ... BW84: =SUMIF(Recibos!$D$4:$D$7493,Cobranza!$B84,Recibos!AI$4:AI$7493) -> 400 | BX84: =SUM(BL84:BW84) -> 4800 | BY84: =SUMIF(Recibos!$D$4:$D$7493,Cobranza!$B84,Recibos!AK$4:AK$7493) -> 400 | BZ84: =SUMIF(Recibos!$D$4:$D$7493,Cobranza!$B84,Recibos!AL$4:AL$7493) -> 400 | CA84: =SUMIF(Recibos!$D$4:$D$7493,Cobranza!$B84,Recibos!AM$4:AM$7493) -> 400 | CB84: =SUMIF(Recibos!$D$4:$D$7493,Cobranza!$B84,Recibos!AN$4:AN$7493) -> 400 | CC84: =SUMIF(Recibos!$D$4:$D$7493,Cobranza!$B84,Recibos!AO$4:AO$7493) -> 400 | CD84: =SUMIF(Recibos!$D$4:$D$7493,Cobranza!$B84,Recibos!AP$4:AP$7493) -> 400 | CE84: =SUMIF(Recibos!$D$4:$D$7493,Cobranza!$B84,Recibos!AQ$4:AQ$7493) -> 400 | CF84: =SUMIF(Recibos!$D$4:$D$7493,Cobranza!$B84,Recibos!AR$4:AR$7493) -> 400 | ... CJ84: =SUMIF(Recibos!$D$4:$D$7493,Cobranza!$B84,Recibos!AV$4:AV$7493) -> 0 | CK84: =SUM(BY84:CJ84) -> 3600
B85: CL_95_ | C85: Rancho La Cuchilla No. 95 | D85: Cruz Huerta | E85: 0 | F85: 0 | G85: 0 | H85: 0 | I85: 0 | J85: 300 | K85: =SUM(E85:J85) -> 300 | L85: 300 | M85: 300 | N85: 300 | O85: 300 | P85: 300 | Q85: 300 | R85: 300 | S85: 300 | T85: 300 | U85: 300 | V85: 400 | W85: 400 | X85: =SUM(L85:W85) -> 3800 | Y85: 400 | Z85: 400 | AA85: 400 | AB85: 400 | AC85: 400 | AD85: 400 | AE85: 400 | AF85: 400 | AG85: 400 | AH85: 400 | AI85: 400 | AJ85: 400 | AK85: =SUM(Y85:AJ85) -> 4800 | AL85: 400 | AM85: 400 | AN85: 400 | AO85: 400 | AP85: 400 | AQ85: 400 | AR85: 400 | AS85: 400 | AT85: 400 | AU85: 400 | AV85: 400 | AW85: 0 | AX85: =SUM(AL85:AW85) -> 4400 | AY85: =SUMIF(Recibos!$D$4:$D$7493,Cobranza!$B85,Recibos!K$4:K$7493) -> 0 | AZ85: =SUMIF(Recibos!$D$4:$D$7493,Cobranza!$B85,Recibos!L$4:L$7493) -> 0 | BA85: =SUMIF(Recibos!$D$4:$D$7493,Cobranza!$B85,Recibos!M$4:M$7493) -> 0 | BB85: =SUMIF(Recibos!$D$4:$D$7493,Cobranza!$B85,Recibos!N$4:N$7493) -> 0 | BC85: =SUMIF(Recibos!$D$4:$D$7493,Cobranza!$B85,Recibos!O$4:O$7493) -> 0 | BD85: =SUMIF(Recibos!$D$4:$D$7493,Cobranza!$B85,Recibos!P$4:P$7493) -> 0 | BE85: =SUMIF(Recibos!$D$4:$D$7493,Cobranza!$B85,Recibos!Q$4:Q$7493) -> 0 | BF85: =SUMIF(Recibos!$D$4:$D$7493,Cobranza!$B85,Recibos!R$4:R$7493) -> 0 | ... BJ85: =SUMIF(Recibos!$D$4:$D$7493,Cobranza!$B85,Recibos!V$4:V$7493) -> 0 | BK85: =SUM(AY85:BJ85) -> 0 | BL85: =SUMIF(Recibos!$D$4:$D$7493,Cobranza!$B85,Recibos!X$4:X$7493) -> 400 | BM85: =SUMIF(Recibos!$D$4:$D$7493,Cobranza!$B85,Recibos!Y$4:Y$7493) -> 400 | BN85: =SUMIF(Recibos!$D$4:$D$7493,Cobranza!$B85,Recibos!Z$4:Z$7493) -> 400 | BO85: =SUMIF(Recibos!$D$4:$D$7493,Cobranza!$B85,Recibos!AA$4:AA$7493) -> 400 | BP85: =SUMIF(Recibos!$D$4:$D$7493,Cobranza!$B85,Recibos!AB$4:AB$7493) -> 400 | BQ85: =SUMIF(Recibos!$D$4:$D$7493,Cobranza!$B85,Recibos!AC$4:AC$7493) -> 400 | BR85: =SUMIF(Recibos!$D$4:$D$7493,Cobranza!$B85,Recibos!AD$4:AD$7493) -> 400 | BS85: =SUMIF(Recibos!$D$4:$D$7493,Cobranza!$B85,Recibos!AE$4:AE$7493) -> 400 | ... BW85: =SUMIF(Recibos!$D$4:$D$7493,Cobranza!$B85,Recibos!AI$4:AI$7493) -> 0 | BX85: =SUM(BL85:BW85) -> 4400 | BY85: =SUMIF(Recibos!$D$4:$D$7493,Cobranza!$B85,Recibos!AK$4:AK$7493) -> 400 | BZ85: =SUMIF(Recibos!$D$4:$D$7493,Cobranza!$B85,Recibos!AL$4:AL$7493) -> 400 | CA85: =SUMIF(Recibos!$D$4:$D$7493,Cobranza!$B85,Recibos!AM$4:AM$7493) -> 400 | CB85: =SUMIF(Recibos!$D$4:$D$7493,Cobranza!$B85,Recibos!AN$4:AN$7493) -> 400 | CC85: =SUMIF(Recibos!$D$4:$D$7493,Cobranza!$B85,Recibos!AO$4:AO$7493) -> 400 | CD85: =SUMIF(Recibos!$D$4:$D$7493,Cobranza!$B85,Recibos!AP$4:AP$7493) -> 400 | CE85: =SUMIF(Recibos!$D$4:$D$7493,Cobranza!$B85,Recibos!AQ$4:AQ$7493) -> 400 | CF85: =SUMIF(Recibos!$D$4:$D$7493,Cobranza!$B85,Recibos!AR$4:AR$7493) -> 400 | ... CJ85: =SUMIF(Recibos!$D$4:$D$7493,Cobranza!$B85,Recibos!AV$4:AV$7493) -> 0 | CK85: =SUM(BY85:CJ85) -> 4400
B86: CL_96_ | C86: Rancho La Cuchilla No. 96 | D86: Valdez Álvarez | E86: 300 | F86: 300 | G86: 300 | H86: 300 | I86: 300 | J86: 300 | K86: =SUM(E86:J86) -> 1800 | L86: 300 | M86: 300 | N86: 300 | O86: 300 | P86: 300 | Q86: 300 | R86: 300 | S86: 300 | T86: 300 | U86: 400 | V86: 400 | W86: 400 | X86: =SUM(L86:W86) -> 3900 | Y86: 400 | Z86: 400 | AA86: 400 | AB86: 400 | AC86: 400 | AD86: 400 | AE86: 400 | AF86: 400 | AG86: 400 | AH86: 400 | AI86: 400 | AJ86: 0 | AK86: =SUM(Y86:AJ86) -> 4400 | AL86: 400 | AM86: 400 | AN86: 400 | AO86: 400 | AP86: 400 | AQ86: 400 | AR86: 400 | AS86: 400 | AT86: 400 | AU86: 400 | AV86: 400 | AW86: 0 | AX86: =SUM(AL86:AW86) -> 4400 | AY86: =SUMIF(Recibos!$D$4:$D$7493,Cobranza!$B86,Recibos!K$4:K$7493) -> 400 | AZ86: =SUMIF(Recibos!$D$4:$D$7493,Cobranza!$B86,Recibos!L$4:L$7493) -> 400 | BA86: =SUMIF(Recibos!$D$4:$D$7493,Cobranza!$B86,Recibos!M$4:M$7493) -> 400 | BB86: =SUMIF(Recibos!$D$4:$D$7493,Cobranza!$B86,Recibos!N$4:N$7493) -> 400 | BC86: =SUMIF(Recibos!$D$4:$D$7493,Cobranza!$B86,Recibos!O$4:O$7493) -> 400 | BD86: =SUMIF(Recibos!$D$4:$D$7493,Cobranza!$B86,Recibos!P$4:P$7493) -> 400 | BE86: =SUMIF(Recibos!$D$4:$D$7493,Cobranza!$B86,Recibos!Q$4:Q$7493) -> 400 | BF86: =SUMIF(Recibos!$D$4:$D$7493,Cobranza!$B86,Recibos!R$4:R$7493) -> 400 | ... BJ86: =SUMIF(Recibos!$D$4:$D$7493,Cobranza!$B86,Recibos!V$4:V$7493) -> 0 | BK86: =SUM(AY86:BJ86) -> 4400 | BL86: =SUMIF(Recibos!$D$4:$D$7493,Cobranza!$B86,Recibos!X$4:X$7493) -> 400 | BM86: =SUMIF(Recibos!$D$4:$D$7493,Cobranza!$B86,Recibos!Y$4:Y$7493) -> 400 | BN86: =SUMIF(Recibos!$D$4:$D$7493,Cobranza!$B86,Recibos!Z$4:Z$7493) -> 400 | BO86: =SUMIF(Recibos!$D$4:$D$7493,Cobranza!$B86,Recibos!AA$4:AA$7493) -> 400 | BP86: =SUMIF(Recibos!$D$4:$D$7493,Cobranza!$B86,Recibos!AB$4:AB$7493) -> 400 | BQ86: =SUMIF(Recibos!$D$4:$D$7493,Cobranza!$B86,Recibos!AC$4:AC$7493) -> 400 | BR86: =SUMIF(Recibos!$D$4:$D$7493,Cobranza!$B86,Recibos!AD$4:AD$7493) -> 400 | BS86: =SUMIF(Recibos!$D$4:$D$7493,Cobranza!$B86,Recibos!AE$4:AE$7493) -> 400 | ... BW86: =SUMIF(Recibos!$D$4:$D$7493,Cobranza!$B86,Recibos!AI$4:AI$7493) -> 0 | BX86: =SUM(BL86:BW86) -> 4400 | BY86: =SUMIF(Recibos!$D$4:$D$7493,Cobranza!$B86,Recibos!AK$4:AK$7493) -> 400 | BZ86: =SUMIF(Recibos!$D$4:$D$7493,Cobranza!$B86,Recibos!AL$4:AL$7493) -> 400 | CA86: =SUMIF(Recibos!$D$4:$D$7493,Cobranza!$B86,Recibos!AM$4:AM$7493) -> 400 | CB86: =SUMIF(Recibos!$D$4:$D$7493,Cobranza!$B86,Recibos!AN$4:AN$7493) -> 400 | CC86: =SUMIF(Recibos!$D$4:$D$7493,Cobranza!$B86,Recibos!AO$4:AO$7493) -> 400 | CD86: =SUMIF(Recibos!$D$4:$D$7493,Cobranza!$B86,Recibos!AP$4:AP$7493) -> 400 | CE86: =SUMIF(Recibos!$D$4:$D$7493,Cobranza!$B86,Recibos!AQ$4:AQ$7493) -> 400 | CF86: =SUMIF(Recibos!$D$4:$D$7493,Cobranza!$B86,Recibos!AR$4:AR$7493) -> 400 | ... CJ86: =SUMIF(Recibos!$D$4:$D$7493,Cobranza!$B86,Recibos!AV$4:AV$7493) -> 0 | CK86: =SUM(BY86:CJ86) -> 4400
B87: CL_97_ | C87: Rancho La Cuchilla No. 97 | D87: López Ruiz | E87: 0 | F87: 0 | G87: 0 | H87: 0 | I87: 0 | J87: 300 | K87: =SUM(E87:J87) -> 300 | L87: 300 | M87: 300 | N87: 300 | O87: 300 | P87: 300 | Q87: 300 | R87: 300 | S87: 300 | T87: 300 | U87: 300 | V87: 300 | W87: 300 | X87: =SUM(L87:W87) -> 3600 | Y87: 300 | Z87: 300 | AA87: 300 | AB87: 300 | AC87: 300 | AD87: 300 | AE87: 300 | AF87: 300 | AG87: 300 | AH87: 300 | AI87: 300 | AJ87: 300 | AK87: =SUM(Y87:AJ87) -> 3600 | AL87: 300 | AM87: 300 | AN87: 300 | AO87: 300 | AP87: 300 | AQ87: 300 | AR87: 300 | AS87: 300 | AT87: 300 | AU87: 300 | AV87: 300 | AW87: 300 | AX87: =SUM(AL87:AW87) -> 3600 | AY87: =SUMIF(Recibos!$D$4:$D$7493,Cobranza!$B87,Recibos!K$4:K$7493) -> 300 | AZ87: =SUMIF(Recibos!$D$4:$D$7493,Cobranza!$B87,Recibos!L$4:L$7493) -> 300 | BA87: =SUMIF(Recibos!$D$4:$D$7493,Cobranza!$B87,Recibos!M$4:M$7493) -> 300 | BB87: =SUMIF(Recibos!$D$4:$D$7493,Cobranza!$B87,Recibos!N$4:N$7493) -> 300 | BC87: =SUMIF(Recibos!$D$4:$D$7493,Cobranza!$B87,Recibos!O$4:O$7493) -> 300 | BD87: =SUMIF(Recibos!$D$4:$D$7493,Cobranza!$B87,Recibos!P$4:P$7493) -> 300 | BE87: =SUMIF(Recibos!$D$4:$D$7493,Cobranza!$B87,Recibos!Q$4:Q$7493) -> 300 | BF87: =SUMIF(Recibos!$D$4:$D$7493,Cobranza!$B87,Recibos!R$4:R$7493) -> 300 | ... BJ87: =SUMIF(Recibos!$D$4:$D$7493,Cobranza!$B87,Recibos!V$4:V$7493) -> 300 | BK87: =SUM(AY87:BJ87) -> 3600 | BL87: =SUMIF(Recibos!$D$4:$D$7493,Cobranza!$B87,Recibos!X$4:X$7493) -> 300 | BM87: =SUMIF(Recibos!$D$4:$D$7493,Cobranza!$B87,Recibos!Y$4:Y$7493) -> 300 | BN87: =SUMIF(Recibos!$D$4:$D$7493,Cobranza!$B87,Recibos!Z$4:Z$7493) -> 300 | BO87: =SUMIF(Recibos!$D$4:$D$7493,Cobranza!$B87,Recibos!AA$4:AA$7493) -> 300 | BP87: =SUMIF(Recibos!$D$4:$D$7493,Cobranza!$B87,Recibos!AB$4:AB$7493) -> 300 | BQ87: =SUMIF(Recibos!$D$4:$D$7493,Cobranza!$B87,Recibos!AC$4:AC$7493) -> 300 | BR87: =SUMIF(Recibos!$D$4:$D$7493,Cobranza!$B87,Recibos!AD$4:AD$7493) -> 300 | BS87: =SUMIF(Recibos!$D$4:$D$7493,Cobranza!$B87,Recibos!AE$4:AE$7493) -> 300 | ... BW87: =SUMIF(Recibos!$D$4:$D$7493,Cobranza!$B87,Recibos!AI$4:AI$7493) -> 300 | BX87: =SUM(BL87:BW87) -> 3600 | BY87: =SUMIF(Recibos!$D$4:$D$7493,Cobranza!$B87,Recibos!AK$4:AK$7493) -> 300 | BZ87: =SUMIF(Recibos!$D$4:$D$7493,Cobranza!$B87,Recibos!AL$4:AL$7493) -> 300 | CA87: =SUMIF(Recibos!$D$4:$D$7493,Cobranza!$B87,Recibos!AM$4:AM$7493) -> 300 | CB87: =SUMIF(Recibos!$D$4:$D$7493,Cobranza!$B87,Recibos!AN$4:AN$7493) -> 300 | CC87: =SUMIF(Recibos!$D$4:$D$7493,Cobranza!$B87,Recibos!AO$4:AO$7493) -> 300 | CD87: =SUMIF(Recibos!$D$4:$D$7493,Cobranza!$B87,Recibos!AP$4:AP$7493) -> 300 | CE87: =SUMIF(Recibos!$D$4:$D$7493,Cobranza!$B87,Recibos!AQ$4:AQ$7493) -> 300 | CF87: =SUMIF(Recibos!$D$4:$D$7493,Cobranza!$B87,Recibos!AR$4:AR$7493) -> 0 | ... CJ87: =SUMIF(Recibos!$D$4:$D$7493,Cobranza!$B87,Recibos!AV$4:AV$7493) -> 0 | CK87: =SUM(BY87:CJ87) -> 2100
B88: CL_101_ | C88: Rancho La Cuchilla No. 101 | D88: Rodríguez Ramírez | E88: 0 | F88: 0 | G88: 0 | H88: 0 | I88: 0 | J88: 0 | K88: =SUM(E88:J88) -> 0 | L88: 0 | M88: 0 | N88: 0 | O88: 0 | P88: 0 | Q88: 0 | R88: 0 | S88: 0 | T88: 0 | U88: 0 | V88: 0 | W88: 0 | X88: =SUM(L88:W88) -> 0 | Y88: 0 | Z88: 0 | AA88: 0 | AB88: 0 | AC88: 0 | AD88: 0 | AE88: 0 | AF88: 0 | AG88: 0 | AH88: 0 | AI88: 0 | AJ88: 0 | AK88: =SUM(Y88:AJ88) -> 0 | AL88: 0 | AM88: 0 | AN88: 0 | AO88: 0 | AP88: 0 | AQ88: 0 | AR88: 0 | AS88: 0 | AT88: 0 | AU88: 0 | AV88: 0 | AW88: 0 | AX88: =SUM(AL88:AW88) -> 0 | AY88: =SUMIF(Recibos!$D$4:$D$7493,Cobranza!$B88,Recibos!K$4:K$7493) -> 0 | AZ88: =SUMIF(Recibos!$D$4:$D$7493,Cobranza!$B88,Recibos!L$4:L$7493) -> 0 | BA88: =SUMIF(Recibos!$D$4:$D$7493,Cobranza!$B88,Recibos!M$4:M$7493) -> 0 | BB88: =SUMIF(Recibos!$D$4:$D$7493,Cobranza!$B88,Recibos!N$4:N$7493) -> 0 | BC88: =SUMIF(Recibos!$D$4:$D$7493,Cobranza!$B88,Recibos!O$4:O$7493) -> 0 | BD88: =SUMIF(Recibos!$D$4:$D$7493,Cobranza!$B88,Recibos!P$4:P$7493) -> 0 | BE88: =SUMIF(Recibos!$D$4:$D$7493,Cobranza!$B88,Recibos!Q$4:Q$7493) -> 0 | BF88: =SUMIF(Recibos!$D$4:$D$7493,Cobranza!$B88,Recibos!R$4:R$7493) -> 0 | ... BJ88: =SUMIF(Recibos!$D$4:$D$7493,Cobranza!$B88,Recibos!V$4:V$7493) -> 0 | BK88: =SUM(AY88:BJ88) -> 100 | BL88: =SUMIF(Recibos!$D$4:$D$7493,Cobranza!$B88,Recibos!X$4:X$7493) -> 0 | BM88: =SUMIF(Recibos!$D$4:$D$7493,Cobranza!$B88,Recibos!Y$4:Y$7493) -> 0 | BN88: =SUMIF(Recibos!$D$4:$D$7493,Cobranza!$B88,Recibos!Z$4:Z$7493) -> 0 | BO88: =SUMIF(Recibos!$D$4:$D$7493,Cobranza!$B88,Recibos!AA$4:AA$7493) -> 0 | BP88: =SUMIF(Recibos!$D$4:$D$7493,Cobranza!$B88,Recibos!AB$4:AB$7493) -> 0 | BQ88: =SUMIF(Recibos!$D$4:$D$7493,Cobranza!$B88,Recibos!AC$4:AC$7493) -> 0 | BR88: =SUMIF(Recibos!$D$4:$D$7493,Cobranza!$B88,Recibos!AD$4:AD$7493) -> 0 | BS88: =SUMIF(Recibos!$D$4:$D$7493,Cobranza!$B88,Recibos!AE$4:AE$7493) -> 0 | ... BW88: =SUMIF(Recibos!$D$4:$D$7493,Cobranza!$B88,Recibos!AI$4:AI$7493) -> 0 | BX88: =SUM(BL88:BW88) -> 0 | BY88: =SUMIF(Recibos!$D$4:$D$7493,Cobranza!$B88,Recibos!AK$4:AK$7493) -> 0 | BZ88: =SUMIF(Recibos!$D$4:$D$7493,Cobranza!$B88,Recibos!AL$4:AL$7493) -> 0 | CA88: =SUMIF(Recibos!$D$4:$D$7493,Cobranza!$B88,Recibos!AM$4:AM$7493) -> 0 | CB88: =SUMIF(Recibos!$D$4:$D$7493,Cobranza!$B88,Recibos!AN$4:AN$7493) -> 0 | CC88: =SUMIF(Recibos!$D$4:$D$7493,Cobranza!$B88,Recibos!AO$4:AO$7493) -> 0 | CD88: =SUMIF(Recibos!$D$4:$D$7493,Cobranza!$B88,Recibos!AP$4:AP$7493) -> 0 | CE88: =SUMIF(Recibos!$D$4:$D$7493,Cobranza!$B88,Recibos!AQ$4:AQ$7493) -> 0 | CF88: =SUMIF(Recibos!$D$4:$D$7493,Cobranza!$B88,Recibos!AR$4:AR$7493) -> 0 | ... CJ88: =SUMIF(Recibos!$D$4:$D$7493,Cobranza!$B88,Recibos!AV$4:AV$7493) -> 0 | CK88: =SUM(BY88:CJ88) -> 0
